Workbook

Sheet Inputs
A1: Falcon Distribution — Underwriting Inputs (Revised)
A2: Effective 2026-09-01 per revision-notice.pdf
A4: Gross potential rent (all suites x12, revised roll) | B4: 1335225
A5: Other income $/unit/yr | B5: 350
A6: Units | B6: 8
A7: Economic loss % | B7: 0.05
A8: Real estate tax | B8: 147294
A9: Insurance expense | B9: 49098
A10: Other recurring opex | B10: 196392
A11: Management % of EGI | B11: 0.03
A12: Replacement reserve $/unit/yr | B12: 300
A14: Cap rate (prior 6.25% + 25 bps) | B14: 0.065
A15: Sizing rate (prior 7.00% + 75 bps) | B15: 0.0775
A16: Note rate | B16: 0.061
... A24: Existing payoff | B24: 7800000

Sheet UW
A1: Underwriting build (Revised)
A3: Gross potential rent | B3: =Inputs!B4
A4: Other income | B4: =Inputs!B5*Inputs!B6
A5: Gross potential income | B5: =B3+B4
A6: Economic loss (5%) | B6: =-B5*Inputs!B7
A7: Underwritten EGI | B7: =B5+B6
A9: Real estate tax | B9: =Inputs!B8
A10: Insurance | B10: =Inputs!B9
A11: Other recurring opex | B11: =Inputs!B10
A12: Management fee (3% EGI) | B12: =B7*Inputs!B11
A13: Total operating expenses | B13: =SUM(B9:B12)
A15: UW NOI (before reserves) | B15: =B7-B13
A16: Replacement reserves | B16: =Inputs!B12*Inputs!B6
A17: UW NCF | B17: =B15-B16
A19: Capitalization value | B19: =B15/Inputs!B14

Sheet Debt
A1: Debt sizing (Revised)
A3: Sizing rate | B3: =Inputs!B15
A4: Monthly rate | B4: =B3/12
A5: Amort months | B5: =Inputs!B18
A6: Annual debt service per $1 loan | B6: =-PMT(B4,B5,1)*12
A8: LTV-constrained loan | B8: =UW!B19*Inputs!B19
A9: DSCR-constrained loan | B9: =UW!B17/(Inputs!B20*B6)
A10: Debt-yield-constrained loan | B10: =UW!B17/Inputs!B21
A12: Maximum loan (min) | B12: =MIN(B8,B9,B10)
A13: Binding constraint | B13: =IF(B12=B8,"LTV",IF(B12=B9,"DSCR","Debt yield"))
A15: Sources & Uses
A16: Loan proceeds | B16: =B12
A17: Origination fee | B17: =B12*Inputs!B22
A18: Closing costs | B18: =Inputs!B23
A19: Existing payoff | B19: =Inputs!B24
A20: Net cash-out (negative = equity in) | B20: =B16-B17-B18-B19

Sheet Sensitivity
A1: Cap value sensitivity
A3: Cap \ NOI | B3: =UW!B15*0.95 | C3: =UW!B15 | D3: =UW!B15*1.05
A4: 0.0625 | B4: =B$3/$A4 | C4: =C$3/$A4 | D4: =D$3/$A4
A5: 0.065 | B5: =B$3/$A5 | C5: =C$3/$A5 | D5: =D$3/$A5
A6: 0.0675 | B6: =B$3/$A6 | C6: =C$3/$A6 | D6: =D$3/$A6
A7: 0.07 | B7: =B$3/$A7 | C7: =C$3/$A7 | D7: =D$3/$A7
A10: Max loan sensitivity (DSCR-bound test)
A12: Rate \ NCF | B12: =UW!B17*0.95 | C12: =UW!B17 | D12: =UW!B17*1.05
A13: 0.0725 | B13: =B$12/(Inputs!$B$20*(-PMT($A13/12,Inputs!$B$18,1)*12)) | C13: =C$12/(Inputs!$B$20*(-PMT($A13/12,Inputs!$B$18,1)*12)) | D13: =D$12/(Inputs!$B$20*(-PMT($A13/12,Inputs!$B$18,1)*12))
A14: 0.0775 | B14: =B$12/(Inputs!$B$20*(-PMT($A14/12,Inputs!$B$18,1)*12)) | C14: =C$12/(Inputs!$B$20*(-PMT($A14/12,Inputs!$B$18,1)*12)) | D14: =D$12/(Inputs!$B$20*(-PMT($A14/12,Inputs!$B$18,1)*12))
A15: 0.0825 | B15: =B$12/(Inputs!$B$20*(-PMT($A15/12,Inputs!$B$18,1)*12)) | C15: =C$12/(Inputs!$B$20*(-PMT($A15/12,Inputs!$B$18,1)*12)) | D15: =D$12/(Inputs!$B$20*(-PMT($A15/12,Inputs!$B$18,1)*12))
A16: 0.0875 | B16: =B$12/(Inputs!$B$20*(-PMT($A16/12,Inputs!$B$18,1)*12)) | C16: =C$12/(Inputs!$B$20*(-PMT($A16/12,Inputs!$B$18,1)*12)) | D16: =D$12/(Inputs!$B$20*(-PMT($A16/12,Inputs!$B$18,1)*12))

Sheet RentRoll
A1: Revised certified rent roll (2026-09-01) — controlling
A3: Suite | B3: Type/Group | C3: Area SF | D3: Possession | E3: Monthly rent | F3: Expiration
A4: 001 | B4: Small (A) | C4: 21880 | D4: active | E4: 14450 | F4: 2029-08-31
A5: 002 | B5: Standard (B) | C5: 22000 | D5: active | E5: 14825 | F5: 2029-08-31
A6: 003 | B6: Large (C) | C6: 22210 | D6: active | E6: 14875 | F6: 2029-08-31
A7: 004 | B7: Small (A) | C7: 21880 | D7: active | E7: 14450 | F7: 2029-08-31
A8: 005 | B8: Standard (B) | C8: 22000 | D8: active | E8: 14600 | F8: 2029-08-31
A9: 006 | B9: Large (C) | C9: 22210 | D9: active | E9: 14875 | F9: 2029-08-31
A10: 007 | B10: Small (A) | C10: 21880 | D10: active | E10: 14450 | F10: 2029-08-31
A11: 008 | B11: Standard (B) | C11: 22000 | D11: vacant | E11: 14600 | F11: 2029-08-31
A13: Totals | C13: =SUM(C4:C11) | E13: =SUM(E4:E11)
A14: Occupied (active only) | C14: =SUMIF(D4:D11,"active",C4:C11) | E14: =SUMIF(D4:D11,"active",E4:E11)
A15: Annual in-place rent | E15: =E14*12
A16: Unit occupancy | E16: =COUNTIF(D4:D11,"active")/COUNTA(A4:A11)
A17: Area occupancy | E17: =C14/C13

Sheet Changes
A1: Revision change log
A3: Item | B3: Prior | C3: Revised
A4: Certified roll as-of | B4: 2026-08-31 | C4: 2026-09-01
A5: Suite 002 status | B5: active | C5: active (still)
A6: Suite 002 monthly rent | B6: 14600 | C6: 14825
A7: Cap rate | B7: 0.0625 | C7: 0.065
A8: Sizing rate | B8: 0.07 | C8: 0.0775
A9: GPR (annual) | B9: 1402800 | C9: 1405500
A10: UW EGI | B10: 1335320 | C10: 1337885
A11: UW NOI | B11: 902476.4 | C11: 904964.45
A12: UW NCF | B12: 900076.4 | C12: 902564.45
A13: Cap value | B13: 14439622 | C13: 13922530
A14: Max loan | B14: 9019220 | C14: 8398930
A15: Net cash-out | B15: 1084027 | C15: 469941

Sheet Sources
A1: Source register (Revised)
A3: Item | B3: Value | C3: Source
A4: Revised certified rent roll as-of | B4: 2026-09-01 | C4: rent-roll-revised.xlsx B2 (controlling)
A5: Prior certified rent roll | B5: 2026-08-31 | C5: rent-roll-certified.xlsx B2 (superseded)
A6: Archive rent roll | B6: 2026-06-30 | C6: rent-roll-archive.xlsx B2 (stale)
A7: Suite 002 rent step | B7: 225 | C7: revision-notice.pdf p.1 ($225 increase)
A8: Cap rate adjustment | B8: +25 bps | C8: revision-notice.pdf p.1
A9: Sizing rate adjustment | B9: +75 bps | C9: revision-notice.pdf p.1
A10: Suite 001 base rent | B10: 14450 | C10: lease-001.pdf p.1; lease-correspondence.pdf p.1
A11: Reported T12 NOI | B11: 869736 | C11: operating-statement.pdf p.1
A12: Insurance GL aggregate limit | B12: 2000000 | C12: insurance.pdf p.1
