Workbook

Sheet Assumptions
A1: Cap rate | B1: 0.0625
A2: Sizing rate (annual) | B2: 0.0735
A3: EGI (annual) | B3: 921000
A4: Gross potential base rent (scenario) | B4: 780000
A5: Combined revenue loss % (scenario) | B5: 0.05
A6: Other income (scenario) | B6: 180000
A7: EGI from scenario = GPR*(1-Loss%)+Other | B7: =B4*(1-B5)+B6 -> 921000
A8: Rentable SF | B8: 28800
A9: Reserve per SF (annual) | B9: 0.15
A10: T12 management fee (annual) | B10: 18000
A11: Contract rate (annual) | B11: 0.0635

Sheet T12
A1: Hawthorn Center | T12 summary (Sep 2025 - Aug 2026)
A3: Gross potential base rent | B3: 759600
A4: Vacancy loss | B4: 40800
A5: Concessions | B5: 22800
A6: Bad debt | B6: 6000
A7: Other income / recoveries | B7: 176400
A8: EGI (calculated) | B8: =B3-B4-B5-B6+B7 -> 866400
A10: Real estate taxes | B10: 114000
A11: Property insurance | B11: 32400
A12: Utilities | B12: 21600
A13: Repairs and maintenance | B13: 36000
A14: Payroll / contract labor | B14: 24000
A15: Administrative / legal | B15: 18000
A16: Management fee | B16: 18000
A17: Operating expenses total (before reserves) | B17: =SUM(B10:B16) -> 264000
A18: NOI before reserves | B18: =B8-B17 -> 602400
A20: Replacement reserves (below NOI) | B20: 11520
A21: NCF after reserves | B21: =B18-B20 -> 590880

Sheet Rent Roll
A1: Hawthorn Center | Rent roll as of 2026-08-31
A3: Unit / suite | B3: Tenant | C3: Area SF | D3: Status | E3: Monthly base rent | F3: Market monthly rent | G3: Lease expiry
A4: 101 | B4: Tenant A LLC | C4: 1400 | D4: Occupied | E4: 3000 | F4: 3000 | G4: 2029-08-31
A5: 102 | B5: Tenant B LLC | C5: 1800 | D5: Occupied | E5: 4000 | F5: 4000 | G5: 2028-08-31
A6: 103 | B6: Tenant C LLC | C6: 2200 | D6: Occupied | E6: 4900 | F6: 4900 | G6: 2029-08-31
A7: 104 | B7: Tenant D LLC | C7: 2500 | D7: Occupied | E7: 5600 | F7: 5600 | G7: 2030-08-31
A8: 105 | B8: Tenant E LLC | C8: 3000 | D8: Occupied | E8: 6500 | F8: 6500 | G8: 2031-08-31
A9: 106 | B9: Tenant F LLC | C9: 3300 | D9: Occupied | E9: 7400 | F9: 7400 | G9: 2027-08-31
A10: 107 | B10: Tenant G LLC | C10: 3800 | D10: Occupied | E10: 8600 | F10: 8600 | G10: 2028-08-31
A11: 108 | B11: Tenant H LLC | C11: 4200 | D11: Occupied | E11: 9200 | F11: 9200 | G11: 2029-08-31
A12: 109 | B12: Tenant I LLC | C12: 5000 | D12: Occupied | E12: 10800 | F12: 10800 | G12: 2030-08-31
A13: 110 | B13: Vacant | C13: 1600 | D13: Vacant | E13: 0 | F13: 3400
A15: Totals | B15: Count / Area / Rent sums
A16: Space count | B16: 10
A17: Occupied count | B17: 9
A18: Total area SF | B18: =SUM(C4:C13) -> 28800
A19: Occupied area SF | B19: =SUMIF(D4:D13,"Occupied",C4:C13) -> 27200
A20: Occupancy by count % | B20: =B17/B16 -> 0.9
A21: Occupancy by area % | B21: =B19/B18 -> 0.94444444
A22: Monthly base rent (as printed) | B22: =SUM(E4:E12) -> 60000

Sheet Underwriting
A1: Underwriting summary
A3: EGI (input) | B3: =Assumptions!B3 -> 921000
A5: Operating expenses (before reserves)
A6: Real estate taxes | B6: 120000
A7: Property insurance (renewal) | B7: 34800
A8: Utilities | B8: 21600
A9: Repairs and maintenance | B9: 36000
A10: Payroll / contract labor | B10: 24000
A11: Administrative / legal | B11: 18000
A12: Management fee (greater of T12 or 4% of EGI) | B12: =MAX(Assumptions!B10,0.04*B3) -> 36840
A13: Operating expenses total (before reserves) | B13: =SUM(B6:B12) -> 291240
A15: NOI before reserves | B15: =B3-B13 -> 629760
A17: Replacement reserves | B17: =Assumptions!B8*Assumptions!B9 -> 4320
A18: NCF after reserves | B18: =B15-B17 -> 625440

Sheet Sizing
A1: Loan sizing
A3: Cap rate | B3: =Assumptions!B1 -> 0.0625
A4: Sizing rate (annual) | B4: =Assumptions!B2 -> 0.0735
A5: Amortization (years) | B5: 25
A6: Annual debt constant at sizing rate | B6: =12*ABS(PMT(B4/12,B5*12,1)) -> 0.087511438
A8: Capitalization value (NOI before reserves / cap rate) | B8: =Underwriting!B15/B3 -> 10076160
A9: LTV limit (62.5% of value) | B9: =0.625*B8 -> 6297600
A10: Debt yield limit (NOI before reserves / 9%) | B10: =Underwriting!B15/0.09 -> 6997333.3
A11: DSCR limit (NCF / (1.25 x constant)) | B11: =Underwriting!B18/(1.25*B6) -> 5717561.2
A12: Maximum loan (min of three) | B12: =MIN(B9,B10,B11) -> 5717561.2
A14: Annual debt service at maximum (sizing rate) | B14: =B12*B6 -> 500352
A15: Sizing DSCR (NCF / ADS) | B15: =Underwriting!B18/B14 -> 1.25
A16: Sizing debt yield (NOI / Loan) | B16: =Underwriting!B15/B12 -> 0.11014486
A18: First-year contractual annual debt service | B18: =B14 -> 500352
A21: Stress: EGI -5% and sizing rate +100 bps
A22: Stress EGI | B22: =0.95*Assumptions!B3 -> 874950
A23: Stress management fee (greater of T12 or 4% of stress EGI) | B23: =MAX(Assumptions!B10,0.04*B22) -> 34998
A24: Operating expenses excl. management (hold constant) | B24: =Underwriting!B13-Underwriting!B12 -> 254400
A25: Stress NOI before reserves | B25: =B22-(B24+B23) -> 585552
A26: Stress NCF after reserves | B26: =B25-Underwriting!B17 -> 581232
A27: Stress sizing rate | B27: =B4+0.01 -> 0.0835
A28: Annual debt constant at stress sizing rate | B28: =12*ABS(PMT(B27/12,B5*12,1)) -> 0.095417273
A29: Stress capitalization value (cap unchanged) | B29: =B25/B3 -> 9368832
A30: Stress LTV limit (62.5% of stress value) | B30: =0.625*B29 -> 5855520
A31: Stress DSCR limit | B31: =B26/(1.25*B28) -> 4873180.6
A32: Stress Debt yield limit | B32: =B25/0.09 -> 6506133.3
A33: Stress maximum loan (min of three) | B33: =MIN(B30,B31,B32) -> 4873180.6
A36: Cap-rate +50 bps sensitivity (value only)
A37: Cap rate +50 bps | B37: =B3+0.005 -> 0.0675
A38: Value at Cap +50 bps | B38: =Underwriting!B15/B37 -> 9329777.8

Sheet Sources & Uses
A1: Sources and uses at maximum loan
A3: Gross loan amount (maximum) | B3: =Sizing!B12 -> 5717561.2
A4: Origination fee (0.80%) | B4: =0.008*B3 -> 45740.49
A5: Net loan proceeds after fee | B5: =B3-B4 -> 5671820.7
A7: Existing debt payoff | B7: 4200000
A8: Fixed closing costs | B8: 52000
A9: Cash to/(from) borrower | B9: =B5-B7-B8 -> 1419820.7
