Workbook

Sheet UW
A1: Maple Crossing Underwriting (Revised 2026-09-01)
A3: Inputs
A4: Gross potential rent (annual) | B4: 821400
A5: Economic loss % | B5: 0.05
A6: Other income (annual) | B6: 3500
A7: Underwritten EGI | B7: =B4*(1-B5)+B6 -> 783830
A8: Cap rate | B8: 0.07
A10: Real estate taxes | B10: 85964
A11: Insurance expense | B11: 28655
A12: Other recurring opex | B12: 114618
A13: Management fee % of EGI | B13: 0.03
A14: Mgmt fee (calc) | B14: =B7*B13 -> 23514.9
A15: Total opex excl reserves | B15: =SUM(B10:B12)+B14 -> 252751.9
A16: NOI before reserves | B16: =B7-B15 -> 531078.1
A18: Units/Suites | B18: 10
A19: Reserves per unit | B19: 300
A20: Annual reserves | B20: =B18*B19 -> 3000
A21: NCF after reserves | B21: =B16-B20 -> 528078.1
A23: Capitalization value | B23: =B16/B8 -> 7586830
A25: Sizing note rate | B25: 0.0825
A26: Amortization years | B26: 30
A27: Annual payment constant | B27: =ABS(PMT(B25/12,B26*12,1))*12 -> 0.090151992
A28: DSCR minimum | B28: 1.25
A29: Debt yield minimum | B29: 0.09
A30: LTV maximum | B30: 0.65
A31: LTV constraint ($) | B31: =B23*B30 -> 4931439.5
A32: DSCR constraint ($) | B32: =(B21/B28)/B27 -> 4686113.6
A33: Debt yield constraint ($) | B33: =B21/B29 -> 5867534.4
A34: Maximum loan | B34: =MIN(B31,B32,B33) -> 4686113.6
A36: Origination fee % | B36: 0.01
A37: Origination fee ($) | B37: =B34*B36 -> 46861.136
A38: Closing costs ($) | B38: 45000
A39: Existing payoff ($) | B39: 4300000
A40: Net cash out ($) | B40: =B34-(B37+B38+B39) -> 294252.49

Sheet Sensitivity
A1: Sensitivity (Revised)
A3: NOI (from UW) | B3: =UW!B16 -> 531078.1 | D3: Sizing rate | E3: Max Loan vs Rate
D4: 0.06 | E4: =MIN(UW!B31,(UW!B21/UW!B28)/(ABS(PMT(D4/12,UW!B26*12,1))*12),UW!B33) -> 4931439.5
A5: Cap rate | B5: Value | D5: 0.065 | E5: =MIN(UW!B31,(UW!B21/UW!B28)/(ABS(PMT(D5/12,UW!B26*12,1))*12),UW!B33) -> 4931439.5
A6: 0.065 | B6: =B3/A6 -> 8170432.3 | D6: 0.0725 | E6: =MIN(UW!B31,(UW!B21/UW!B28)/(ABS(PMT(D6/12,UW!B26*12,1))*12),UW!B33) -> 4931439.5
A7: 0.0675 | B7: =B3/A7 -> 7867823.7 | D7: 0.075 | E7: =MIN(UW!B31,(UW!B21/UW!B28)/(ABS(PMT(D7/12,UW!B26*12,1))*12),UW!B33) -> 4931439.5
A8: 0.07 | B8: =B3/A8 -> 7586830 | D8: 0.0775 | E8: =MIN(UW!B31,(UW!B21/UW!B28)/(ABS(PMT(D8/12,UW!B26*12,1))*12),UW!B33) -> 4914099
A9: 0.0725 | B9: =B3/A9 -> 7325215.2 | D9: 0.08 | E9: =MIN(UW!B31,(UW!B21/UW!B28)/(ABS(PMT(D9/12,UW!B26*12,1))*12),UW!B33) -> 4797888.6
A10: 0.075 | B10: =B3/A10 -> 7081041.3

Sheet Sources
A1: Source Register (Revised)
A3: Document | B3: Location | C3: Key updates
A4: revision-notice.pdf | B4: Page 1 | C4: Raise sizing rate +75 bps (to 7.25%); cap rate +25 bps (to 7.00%); use revised certified roll for GPR
A5: rent-roll-revised.xlsx | B5: Rent Roll!A2:B14 | C5: Suite 002 now active; its monthly rent +$225 to $7,025; all else unchanged
A6: underwriting-instructions.pdf | B6: Page 1 | C6: All other rules (loss 5%, other income $350/unit, taxes, insurance, opex, reserves, constraints, fees, payoff) unchanged
