Workbook

Sheet Inputs
A1: Willow Gardens - Underwriting Inputs (as of 2026-08-31)
A3: Input | B3: Value | C3: Source / note
A4: Gross potential rent (annual, all 64 suites) | B4: 1354500 | C4: Certified roll scheduled monthly rent (E5:E68 = $112,875) x 12; rent-roll-certified.xlsx
A5: Economic loss (vacancy/credit) % | B5: 0.05 | C5: underwriting-instructions.pdf p.1
A6: Other income per unit (annual) | B6: 350 | C6: underwriting-instructions.pdf p.1; reimbursements already included
A7: Total units / suites | B7: ='Rent Roll'!B71 | C7: Count from certified roll
A8: Real estate taxes | B8: 142222 | C8: underwriting-instructions.pdf p.1 (= operating-statement.pdf T-12)
A9: Insurance expense | B9: 47408 | C9: underwriting-instructions.pdf p.1 (= operating-statement.pdf T-12)
A10: Other recurring operating expenses | B10: 189630 | C10: underwriting-instructions.pdf p.1 (= operating-statement.pdf T-12)
A11: Management fee (% of underwritten EGI) | B11: 0.03 | C11: underwriting-instructions.pdf p.1
A12: Replacement reserve per unit (annual) | B12: 300 | C12: underwriting-instructions.pdf p.1
A13: Capitalization rate (on NOI before reserves) | B13: 0.06 | C13: underwriting-instructions.pdf p.1
A14: Note rate | B14: 0.069 | C14: underwriting-instructions.pdf p.1
A15: Underwriting rate floor | B15: 0.06 | C15: underwriting-instructions.pdf p.1
A16: Sizing rate (greater of note rate and floor) | B16: 0.069 | C16: Note rate 6.9000% exceeds the 6.00% floor, so the floor is not binding
A17: Amortization term (months) | B17: 360 | C17: 30-year amortization, monthly payments
A18: Maximum LTV | B18: 0.6 | C18: underwriting-instructions.pdf p.1
A19: Minimum DSCR (on NCF) | B19: 1.25 | C19: underwriting-instructions.pdf p.1
... A23: Existing loan payoff | B23: 7200000 | C23: underwriting-instructions.pdf p.1
A25: Note: first 24 months are interest-only, but sizing uses the 30-year amortizing constant at the sizing rate per instructions.

Sheet Rent Roll
A1: Certified rent roll (controlling) - rent-roll-certified.xlsx
A2: As of | B2: 2026-08-31
A4: Suite | B4: Unit type | C4: Group | D4: Area SF | E4: Possession | F4: Monthly rent | G4: Expiration | H4: Occupied | I4: Occupied SF | J4: In-place rent
A5: 001 | B5: Studio | C5: A | D5: 820 | E5: active | F5: 1575 | G5: 2029-08-31 | H5: =IF(E5="active",1,0) | I5: =H5*D5 | J5: =H5*F5
A6: 002 | B6: 1BR | C6: B | D6: 940 | E6: active | F6: 1725 | G6: 2029-08-31 | H6: =IF(E6="active",1,0) | I6: =H6*D6 | J6: =H6*F6
A7: 003 | B7: 2BR | C7: C | D7: 1150 | E7: active | F7: 2000 | G7: 2029-08-31 | H7: =IF(E7="active",1,0) | I7: =H7*D7 | J7: =H7*F7
A8: 004 | B8: Studio | C8: A | D8: 820 | E8: active | F8: 1575 | G8: 2029-08-31 | H8: =IF(E8="active",1,0) | I8: =H8*D8 | J8: =H8*F8
A9: 005 | B9: 1BR | C9: B | D9: 940 | E9: active | F9: 1725 | G9: 2029-08-31 | H9: =IF(E9="active",1,0) | I9: =H9*D9 | J9: =H9*F9
A10: 006 | B10: 2BR | C10: C | D10: 1150 | E10: active | F10: 2000 | G10: 2029-08-31 | H10: =IF(E10="active",1,0) | I10: =H10*D10 | J10: =H10*F10
A11: 007 | B11: Studio | C11: A | D11: 820 | E11: active | F11: 1575 | G11: 2029-08-31 | H11: =IF(E11="active",1,0) | I11: =H11*D11 | J11: =H11*F11
A12: 008 | B12: 1BR | C12: B | D12: 940 | E12: active | F12: 1725 | G12: 2029-08-31 | H12: =IF(E12="active",1,0) | I12: =H12*D12 | J12: =H12*F12
A13: 009 | B13: 2BR | C13: C | D13: 1150 | E13: active | F13: 2000 | G13: 2029-08-31 | H13: =IF(E13="active",1,0) | I13: =H13*D13 | J13: =H13*F13
A14: 010 | B14: Studio | C14: A | D14: 820 | E14: active | F14: 1575 | G14: 2029-08-31 | H14: =IF(E14="active",1,0) | I14: =H14*D14 | J14: =H14*F14
A15: 011 | B15: 1BR | C15: B | D15: 940 | E15: active | F15: 1725 | G15: 2029-08-31 | H15: =IF(E15="active",1,0) | I15: =H15*D15 | J15: =H15*F15
A16: 012 | B16: 2BR | C16: C | D16: 1150 | E16: active | F16: 2000 | G16: 2029-08-31 | H16: =IF(E16="active",1,0) | I16: =H16*D16 | J16: =H16*F16
... A68: 064 | B68: Studio | C68: A | D68: 820 | E68: vacant | F68: 1575 | G68: 2029-08-31 | H68: =IF(E68="active",1,0) | I68: =H68*D68 | J68: =H68*F68
A70: Roll summary
A71: Total units / suites | B71: =COUNTA(A5:A68)
A72: Occupied units (active / in possession) | B72: =COUNTIF(E5:E68,"active")
A73: Pending units (not in possession) | B73: =COUNTIF(E5:E68,"pending")
A74: Vacant units | B74: =COUNTIF(E5:E68,"vacant")
A75: Total area SF | B75: =SUM(D5:D68)
A76: Occupied area SF | B76: =SUM(I5:I68)
A77: Unit occupancy (physical) | B77: =B72/B71
A78: Area occupancy (physical) | B78: =B76/B75
A79: Scheduled monthly rent - all suites | B79: =SUM(F5:F68)
A80: Gross potential rent (annual) - check vs Inputs!B4 | B80: =B79*12
A81: In-place monthly rent (occupied only) | B81: =SUM(J5:J68)
A82: Annual in-place rent (occupied only) | B82: =B81*12
A83: Manager 'leased' count (occupied + pending) | B83: =B72+B73
A84: Suite 001 monthly rent (certified / executed lease) | B84: =F5
A85: All lease expirations on roll: 2029-08-31 (none within 12 months of 2026-08-31)
A87: Group | B87: Unit type | C87: Units | D87: Occupied | E87: Area SF | F87: Monthly rent/unit
A88: A | B88: Studio | C88: =COUNTIF($C$5:$C$68,"A") | D88: =SUMIF($C$5:$C$68,"A",$H$5:$H$68) | E88: =SUMIF($C$5:$C$68,"A",$D$5:$D$68) | F88: 1575
A89: B | B89: 1BR | C89: =COUNTIF($C$5:$C$68,"B") | D89: =SUMIF($C$5:$C$68,"B",$H$5:$H$68) | E89: =SUMIF($C$5:$C$68,"B",$D$5:$D$68) | F89: 1725
A90: C | B90: 2BR | C90: =COUNTIF($C$5:$C$68,"C") | D90: =SUMIF($C$5:$C$68,"C",$H$5:$H$68) | E90: =SUMIF($C$5:$C$68,"C",$D$5:$D$68) | F90: 2000
A91: Total | C91: =SUM(C88:C90) | D91: =SUM(D88:D90) | E91: =SUM(E88:E90)
A93: Group mapping A/B/C = Studio/1BR/2BR per manager-cover.pdf p.1

Sheet UW
A1: Underwritten cash flow (stabilized) vs T-12 actual
A3: Gross potential rent (annual) | B3: =Inputs!B4 | D3: Certified roll x 12; Suite 001 at executed $1,575
A4: Economic loss (vacancy/credit) | B4: =-Inputs!B5*B3 | D4: 5.00% of GPR
A5: Other income ($350/unit) | B5: =Inputs!B6*Inputs!B7 | D5: Reimbursements already included; not added twice
A6: Underwritten EGI | B6: =B3+B4+B5
A8: Real estate taxes | B8: =-Inputs!B8
A9: Insurance | B9: =-Inputs!B9
A10: Other recurring operating expenses | B10: =-Inputs!B10
A11: Management fee (3.00% of EGI) | B11: =-Inputs!B11*B6
A12: Total underwritten operating expenses | B12: =-SUM(B8:B11)
A13: Underwritten NOI (before reserves) | B13: =B6-B12
A14: Replacement reserves ($300/unit) | B14: =Inputs!B12*Inputs!B7
A15: Underwritten NCF (after reserves) | B15: =B13-B14
A17: Operating expense ratio (% of EGI) | B17: =B12/B6
A18: Capitalization value (NOI before reserves / cap rate) | B18: =B13/Inputs!B13
A19: Value per unit | B19: =B18/Inputs!B7
A21: Historical T-12 (2025-09-01 to 2026-08-31) vs underwritten | B21: T-12 actual | C21: Underwritten
A22: Revenue (collections / EGI) | B22: 1219050 | C22: =B6
A23: Real estate taxes | B23: 142222 | C23: =Inputs!B8
A24: Insurance | B24: 47408 | C24: =Inputs!B9
A25: Other recurring operating expenses | B25: 189630 | C25: =Inputs!B10
A26: Roof replacement booked in repairs (capital) | B26: 0
A27: Management fee | B27: 0 | C27: =-B11
A28: NOI before reserves | B28: =B22-B23-B24-B25-B26-B27 | C28: =B13
A29: Reported T-12 NOI per operating statement | B29: 839790
A30: Historical collections are cash receipts, not an annualized roll; no management fee is separately reported in the T-12 ledger and the roof replacement is booked at $0 in repairs (capital item, per operating-statement.pdf p.1).

Sheet Debt
A1: Debt sizing and sources / uses
A3: Sizing rate (greater of note rate and floor) | B3: =Inputs!B16 | C3: Note 6.9000% vs floor 6.0000%
A4: Monthly amortizing constant per $1 of loan | B4: =-PMT(B3/12,Inputs!B17,1)
A5: LTV limit (60.00% of capitalization value) | B5: =Inputs!B18*UW!B18
A6: DSCR limit (1.25x on NCF, 30-yr amortizing) | B6: =(UW!B15/Inputs!B19/12)/B4
A7: Debt yield limit (NCF / 9.00%) | B7: =UW!B15/Inputs!B20
A8: Maximum loan (most restrictive) | B8: =MIN(B5,B6,B7)
A9: Binding constraint | B9: =IF(B8=B5,"LTV",IF(B8=B6,"DSCR","Debt yield"))
A10: Implied LTV at maximum loan | B10: =B8/UW!B18
A11: Annual debt service (amortizing, sizing rate) | B11: =B8*B4*12
A12: DSCR at maximum loan (NCF) | B12: =UW!B15/B11
A13: NCF debt yield at maximum loan | B13: =UW!B15/B8
A14: Interest-only annual debt service (first 24 months) | B14: =B8*B3
A15: DSCR during interest-only period | B15: =UW!B15/B14
A17: Sources and uses
A18: Use - existing loan payoff | B18: =Inputs!B23
A19: Use - origination fee (1.00% of loan) | B19: =B8*Inputs!B21
A20: Use - closing costs | B20: =Inputs!B22
A21: Total uses | B21: =SUM(B18:B20)
A22: Source - new loan proceeds | B22: =B8
A23: Net cash-out to sponsor (negative = equity required) | B23: =B22-B21
A24: Additional equity required | B24: =MAX(0,-B23)
A26: Refinance test: proceeds exceed payoff plus costs, so no shortfall at the underwritten NCF and 6.0000% cap rate.

Sheet Sensitivity
A1: Sensitivity - maximum loan ($) by cap rate (rows) and sizing rate (columns)
A3: Cap rate \ sizing rate
B4: 0.06 | C4: 0.065 | D4: 0.069 | E4: 0.075
A5: 0.055 | B5: =MIN(Inputs!$B$18*UW!$B$13/$A5,(UW!$B$15/Inputs!$B$19/12)/(-PMT(B$4/12,Inputs!$B$17,1)),UW!$B$15/Inputs!$B$20) | C5: =MIN(Inputs!$B$18*UW!$B$13/$A5,(UW!$B$15/Inputs!$B$19/12)/(-PMT(C$4/12,Inputs!$B$17,1)),UW!$B$15/Inputs!$B$20) | D5: =MIN(Inputs!$B$18*UW!$B$13/$A5,(UW!$B$15/Inputs!$B$19/12)/(-PMT(D$4/12,Inputs!$B$17,1)),UW!$B$15/Inputs!$B$20) | E5: =MIN(Inputs!$B$18*UW!$B$13/$A5,(UW!$B$15/Inputs!$B$19/12)/(-PMT(E$4/12,Inputs!$B$17,1)),UW!$B$15/Inputs!$B$20)
A6: 0.0575 | B6: =MIN(Inputs!$B$18*UW!$B$13/$A6,(UW!$B$15/Inputs!$B$19/12)/(-PMT(B$4/12,Inputs!$B$17,1)),UW!$B$15/Inputs!$B$20) | C6: =MIN(Inputs!$B$18*UW!$B$13/$A6,(UW!$B$15/Inputs!$B$19/12)/(-PMT(C$4/12,Inputs!$B$17,1)),UW!$B$15/Inputs!$B$20) | D6: =MIN(Inputs!$B$18*UW!$B$13/$A6,(UW!$B$15/Inputs!$B$19/12)/(-PMT(D$4/12,Inputs!$B$17,1)),UW!$B$15/Inputs!$B$20) | E6: =MIN(Inputs!$B$18*UW!$B$13/$A6,(UW!$B$15/Inputs!$B$19/12)/(-PMT(E$4/12,Inputs!$B$17,1)),UW!$B$15/Inputs!$B$20)
A7: 0.06 | B7: =MIN(Inputs!$B$18*UW!$B$13/$A7,(UW!$B$15/Inputs!$B$19/12)/(-PMT(B$4/12,Inputs!$B$17,1)),UW!$B$15/Inputs!$B$20) | C7: =MIN(Inputs!$B$18*UW!$B$13/$A7,(UW!$B$15/Inputs!$B$19/12)/(-PMT(C$4/12,Inputs!$B$17,1)),UW!$B$15/Inputs!$B$20) | D7: =MIN(Inputs!$B$18*UW!$B$13/$A7,(UW!$B$15/Inputs!$B$19/12)/(-PMT(D$4/12,Inputs!$B$17,1)),UW!$B$15/Inputs!$B$20) | E7: =MIN(Inputs!$B$18*UW!$B$13/$A7,(UW!$B$15/Inputs!$B$19/12)/(-PMT(E$4/12,Inputs!$B$17,1)),UW!$B$15/Inputs!$B$20)
A8: 0.0625 | B8: =MIN(Inputs!$B$18*UW!$B$13/$A8,(UW!$B$15/Inputs!$B$19/12)/(-PMT(B$4/12,Inputs!$B$17,1)),UW!$B$15/Inputs!$B$20) | C8: =MIN(Inputs!$B$18*UW!$B$13/$A8,(UW!$B$15/Inputs!$B$19/12)/(-PMT(C$4/12,Inputs!$B$17,1)),UW!$B$15/Inputs!$B$20) | D8: =MIN(Inputs!$B$18*UW!$B$13/$A8,(UW!$B$15/Inputs!$B$19/12)/(-PMT(D$4/12,Inputs!$B$17,1)),UW!$B$15/Inputs!$B$20) | E8: =MIN(Inputs!$B$18*UW!$B$13/$A8,(UW!$B$15/Inputs!$B$19/12)/(-PMT(E$4/12,Inputs!$B$17,1)),UW!$B$15/Inputs!$B$20)
A9: 0.065 | B9: =MIN(Inputs!$B$18*UW!$B$13/$A9,(UW!$B$15/Inputs!$B$19/12)/(-PMT(B$4/12,Inputs!$B$17,1)),UW!$B$15/Inputs!$B$20) | C9: =MIN(Inputs!$B$18*UW!$B$13/$A9,(UW!$B$15/Inputs!$B$19/12)/(-PMT(C$4/12,Inputs!$B$17,1)),UW!$B$15/Inputs!$B$20) | D9: =MIN(Inputs!$B$18*UW!$B$13/$A9,(UW!$B$15/Inputs!$B$19/12)/(-PMT(D$4/12,Inputs!$B$17,1)),UW!$B$15/Inputs!$B$20) | E9: =MIN(Inputs!$B$18*UW!$B$13/$A9,(UW!$B$15/Inputs!$B$19/12)/(-PMT(E$4/12,Inputs!$B$17,1)),UW!$B$15/Inputs!$B$20)
A11: Value and net cash-out sensitivity to cap rate (sizing rate held at Inputs!B16)
A12: Cap rate | B12: Capitalization value | C12: Maximum loan | D12: Net cash-out
A13: =A5 | B13: =UW!$B$13/A13 | C13: =MIN(Inputs!$B$18*B13,Debt!$B$6,Debt!$B$7) | D13: =C13*(1-Inputs!$B$21)-Inputs!$B$23-Inputs!$B$22
A14: =A6 | B14: =UW!$B$13/A14 | C14: =MIN(Inputs!$B$18*B14,Debt!$B$6,Debt!$B$7) | D14: =C14*(1-Inputs!$B$21)-Inputs!$B$23-Inputs!$B$22
A15: =A7 | B15: =UW!$B$13/A15 | C15: =MIN(Inputs!$B$18*B15,Debt!$B$6,Debt!$B$7) | D15: =C15*(1-Inputs!$B$21)-Inputs!$B$23-Inputs!$B$22
A16: =A8 | B16: =UW!$B$13/A16 | C16: =MIN(Inputs!$B$18*B16,Debt!$B$6,Debt!$B$7) | D16: =C16*(1-Inputs!$B$21)-Inputs!$B$23-Inputs!$B$22
A17: =A9 | B17: =UW!$B$13/A17 | C17: =MIN(Inputs!$B$18*B17,Debt!$B$6,Debt!$B$7) | D17: =C17*(1-Inputs!$B$21)-Inputs!$B$23-Inputs!$B$22
A19: Sensitivity is illustrative mechanics only; no market cap-rate or comparable-sale data is supplied in the packet.

Sheet Sources
A1: Source register
A2: File | B2: Date / as-of | C2: Location used | D2: Use in this analysis
A3: rent-roll-certified.xlsx | B3: 2026-08-31 | C3: Rent Roll A5:G68, B2 | D3: Controlling unit count, areas, possession status, scheduled rents, expirations
A4: rent-roll-archive.xlsx | B4: 2026-06-30 | C4: Rent Roll E5:E68 | D4: Stale archive (superseded): rents $1,500/$1,650/$1,925; not used for underwriting
A5: lease-001.pdf | B5: n/a | C5: p.1 | D5: Suite 001 executed rent $1,575, 820 SF, expiry 2029-08-31, no free rent
A6: lease-correspondence.pdf | B6: 2026-08-31 | C6: p.1 | D6: Manager confirmation: no amendments or new concessions on Suite 001
A7: operating-statement.pdf | B7: 2025-09-01 to 2026-08-31 | C7: p.1 | D7: T-12 collections $1,219,050; tax, insurance, other opex; reported NOI $839,790; roof capital $0
A8: insurance.pdf | B8: 2026-07-01 to 2027-06-30 | C8: p.1 | D8: General liability aggregate limit $2,000,000 (coverage limit, not expense)
A9: underwriting-instructions.pdf | B9: n/a | C9: p.1 | D9: All underwriting and loan-sizing assumptions and constraints
A10: manager-cover.pdf | B10: n/a | C10: p.1 | D10: Manager 53/64 leased headline; A/B/C group mapping; certified detail controls
A11: diligence-status.pdf | B11: n/a | C11: p.1 | D11: Legal, environmental, PCA and title reviews outstanding; no defect findings
A13: Not supplied by the packet and therefore explicitly unknown: photographs, asking price, market rent and sale comparables, sponsor track record, address, debt quote/term sheet, unit-level tenant credit, capital plan detail, property tax appeal status.
