Workbook

Sheet Assumptions
A1: Market Row | Editable underwriting assumptions (as of 2026-08-31)
A3: Item | B3: Value | C3: Source / note
A4: Total rentable SF | B4: 23000 | C4: Rent-Roll.xlsx rows 7-14 (sum of Area SF)
A5: Gross potential base rent (annual, underwritten) | B5: 657600 | C5: Property-and-Plan.pdf p.2 - supplied scenario, not from T12
A6: Combined revenue loss % of gross potential rent | B6: 0.06 | C6: Property-and-Plan.pdf p.2 - vacancy, concessions, bad debt
A7: Other income / recoveries (annual, underwritten) | B7: 150000 | C7: Property-and-Plan.pdf p.2 - added after revenue loss
A8: Capitalization rate | B8: 0.07 | C8: Lender-Terms.pdf p.1 - NOI before reserves / 6.50%
A9: Contract rate (annual, fixed) | B9: 0.0625 | C9: Lender-Terms.pdf p.1
A10: Sizing rate floor | B10: 0.065 | C10: Lender-Terms.pdf p.1 - greater of contract rate and 6.50%
A11: Sizing rate increment (stress lever, e.g. 0.01 = +100 bps) | B11: 0 | C11: Reviewer lever; base case 0
A12: Sizing rate used = MAX(contract, floor) + increment | B12: =MAX(B9,B10)+B11 -> 0.065
A13: Amortization (months) | B13: 300 | C13: Lender-Terms.pdf p.1 - 25 years, monthly
A14: Interest-only period (months) | B14: 0 | C14: Lender-Terms.pdf p.1 - 0 months
A15: Maximum LTV | B15: 0.65
A16: Minimum DSCR (NCF after reserves) | B16: 1.25
A17: Minimum debt yield (NOI before reserves) | B17: 0.09
A18: Origination fee % of initial principal | B18: 0.01
A19: Fixed closing costs | B19: 48000 | C19: Property-and-Plan.pdf p.1
A20: Existing debt payoff | B20: 3400000 | C20: Property-and-Plan.pdf p.1
A21: Replacement reserves per SF per year | B21: 0.2
A22: Management fee % of underwritten EGI (minimum test) | B22: 0.04
A23: T12 actual management fee (floor for UW fee) | B23: 24000
A24: Cap-rate sensitivity increment | B24: 0.005
A25: EGI stress factor (0.95 = EGI -5%) | B25: 0.95
A27: Underwritten operating expenses (before reserves) | B27: Annual | C27: Treatment
A28: Real estate taxes | B28: 90000 | C28: Plan p.2: T12 $86,400 stepped to $90,000
A29: Property insurance | B29: 27600 | C29: Plan p.2: renewal allowance in scenario (T12 $25,200)
A30: Utilities | B30: 19200 | C30: Plan p.2: T12 actual
A31: Repairs and maintenance | B31: 24000 | C31: Plan p.2: T12 $28,800 less $4,800 one-time casualty cleanup
A32: Payroll / contract labor | B32: 18000 | C32: Plan p.2: T12 actual
A33: Administrative / legal | B33: 14400 | C33: Plan p.2: T12 actual
A34: Subtotal, expenses other than management fee | B34: =SUM(B28:B33) -> 193200

Sheet Rent Roll
A1: Market Row | Rent roll as of 2026-08-31 reconciled to executed lease amendment
A3: Unit | B3: Tenant | C3: Area SF | D3: Status | E3: Rent roll monthly base | F3: Amendment adjustment | G3: Effective monthly base | H3: Authoritative expiry
A4: 101 | B4: Tenant A LLC | C4: 1800 | D4: Occupied | E4: 7000 | F4: 500 | G4: =E4+F4 -> 7500 | H4: 2031-08-31
A5: 102 | B5: Tenant B LLC | C5: 2200 | D5: Occupied | E5: 5500 | F5: 0 | G5: =E5+F5 -> 5500 | H5: 2028-08-31
A6: 103 | B6: Tenant C LLC | C6: 2500 | D6: Occupied | E6: 6000 | F6: 0 | G6: =E6+F6 -> 6000 | H6: 2029-08-31
A7: 104 | B7: Tenant D LLC | C7: 3200 | D7: Occupied | E7: 7200 | F7: 0 | G7: =E7+F7 -> 7200 | H7: 2030-08-31
A8: 105 | B8: Tenant E LLC | C8: 4000 | D8: Occupied | E8: 9000 | F8: 0 | G8: =E8+F8 -> 9000 | H8: 2031-08-31
A9: 106 | B9: Tenant F LLC | C9: 5000 | D9: Occupied | E9: 10500 | F9: 0 | G9: =E9+F9 -> 10500 | H9: 2027-08-31
A10: 107 | B10: Tenant G LLC | C10: 1500 | D10: Occupied | E10: 3400 | F10: 0 | G10: =E10+F10 -> 3400 | H10: 2028-08-31
A11: 108 | B11: Vacant | C11: 2800 | D11: Vacant | E11: 0 | F11: 0 | G11: =E11+F11 -> 0 | H11: n/a
A12: Total | C12: =SUM(C4:C11) -> 23000 | E12: =SUM(E4:E11) -> 48600 | F12: =SUM(F4:F11) -> 500 | G12: =SUM(G4:G11) -> 49100
A14: Occupancy metrics
A15: Space count | B15: =COUNTA(A4:A11) -> 8
A16: Occupied count | B16: =COUNTIF(D4:D11,"Occupied") -> 7
A17: Total area SF | B17: =C12 -> 23000
A18: Occupied area SF | B18: =SUMIF(D4:D11,"Occupied",C4:C11) -> 20200
A19: Occupancy by count (%) | B19: =100*B16/B15 -> 87.5
A20: Occupancy by area (%) | B20: =100*B18/B17 -> 87.826087
A21: Rent roll monthly base as printed | B21: =E12 -> 48600
A22: Effective monthly base after executed first amendment | B22: =G12 -> 49100
A23: Annualized effective contractual base rent (context only) | B23: =12*G12 -> 589200
A25: Unit 101 is reconciled to the executed first amendment (Lease-File.pdf p.2, signed 2026-07-20, effective 2026-08-01): $7,500/month. The unsigned broker proposal ($8,000/month, extension to 2033) is not authoritative and is excluded.
A26: Vacant suite 108 carries market rent of $5,200/month for context only; no contractual rent is included.

Sheet T12 Historical
A1: Historical T12 | September 2025 - August 2026 actuals (T12-Statement.pdf p.1-2)
A3: Line | B3: Annual actual | C3: Note
A4: Gross potential base rent | B4: 645600 | C4: T12 p.2 Annual column
A5: Vacancy loss | B5: -46800
A6: Concessions | B6: -14400
A7: Bad debt | B7: -3600
A8: Other income / recoveries | B8: 142800
A9: T12 effective gross income (EGI) | B9: =SUM(B4:B8) -> 723600
A11: Real estate taxes | B11: 86400
A12: Property insurance | B12: 25200
A13: Utilities | B13: 19200
A14: Repairs and maintenance | B14: 28800 | C14: Includes $4,800 one-time casualty cleanup per plan p.2
A15: Payroll / contract labor | B15: 18000
A16: Administrative / legal | B16: 14400
A17: Management fee | B17: 24000
A18: T12 operating expenses (excl. reserves, capex, debt, depreciation) | B18: =SUM(B11:B17) -> 216000
A19: T12 NOI before replacement reserves | B19: =B9-B18 -> 507600
A20: Replacement reserves (below NOI) | B20: 9200
A21: T12 NCF after replacement reserves | B21: =B19-B20 -> 498400
A23: Below cash flow (reconciliation only, not operating expenses)
A24: Capital improvements | B24: 98000
A25: Loan principal and interest (existing debt) | B25: 294000
A26: Depreciation (noncash) | B26: 180000
A28: The accounting package may label cash flow after reserves as 'property NOI'. Per Property-and-Plan.pdf p.1, NOI before reserves ($507,600) and NCF after reserves ($498,400) are reported separately; capex, debt service and depreciation are excluded from operating expense.
A29: T12 expense ratio | B29: =B18/B9 -> 0.29850746

Sheet Underwriting
A1: Underwritten cash flow | supplied scenario, September 2026 forward (Property-and-Plan.pdf p.2)
A3: Gross potential base rent (annual) | B3: =Assumptions!B5 -> 657600
A4: Less combined revenue loss (vacancy, concessions, bad debt) | B4: =-Assumptions!B6*B3 -> -39456
A5: Effective base rental income | B5: =B3+B4 -> 618144
A6: Other income / recoveries | B6: =Assumptions!B7 -> 150000
A7: Underwritten EGI | B7: =B5+B6 -> 768144
A9: Real estate taxes | B9: =Assumptions!B28 -> 90000
A10: Property insurance | B10: =Assumptions!B29 -> 27600
A11: Utilities | B11: =Assumptions!B30 -> 19200
A12: Repairs and maintenance | B12: =Assumptions!B31 -> 24000
A13: Payroll / contract labor | B13: =Assumptions!B32 -> 18000
A14: Administrative / legal | B14: =Assumptions!B33 -> 14400
A15: Management fee (greater of T12 actual and 4.00% of UW EGI) | B15: =MAX(Assumptions!B23,Assumptions!B22*B7) -> 30725.76
A16: Underwritten operating expenses before reserves | B16: =SUM(B9:B15) -> 223925.76
A17: Underwritten NOI before replacement reserves | B17: =B7-B16 -> 544218.24
A18: Replacement reserves ($/SF x total SF) | B18: =Assumptions!B21*Assumptions!B4 -> 4600
A19: Underwritten NCF after replacement reserves | B19: =B17-B18 -> 539618.24
A21: Capitalization rate | B21: =Assumptions!B8 -> 0.07
A22: Indicative capitalization value (UW NOI before reserves / cap rate) | B22: =B17/B21 -> 7774546.3
A23: Underwritten expense ratio | B23: =B16/B7 -> 0.29151534
A24: Value per SF | B24: =B22/Assumptions!B4 -> 338.02375
A26: The underwriting scenario is supplied by the plan and is not a lender-approved forecast; it is not reconciled to and should not be forced to equal T12 actuals or annualized point-in-time rent roll.

Sheet Loan Sizing
A1: Loan sizing | Lender-Terms.pdf p.1 definitions
A3: Sizing rate (greater of contract rate and 6.50% floor, plus increment) | B3: =Assumptions!B12 -> 0.065
A4: Amortization (months) | B4: =Assumptions!B13 -> 300
A5: Annual debt constant per $1 of principal (12 monthly payments) | B5: =12*-PMT(B3/12,B4,1) -> 0.081024859
A7: LTV limit (65.00% x indicative value) | B7: =Assumptions!B15*Underwriting!B22 -> 5053455.1
A8: DSCR limit ((UW NCF / 1.25x) / annual debt constant) | B8: =(Underwriting!B19/Assumptions!B16)/B5 -> 5327927.7
A9: Debt yield limit (UW NOI before reserves / 9.00%) | B9: =Underwriting!B17/Assumptions!B17 -> 6046869.3
A10: Maximum loan (lowest constraint) | B10: =MIN(B7:B9) -> 5053455.1
A11: Binding constraint | B11: =IF(B10=B8,"DSCR",IF(B10=B7,"LTV","Debt yield")) -> LTV
A13: Sizing annual debt service (max loan x annual debt constant) | B13: =B10*B5 -> 409455.49
A14: Sizing DSCR (UW NCF / sizing annual debt service) | B14: =Underwriting!B19/B13 -> 1.3178923
A15: Sizing debt yield (UW NOI before reserves / max loan) | B15: =Underwriting!B17/B10 -> 0.10769231
A16: LTV at maximum loan | B16: =B10/Underwriting!B22 -> 0.65
A18: Contract rate | B18: =Assumptions!B9 -> 0.0625
A19: First-year contractual debt service (IO months observed) | B19: =IF(Assumptions!B14>=12,B10*B18,Assumptions!B14*B10*B18/12+(12-Assumptions!B14)*(-PMT(B18/12,B4,1)*B10)) -> 400033.15
A20: First-year DSCR on UW NCF at contract rate | B20: =Underwriting!B19/B19 -> 1.3489338
A21: Monthly contractual payment at contract rate | B21: =-PMT(B18/12,B4,B10) -> 33336.096
A22: Difference: sizing debt service less first-year contractual debt service | B22: =B13-B19 -> 9422.3386
A24: IO period is 0 months, so first-year contractual debt service is fully amortizing at the 6.25% contract rate, while sizing uses the 6.50% sizing rate.

Sheet Sources and Uses
A1: Sources and uses at maximum loan
A3: Sources | B3: Amount
A4: New first mortgage (maximum loan) | B4: ='Loan Sizing'!B10 -> 5053455.1
A5: Borrower cash in (if required) | B5: =MAX(0,-(B4-Assumptions!B20-Assumptions!B18*B4-Assumptions!B19)) -> 0
A6: Total sources | B6: =B4+B5 -> 5053455.1
A8: Uses
A9: Existing debt payoff | B9: =Assumptions!B20 -> 3400000
A10: Origination fee (1.00% of initial principal) | B10: =Assumptions!B18*B4 -> 50534.551
A11: Fixed closing costs | B11: =Assumptions!B19 -> 48000
A12: Net cash to borrower (cash-out) | B12: =MAX(0,B4-B9-B10-B11) -> 1554920.5
A13: Total uses | B13: =SUM(B9:B12) -> 5053455.1
A15: Net cash to (from) borrower; negative = cash in | B15: =B4-Assumptions!B20-Assumptions!B18*B4-Assumptions!B19 -> 1554920.5
A17: No fee capitalization, interest reserve, holdback or earn-out is assumed (Lender-Terms.pdf p.1).

Sheet Sensitivity
A1: Sensitivity | EGI -5%, cap rate +50 bps, and combined EGI -5% with sizing rate +100 bps
A3: Line | B3: Base case | C3: EGI -5% | D3: Cap rate +50 bps | E3: Combined: EGI -5% and rate +100 bps
A4: EGI factor | B4: 1 | C4: =Assumptions!B25 -> 0.95 | D4: 1 | E4: =Assumptions!B25 -> 0.95
A5: Cap rate | B5: =Assumptions!B8 -> 0.07 | C5: =Assumptions!B8 -> 0.07 | D5: =Assumptions!B8+Assumptions!B24 -> 0.075 | E5: =Assumptions!B8 -> 0.07
A6: Sizing rate | B6: ='Loan Sizing'!B3 -> 0.065 | C6: ='Loan Sizing'!B3 -> 0.065 | D6: ='Loan Sizing'!B3 -> 0.065 | E6: ='Loan Sizing'!B3+0.01 -> 0.075
A7: EGI | B7: =Underwriting!$B$7*B4 -> 768144 | C7: =Underwriting!$B$7*C4 -> 729736.8 | D7: =Underwriting!$B$7*D4 -> 768144 | E7: =Underwriting!$B$7*E4 -> 729736.8
A8: Operating expenses other than management fee | B8: =Assumptions!$B$34 -> 193200 | C8: =Assumptions!$B$34 -> 193200 | D8: =Assumptions!$B$34 -> 193200 | E8: =Assumptions!$B$34 -> 193200
A9: Management fee (recomputed minimum) | B9: =MAX(Assumptions!$B$23,Assumptions!$B$22*B7) -> 30725.76 | C9: =MAX(Assumptions!$B$23,Assumptions!$B$22*C7) -> 29189.472 | D9: =MAX(Assumptions!$B$23,Assumptions!$B$22*D7) -> 30725.76 | E9: =MAX(Assumptions!$B$23,Assumptions!$B$22*E7) -> 29189.472
A10: NOI before reserves | B10: =B7-B8-B9 -> 544218.24 | C10: =C7-C8-C9 -> 507347.33 | D10: =D7-D8-D9 -> 544218.24 | E10: =E7-E8-E9 -> 507347.33
A11: Replacement reserves | B11: =Underwriting!$B$18 -> 4600 | C11: =Underwriting!$B$18 -> 4600 | D11: =Underwriting!$B$18 -> 4600 | E11: =Underwriting!$B$18 -> 4600
A12: NCF after reserves | B12: =B10-B11 -> 539618.24 | C12: =C10-C11 -> 502747.33 | D12: =D10-D11 -> 539618.24 | E12: =E10-E11 -> 502747.33
A13: Indicative value | B13: =B10/B5 -> 7774546.3 | C13: =C10/C5 -> 7247819 | D13: =D10/D5 -> 7256243.2 | E13: =E10/E5 -> 7247819
A14: Annual debt constant at scenario sizing rate | B14: =12*-PMT(B6/12,Assumptions!$B$13,1) -> 0.081024859 | C14: =12*-PMT(C6/12,Assumptions!$B$13,1) -> 0.081024859 | D14: =12*-PMT(D6/12,Assumptions!$B$13,1) -> 0.081024859 | E14: =12*-PMT(E6/12,Assumptions!$B$13,1) -> 0.088678941
A15: LTV limit | B15: =Assumptions!$B$15*B13 -> 5053455.1 | C15: =Assumptions!$B$15*C13 -> 4711082.3 | D15: =Assumptions!$B$15*D13 -> 4716558.1 | E15: =Assumptions!$B$15*E13 -> 4711082.3
A16: DSCR limit | B16: =(B12/Assumptions!$B$16)/B14 -> 5327927.7 | C16: =(C12/Assumptions!$B$16)/C14 -> 4963882.3 | D16: =(D12/Assumptions!$B$16)/D14 -> 5327927.7 | E16: =(E12/Assumptions!$B$16)/E14 -> 4535438.2
A17: Debt yield limit | B17: =B10/Assumptions!$B$17 -> 6046869.3 | C17: =C10/Assumptions!$B$17 -> 5637192.5 | D17: =D10/Assumptions!$B$17 -> 6046869.3 | E17: =E10/Assumptions!$B$17 -> 5637192.5
A18: Maximum loan | B18: =MIN(B15:B17) -> 5053455.1 | C18: =MIN(C15:C17) -> 4711082.3 | D18: =MIN(D15:D17) -> 4716558.1 | E18: =MIN(E15:E17) -> 4535438.2
A19: Binding constraint | B19: =IF(B18=B16,"DSCR",IF(B18=B15,"LTV","Debt yield")) -> LTV | C19: =IF(C18=C16,"DSCR",IF(C18=C15,"LTV","Debt yield")) -> LTV | D19: =IF(D18=D16,"DSCR",IF(D18=D15,"LTV","Debt yield")) -> LTV | E19: =IF(E18=E16,"DSCR",IF(E18=E15,"LTV","Debt yield")) -> DSCR
A20: Change in maximum loan vs base | C20: =C18-$B$18 -> -342372.75 | D20: =D18-$B$18 -> -336897.01 | E20: =E18-$B$18 -> -518016.84
A22: Per plan p.2: in the combined downside the cap rate is unchanged; the cap-rate sensitivity (+50 bps) is run separately.

Sheet Map
A1: Input and output location map
A3: Item | B3: Cell | C3: Description
A4: INPUT cap_rate | B4: Assumptions!B8 | C4: Valuation cap rate; drives value and LTV limit
A5: INPUT sizing_rate_increment | B5: Assumptions!B11 | C5: Added to MAX(contract rate, 6.50% floor) in Assumptions!B12
A6: INPUT egi_gross_potential_rent | B6: Assumptions!B5 | C6: Underwritten gross potential base rent; loss % held constant
A7: INPUT egi_other_income | B7: Assumptions!B7 | C7: Other income / recoveries added after revenue loss
A8: INPUT revenue loss % | B8: Assumptions!B6
A9: INPUT contract rate | B9: Assumptions!B9
A10: INPUT amortization months | B10: Assumptions!B13
A11: INPUT IO months | B11: Assumptions!B14
A12: INPUT cap-rate sensitivity increment | B12: Assumptions!B24
A13: INPUT EGI stress factor | B13: Assumptions!B25
A14: OUTPUT uw_egi | B14: Underwriting!B7
A15: OUTPUT uw_noi_before_reserves | B15: Underwriting!B17
A16: OUTPUT uw_ncf | B16: Underwriting!B19
A17: OUTPUT capitalization_value | B17: Underwriting!B22
A18: OUTPUT ltv_limit | B18: 'Loan Sizing'!B7
A19: OUTPUT dscr_limit | B19: 'Loan Sizing'!B8
... A28: OUTPUT T12 NOI before reserves / NCF | B28: 'T12 Historical'!B19 / B21
