Workbook

Sheet Assumptions
B1: Hawthorn Center | Editable underwriting assumptions
B2: As of 2026-08-31 | fictional packet | USD
B4: Item | C4: Value | D4: Source
B6: Capitalization rate (EDITABLE) | C6: 0.0625 | D6: Lender-Terms.pdf p.1 Valuation
B7: Maximum LTV | C7: 0.625 | D7: Lender-Terms.pdf p.1 LTV
B8: Minimum DSCR (NCF after reserves) | C8: 1.25 | D8: Lender-Terms.pdf p.1 DSCR
B9: Minimum debt yield (NOI before reserves) | C9: 0.09 | D9: Lender-Terms.pdf p.1 Debt yield
B10: Contract rate (fixed) | C10: 0.0635 | D10: Lender-Terms.pdf p.1 Contract rate
B11: Sizing rate input / floor (EDITABLE) | C11: 0.0635 | D11: Sizing = MAX(contract, floor)
B12: Amortization (years) | C12: 25
B13: Interest-only period (months) | C13: 0
B14: Origination fee (% of principal) | C14: 0.008
B15: Fixed closing costs | C15: 52000
B16: Existing debt payoff | C16: 4200000 | D16: Property-and-Plan.pdf p.1
B17: Gross potential base rent (EDITABLE) | C17: 780000 | D17: Property-and-Plan.pdf p.2
B18: Combined revenue loss % | C18: 0.05
B19: Other income / recoveries (EDITABLE) | C19: 180000
B20: Management fee % of EGI | C20: 0.04
B21: T12 actual management fee (floor) | C21: 18000
B22: Replacement reserves per SF | C22: 0.15
B23: Total rentable SF (rent roll) | C23: ='Rent Roll'!C16 -> 28800
B24: EGI stress factor | C24: 0.95
B25: Sizing rate shock (downside) | C25: 0.01
B26: Cap rate shock (separate case) | C26: 0.005

Sheet Rent Roll
A1: Contractual rent roll as of 2026-08-31
A2: Source: Rent-Roll.xlsx rows 7-16; premises 101 reconciled to Lease-File.pdf p.1
A3: Unit | B3: Tenant | C3: Area SF | D3: Status | E3: Monthly rent | F3: Market rent | G3: Expiry
A4: 101 | B4: Tenant A LLC | C4: 1400 | D4: Occupied | E4: 3000 | F4: 3000 | G4: 2029-08-31
A5: 102 | B5: Tenant B LLC | C5: 1800 | D5: Occupied | E5: 4000 | F5: 4000 | G5: 2028-08-31
A6: 103 | B6: Tenant C LLC | C6: 2200 | D6: Occupied | E6: 4900 | F6: 4900 | G6: 2029-08-31
A7: 104 | B7: Tenant D LLC | C7: 2500 | D7: Occupied | E7: 5600 | F7: 5600 | G7: 2030-08-31
A8: 105 | B8: Tenant E LLC | C8: 3000 | D8: Occupied | E8: 6500 | F8: 6500 | G8: 2031-08-31
A9: 106 | B9: Tenant F LLC | C9: 3300 | D9: Occupied | E9: 7400 | F9: 7400 | G9: 2027-08-31
A10: 107 | B10: Tenant G LLC | C10: 3800 | D10: Occupied | E10: 8600 | F10: 8600 | G10: 2028-08-31
A11: 108 | B11: Tenant H LLC | C11: 4200 | D11: Occupied | E11: 9200 | F11: 9200 | G11: 2029-08-31
A12: 109 | B12: Tenant I LLC | C12: 5000 | D12: Occupied | E12: 10800 | F12: 10800 | G12: 2030-08-31
A13: 110 | B13: Vacant | C13: 1600 | D13: Vacant | E13: 0 | F13: 3400 | G13: n/a
A15: Metric | C15: Value
A16: total_area_sf | C16: =SUM(C4:C13) -> 28800
A17: rent_roll_monthly_base | C17: =SUM(E4:E13) -> 60000
A18: space_count | C18: =COUNTA(A4:A13) -> 10
A19: occupied_count | C19: =COUNTIF(D4:D13,"Occupied") -> 9
A20: occupied_area_sf | C20: =SUMIF(D4:D13,"Occupied",C4:C13) -> 27200
A21: occupancy_count_pct | C21: =C19/C18*100 -> 90
A22: occupancy_area_pct | C22: =C20/C16*100 -> 94.444444
A23: effective_monthly_base | C23: =C17 -> 60000
A24: Annualized contractual rent (point in time) | C24: =C23*12 -> 720000
A26: Premises 101 executed lease: $3,000/month, expiry 2029-08-31, deposit $6,000; no amendment or renewal exercise notice supplied, so effective base equals printed base.

Sheet Historical T12
B1: Historical T12 | September 2025 - August 2026 (actual)
B2: Source: T12-Statement.pdf p.2 Annual column. Historical only.
B3: Line | C3: Annual
B4: Gross potential base rent | C4: 759600
B5: Vacancy loss | C5: -40800
B6: Concessions | C6: -22800
B7: Bad debt | C7: -6000
B8: Other income / recoveries | C8: 176400
B9: t12_egi | C9: =SUM(C4:C8) -> 866400
B10: Real estate taxes | C10: 114000
B11: Property insurance | C11: 32400
B12: Utilities | C12: 21600
B13: Repairs and maintenance | C13: 36000
B14: Payroll / contract labor | C14: 24000
B15: Administrative / legal | C15: 18000
B16: Management fee | C16: 18000
B17: t12_operating_expenses | C17: =SUM(C10:C16) -> 264000
B18: t12_noi_before_reserves | C18: =C9-C17 -> 602400
B19: t12_reserves | C19: 11520
B20: t12_ncf (after reserves) | C20: =C18-C19 -> 590880
B22: Below cash flow (not operating expense)
B23: Capital improvements | C23: 74000
B24: Existing loan principal and interest | C24: 294000
B25: Depreciation (noncash) | C25: 180000
B27: The accounting package may call cash flow after reserves 'property NOI'; NOI before reserves and NCF after reserves are shown separately (Property-and-Plan.pdf p.1).

Sheet Underwriting
B1: Underwritten scenario | September 2026 forward (annual)
B2: Source: Property-and-Plan.pdf p.2. Supplied scenario, not a lender-approved forecast.
B3: Line | C3: Annual | D3: Basis
B4: Gross potential base rent | C4: =Assumptions!C17 -> 780000 | D4: Assumptions!C17
B5: Combined revenue loss | C5: =-C4*Assumptions!C18 -> -39000 | D5: 5.00% of gross potential rent
B6: Net rental income | C6: =C4+C5 -> 741000
B7: Other income / recoveries | C7: =Assumptions!C19 -> 180000 | D7: Added after loss
B8: uw_egi | C8: =C6+C7 -> 921000
B9: Real estate taxes | C9: 120000 | D9: Plan underwriting treatment
B10: Property insurance | C10: 34800 | D10: Scenario renewal allowance
B11: Utilities | C11: 21600 | D11: T12 actual
B12: Repairs and maintenance | C12: 36000 | D12: T12 actual; $0 one-time removed
B13: Payroll / contract labor | C13: 24000 | D13: T12 actual
B14: Administrative / legal | C14: 18000 | D14: T12 actual
B15: uw_management_fee | C15: =MAX(Assumptions!C21,Assumptions!C20*C8) -> 36840 | D15: Greater of T12 actual and 4.00% of EGI
B16: uw_operating_expenses (before reserves) | C16: =SUM(C9:C15) -> 291240
B17: uw_noi_before_reserves | C17: =C8-C16 -> 629760
B18: uw_reserves | C18: =Assumptions!C22*Assumptions!C23 -> 4320 | D18: $0.15/SF x rentable SF
B19: uw_ncf (after reserves) | C19: =C17-C18 -> 625440
B20: capitalization_value | C20: =C17/Assumptions!C6 -> 10076160 | D20: NOI before reserves / cap rate
B21: Expense ratio (opex / EGI) | C21: =C16/C8 -> 0.3162215

Sheet Loan Sizing
B1: Loan sizing | LTV, DSCR and debt yield
B2: Source: Lender-Terms.pdf p.1; unrounded intermediates.
B3: Item | C3: Value | D3: Basis
B4: sizing_rate | C4: =MAX(Assumptions!C10,Assumptions!C11) -> 0.0635 | D4: Greater of contract rate and floor
B5: annual_debt_constant | C5: =-PMT(C4/12,Assumptions!C12*12,1)*12 -> 0.079903715 | D5: 12 monthly payments per $1
B6: UW NOI before reserves | C6: =Underwriting!C17 -> 629760
B7: UW NCF after reserves | C7: =Underwriting!C19 -> 625440
B8: ltv_limit | C8: =Assumptions!C7*Underwriting!C20 -> 6297600 | D8: 62.50% x indicative value
B9: dscr_limit | C9: =(C7/Assumptions!C8)/C5 -> 6261936.6 | D9: (NCF / 1.25) / debt constant
B10: debt_yield_limit | C10: =C6/Assumptions!C9 -> 6997333.3 | D10: NOI before reserves / 9.00%
B12: maximum_loan | C12: =MIN(C8,C9,C10) -> 6261936.6
B13: binding_constraint | C13: =IF(C12=C9,"DSCR",IF(C12=C8,"LTV","Debt yield")) -> DSCR
B14: sizing_annual_debt_service | C14: =C12*C5 -> 500352
B15: sizing_dscr | C15: =C7/C14 -> 1.25
B16: sizing_debt_yield | C16: =C6/C12 -> 0.10056953
B17: Implied LTV at maximum loan | C17: =C12/Underwriting!C20 -> 0.62146062
B18: Contract-rate annual debt constant | C18: =-PMT(Assumptions!C10/12,Assumptions!C12*12,1)*12 -> 0.079903715
B19: first_year_debt_service | C19: =C12*Assumptions!C10*(MIN(Assumptions!C13,12)/12)+C12*C18*((12-MIN(Assumptions!C13,12))/12) -> 500352 | D19: IO months at contract rate, balance amortizing
B20: First-year DSCR on UW NCF | C20: =C7/C19 -> 1.25
B22: IO period is 0 months, so year one is 12 amortizing payments at the 6.35% contract rate, which equals the sizing rate.

Sheet Sources and Uses
B1: Sources and uses at maximum loan
B2: Fee: Lender-Terms.pdf p.1; payoff and closing costs: Property-and-Plan.pdf p.1
B3: Item | C3: Amount
B4: SOURCES
B5: New first-mortgage loan | C5: ='Loan Sizing'!C12 -> 6261936.6
B6: Total sources | C6: =C5 -> 6261936.6
B8: USES
B9: Existing debt payoff | C9: =Assumptions!C16 -> 4200000
B10: Origination fee (0.80% of principal) | C10: =Assumptions!C14*C5 -> 50095.493
B11: Fixed closing costs | C11: =Assumptions!C15 -> 52000
B12: cash_to_borrower (negative = cash in) | C12: =C6-SUM(C9:C11) -> 1959841.1
B13: Total uses including distribution | C13: =SUM(C9:C12) -> 6261936.6
B15: No fee capitalization, interest reserve, holdback or earn-out assumed.

Sheet Sensitivity
B1: Sensitivity analysis
B2: Downside: EGI -5% with management recalculated, other expenses and reserves constant; combined case adds +100 bps to sizing rate with cap rate unchanged. Separate case: cap rate +50 bps.
B3: Line | C3: Base case | D3: EGI -5%, rate +100bps | E3: Cap +50 bps
B4: EGI | C4: =Underwriting!C8 -> 921000 | D4: =Underwriting!C8*Assumptions!C24 -> 874950 | E4: =C4 -> 921000
B5: Management fee (recalculated) | C5: =Underwriting!C15 -> 36840 | D5: =MAX(Assumptions!C21,Assumptions!C20*D4) -> 34998 | E5: =C5 -> 36840
B6: Other operating expenses (constant) | C6: =Underwriting!C16-Underwriting!C15 -> 254400 | D6: =C6 -> 254400 | E6: =C6 -> 254400
B7: Total operating expenses | C7: =C5+C6 -> 291240 | D7: =D5+D6 -> 289398 | E7: =E5+E6 -> 291240
B8: NOI before reserves | C8: =C4-C7 -> 629760 | D8: =D4-D7 -> 585552 | E8: =E4-E7 -> 629760
B9: Replacement reserves | C9: =Underwriting!C18 -> 4320 | D9: =C9 -> 4320 | E9: =C9 -> 4320
B10: NCF after reserves | C10: =C8-C9 -> 625440 | D10: =D8-D9 -> 581232 | E10: =E8-E9 -> 625440
B11: Cap rate applied | C11: =Assumptions!C6 -> 0.0625 | D11: =Assumptions!C6 -> 0.0625 | E11: =Assumptions!C6+Assumptions!C26 -> 0.0675
B12: Indicative value | C12: =C8/C11 -> 10076160 | D12: =D8/D11 -> 9368832 | E12: =E8/E11 -> 9329777.8
B13: Sizing rate applied | C13: ='Loan Sizing'!C4 -> 0.0635 | D13: ='Loan Sizing'!C4+Assumptions!C25 -> 0.0735 | E13: ='Loan Sizing'!C4 -> 0.0635
B14: Annual debt constant | C14: =-PMT(C13/12,Assumptions!C12*12,1)*12 -> 0.079903715 | D14: =-PMT(D13/12,Assumptions!C12*12,1)*12 -> 0.087511438 | E14: =-PMT(E13/12,Assumptions!C12*12,1)*12 -> 0.079903715
B15: LTV limit | C15: =Assumptions!C7*C12 -> 6297600 | D15: =Assumptions!C7*D12 -> 5855520 | E15: =Assumptions!C7*E12 -> 5831111.1
B16: DSCR limit | C16: =(C10/Assumptions!C8)/C14 -> 6261936.6 | D16: =(D10/Assumptions!C8)/D14 -> 5313426.6 | E16: =(E10/Assumptions!C8)/E14 -> 6261936.6
B17: Debt yield limit | C17: =C8/Assumptions!C9 -> 6997333.3 | D17: =D8/Assumptions!C9 -> 6506133.3 | E17: =E8/Assumptions!C9 -> 6997333.3
B18: Maximum loan | C18: =MIN(C15,C16,C17) -> 6261936.6 | D18: =MIN(D15,D16,D17) -> 5313426.6 | E18: =MIN(E15,E16,E17) -> 5831111.1
B19: Binding constraint | C19: =IF(C18=C16,"DSCR",IF(C18=C15,"LTV","Debt yield")) -> DSCR | D19: =IF(D18=D16,"DSCR",IF(D18=D15,"LTV","Debt yield")) -> DSCR | E19: =IF(E18=E16,"DSCR",IF(E18=E15,"LTV","Debt yield")) -> LTV
B20: Change vs. base maximum loan | D20: =D18-C18 -> -948510.01 | E20: =E18-C18 -> -430825.5

Sheet Input-Output Map
B1: Reviewer guide | editable inputs and key outputs
B3: Editable input | C3: Location | D3: Effect
B4: Capitalization rate | C4: Assumptions!C6 | D4: Value, LTV limit, cap sensitivity
B5: Sizing interest rate | C5: Assumptions!C11 | D5: Debt constant, DSCR limit
B6: EGI: gross potential base rent | C6: Assumptions!C17 | D6: EGI, management fee, NOI, all limits
B7: EGI: other income | C7: Assumptions!C19 | D7: EGI and downstream outputs
B8: Other assumptions | C8: Assumptions!C7:C26; Underwriting!C9:C14 | D8: Tests, fees, reserves, expenses
B10: Key output | C10: Location
B11: uw_egi | C11: Underwriting!C8
B12: uw_management_fee | C12: Underwriting!C15
B13: uw_operating_expenses | C13: Underwriting!C16
B14: uw_noi_before_reserves | C14: Underwriting!C17
B15: uw_reserves / uw_ncf | C15: Underwriting!C18 / C19
B16: capitalization_value | C16: Underwriting!C20
B17: annual_debt_constant | C17: Loan Sizing!C5
B18: ltv_limit / dscr_limit / debt_yield_limit | C18: Loan Sizing!C8 / C9 / C10
B19: maximum_loan / binding_constraint | C19: Loan Sizing!C12 / C13
B20: sizing DS / DSCR / debt yield | C20: Loan Sizing!C14 / C15 / C16
B21: first_year_debt_service | C21: Loan Sizing!C19
... B25: Rent roll metrics | C25: 'Rent Roll'!C16:C24
