Workbook

Sheet Inputs
A1: Maple Crossing – Inputs
A3: Gross Potential Rent (annual) | B3: 818700
A4: Other Income per unit (annual) | B4: 350
A5: Total units | B5: 10
A6: Economic loss % | B6: 0.05
A7: Real estate tax | B7: 85964
A8: Insurance expense | B8: 28655
A9: Other recurring opex | B9: 114618
A10: Management % of EGI | B10: 0.03
A11: Replacement reserve per unit | B11: 300
A12: Cap rate | B12: 0.0725
A13: Sizing rate (greater of note & floor) | B13: 0.065
A14: Note rate | B14: 0.065
... A22: Existing payoff | B22: 4300000

Sheet UW
A1: Underwriting
A3: Gross Potential Rent | B3: =Inputs!B3 -> 818700
A4: Other income (annual) | B4: =Inputs!B4*Inputs!B5 -> 3500
A5: Gross Revenue | B5: =B3+B4 -> 822200
A6: Less: Economic loss (5%) | B6: =-B5*Inputs!B6 -> -41110
A7: Effective Gross Income (EGI) | B7: =B5+B6 -> 781090
A9: Real estate tax | B9: =Inputs!B7 -> 85964
A10: Insurance | B10: =Inputs!B8 -> 28655
A11: Other recurring opex | B11: =Inputs!B9 -> 114618
A12: Management fee (3% EGI) | B12: =B7*Inputs!B10 -> 23432.7
A13: Total operating expenses | B13: =SUM(B9:B12) -> 252669.7
A15: NOI (before reserves) | B15: =B7-B13 -> 528420.3
A16: Replacement reserves | B16: =Inputs!B11*Inputs!B5 -> 3000
A17: NCF (after reserves) | B17: =B15-B16 -> 525420.3
A19: Capitalization value (NOI/Cap) | B19: =B15/Inputs!B12 -> 7288555.9

Sheet Debt
A1: Debt sizing & Sources/Uses
A3: Sizing rate | B3: =MAX(Inputs!B14,Inputs!B15) -> 0.065
A4: Annual DS per $1 (30yr amort) | B4: =PMT(B3/12,Inputs!B16,-1)*12 -> 0.075848163
A6: LTV-constrained loan | B6: =UW!B19*Inputs!B17 -> 4737561.3
A7: DSCR-constrained loan | B7: =UW!B17/(Inputs!B18*B4) -> 5541811.8
A8: Debt-yield-constrained loan | B8: =UW!B17/Inputs!B19 -> 5838003.3
A10: Maximum loan (min of tests) | B10: =MIN(B6:B8) -> 4737561.3
A12: Sources / Uses
A13: Loan proceeds | B13: =B10 -> 4737561.3
A14: Existing payoff | B14: =Inputs!B22 -> 4300000
A15: Origination fee (1%) | B15: =B10*Inputs!B20 -> 47375.613
A16: Closing costs | B16: =Inputs!B21 -> 45000
A17: Net cash-out (proceeds - payoff - fee - costs) | B17: =B13-B14-B15-B16 -> 345185.7
A19: Sanity: DSCR at max loan | B19: =UW!B17/(B10*B4) -> 1.4622005
A20: Sanity: Debt yield at max loan | B20: =UW!B17/B10 -> 0.11090522
A21: Sanity: LTV at max loan | B21: =B10/UW!B19 -> 0.65

Sheet Sensitivity
A1: Capitalization value sensitivity (NOI / Cap rate)
A3: Cap Rate \ NOI | B3: =UW!B15*0.95 -> 501999.28 | C3: =UW!B15 -> 528420.3 | D3: =UW!B15*1.05 -> 554841.31
A4: 0.0625 | B4: =B$3/$A4 -> 8031988.6 | C4: =C$3/$A4 -> 8454724.8 | D4: =D$3/$A4 -> 8877461
A5: 0.0675 | B5: =B$3/$A5 -> 7437026.4 | C5: =C$3/$A5 -> 7828448.9 | D5: =D$3/$A5 -> 8219871.3
A6: 0.0725 | B6: =B$3/$A6 -> 6924128.1 | C6: =C$3/$A6 -> 7288555.9 | D6: =D$3/$A6 -> 7652983.7
A9: Max loan sensitivity to sizing rate
A11: Sizing rate | B11: LTV loan | C11: DSCR loan | D11: DY loan | E11: Max loan
A12: 0.06 | B12: =UW!$B$19*Inputs!$B$17 -> 4737561.3 | C12: =UW!$B$17/(Inputs!$B$18*(PMT(A12/12,Inputs!$B$16,-1)*12)) -> 5842380 | D12: =UW!$B$17/Inputs!$B$19 -> 5838003.3 | E12: =MIN(B12:D12) -> 4737561.3
A13: 0.065 | B13: =UW!$B$19*Inputs!$B$17 -> 4737561.3 | C13: =UW!$B$17/(Inputs!$B$18*(PMT(A13/12,Inputs!$B$16,-1)*12)) -> 5541811.8 | D13: =UW!$B$17/Inputs!$B$19 -> 5838003.3 | E13: =MIN(B13:D13) -> 4737561.3
A14: 0.07 | B14: =UW!$B$19*Inputs!$B$17 -> 4737561.3 | C14: =UW!$B$17/(Inputs!$B$18*(PMT(A14/12,Inputs!$B$16,-1)*12)) -> 5264976.5 | D14: =UW!$B$17/Inputs!$B$19 -> 5838003.3 | E14: =MIN(B14:D14) -> 4737561.3
A15: 0.075 | B15: =UW!$B$19*Inputs!$B$17 -> 4737561.3 | C15: =UW!$B$17/(Inputs!$B$18*(PMT(A15/12,Inputs!$B$16,-1)*12)) -> 5009624.3 | D15: =UW!$B$17/Inputs!$B$19 -> 5838003.3 | E15: =MIN(B15:D15) -> 4737561.3

Sheet RentRoll
A1: Certified Rent Roll (as of 2026-08-31), with lease-001 amendment applied
A3: Suite | B3: Type | C3: Group | D3: Area SF | E3: Status | F3: Contractual Monthly | G3: Certified Monthly (pre-amend) | H3: Expiration
A4: 001 | B4: Small | C4: A | D4: 3080 | E4: active | F4: 7000 | G4: 6650 | H4: 2029-08-31
A5: 002 | B5: Standard | C5: B | D5: 3200 | E5: active | F5: 6800 | G5: 6800 | H5: 2029-08-31
A6: 003 | B6: Large | C6: C | D6: 3410 | E6: active | F6: 7075 | G6: 7075 | H6: 2029-08-31
A7: 004 | B7: Small | C7: A | D7: 3080 | E7: active | F7: 6650 | G7: 6650 | H7: 2029-08-31
A8: 005 | B8: Standard | C8: B | D8: 3200 | E8: active | F8: 6800 | G8: 6800 | H8: 2029-08-31
A9: 006 | B9: Large | C9: C | D9: 3410 | E9: active | F9: 7075 | G9: 7075 | H9: 2029-08-31
A10: 007 | B10: Small | C10: A | D10: 3080 | E10: active | F10: 6650 | G10: 6650 | H10: 2029-08-31
A11: 008 | B11: Standard | C11: B | D11: 3200 | E11: active | F11: 6800 | G11: 6800 | H11: 2029-08-31
A12: 009 | B12: Large | C12: C | D12: 3410 | E12: active | F12: 7075 | G12: 7075 | H12: 2029-08-31
A13: 010 | B13: Small | C13: A | D13: 3080 | E13: vacant | F13: 0 | G13: 6650 | H13: 2029-08-31
A15: Totals | D15: =SUM(D4:D13) -> 32150 | F15: =SUM(F4:F13) -> 61925 | G15: =SUM(G4:G13) -> 68225
A17: Occupied units (active) | B17: =COUNTIF(E4:E13,"active") -> 9
A18: Occupied area SF | B18: =SUMIF(E4:E13,"active",D4:D13) -> 29070
A19: In-place annual rent (post-amend) | B19: =SUMIF(E4:E13,"active",F4:F13)*12 -> 743100
A20: GPR (all suites × 12, certified pre-amend) | B20: =SUM(G4:G13)*12 -> 818700

Sheet Sources
A1: Source Register
A3: Item | B3: Value | C3: Source file | D3: Location
A4: Certified rent roll date | B4: 2026-08-31 | C4: rent-roll-certified.xlsx | D4: B2
A5: Archive rent roll date | B5: 2026-06-30 | C5: rent-roll-archive.xlsx | D5: B2
A6: Suite 001 pre-amend rent | B6: 6650 | C6: lease-001.pdf | D6: p.1
A7: Amendment (+$350) executed | B7: 2026-07-20 | C7: lease-correspondence.pdf | D7: p.1
A8: Manager 9/10 leased (incl pending) | B8: note | C8: manager-cover.pdf | D8: p.1
A9: T12 collections | B9: 736830 | C9: operating-statement.pdf | D9: p.1
A10: T12 taxes | B10: 85964 | C10: operating-statement.pdf | D10: p.1
A11: T12 insurance | B11: 28655 | C11: operating-statement.pdf | D11: p.1
A12: T12 other opex | B12: 114618 | C12: operating-statement.pdf | D12: p.1
A13: Reported NOI (T12) | B13: 507593 | C13: operating-statement.pdf | D13: p.1
A14: GL insurance policy limit | B14: 2000000 | C14: insurance.pdf | D14: p.1
A15: Cap rate & UW assumptions | B15: per instructions | C15: underwriting-instructions.pdf | D15: p.1
A16: Diligence status | B16: pending routine | C16: diligence-status.pdf | D16: p.1
