Workbook

Sheet Inputs
A1: BEACON PLAZA — UNDERWRITING INPUTS
A2: Evaluation date | B2: 2026-08-31 | D2: Source: manager cover / certified rent roll
A3: Legend | B3: Blue = input | C3: Yellow fill = key input | D3: Black = formula | Green = cross-sheet link
A5: LOAN CONSTRAINTS & RATES
A6: ltv_limit | B6: 0.6 | D6: Underwriting instructions
A7: dscr_limit | B7: 1.25 | D7: Minimum DSCR — instructions
A8: debt_yield_limit | B8: 0.09 | D8: Minimum NCF debt yield — instructions
A9: note_rate | B9: 0.0675 | D9: Note rate — instructions
A10: rate_floor | B10: 0.06 | D10: UW rate floor — instructions
A11: amort_years | B11: 30 | D11: Amortization years — instructions
A12: origination_fee_pct | B12: 0.01 | D12: 1% of sized loan — instructions
A13: closing_costs | B13: 45000 | D13: Closing costs — instructions
A14: existing_payoff | B14: 6500000 | D14: Existing payoff — instructions
A15: SIZING RATE (computed — surfaced as required output)
A16: sizing_rate | B16: =MAX(B9,B10) | D16: MAX(note_rate, rate_floor) — instructions: size on the greater rate
A18: UNDERWRITING ASSUMPTIONS
A19: economic_loss_pct | B19: 0.05 | D19: Economic loss — instructions
A20: other_income_per_unit | B20: 350 | D20: $350 / unit / year — instructions
A21: management_fee_pct | B21: 0.03 | D21: 3% of EGI — instructions
A22: replacement_reserve_per_unit | B22: 300 | D22: $300 / unit / year — instructions
A23: cap_rate | B23: 0.08 | D23: Capitalize NOI before reserves — instructions
A24: uw_tax | B24: 169974 | D24: Real estate tax — instructions & operating stmt
A25: uw_insurance | B25: 56658 | D25: Insurance expense — instructions & operating stmt
A26: uw_other_recurring_opex | B26: 226632 | D26: Other recurring opex — instructions & operating stmt
A27: total_units | B27: 12 | D27: Certified rent roll

Sheet Rent Roll
A1: BEACON PLAZA — CERTIFIED RENT ROLL (AS OF 2026-08-31)
A3: Suite | B3: Unit type | C3: Group | D3: Area SF | E3: Possession | F3: Monthly rent (certified) | G3: Lease expiration | H3: Monthly rent for GPR (pre-001 amend.) | I3: Annual in-place rent | J3: Near-term rollover?
A4: 001 | B4: Small suite | C4: A | D4: 5380 | E4: active | F4: 11050 | G4: 2027-02-28 | H4: 10975 | I4: =IF(E4="active",F4*12,0) | J4: =IF(AND(E4="active",DATEVALUE(G4)<DATEVALUE("2027-08-31")),"YES","")
A5: 002 | B5: Standard suite | C5: B | D5: 5500 | E5: active | F5: 11200 | G5: 2029-08-31 | H5: 11200 | I5: =IF(E5="active",F5*12,0) | J5: =IF(AND(E5="active",DATEVALUE(G5)<DATEVALUE("2027-08-31")),"YES","")
A6: 003 | B6: Large suite | C6: C | D6: 5710 | E6: active | F6: 11475 | G6: 2029-08-31 | H6: 11475 | I6: =IF(E6="active",F6*12,0) | J6: =IF(AND(E6="active",DATEVALUE(G6)<DATEVALUE("2027-08-31")),"YES","")
A7: 004 | B7: Small suite | C7: A | D7: 5380 | E7: active | F7: 11050 | G7: 2029-08-31 | H7: 10975 | I7: =IF(E7="active",F7*12,0) | J7: =IF(AND(E7="active",DATEVALUE(G7)<DATEVALUE("2027-08-31")),"YES","")
A8: 005 | B8: Standard suite | C8: B | D8: 5500 | E8: active | F8: 11200 | G8: 2029-08-31 | H8: 11200 | I8: =IF(E8="active",F8*12,0) | J8: =IF(AND(E8="active",DATEVALUE(G8)<DATEVALUE("2027-08-31")),"YES","")
A9: 006 | B9: Large suite | C9: C | D9: 5710 | E9: active | F9: 11475 | G9: 2029-08-31 | H9: 11475 | I9: =IF(E9="active",F9*12,0) | J9: =IF(AND(E9="active",DATEVALUE(G9)<DATEVALUE("2027-08-31")),"YES","")
A10: 007 | B10: Small suite | C10: A | D10: 5380 | E10: active | F10: 11050 | G10: 2029-08-31 | H10: 10975 | I10: =IF(E10="active",F10*12,0) | J10: =IF(AND(E10="active",DATEVALUE(G10)<DATEVALUE("2027-08-31")),"YES","")
A11: 008 | B11: Standard suite | C11: B | D11: 5500 | E11: active | F11: 11200 | G11: 2029-08-31 | H11: 11200 | I11: =IF(E11="active",F11*12,0) | J11: =IF(AND(E11="active",DATEVALUE(G11)<DATEVALUE("2027-08-31")),"YES","")
A12: 009 | B12: Large suite | C12: C | D12: 5710 | E12: active | F12: 11475 | G12: 2029-08-31 | H12: 11475 | I12: =IF(E12="active",F12*12,0) | J12: =IF(AND(E12="active",DATEVALUE(G12)<DATEVALUE("2027-08-31")),"YES","")
A13: 010 | B13: Small suite | C13: A | D13: 5380 | E13: pending | F13: 11050 | G13: 2029-08-31 | H13: 10975 | I13: =IF(E13="active",F13*12,0) | J13: =IF(AND(E13="active",DATEVALUE(G13)<DATEVALUE("2027-08-31")),"YES","")
A14: 011 | B14: Standard suite | C14: B | D14: 5500 | E14: vacant | F14: 11200 | G14: 2029-08-31 | H14: 11200 | I14: =IF(E14="active",F14*12,0) | J14: =IF(AND(E14="active",DATEVALUE(G14)<DATEVALUE("2027-08-31")),"YES","")
A15: 012 | B15: Large suite | C15: C | D15: 5710 | E15: vacant | F15: 11475 | G15: 2029-08-31 | H15: 11475 | I15: =IF(E15="active",F15*12,0) | J15: =IF(AND(E15="active",DATEVALUE(G15)<DATEVALUE("2027-08-31")),"YES","")
A16: TOTAL | D16: =SUM(D4:D15) | F16: =SUM(F4:F15) | H16: =SUM(H4:H15) | I16: =SUM(I4:I15)
A18: Notes:
A19: Group mapping (manager cover): A = Small suite, B = Standard suite, C = Large suite.
A20: Physical occupancy = "active" only. "Pending" is not in possession (manager cover; certified rent roll note).
A21: "Monthly rent for GPR" strips the Suite 001 amendment ($10,975 pre-amendment on archive roll); UW instructions require the pre-amendment monthly for GPR.
A22: Near-term rollover horizon = active leases expiring on or before 2027-08-31 (12 months from evaluation date).

Sheet Underwriting
A1: BEACON PLAZA — RECONCILED UNDERWRITING
A3: INCOME
A4: gross_potential_rent | B4: =SUM('Rent Roll'!H4:H15)*12 | D4: All-suite monthly rent (pre-001 amendment) × 12 — instructions
A5: Economic loss (vacancy/credit) | B5: =-Underwriting!$B$4*Inputs!$B$19 | D5: 5% of GPR — instructions
A6: Effective rental income | B6: =Underwriting!$B$4+Underwriting!$B$5
A7: Other income ($350 × total units) | B7: =Inputs!$B$20*Inputs!$B$27 | D7: $350 per unit/suite — instructions (reimbursement already included, not doubled)
A8: uw_egi | B8: =Underwriting!$B$6+Underwriting!$B$7
A10: OPERATING EXPENSES
A11: uw_tax | B11: =Inputs!$B$24
A12: uw_insurance | B12: =Inputs!$B$25
A13: Other recurring opex | B13: =Inputs!$B$26
A14: Management fee (3% of EGI) | B14: =Underwriting!$B$8*Inputs!$B$21
A15: uw_operating_expenses | B15: =Underwriting!$B$11+Underwriting!$B$12+Underwriting!$B$13+Underwriting!$B$14
A17: NOI / NCF
A18: uw_noi (before reserves) | B18: =Underwriting!$B$8-Underwriting!$B$15
A19: Replacement reserves ($300 × units) | B19: =Inputs!$B$22*Inputs!$B$27
A20: uw_ncf (after reserves) | B20: =Underwriting!$B$18-Underwriting!$B$19
A22: VALUATION
A23: capitalization_value (NOI ÷ cap_rate) | B23: =Underwriting!$B$18/Inputs!$B$23
A25: DEBT SIZING
A26: Sizing rate (MAX of note vs floor) | B26: =Inputs!$B$16
A27: Monthly rate | B27: =Underwriting!$B$26/12
A28: Amort periods (months) | B28: =Inputs!$B$11*12
A29: Annual debt service constant per $1 | B29: =12*(Underwriting!$B$27*(1+Underwriting!$B$27)^Underwriting!$B$28)/((1+Underwriting!$B$27)^Underwriting!$B$28-1)
A30: LTV-constrained loan | B30: =Underwriting!$B$23*Inputs!$B$6
A31: DSCR-constrained loan (NCF basis) | B31: =Underwriting!$B$20/(Inputs!$B$7*Underwriting!$B$29)
A32: Debt yield-constrained loan (NCF basis) | B32: =Underwriting!$B$20/Inputs!$B$8
A33: maximum_loan (binding constraint) | B33: =MIN(Underwriting!$B$30,Underwriting!$B$31,Underwriting!$B$32)
A34: Binding constraint | B34: =IF(Underwriting!$B$33=Underwriting!$B$30,"LTV",IF(Underwriting!$B$33=Underwriting!$B$31,"DSCR","Debt Yield"))
A36: SOURCES & USES
A37: Origination fee (1% of sized loan) | B37: =Underwriting!$B$33*Inputs!$B$12
A38: Closing costs | B38: =Inputs!$B$13
A39: Existing loan payoff | B39: =Inputs!$B$14
A40: net_cash_out (negative = equity required) | B40: =Underwriting!$B$33-Underwriting!$B$37-Underwriting!$B$38-Underwriting!$B$39
A42: CREDIT METRICS AT SIZED LOAN
A43: LTV at sized loan | B43: =Underwriting!$B$33/Underwriting!$B$23
A44: DSCR at sized loan (NCF) | B44: =Underwriting!$B$20/(Underwriting!$B$33*Underwriting!$B$29)
A45: Debt yield at sized loan (NCF) | B45: =Underwriting!$B$20/Underwriting!$B$33

Sheet Historical vs UW
A1: HISTORICAL T-12 (2025-09-01 → 2026-08-31) vs UNDERWRITTEN
A3: Line item | B3: Historical T-12 | C3: Underwritten | D3: Δ | E3: Notes
A4: Rental / ancillary collections (hist.) vs UW EGI | B4: 1456920 | C4: =Underwriting!$B$8 | D4: =C4-B4 | E4: Historical = cash collections; UW EGI = GPR pre-amendment × (1 - loss) + other income.
A5: Real estate tax | B5: -169974 | C5: =-Underwriting!$B$11 | D5: =C5-B5 | E5: Same figure — instructions
A6: Insurance expense | B6: -56658 | C6: =-Underwriting!$B$12 | D6: =C6-B6 | E6: Same figure — instructions
A7: Other recurring opex | B7: -226632 | C7: =-Underwriting!$B$13 | D7: =C7-B7 | E7: Same figure — instructions
A8: Roof replacement (in ledger) | B8: 0 | C8: 0 | D8: =C8-B8 | E8: Capital improvement; not in recurring opex — operating statement
A9: Management fee (UW only) | B9: 0 | C9: =-Underwriting!$B$14 | D9: =C9-B9 | E9: Historical stmt has no mgmt fee; UW adds 3% of EGI
A10: Replacement reserves (UW only) | B10: 0 | C10: =-Underwriting!$B$19 | D10: =C10-B10 | E10: Historical is cash; UW adds $300/unit
A11: Reported historical NOI (as stated) | B11: 1003656 | E11: Operating statement, 'Reported NOI' line. Cash basis, no mgmt or reserves.
A12: uw_noi (before reserves) | C12: =Underwriting!$B$18
A13: uw_ncf (after reserves) | C13: =Underwriting!$B$20

Sheet Occupancy & Mix
A1: OCCUPANCY & UNIT MIX (as of 2026-08-31, certified roll)
A3: Metric | B3: Type A (Small) | C3: Type B (Standard) | D3: Type C (Large) | E3: Total | F3: Notes
A4: Units in group | B4: =COUNTIF('Rent Roll'!C4:C15,"A") | C4: =COUNTIF('Rent Roll'!C4:C15,"B") | D4: =COUNTIF('Rent Roll'!C4:C15,"C") | E4: =SUM(B4:D4)
A5: Occupied (active) in group | B5: =COUNTIFS('Rent Roll'!C4:C15,"A",'Rent Roll'!E4:E15,"active") | C5: =COUNTIFS('Rent Roll'!C4:C15,"B",'Rent Roll'!E4:E15,"active") | D5: =COUNTIFS('Rent Roll'!C4:C15,"C",'Rent Roll'!E4:E15,"active") | E5: =SUM(B5:D5) | F5: "Active" only. Pending is not in possession (manager cover).
A6: Pending in group | B6: =COUNTIFS('Rent Roll'!C4:C15,"A",'Rent Roll'!E4:E15,"pending") | C6: =COUNTIFS('Rent Roll'!C4:C15,"B",'Rent Roll'!E4:E15,"pending") | D6: =COUNTIFS('Rent Roll'!C4:C15,"C",'Rent Roll'!E4:E15,"pending") | E6: =SUM(B6:D6)
A7: Vacant in group | B7: =COUNTIFS('Rent Roll'!C4:C15,"A",'Rent Roll'!E4:E15,"vacant") | C7: =COUNTIFS('Rent Roll'!C4:C15,"B",'Rent Roll'!E4:E15,"vacant") | D7: =COUNTIFS('Rent Roll'!C4:C15,"C",'Rent Roll'!E4:E15,"vacant") | E7: =SUM(B7:D7)
A8: Total area SF (group) | B8: =SUMIF('Rent Roll'!C4:C15,"A",'Rent Roll'!D4:D15) | C8: =SUMIF('Rent Roll'!C4:C15,"B",'Rent Roll'!D4:D15) | D8: =SUMIF('Rent Roll'!C4:C15,"C",'Rent Roll'!D4:D15) | E8: =SUM(B8:D8)
A9: Occupied area SF (active) | B9: =SUMIFS('Rent Roll'!D4:D15,'Rent Roll'!C4:C15,"A",'Rent Roll'!E4:E15,"active") | C9: =SUMIFS('Rent Roll'!D4:D15,'Rent Roll'!C4:C15,"B",'Rent Roll'!E4:E15,"active") | D9: =SUMIFS('Rent Roll'!D4:D15,'Rent Roll'!C4:C15,"C",'Rent Roll'!E4:E15,"active") | E9: =SUM(B9:D9)
A11: Unit occupancy | E11: ='Occupancy & Mix'!$E$5/'Occupancy & Mix'!$E$4
A12: Area occupancy | E12: ='Occupancy & Mix'!$E$9/'Occupancy & Mix'!$E$8
A13: Annual in-place rent (active suites only) | E13: ='Rent Roll'!I16
A14: Manager's 'leased' count (active + pending) [for comparison] | E14: ='Occupancy & Mix'!$E$5+'Occupancy & Mix'!$E$6 | F14: Manager cover headline counts 10 of 12; treats pending as leased.

Sheet Sensitivity
A1: SENSITIVITY: Maximum loan by cap rate & sizing rate
A3: Cap rate ↓ / Sizing rate → | B3: 0.06 | C3: 0.0625 | D3: 0.065 | E3: 0.0675 | F3: 0.07 | G3: 0.0725 | H3: 0.075
A4: 0.065 | B4: =MIN((Inputs!$B$6*(Underwriting!$B$18/0.065)),(Underwriting!$B$20/(Inputs!$B$7*(12*((0.06/12)*(1+(0.06/12))^360)/((1+(0.06/12))^360-1)))),(Underwriting!$B$20/Inputs!$B$8)) | C4: =MIN((Inputs!$B$6*(Underwriting!$B$18/0.065)),(Underwriting!$B$20/(Inputs!$B$7*(12*((0.0625/12)*(1+(0.0625/12))^360)/((1+(0.0625/12))^360-1)))),(Underwriting!$B$20/Inputs!$B$8)) | D4: =MIN((Inputs!$B$6*(Underwriting!$B$18/0.065)),(Underwriting!$B$20/(Inputs!$B$7*(12*((0.065/12)*(1+(0.065/12))^360)/((1+(0.065/12))^360-1)))),(Underwriting!$B$20/Inputs!$B$8)) | E4: =MIN((Inputs!$B$6*(Underwriting!$B$18/0.065)),(Underwriting!$B$20/(Inputs!$B$7*(12*((0.0675/12)*(1+(0.0675/12))^360)/((1+(0.0675/12))^360-1)))),(Underwriting!$B$20/Inputs!$B$8)) | F4: =MIN((Inputs!$B$6*(Underwriting!$B$18/0.065)),(Underwriting!$B$20/(Inputs!$B$7*(12*((0.07/12)*(1+(0.07/12))^360)/((1+(0.07/12))^360-1)))),(Underwriting!$B$20/Inputs!$B$8)) | G4: =MIN((Inputs!$B$6*(Underwriting!$B$18/0.065)),(Underwriting!$B$20/(Inputs!$B$7*(12*((0.0725/12)*(1+(0.0725/12))^360)/((1+(0.0725/12))^360-1)))),(Underwriting!$B$20/Inputs!$B$8)) | H4: =MIN((Inputs!$B$6*(Underwriting!$B$18/0.065)),(Underwriting!$B$20/(Inputs!$B$7*(12*((0.075/12)*(1+(0.075/12))^360)/((1+(0.075/12))^360-1)))),(Underwriting!$B$20/Inputs!$B$8))
A5: 0.07 | B5: =MIN((Inputs!$B$6*(Underwriting!$B$18/0.07)),(Underwriting!$B$20/(Inputs!$B$7*(12*((0.06/12)*(1+(0.06/12))^360)/((1+(0.06/12))^360-1)))),(Underwriting!$B$20/Inputs!$B$8)) | C5: =MIN((Inputs!$B$6*(Underwriting!$B$18/0.07)),(Underwriting!$B$20/(Inputs!$B$7*(12*((0.0625/12)*(1+(0.0625/12))^360)/((1+(0.0625/12))^360-1)))),(Underwriting!$B$20/Inputs!$B$8)) | D5: =MIN((Inputs!$B$6*(Underwriting!$B$18/0.07)),(Underwriting!$B$20/(Inputs!$B$7*(12*((0.065/12)*(1+(0.065/12))^360)/((1+(0.065/12))^360-1)))),(Underwriting!$B$20/Inputs!$B$8)) | E5: =MIN((Inputs!$B$6*(Underwriting!$B$18/0.07)),(Underwriting!$B$20/(Inputs!$B$7*(12*((0.0675/12)*(1+(0.0675/12))^360)/((1+(0.0675/12))^360-1)))),(Underwriting!$B$20/Inputs!$B$8)) | F5: =MIN((Inputs!$B$6*(Underwriting!$B$18/0.07)),(Underwriting!$B$20/(Inputs!$B$7*(12*((0.07/12)*(1+(0.07/12))^360)/((1+(0.07/12))^360-1)))),(Underwriting!$B$20/Inputs!$B$8)) | G5: =MIN((Inputs!$B$6*(Underwriting!$B$18/0.07)),(Underwriting!$B$20/(Inputs!$B$7*(12*((0.0725/12)*(1+(0.0725/12))^360)/((1+(0.0725/12))^360-1)))),(Underwriting!$B$20/Inputs!$B$8)) | H5: =MIN((Inputs!$B$6*(Underwriting!$B$18/0.07)),(Underwriting!$B$20/(Inputs!$B$7*(12*((0.075/12)*(1+(0.075/12))^360)/((1+(0.075/12))^360-1)))),(Underwriting!$B$20/Inputs!$B$8))
A6: 0.075 | B6: =MIN((Inputs!$B$6*(Underwriting!$B$18/0.075)),(Underwriting!$B$20/(Inputs!$B$7*(12*((0.06/12)*(1+(0.06/12))^360)/((1+(0.06/12))^360-1)))),(Underwriting!$B$20/Inputs!$B$8)) | C6: =MIN((Inputs!$B$6*(Underwriting!$B$18/0.075)),(Underwriting!$B$20/(Inputs!$B$7*(12*((0.0625/12)*(1+(0.0625/12))^360)/((1+(0.0625/12))^360-1)))),(Underwriting!$B$20/Inputs!$B$8)) | D6: =MIN((Inputs!$B$6*(Underwriting!$B$18/0.075)),(Underwriting!$B$20/(Inputs!$B$7*(12*((0.065/12)*(1+(0.065/12))^360)/((1+(0.065/12))^360-1)))),(Underwriting!$B$20/Inputs!$B$8)) | E6: =MIN((Inputs!$B$6*(Underwriting!$B$18/0.075)),(Underwriting!$B$20/(Inputs!$B$7*(12*((0.0675/12)*(1+(0.0675/12))^360)/((1+(0.0675/12))^360-1)))),(Underwriting!$B$20/Inputs!$B$8)) | F6: =MIN((Inputs!$B$6*(Underwriting!$B$18/0.075)),(Underwriting!$B$20/(Inputs!$B$7*(12*((0.07/12)*(1+(0.07/12))^360)/((1+(0.07/12))^360-1)))),(Underwriting!$B$20/Inputs!$B$8)) | G6: =MIN((Inputs!$B$6*(Underwriting!$B$18/0.075)),(Underwriting!$B$20/(Inputs!$B$7*(12*((0.0725/12)*(1+(0.0725/12))^360)/((1+(0.0725/12))^360-1)))),(Underwriting!$B$20/Inputs!$B$8)) | H6: =MIN((Inputs!$B$6*(Underwriting!$B$18/0.075)),(Underwriting!$B$20/(Inputs!$B$7*(12*((0.075/12)*(1+(0.075/12))^360)/((1+(0.075/12))^360-1)))),(Underwriting!$B$20/Inputs!$B$8))
A7: 0.08 | B7: =MIN((Inputs!$B$6*(Underwriting!$B$18/0.08)),(Underwriting!$B$20/(Inputs!$B$7*(12*((0.06/12)*(1+(0.06/12))^360)/((1+(0.06/12))^360-1)))),(Underwriting!$B$20/Inputs!$B$8)) | C7: =MIN((Inputs!$B$6*(Underwriting!$B$18/0.08)),(Underwriting!$B$20/(Inputs!$B$7*(12*((0.0625/12)*(1+(0.0625/12))^360)/((1+(0.0625/12))^360-1)))),(Underwriting!$B$20/Inputs!$B$8)) | D7: =MIN((Inputs!$B$6*(Underwriting!$B$18/0.08)),(Underwriting!$B$20/(Inputs!$B$7*(12*((0.065/12)*(1+(0.065/12))^360)/((1+(0.065/12))^360-1)))),(Underwriting!$B$20/Inputs!$B$8)) | E7: =MIN((Inputs!$B$6*(Underwriting!$B$18/0.08)),(Underwriting!$B$20/(Inputs!$B$7*(12*((0.0675/12)*(1+(0.0675/12))^360)/((1+(0.0675/12))^360-1)))),(Underwriting!$B$20/Inputs!$B$8)) | F7: =MIN((Inputs!$B$6*(Underwriting!$B$18/0.08)),(Underwriting!$B$20/(Inputs!$B$7*(12*((0.07/12)*(1+(0.07/12))^360)/((1+(0.07/12))^360-1)))),(Underwriting!$B$20/Inputs!$B$8)) | G7: =MIN((Inputs!$B$6*(Underwriting!$B$18/0.08)),(Underwriting!$B$20/(Inputs!$B$7*(12*((0.0725/12)*(1+(0.0725/12))^360)/((1+(0.0725/12))^360-1)))),(Underwriting!$B$20/Inputs!$B$8)) | H7: =MIN((Inputs!$B$6*(Underwriting!$B$18/0.08)),(Underwriting!$B$20/(Inputs!$B$7*(12*((0.075/12)*(1+(0.075/12))^360)/((1+(0.075/12))^360-1)))),(Underwriting!$B$20/Inputs!$B$8))
A8: 0.085 | B8: =MIN((Inputs!$B$6*(Underwriting!$B$18/0.085)),(Underwriting!$B$20/(Inputs!$B$7*(12*((0.06/12)*(1+(0.06/12))^360)/((1+(0.06/12))^360-1)))),(Underwriting!$B$20/Inputs!$B$8)) | C8: =MIN((Inputs!$B$6*(Underwriting!$B$18/0.085)),(Underwriting!$B$20/(Inputs!$B$7*(12*((0.0625/12)*(1+(0.0625/12))^360)/((1+(0.0625/12))^360-1)))),(Underwriting!$B$20/Inputs!$B$8)) | D8: =MIN((Inputs!$B$6*(Underwriting!$B$18/0.085)),(Underwriting!$B$20/(Inputs!$B$7*(12*((0.065/12)*(1+(0.065/12))^360)/((1+(0.065/12))^360-1)))),(Underwriting!$B$20/Inputs!$B$8)) | E8: =MIN((Inputs!$B$6*(Underwriting!$B$18/0.085)),(Underwriting!$B$20/(Inputs!$B$7*(12*((0.0675/12)*(1+(0.0675/12))^360)/((1+(0.0675/12))^360-1)))),(Underwriting!$B$20/Inputs!$B$8)) | F8: =MIN((Inputs!$B$6*(Underwriting!$B$18/0.085)),(Underwriting!$B$20/(Inputs!$B$7*(12*((0.07/12)*(1+(0.07/12))^360)/((1+(0.07/12))^360-1)))),(Underwriting!$B$20/Inputs!$B$8)) | G8: =MIN((Inputs!$B$6*(Underwriting!$B$18/0.085)),(Underwriting!$B$20/(Inputs!$B$7*(12*((0.0725/12)*(1+(0.0725/12))^360)/((1+(0.0725/12))^360-1)))),(Underwriting!$B$20/Inputs!$B$8)) | H8: =MIN((Inputs!$B$6*(Underwriting!$B$18/0.085)),(Underwriting!$B$20/(Inputs!$B$7*(12*((0.075/12)*(1+(0.075/12))^360)/((1+(0.075/12))^360-1)))),(Underwriting!$B$20/Inputs!$B$8))
A10: Highlighted cell = base case (cap 7.50%, sizing 6.75%).

Sheet I-O Map
A1: INPUT / OUTPUT MAP (Sheet!A1 locations)
A3: Name | B3: Location (Sheet!A1) | C3: Role | D3: Live value
A4: gross_potential_rent | B4: Underwriting!$B$4 | C4: input | D4: =Underwriting!$B$4
A5: cap_rate | B5: Inputs!$B$23 | C5: input | D5: =Inputs!$B$23
A6: sizing_rate | B6: Inputs!$B$16 | C6: input (computed) | D6: =Inputs!$B$16
A7: uw_egi | B7: Underwriting!$B$8 | C7: output | D7: =Underwriting!$B$8
A8: uw_noi | B8: Underwriting!$B$18 | C8: output | D8: =Underwriting!$B$18
A9: uw_ncf | B9: Underwriting!$B$20 | C9: output | D9: =Underwriting!$B$20
A10: capitalization_value | B10: Underwriting!$B$23 | C10: output | D10: =Underwriting!$B$23
A11: maximum_loan | B11: Underwriting!$B$33 | C11: output | D11: =Underwriting!$B$33
A12: net_cash_out | B12: Underwriting!$B$40 | C12: output | D12: =Underwriting!$B$40

Sheet Source Register
A1: SOURCE REGISTER
A3: Source file | B3: Content | C3: Date / As-of | D3: How used in this workbook
A4: manager-cover.pdf | B4: Property/market/asset, group mapping, physical-occupancy convention | C4: n/a | D4: Group mapping (A=Small, B=Standard, C=Large). Confirms 'certified detail controls physical occupancy'; identifies mgr's mis-count.
A5: rent-roll-certified.xlsx | B5: Certified rent roll — 12 suites, area, monthly rents, status, expirations | C5: 2026-08-31 | D5: Primary rent roll used for occupancy, in-place rent, group counts, near-term rollover.
A6: rent-roll-archive.xlsx | B6: Prior rent roll | C6: 2026-06-30 | D6: Provides pre-Suite-001-amendment monthly rent ($10,975) used in GPR per instructions.
A7: lease-001.pdf | B7: Executed lease excerpt for Suite 001 | C7: n/a | D7: Confirms current in-place monthly rent $11,050 and no free-rent concession.
A8: lease-correspondence.pdf | B8: PM confirmation dated 2026-08-31 | C8: 2026-08-31 | D8: Confirms no amendments/new concessions affect Suite 001 as of certified date.
A9: operating-statement.pdf | B9: T-12 cash operating statement | C9: 2025-09-01 → 2026-08-31 | D9: Historical figures; classification of roof replacement as capital (not in opex).
A10: insurance.pdf | B10: Policy declaration — GL aggregate $2,000,000 | C10: Effective 2026-07-01 → 2027-06-30 | D10: Documents policy limit; distinct from annual insurance expense.
A11: underwriting-instructions.pdf | B11: Acquisition analysis instructions | C11: n/a | D11: All UW rules: GPR method, economic loss, other income, mgmt %, reserves, cap rate, loan constraints, rate floor, sizing rule, sources & uses.
A12: diligence-status.pdf | B12: Diligence status memo | C12: n/a | D12: Confirms legal/environmental/PCA/title reviews are routine pending — no findings claimed.
