Workbook

Sheet Inputs
A1: Falcon Distribution — Underwriting Inputs
A2: As of 2026-08-31
A4: Gross potential rent (all suites x12, certified pre-amendment) | B4: 1402800
A5: Other income $/unit/yr | B5: 350
A6: Units | B6: 8
A7: Economic loss % | B7: 0.05
A8: Real estate tax | B8: 147294
A9: Insurance expense | B9: 49098
A10: Other recurring opex | B10: 196392
A11: Management % of EGI | B11: 0.03
A12: Replacement reserve $/unit/yr | B12: 300
A14: Cap rate | B14: 0.0675
A15: Sizing rate (greater of note rate & floor) | B15: 0.07
A16: Note rate | B16: 0.061
... A24: Existing payoff | B24: 7800000

Sheet UW
A1: Underwriting build
A3: Gross potential rent | B3: =Inputs!B4 -> 1402800
A4: Other income | B4: =Inputs!B5*Inputs!B6 -> 2800
A5: Gross potential income | B5: =B3+B4 -> 1405600
A6: Economic loss (5%) | B6: =-B5*Inputs!B7 -> -70280
A7: Underwritten EGI | B7: =B5+B6 -> 1335320
A9: Real estate tax | B9: =Inputs!B8 -> 147294
A10: Insurance | B10: =Inputs!B9 -> 49098
A11: Other recurring opex | B11: =Inputs!B10 -> 196392
A12: Management fee (3% EGI) | B12: =B7*Inputs!B11 -> 40059.6
A13: Total operating expenses | B13: =SUM(B9:B12) -> 432843.6
A15: UW NOI (before reserves) | B15: =B7-B13 -> 902476.4
A16: Replacement reserves | B16: =Inputs!B12*Inputs!B6 -> 2400
A17: UW NCF | B17: =B15-B16 -> 900076.4
A19: Capitalization value (NOI / cap) | B19: =B15/Inputs!B14 -> 13370021

Sheet Debt
A1: Debt sizing
A3: Sizing rate | B3: =Inputs!B15 -> 0.07
A4: Monthly rate | B4: =B3/12 -> 0.0058333333
A5: Amort months | B5: =Inputs!B18 -> 360
A6: Annual debt service per $1 loan | B6: =-PMT(B4,B5,1)*12 -> 0.079836299
A8: LTV-constrained loan | B8: =UW!B19*Inputs!B19 -> 8690513.5
A9: DSCR-constrained loan | B9: =UW!B17/(Inputs!B20*B6) -> 9019219.6
A10: Debt-yield-constrained loan | B10: =UW!B17/Inputs!B21 -> 10000849
A12: Maximum loan (min) | B12: =MIN(B8,B9,B10) -> 8690513.5
A13: Binding constraint | B13: =IF(B12=B8,"LTV",IF(B12=B9,"DSCR","Debt yield")) -> LTV
A15: Sources & Uses
A16: Loan proceeds | B16: =B12 -> 8690513.5
A17: Origination fee | B17: =B12*Inputs!B22 -> 86905.135
A18: Closing costs | B18: =Inputs!B23 -> 45000
A19: Existing payoff | B19: =Inputs!B24 -> 7800000
A20: Net cash-out (negative = equity in) | B20: =B16-B17-B18-B19 -> 758608.35

Sheet Sensitivity
A1: Cap value sensitivity — NOI vs cap rate
A3: Cap rate \ NOI | B3: =UW!B15*0.95 -> 857352.58 | C3: =UW!B15 -> 902476.4 | D3: =UW!B15*1.05 -> 947600.22
A4: 0.06 | B4: =B$3/$A4 -> 14289210 | C4: =C$3/$A4 -> 15041273 | D4: =D$3/$A4 -> 15793337
A5: 0.0625 | B5: =B$3/$A5 -> 13717641 | C5: =C$3/$A5 -> 14439622 | D5: =D$3/$A5 -> 15161604
A6: 0.065 | B6: =B$3/$A6 -> 13190040 | C6: =C$3/$A6 -> 13884252 | D6: =D$3/$A6 -> 14578465
A7: 0.0675 | B7: =B$3/$A7 -> 12701520 | C7: =C$3/$A7 -> 13370021 | D7: =D$3/$A7 -> 14038522
A8: 0.07 | B8: =B$3/$A8 -> 12247894 | C8: =C$3/$A8 -> 12892520 | D8: =D$3/$A8 -> 13537146
A11: Max loan sensitivity — sizing rate vs NCF
A13: Sizing rate \ NCF | B13: =UW!B17*0.95 -> 855072.58 | C13: =UW!B17 -> 900076.4 | D13: =UW!B17*1.05 -> 945080.22
A14: 0.065 | B14: =B$13/(Inputs!$B$20*(-PMT($A14/12,Inputs!$B$18,1)*12)) -> 9018782.2 | C14: =C$13/(Inputs!$B$20*(-PMT($A14/12,Inputs!$B$18,1)*12)) -> 9493455 | D14: =D$13/(Inputs!$B$20*(-PMT($A14/12,Inputs!$B$18,1)*12)) -> 9968127.7
A15: 0.07 | B15: =B$13/(Inputs!$B$20*(-PMT($A15/12,Inputs!$B$18,1)*12)) -> 8568258.7 | C15: =C$13/(Inputs!$B$20*(-PMT($A15/12,Inputs!$B$18,1)*12)) -> 9019219.6 | D15: =D$13/(Inputs!$B$20*(-PMT($A15/12,Inputs!$B$18,1)*12)) -> 9470180.6
A16: 0.075 | B16: =B$13/(Inputs!$B$20*(-PMT($A16/12,Inputs!$B$18,1)*12)) -> 8152696.8 | C16: =C$13/(Inputs!$B$20*(-PMT($A16/12,Inputs!$B$18,1)*12)) -> 8581786.1 | D16: =D$13/(Inputs!$B$20*(-PMT($A16/12,Inputs!$B$18,1)*12)) -> 9010875.4
A17: 0.08 | B17: =B$13/(Inputs!$B$20*(-PMT($A17/12,Inputs!$B$18,1)*12)) -> 7768818.6 | C17: =C$13/(Inputs!$B$20*(-PMT($A17/12,Inputs!$B$18,1)*12)) -> 8177703.8 | D17: =D$13/(Inputs!$B$20*(-PMT($A17/12,Inputs!$B$18,1)*12)) -> 8586589

Sheet RentRoll
A1: Certified rent roll (2026-08-31) — controlling
A3: Suite | B3: Type/Group | C3: Area SF | D3: Possession | E3: Monthly rent | F3: Expiration
A4: 001 | B4: Small (A) | C4: 21880 | D4: active | E4: 14450 | F4: 2029-08-31
A5: 002 | B5: Standard (B) | C5: 22000 | D5: active | E5: 14600 | F5: 2029-08-31
A6: 003 | B6: Large (C) | C6: 22210 | D6: active | E6: 14875 | F6: 2029-08-31
A7: 004 | B7: Small (A) | C7: 21880 | D7: active | E7: 14450 | F7: 2029-08-31
A8: 005 | B8: Standard (B) | C8: 22000 | D8: active | E8: 14600 | F8: 2029-08-31
A9: 006 | B9: Large (C) | C9: 22210 | D9: active | E9: 14875 | F9: 2029-08-31
A10: 007 | B10: Small (A) | C10: 21880 | D10: active | E10: 14450 | F10: 2029-08-31
A11: 008 | B11: Standard (B) | C11: 22000 | D11: vacant | E11: 14600 | F11: 2029-08-31
A13: Totals | C13: =SUM(C4:C11) -> 176060 | E13: =SUM(E4:E11) -> 116900
A14: Occupied (active only) | C14: =SUMIF(D4:D11,"active",C4:C11) -> 154060 | E14: =SUMIF(D4:D11,"active",E4:E11) -> 102300
A15: Annual in-place rent | E15: =E14*12 -> 1227600
A16: Unit occupancy | E16: =COUNTIF(D4:D11,"active")/COUNTA(A4:A11) -> 0.875
A17: Area occupancy | E17: =C14/C13 -> 0.8750426

Sheet Sources
A1: Source register
A3: Item | B3: Value | C3: Source
A4: Certified rent roll as-of | B4: 2026-08-31 | C4: rent-roll-certified.xlsx B2
A5: Archive rent roll as-of | B5: 2026-06-30 | C5: rent-roll-archive.xlsx B2 (stale)
A6: Suite 001 base rent | B6: 14450 | C6: lease-001.pdf p.1; confirmed lease-correspondence.pdf p.1
A7: Reported T12 NOI | B7: 869736 | C7: operating-statement.pdf p.1
A8: Real estate tax (UW) | B8: 147294 | C8: underwriting-instructions.pdf p.1
A9: Insurance expense (UW) | B9: 49098 | C9: underwriting-instructions.pdf p.1
A10: Other opex (UW) | B10: 196392 | C10: underwriting-instructions.pdf p.1
A11: Cap rate | B11: 0.0625 | C11: underwriting-instructions.pdf p.1
A12: Note rate / floor | B12: 6.10% / 7.00% | C12: underwriting-instructions.pdf p.1
A13: LTV / DSCR / DY | B13: 65% / 1.25 / 9% | C13: underwriting-instructions.pdf p.1
A14: Existing payoff | B14: 7800000 | C14: underwriting-instructions.pdf p.1
A15: Insurance GL aggregate limit | B15: 2000000 | C15: insurance.pdf p.1
A16: Manager occupancy claim | B16: 7 of 8 (incl. pending) | C16: manager-cover.pdf p.1 (overstates physical occupancy)
