Workbook

Sheet Inputs
A1: Juniper Flats | Underwriting Inputs
A3: As-of date | B3: 2026-08-31
A5: Underwritten EGI (annual) | B5: 854160
A6: Valuation cap rate | B6: 0.0575
A7: Sizing rate (annual) | B7: 0.0725
A8: Contractual rate (annual) | B8: 0.059
A9: Interest-only months | B9: 24
A10: Amortization (years) | B10: 30
A12: Unit count | B12: 36
A13: Reserves per unit per year | B13: 300
A15: Existing debt payoff | B15: 3300000
A16: Fixed closing costs | B16: 45000
A17: Origination fee rate | B17: 0.0075
A19: T12 actual management fee | B19: 30000
... A30: LTV maximum percent | B30: 0.65

Sheet T12
A1: Juniper Flats | Trailing 12 months (Sep 2025 - Aug 2026)
A3: Gross potential base rent | B3: 840000
A4: Vacancy loss | B4: -42000
A5: Concessions | B5: -12000
A6: Bad debt | B6: -4500
A7: Other income / recoveries | B7: 39600
A9: Effective gross income (EGI) | B9: =B3+B4+B5+B6+B7 -> 821100
A11: Real estate taxes | B11: 108000
A12: Property insurance | B12: 31200
A13: Utilities | B13: 28800
A14: Repairs and maintenance | B14: 46200
A15: Payroll / contract labor | B15: 42000
A16: Administrative / legal | B16: 21600
A17: Management fee | B17: 30000
A19: Total operating expenses (before reserves) | B19: =SUM(B11:B17) -> 307800
A21: NOI before reserves | B21: =B9-B19 -> 513300
A23: Replacement reserves | B23: 10800
A25: NCF after reserves | B25: =B21-B23 -> 502500

Sheet UW
A1: Juniper Flats | Underwriting
A3: Underwritten EGI | B3: =Inputs!B5 -> 854160
A5: UW: Real estate taxes | B5: =Inputs!B22 -> 112000
A6: UW: Property insurance (renewal) | B6: =Inputs!B23 -> 33600
A7: UW: Utilities | B7: =Inputs!B24 -> 28800
A8: UW: Repairs and maintenance (adj) | B8: =Inputs!B25 -> 40200
A9: UW: Payroll / contract labor | B9: =Inputs!B26 -> 42000
A10: UW: Administrative / legal | B10: =Inputs!B27 -> 21600
A11: UW: Management fee = max(T12 actual, % of EGI) | B11: =MAX(Inputs!B19,Inputs!B20*B3) -> 30000
A12: Total operating expenses (before reserves) | B12: =SUM(B5:B11) -> 308200
A14: UW NOI before reserves | B14: =B3-B12 -> 545960
A16: Replacement reserves | B16: =Inputs!B12*Inputs!B13 -> 10800
A18: UW NCF after reserves | B18: =B14-B16 -> 535160
A20: Indicative value (NOI / cap rate) | B20: =B14/Inputs!B6 -> 9494956.5

Sheet Sizing
A1: Juniper Flats | Loan sizing
A2: Annual debt constant (sizing rate, 30yr amort) | B2: =ABS(12*PMT(Inputs!B7/12,Inputs!B10*12,1)) -> 0.081861154
A3: Indicative value (from UW) | B3: =UW!B20 -> 9494956.5
A4: LTV maximum percent | B4: =Inputs!B30 -> 0.65
A5: LTV limit ($) | B5: =B4*B3 -> 6171721.7
A6: DSCR limit ($) = NCF / (const * 1.25) | B6: =UW!B18/(B2*1.25) -> 5229928.7
A7: Debt yield minimum | B7: =Inputs!B29 -> 0.085
A8: Debt yield limit ($) = NCF / DY% | B8: =UW!B18/B7 -> 6296000
A10: Maximum loan (min of constraints) | B10: =MIN(B5,B6,B8) -> 5229928.7
A11: Sizing annual debt service | B11: =B10*B2 -> 428128
A12: Sizing DSCR (UW NCF / sizing DS) | B12: =UW!B18/B11 -> 1.25
A13: Sizing debt yield (UW NCF / loan) | B13: =UW!B18/B10 -> 0.10232644
A14: First-year contractual debt service (IO year) | B14: =Inputs!B8*B10 -> 308565.8
A15: Binding constraint | B15: =IF(B10=B6,"DSCR",IF(B10=B5,"LTV","Debt yield")) -> DSCR

Sheet SourcesUses
A1: Juniper Flats | Sources and Uses
A3: Loan proceeds (sized) | B3: =Sizing!B10 -> 5229928.7
A4: Origination fee (rate x loan) | B4: =Inputs!B17*B3 -> 39224.466
A5: Fixed closing costs | B5: =Inputs!B16 -> 45000
A6: Existing debt payoff | B6: =Inputs!B15 -> 3300000
A8: Net cash to/(from) borrower | B8: =B3-B4-B5-B6 -> 1845704.3

Sheet Sensitivity
A1: Juniper Flats | Sensitivity
A3: Stress EGI (-5%) | B3: =Inputs!B5*0.95 -> 811452
A4: Stress management fee (max of T12 or 3% of stress EGI) | B4: =MAX(Inputs!B19,Inputs!B20*B3) -> 30000
A5: Other operating expenses held constant | B5: =SUM(Inputs!B22:B27) -> 278200
A6: Stress NOI before reserves | B6: =B3-(B4+B5) -> 503252
A7: Stress reserves (unchanged) | B7: =Inputs!B12*Inputs!B13 -> 10800
A8: Stress NCF after reserves | B8: =B6-B7 -> 492452
A9: Stress sizing rate (+100 bps) | B9: =Inputs!B7+0.01 -> 0.0825
A10: Stress annual debt constant | B10: =ABS(12*PMT(B9/12,Inputs!B10*12,1)) -> 0.090151992
A11: Stress DSCR limit ($) | B11: =B8/(B10*1.25) -> 4369971.1
A12: Stress LTV limit ($) (cap rate unchanged) | B12: =Sizing!B5 -> 6171721.7
A13: Stress debt yield limit ($) | B13: =B8/Inputs!B29 -> 5793552.9
A14: Stress maximum loan | B14: =MIN(B11,B12,B13) -> 4369971.1
A16: Cap rate +50 bps | B16: =Inputs!B6+0.005 -> 0.0625
A17: Alternate value at cap+50 bps | B17: =UW!B14/B16 -> 8735360

Sheet RentRoll
A1: Juniper Flats | Rent Roll Summary (as of 2026-08-31)
A3: Total unit/suite count | B3: 36
A4: Occupied unit/suite count | B4: 33
A5: Total rentable area (SF) | B5: 31800
A6: Occupied rentable area (SF) | B6: 28950
A7: Physical occupancy by count (%) | B7: =B4/B3 -> 0.91666667
A8: Occupancy by area (%) | B8: =B6/B5 -> 0.91037736
A9: Monthly base rent (printed) | B9: 62275
A11: Note: Premises 101 base rent confirmed by executed lease extract.
