Workbook

Sheet Assumptions
A1: Meadow Commerce | Editable underwriting assumptions
A2: As of 2026-08-31. Blue-shaded value cells are inputs; all other sheets recalculate from them.
A3: Input | B3: Value | C3: Source / note
A4: Gross potential base rent (annual, UW) | B4: 756000 | C4: Property-and-Plan.pdf p.2 (supplied scenario)
A5: Combined revenue loss (% of GPR) | B5: 0.03 | C5: Property-and-Plan.pdf p.2; vacancy+concessions+bad debt
A6: Other income / recoveries (annual, UW) | B6: 162000 | C6: Property-and-Plan.pdf p.2; added after loss
A7: Valuation cap rate | B7: 0.065 | C7: Lender-Terms.pdf p.1
A8: Sizing rate (annual) | B8: 0.065 | C8: Greater of 6.10% contract and 6.50% floor (Lender-Terms.pdf p.1)
A9: Contract rate (annual, fixed) | B9: 0.061 | C9: Lender-Terms.pdf p.1
A10: Underwriting rate floor | B10: 0.065 | C10: Lender-Terms.pdf p.1
A11: Amortization term (years) | B11: 30 | C11: Lender-Terms.pdf p.1
A12: Payments per year | B12: 12 | C12: Monthly payments; annual DS = 12 payments
A13: Interest-only period (months) | B13: 12 | C13: Lender-Terms.pdf p.1
A14: Maximum LTV | B14: 0.6 | C14: Lender-Terms.pdf p.1
A15: Minimum DSCR (NCF after reserves) | B15: 1.3 | C15: Lender-Terms.pdf p.1
... A32: Cap rate stress increment (separate test) | B32: 0.005 | C32: +50 bps cap-rate sensitivity

Sheet RentRoll
A1: Rent roll | as of 2026-08-31 (current contractual)
A2: Source: Rent-Roll.xlsx, worksheet 'Rent Roll', rows 7-9. Market rent is context only, not income.
A3: Unit | B3: Tenant | C3: Area SF | D3: Status | E3: Monthly base rent | F3: Market monthly rent | G3: Lease expiry
A4: 101 | B4: Tenant A LLC | C4: 16000 | D4: Occupied | E4: 12800 | F4: 12800 | G4: 2028-08-31
A5: 102 | B5: Tenant B LLC | C5: 24000 | D5: Occupied | E5: 20400 | F5: 20400 | G5: 2028-08-31
A6: 103 | B6: Tenant C LLC | C6: 32000 | D6: Occupied | E6: 28800 | F6: 28800 | G6: 2029-08-31
A7: Total | C7: =SUM(C4:C6) -> 72000 | E7: =SUM(E4:E6) -> 62000 | F7: =SUM(F4:F6) -> 62000
A9: Space count | C9: =COUNTA(A4:A6) -> 3
A10: Occupied count | C10: =COUNTIF(D4:D6,"Occupied") -> 3
A11: Occupied area SF | C11: =SUMIF(D4:D6,"Occupied",C4:C6) -> 72000
A12: Occupancy by count (%) | C12: =100*C10/C9 -> 100
A13: Occupancy by area (%) | C13: =100*C11/C7 -> 100
A14: Monthly base rent as printed | C14: =E7 -> 62000
A15: Effective monthly base rent (after authoritative lease evidence) | C15: =E7 -> 62000
A16: Lease-File.pdf p.1 confirms premises 101 base rent of $12,800/month as of 2026-08-31 and expiry 2028-08-31; no signed amendment or renewal-exercise notice is in the packet, so the printed roll stands.
A18: Annualized contractual base rent (context only, not underwritten) | C18: =12*C15 -> 744000

Sheet T12
A1: Historical T12 | September 2025 - August 2026 (actual)
A2: Source: T12-Statement.pdf pp.1-2, annual column. Historical only; not the underwriting scenario.
A3: Line | B3: Amount | C3: Note
A4: Gross potential base rent | B4: 744000
A5: Vacancy loss | B5: 0
A6: Concessions | B6: -18000
A7: Bad debt | B7: -2400
A8: Other income / recoveries | B8: 158400
A9: T12 effective gross income (EGI) | B9: =SUM(B4:B8) -> 882000
A10: Real estate taxes | B10: 102000
A11: Property insurance | B11: 26400
A12: Utilities | B12: 9600
A13: Repairs and maintenance | B13: 19200
A14: Payroll / contract labor | B14: 12000
A15: Administrative / legal | B15: 16800
A16: Management fee | B16: 26400
A17: T12 operating expenses (excl. reserves/capex/debt/depreciation) | B17: =SUM(B10:B16) -> 212400
A18: T12 NOI before replacement reserves | B18: =B9-B17 -> 669600
A19: Replacement reserves (below NOI) | B19: 14400
A20: T12 NCF after replacement reserves | B20: =B18-B19 -> 655200 | C20: Equals the figure the accounting package may label 'property NOI'
A22: Below cash flow (reconciliation only, not operating expense)
A23: Capital improvements | B23: 112000
A24: Loan principal and interest (existing debt) | B24: 294000
A25: Depreciation (noncash) | B25: 180000
A26: T12 expense ratio (opex / EGI) | B26: =B17/B9 -> 0.24081633

Sheet Underwriting
A1: Underwritten cash flow | supplied scenario, September 2026 forward
A2: Live formulas from Assumptions. Not a lender-approved forecast (Property-and-Plan.pdf p.1).
A3: Line | B3: Amount | C3: Formula basis
A4: Gross potential base rent | B4: =Assumptions!B4 -> 756000
A5: Combined revenue loss (vacancy/concessions/bad debt) | B5: =-Assumptions!B4*Assumptions!B5 -> -22680 | C5: 3.00% of underwritten GPR
A6: Other income / recoveries | B6: =Assumptions!B6 -> 162000
A7: Underwritten EGI | B7: =SUM(B4:B6) -> 895320
A8: Real estate taxes | B8: =Assumptions!B24 -> 108000
A9: Property insurance (provisional allowance) | B9: =Assumptions!B25 -> 36000 | C9: Verified renewal premium unknown
A10: Utilities | B10: =Assumptions!B26 -> 9600
A11: Repairs and maintenance | B11: =Assumptions!B27 -> 19200
A12: Payroll / contract labor | B12: =Assumptions!B28 -> 12000
A13: Administrative / legal | B13: =Assumptions!B29 -> 16800
A14: Management fee (lender-normalized) | B14: =MAX(Assumptions!B22,Assumptions!B23*B7) -> 26859.6 | C14: Greater of T12 actual and 3.00% of UW EGI
A15: Underwritten operating expenses before reserves | B15: =SUM(B8:B14) -> 228459.6
A16: Underwritten NOI before reserves | B16: =B7-B15 -> 666860.4
A17: Replacement reserves | B17: =Assumptions!B17*Assumptions!B18 -> 14400 | C17: $0.20/SF x 72,000 SF
A18: Underwritten NCF after reserves | B18: =B16-B17 -> 652460.4
A20: UW expense ratio (opex / EGI) | B20: =B15/B7 -> 0.25517089
A21: Variance: UW NOI vs T12 NOI (before reserves) | B21: =B16-'T12'!B18 -> -2739.6

Sheet Sizing
A1: Loan sizing | three constraints and binding maximum
A2: Lender definitions per Lender-Terms.pdf p.1. Unrounded intermediates.
A3: Metric | B3: Value | C3: Basis
A4: Indicative capitalization value | B4: =Underwriting!B16/Assumptions!B7 -> 10259391 | C4: UW NOI before reserves / cap rate
A5: LTV constraint (60% of value) | B5: =Assumptions!B14*B4 -> 6155634.5
A6: Sizing rate applied | B6: =Assumptions!B8 -> 0.065 | C6: MAX(contract 6.100%, floor 6.500%)
A7: Monthly payment per $1 of principal | B7: =-PMT(B6/Assumptions!B12,Assumptions!B11*Assumptions!B12,1) -> 0.0063206802
A8: Annual debt constant (12 monthly payments per $1) | B8: =Assumptions!B12*B7 -> 0.075848163
A9: DSCR constraint (NCF / 1.30x / constant) | B9: =Underwriting!B18/Assumptions!B15/B8 -> 6617070.2
A10: Debt yield numerator (UW NCF after reserves) | B10: =Underwriting!B18 -> 652460.4
A12: Debt yield constraint (NCF / 9.50%) | B12: =B10/Assumptions!B16 -> 6868004.2
A14: Maximum loan (lowest constraint) | B14: =MIN(B5,B9,B12) -> 6155634.5
A15: Binding constraint | B15: =IF(B14=B5,"LTV",IF(B14=B9,"DSCR","Debt yield")) -> LTV
A16: Sizing annual debt service (amortizing, sizing rate) | B16: =B14*B8 -> 466893.56
A17: Sizing DSCR (NCF / sizing debt service) | B17: =Underwriting!B18/B16 -> 1.39745
A18: Sizing debt yield (NCF / loan) | B18: =B10/B14 -> 0.10599401
A19: Implied LTV at maximum loan | B19: =B14/B4 -> 0.6
A20: First-year contractual debt service (12 months IO at 6.100%) | B20: =B14*Assumptions!B9*Assumptions!B13/12 -> 375493.7
A21: Post-IO annual debt service (contract rate, 30-yr amortization) | B21: =B14*Assumptions!B12*(-PMT(Assumptions!B9/Assumptions!B12,Assumptions!B11*Assumptions!B12,1)) -> 447633.89
A22: First-year DSCR on contractual (IO) debt service | B22: =Underwriting!B18/B20 -> 1.7376068
A23: Sizing debt service less first-year contractual debt service | B23: =B16-B20 -> 91399.863

Sheet SourcesUses
A1: Sources and uses | net cash to borrower
A3: Item | B3: Amount | C3: Basis
A4: Sources
A5: New first-mortgage loan proceeds | B5: =Sizing!B14 -> 6155634.5
A6: Total sources | B6: =B5 -> 6155634.5
A7: Uses
A8: Existing debt payoff | B8: =Assumptions!B19 -> 3600000
A9: Origination fee (1.00% of initial principal) | B9: =Assumptions!B21*B5 -> 61556.345
A10: Fixed closing costs | B10: =Assumptions!B20 -> 55000
A11: Total uses before distribution | B11: =SUM(B8:B10) -> 3716556.3
A12: Net cash to borrower (negative = cash in) | B12: =B6-B11 -> 2439078.1
A14: Check: total uses incl. distribution equals sources | B14: =B11+B12-B6 -> 0
A15: No fee capitalization, interest reserve, holdback or earn-out is assumed (Lender-Terms.pdf p.1).

Sheet Sensitivity
A1: Sensitivities | EGI -5%, sizing rate +100 bps, cap rate +50 bps
A2: Management fee is recomputed on stressed EGI; all other expenses and reserves held constant.
A3: Metric | B3: Value | C3: Basis
A4: Case 1: EGI -5% (cap rate and sizing rate unchanged)
A5: Stressed EGI | B5: =Underwriting!B7*Assumptions!B30 -> 850554
A6: Recomputed management fee | B6: =MAX(Assumptions!B22,Assumptions!B23*B5) -> 26400
A7: Other operating expenses (unchanged) | B7: =Underwriting!B15-Underwriting!B14 -> 201600
A8: Stressed operating expenses | B8: =B7+B6 -> 228000
A9: Stressed NOI before reserves | B9: =B5-B8 -> 622554
A10: Stressed NCF after reserves | B10: =B9-Underwriting!B17 -> 608154
A11: Stressed value at base cap rate | B11: =B9/Assumptions!B7 -> 9577753.8
A12: Case 2: Combined downside - EGI -5% AND sizing rate +100 bps
A13: Stressed sizing rate | B13: =Assumptions!B8+Assumptions!B31 -> 0.075
A14: Stressed annual debt constant | B14: =Assumptions!B12*(-PMT(B13/Assumptions!B12,Assumptions!B11*Assumptions!B12,1)) -> 0.083905741
A15: LTV constraint (cap rate unchanged) | B15: =Assumptions!B14*B11 -> 5746652.3
A16: DSCR constraint at stressed rate | B16: =B10/Assumptions!B15/B14 -> 5575432.2
A17: Debt yield constraint | B17: =B10/Assumptions!B16 -> 6401621.1
A21: Stressed maximum loan (combined downside) | B21: =MIN(B15,B16,B17) -> 5575432.2
A22: Stressed binding constraint | B22: =IF(B21=B15,"LTV",IF(B21=B16,"DSCR","Debt yield")) -> DSCR
A23: Change vs base maximum loan | B23: =B21-Sizing!B14 -> -580202.27
A24: Case 3: Cap rate +50 bps only (EGI and sizing rate unchanged)
A25: Stressed cap rate | B25: =Assumptions!B7+Assumptions!B32 -> 0.07
A26: Value at stressed cap rate | B26: =Underwriting!B16/B25 -> 9526577.1
A27: LTV constraint at stressed cap rate | B27: =Assumptions!B14*B26 -> 5715946.3
A28: Maximum loan with cap rate +50 bps | B28: =MIN(B27,Sizing!B9,Sizing!B12) -> 5715946.3
A29: Binding constraint (cap +50 bps) | B29: =IF(B28=B27,"LTV",IF(B28=Sizing!B9,"DSCR","Debt yield")) -> LTV

Sheet Map
A1: Input / output location map
A3: Item | B3: Cell | C3: Note
A4: INPUTS
A5: Cap rate | B5: Assumptions!B7 | C5: Drives valuation and LTV constraint
A6: Sizing rate | B6: Assumptions!B8 | C6: Drives annual debt constant and DSCR constraint
A7: EGI - gross potential rent | B7: Assumptions!B4 | C7: Loss % held constant at Assumptions!B5
A8: EGI - other income | B8: Assumptions!B6
A9: Revenue loss % | B9: Assumptions!B5
A10: Contract rate | B10: Assumptions!B9
A11: Sizing rate stress (+bps) | B11: Assumptions!B31
A12: Cap rate stress (+bps) | B12: Assumptions!B32
A13: EGI stress factor | B13: Assumptions!B30
A15: OUTPUTS
A16: uw_egi | B16: Underwriting!B7
A17: uw_noi_before_reserves | B17: Underwriting!B16
A18: uw_ncf | B18: Underwriting!B18
A19: capitalization_value | B19: Sizing!B4
A20: ltv_limit | B20: Sizing!B5
A21: dscr_limit | B21: Sizing!B9
A22: debt_yield_limit | B22: Sizing!B12
A23: maximum_loan | B23: Sizing!B14
A24: binding_constraint | B24: Sizing!B15
A25: annual_debt_constant | B25: Sizing!B8
A26: sizing_annual_debt_service | B26: Sizing!B16
A27: sizing_dscr | B27: Sizing!B17
... A35: occupancy / rent roll metrics | B35: RentRoll!C9:C18
