Workbook

Sheet Inputs
A1: Cedar Landing | Underwriting Inputs
A3: As of | B3: 2026-08-31 | D3: Change these inputs to test sensitivities. Key outputs mapped below.
A4: Cap rate | B4: 0.0575
A5: Sizing rate | B5: 0.065
A6: Contract rate | B6: 0.0625
A7: Amortization months | B7: 360
A8: Interest-only months | B8: 36
A9: Unit count | B9: 48
A10: Reserves per unit (annual) | B10: 325
A11: GPR (UW) | B11: 1056000
A12: Revenue loss % (UW) | B12: 0.07
A13: Other income (UW) | B13: 43200
A14: Underwritten EGI | B14: 974016
A15: T12 management fee (actual) | B15: 28000
... A19: Origination fee rate | B19: 0.01

Sheet T12
A1: Cedar Landing | T12 Summary (Sep 2025 - Aug 2026)
A3: Gross potential base rent | B3: 1036800
A4: Vacancy loss | B4: -302400
A5: Concessions | B5: -64800
A6: Bad debt | B6: -8400
A7: Other income / recoveries | B7: 30000
A8: EGI (historical) | B8: =B3+B4+B5+B6+B7 -> 691200
A10: Real estate taxes | B10: 132000
A11: Property insurance | B11: 40800
A12: Utilities | B12: 33600
A13: Repairs and maintenance | B13: 54000
A14: Payroll / contract labor | B14: 55200
A15: Administrative / legal | B15: 27600
A16: Management fee | B16: 28000
A17: Operating expenses (before reserves) | B17: =SUM(B10:B16) -> 371200
A19: NOI before reserves | B19: =B8-B17 -> 320000
A20: Replacement reserves | B20: 14400
A21: NCF after reserves | B21: =B19-B20 -> 305600

Sheet UW
A1: Underwriting (Scenario)
A3: EGI (from Inputs) | B3: =Inputs!B14 -> 974016
A5: Real estate taxes | B5: 138000
A6: Property insurance (renewal) | B6: 45600
A7: Utilities | B7: 33600
A8: Repairs and maintenance (excl. $12k casualty) | B8: 42000
A9: Payroll / contract labor | B9: 55200
A10: Administrative / legal | B10: 27600
A11: Management fee (max of T12 actual and % of EGI) | B11: =MAX(Inputs!B15,Inputs!B16*B3) -> 34090.56
A12: Operating expenses (before reserves) | B12: =SUM(B5:B11) -> 376090.56
A14: NOI before reserves | B14: =B3-B12 -> 597925.44
A15: Unit count | B15: =Inputs!B9 -> 48
A16: Reserves per unit (annual) | B16: =Inputs!B10 -> 325
A17: Replacement reserves | B17: =B15*B16 -> 15600
A18: NCF after reserves | B18: =B14-B17 -> 582325.44

Sheet Sizing
A1: Loan Sizing
A3: Cap rate | B3: =Inputs!B4 -> 0.0575
A4: Underwritten NOI before reserves | B4: =UW!B14 -> 597925.44
A5: Indicative value (NOI/cap) | B5: =B4/B3 -> 10398703
A6: LTV limit (60%) | B6: =0.6*B5 -> 6239222
A8: Sizing rate | B8: =Inputs!B5 -> 0.065
A9: Annual debt constant (30yr amort) | B9: =12*ABS(PMT(B8/12,Inputs!B7,1)) -> 0.075848163
A10: Underwritten NCF after reserves | B10: =UW!B18 -> 582325.44
A11: DSCR limit (min 1.30x) | B11: =B10/(1.3*B9) -> 5905781.1
A12: Debt yield limit (min 9.00%) | B12: =B10/0.09 -> 6470282.7
A14: Maximum loan (binding of the three) | B14: =MIN(B6,B11,B12) -> 5905781.1
A15: Binding constraint | B15: =IF(B14=B6,"LTV",IF(B14=B11,"DSCR","Debt yield")) -> DSCR
A16: Sizing annual debt service | B16: =B9*B14 -> 447942.65
A17: Sizing DSCR | B17: =B10/B16 -> 1.3
A18: Sizing debt yield | B18: =B10/B14 -> 0.098602612
A19: First-year contractual debt service (IO applies) | B19: =Inputs!B6*B14 -> 369111.32
A21: Existing payoff | B21: =Inputs!B17 -> 4500000
A22: Origination fee (rate x loan) | B22: =Inputs!B19*B14 -> 59057.811
A23: Fixed closing costs | B23: =Inputs!B18 -> 65000
A24: Cash to/(from) borrower | B24: =B14-B21-B22-B23 -> 1281723.3

Sheet Sensitivity
A1: Sensitivity Analysis
A3: Stress: EGI -5% (recompute mgmt), sizing rate +100 bps; cap unchanged
A4: Stressed EGI | B4: =Inputs!B14*0.95 -> 925315.2
A5: Mgmt fee stressed (max of T12 or % of stressed EGI) | B5: =MAX(Inputs!B15,Inputs!B16*B4) -> 32386.032
A6: Operating expenses before reserves (stressed) | B6: =UW!B5+UW!B6+UW!B7+UW!B8+UW!B9+UW!B10+B5 -> 374386.03
A7: NOI before reserves (stressed) | B7: =B4-B6 -> 550929.17
A8: NCF after reserves (stressed) | B8: =B7-(Inputs!B9*Inputs!B10) -> 535329.17
A10: Annual debt constant (stressed sizing rate) | B10: =12*ABS(PMT((Inputs!B5+0.01)/12,Inputs!B7,1)) -> 0.083905741
A11: Indicative value (stressed NOI / current cap) | B11: =B7/Inputs!B4 -> 9581376.8
A12: LTV limit (60%) | B12: =0.6*B11 -> 5748826.1
A13: DSCR limit (min 1.30x) | B13: =B8/(1.3*B10) -> 4907788.9
A14: Debt yield limit (min 9.00%) | B14: =B8/0.09 -> 5948101.9
A15: Maximum loan (stressed) | B15: =MIN(B12,B13,B14) -> 4907788.9
A18: Cap rate +50 bps value | B18: =UW!B14/(Inputs!B4+0.005) -> 9566807

Sheet Rent Roll Summary
A1: Rent Roll Summary (as of 2026-08-31)
A3: Unit/Suite count | B3: 48
A4: Occupied units | B4: 34
A5: Physical occupancy (count %) | B5: =B4/B3 -> 0.70833333
A6: Total rentable area (SF) | B6: 43200
A7: Occupied rentable area (SF) | B7: 27800
A8: Occupancy by area (%) | B8: =B7/B6 -> 0.64351852
A9: Monthly base rent (printed roll) | B9: 58050
