Workbook

Sheet Inputs
A1: Magnolia Terrace — Underwriting Inputs (Revised)
A2: As of | B2: 2026-09-01
A4: Input | B4: Value | C4: Source / note
A5: Gross potential rent (annual) | B5: 977100 | C5: (16*1500 + 16*1650 + 15*1925 + 1*2150)*12 per revised roll
A6: Economic loss % | B6: 0.05 | C6: unchanged
A7: Other income per unit (annual) | B7: 350 | C7: unchanged
A8: Total units | B8: 48 | C8: rent-roll-revised.xlsx rows 5-52
A9: Real estate tax expense | B9: 102312 | C9: unchanged
A10: Insurance expense | B10: 34104 | C10: unchanged
A11: Other recurring opex | B11: 136416 | C11: unchanged
A12: Management fee % of EGI | B12: 0.03 | C12: unchanged
A13: Replacement reserve per unit | B13: 300 | C13: unchanged
A14: Cap rate | B14: 0.06 | C14: REVISED: 5.75% + 25 bps
A15: Sizing rate | B15: 0.07 | C15: REVISED: initial sizing rate 6.25% + 75 bps = 7.00%
A16: Amortization (months) | B16: 360 | C16: unchanged
... A25: Original note rate | B25: 0.0625 | C25: underwriting-instructions.pdf p1

Sheet UW
A1: Underwritten Cash Flow & Debt Sizing (Revised)
A3: Gross potential rent | B3: =Inputs!B5
A4: Less: economic loss | B4: =-B3*Inputs!B6
A5: Plus: other income | B5: =Inputs!B7*Inputs!B8
A6: Underwritten EGI | B6: =B3+B4+B5
A8: Real estate tax | B8: =Inputs!B9
A9: Insurance | B9: =Inputs!B10
A10: Other recurring opex | B10: =Inputs!B11
A11: Management fee (3% of EGI) | B11: =B6*Inputs!B12
A12: Total operating expenses | B12: =SUM(B8:B11)
A14: NOI before reserves (UW) | B14: =B6-B12
A15: Replacement reserves | B15: =Inputs!B13*Inputs!B8
A16: NCF after reserves | B16: =B14-B15
A18: Cap rate | B18: =Inputs!B14
A19: Capitalization value (NOI / cap) | B19: =B14/B18
A21: Sizing rate | B21: =Inputs!B15
A22: Monthly constant (rate, n=360) | B22: =(B21/12)*(1+B21/12)^Inputs!B16/((1+B21/12)^Inputs!B16-1)
A23: LTV-limited loan | B23: =Inputs!B17*B19
A24: DSCR-limited loan | B24: =B16/Inputs!B18/12/B22
A25: Debt-yield-limited loan | B25: =B16/Inputs!B19
A26: Maximum loan | B26: =MIN(B23,B24,B25)
A28: Origination fee | B28: =B26*Inputs!B20
A29: Closing costs | B29: =Inputs!B21
A30: Existing payoff | B30: =Inputs!B22
A31: Net cash-out (neg = additional equity) | B31: =B26-B28-B29-B30
A33: Binding constraint | B33: =IF(B26=B23,"LTV",IF(B26=B24,"DSCR","Debt Yield"))

Sheet RentRoll
A1: Reconciled Rent Roll (revised, as of 2026-09-01; Suite 001 in-place per amendment)
A3: Metric | B3: Value | C3: Note
A4: Total units | B4: 48
A5: Active (occupied) units | B5: 45 | C5: Suite 045 now active
A6: Pending units | B6: 0
A7: Vacant units | B7: 3 | C7: Suites 046, 047, 048
A8: Total area SF | B8: 40800
A9: Occupied area SF | B9: 39770 | C9: 16*700+16*820+15*1030 - vacant 700+820+1030
A10: Unit occupancy | B10: =B5/B4
A11: Area occupancy | B11: =B9/B8
A13: Suite 001 in-place monthly rent | B13: 1850 | C13: $1,500 base + $350 signed amendment
A14: Suite 045 scheduled monthly rent (revised) | B14: 2150 | C14: prior $1,925 + $225 per revision
A15: Annual in-place rent | B15: 920400 | C15: (1*1850+14*1500+15*1650+14*1925+1*2150)*12

Sheet UnitMix
A1: Unit Group Mapping (A=Studio, B=1BR, C=2BR)
A3: Group | B3: Total | C3: Occupied | D3: Pending | E3: Vacant
A4: A - Studio | B4: 16 | C4: 15 | D4: 0 | E4: 1
A5: B - 1BR | B5: 16 | C5: 15 | D5: 0 | E5: 1
A6: C - 2BR | B6: 16 | C6: 15 | D6: 0 | E6: 1
A7: Total | B7: =SUM(B4:B6) | C7: =SUM(C4:C6) | D7: =SUM(D4:D6) | E7: =SUM(E4:E6)

Sheet Historical
A1: Historical T-12 vs Underwritten (Revised)
A3: Item | B3: T-12 actual | C3: Underwritten
A4: Rental collections / EGI | B4: 876960 | C4: =UW!B6
A5: Real estate tax | B5: 102312 | C5: =UW!B8
A6: Insurance | B6: 34104 | C6: =UW!B9
A7: Other recurring opex | B7: 136416 | C7: =UW!B10
A8: Management fee | B8: 0 | C8: =UW!B11
A9: NOI before reserves | B9: 604128 | C9: =UW!B14
A10: Reserves | B10: 0 | C10: =UW!B15
A11: NCF after reserves | B11: Unknown | C11: =UW!B16

Sheet SourcesUses
A1: Sources & Uses (Revised)
A3: Sources | B3: $ | C3: Uses | D3: $
A4: Maximum loan | B4: =UW!B26 | C4: Existing payoff | D4: =Inputs!B22
A5: Sponsor equity to close (plug) | B5: =MAX(0,D6-B4) | C5: Origination fee | D5: =UW!B28
C6: Closing costs + payoff + fees | D6: =Inputs!B21+Inputs!B22+UW!B28
A7: Net cash-out to sponsor | B7: =UW!B31

Sheet Sensitivity
A1: Sensitivity: Max loan by sizing rate x cap rate
A3: Cap \ Sizing | B3: 0.065 | C3: 0.0675 | D3: 0.07 | E3: 0.0725 | F3: 0.075
A4: 0.055 | B4: =MIN(Inputs!$B$17*UW!$B$14/$A4,UW!$B$16/Inputs!$B$18/12/((B$3/12)*(1+B$3/12)^Inputs!$B$16/((1+B$3/12)^Inputs!$B$16-1)),UW!$B$16/Inputs!$B$19) | C4: =MIN(Inputs!$B$17*UW!$B$14/$A4,UW!$B$16/Inputs!$B$18/12/((C$3/12)*(1+C$3/12)^Inputs!$B$16/((1+C$3/12)^Inputs!$B$16-1)),UW!$B$16/Inputs!$B$19) | D4: =MIN(Inputs!$B$17*UW!$B$14/$A4,UW!$B$16/Inputs!$B$18/12/((D$3/12)*(1+D$3/12)^Inputs!$B$16/((1+D$3/12)^Inputs!$B$16-1)),UW!$B$16/Inputs!$B$19) | E4: =MIN(Inputs!$B$17*UW!$B$14/$A4,UW!$B$16/Inputs!$B$18/12/((E$3/12)*(1+E$3/12)^Inputs!$B$16/((1+E$3/12)^Inputs!$B$16-1)),UW!$B$16/Inputs!$B$19) | F4: =MIN(Inputs!$B$17*UW!$B$14/$A4,UW!$B$16/Inputs!$B$18/12/((F$3/12)*(1+F$3/12)^Inputs!$B$16/((1+F$3/12)^Inputs!$B$16-1)),UW!$B$16/Inputs!$B$19)
A5: 0.0575 | B5: =MIN(Inputs!$B$17*UW!$B$14/$A5,UW!$B$16/Inputs!$B$18/12/((B$3/12)*(1+B$3/12)^Inputs!$B$16/((1+B$3/12)^Inputs!$B$16-1)),UW!$B$16/Inputs!$B$19) | C5: =MIN(Inputs!$B$17*UW!$B$14/$A5,UW!$B$16/Inputs!$B$18/12/((C$3/12)*(1+C$3/12)^Inputs!$B$16/((1+C$3/12)^Inputs!$B$16-1)),UW!$B$16/Inputs!$B$19) | D5: =MIN(Inputs!$B$17*UW!$B$14/$A5,UW!$B$16/Inputs!$B$18/12/((D$3/12)*(1+D$3/12)^Inputs!$B$16/((1+D$3/12)^Inputs!$B$16-1)),UW!$B$16/Inputs!$B$19) | E5: =MIN(Inputs!$B$17*UW!$B$14/$A5,UW!$B$16/Inputs!$B$18/12/((E$3/12)*(1+E$3/12)^Inputs!$B$16/((1+E$3/12)^Inputs!$B$16-1)),UW!$B$16/Inputs!$B$19) | F5: =MIN(Inputs!$B$17*UW!$B$14/$A5,UW!$B$16/Inputs!$B$18/12/((F$3/12)*(1+F$3/12)^Inputs!$B$16/((1+F$3/12)^Inputs!$B$16-1)),UW!$B$16/Inputs!$B$19)
A6: 0.06 | B6: =MIN(Inputs!$B$17*UW!$B$14/$A6,UW!$B$16/Inputs!$B$18/12/((B$3/12)*(1+B$3/12)^Inputs!$B$16/((1+B$3/12)^Inputs!$B$16-1)),UW!$B$16/Inputs!$B$19) | C6: =MIN(Inputs!$B$17*UW!$B$14/$A6,UW!$B$16/Inputs!$B$18/12/((C$3/12)*(1+C$3/12)^Inputs!$B$16/((1+C$3/12)^Inputs!$B$16-1)),UW!$B$16/Inputs!$B$19) | D6: =MIN(Inputs!$B$17*UW!$B$14/$A6,UW!$B$16/Inputs!$B$18/12/((D$3/12)*(1+D$3/12)^Inputs!$B$16/((1+D$3/12)^Inputs!$B$16-1)),UW!$B$16/Inputs!$B$19) | E6: =MIN(Inputs!$B$17*UW!$B$14/$A6,UW!$B$16/Inputs!$B$18/12/((E$3/12)*(1+E$3/12)^Inputs!$B$16/((1+E$3/12)^Inputs!$B$16-1)),UW!$B$16/Inputs!$B$19) | F6: =MIN(Inputs!$B$17*UW!$B$14/$A6,UW!$B$16/Inputs!$B$18/12/((F$3/12)*(1+F$3/12)^Inputs!$B$16/((1+F$3/12)^Inputs!$B$16-1)),UW!$B$16/Inputs!$B$19)
A7: 0.0625 | B7: =MIN(Inputs!$B$17*UW!$B$14/$A7,UW!$B$16/Inputs!$B$18/12/((B$3/12)*(1+B$3/12)^Inputs!$B$16/((1+B$3/12)^Inputs!$B$16-1)),UW!$B$16/Inputs!$B$19) | C7: =MIN(Inputs!$B$17*UW!$B$14/$A7,UW!$B$16/Inputs!$B$18/12/((C$3/12)*(1+C$3/12)^Inputs!$B$16/((1+C$3/12)^Inputs!$B$16-1)),UW!$B$16/Inputs!$B$19) | D7: =MIN(Inputs!$B$17*UW!$B$14/$A7,UW!$B$16/Inputs!$B$18/12/((D$3/12)*(1+D$3/12)^Inputs!$B$16/((1+D$3/12)^Inputs!$B$16-1)),UW!$B$16/Inputs!$B$19) | E7: =MIN(Inputs!$B$17*UW!$B$14/$A7,UW!$B$16/Inputs!$B$18/12/((E$3/12)*(1+E$3/12)^Inputs!$B$16/((1+E$3/12)^Inputs!$B$16-1)),UW!$B$16/Inputs!$B$19) | F7: =MIN(Inputs!$B$17*UW!$B$14/$A7,UW!$B$16/Inputs!$B$18/12/((F$3/12)*(1+F$3/12)^Inputs!$B$16/((1+F$3/12)^Inputs!$B$16-1)),UW!$B$16/Inputs!$B$19)
A8: 0.065 | B8: =MIN(Inputs!$B$17*UW!$B$14/$A8,UW!$B$16/Inputs!$B$18/12/((B$3/12)*(1+B$3/12)^Inputs!$B$16/((1+B$3/12)^Inputs!$B$16-1)),UW!$B$16/Inputs!$B$19) | C8: =MIN(Inputs!$B$17*UW!$B$14/$A8,UW!$B$16/Inputs!$B$18/12/((C$3/12)*(1+C$3/12)^Inputs!$B$16/((1+C$3/12)^Inputs!$B$16-1)),UW!$B$16/Inputs!$B$19) | D8: =MIN(Inputs!$B$17*UW!$B$14/$A8,UW!$B$16/Inputs!$B$18/12/((D$3/12)*(1+D$3/12)^Inputs!$B$16/((1+D$3/12)^Inputs!$B$16-1)),UW!$B$16/Inputs!$B$19) | E8: =MIN(Inputs!$B$17*UW!$B$14/$A8,UW!$B$16/Inputs!$B$18/12/((E$3/12)*(1+E$3/12)^Inputs!$B$16/((1+E$3/12)^Inputs!$B$16-1)),UW!$B$16/Inputs!$B$19) | F8: =MIN(Inputs!$B$17*UW!$B$14/$A8,UW!$B$16/Inputs!$B$18/12/((F$3/12)*(1+F$3/12)^Inputs!$B$16/((1+F$3/12)^Inputs!$B$16-1)),UW!$B$16/Inputs!$B$19)

Sheet Changes
A1: Change Log — Initial vs Revised
A3: Item | B3: Initial | C3: Revised | D3: Reason
A4: As-of date | B4: 2026-08-31 | C4: 2026-09-01 | D4: revision-notice.pdf
A5: Suite 045 status | B5: pending | C5: active | D5: Revised roll
A6: Suite 045 scheduled rent | B6: $1,925 | C6: $2,150 | D6: +$225 revision
A7: GPR | B7: $974,400 | C7: $977,100 | D7: New roll all-unit
A8: Cap rate | B8: 5.7500% | C8: 6.0000% | D8: +25 bps
A9: Sizing rate | B9: 6.2500% | C9: 7.0000% | D9: +75 bps
A10: UW EGI | B10: $942,480 | C10: $945,045
A11: UW NOI | B11: $641,374 | C11: $643,862
A12: UW NCF | B12: $626,974 | C12: $629,462
A13: Capitalization value | B13: $11,154,323 | C13: $10,731,028
A14: Maximum loan | B14: $6,788,545 | C14: $6,307,523 | D14: DSCR binding in both
A15: Net cash-out | B15: $2,475,660 | C15: $1,999,448

Sheet Sources
A1: Source Register
A3: File | B3: Loc | C3: Fact
A4: revision-notice.pdf | B4: p1 | C4: Effective 2026-09-01. Suite 045 active, +$225. Cap +25 bps, initial sizing rate +75 bps.
A5: rent-roll-revised.xlsx | B5: A5:G52 | C5: Controlling roll; Suite 045 active at $2,150; Suites 046-048 vacant
A6: rent-roll-certified.xlsx | B6: - | C6: Superseded by revised roll
A7: manager-cover.pdf | B7: p1 | C7: Group mapping A/B/C = Studio/1BR/2BR
A8: underwriting-instructions.pdf | B8: p1 | C8: Base underwriting rules; original note 6.25%, floor 6.00%
A9: operating-statement.pdf | B9: p1 | C9: T-12 collections $876,960; tax/ins/other; roof capital; NOI $604,128
A10: lease-001.pdf | B10: p1 | C10: Suite 001 base $1,500; no free rent
A11: lease-correspondence.pdf | B11: p1 | C11: Signed amendment 2026-07-20 effective 2026-08-01; +$350 on Suite 001
A12: insurance.pdf | B12: p1 | C12: GL aggregate $2,000,000 through 2027-06-30
A13: diligence-status.pdf | B13: p1 | C13: Legal/enviro/PCA/title pending; no defects asserted
