Workbook

Sheet Inputs
A1: Magnolia Terrace — Underwriting Inputs
A2: As of | B2: 2026-08-31
A4: Input | B4: Value | C4: Source
A5: Gross potential rent (annual) | B5: 974400 | C5: 16×$1,500 + 16×$1,650 + 16×$1,925 ×12 (certified roll pre-amendment)
A6: Economic loss % | B6: 0.05 | C6: underwriting-instructions.pdf p1
A7: Other income per unit (annual) | B7: 350 | C7: underwriting-instructions.pdf p1
A8: Total units | B8: 48 | C8: rent-roll-certified.xlsx rows 5-52
A9: Real estate tax expense | B9: 102312 | C9: underwriting-instructions.pdf p1
A10: Insurance expense | B10: 34104 | C10: underwriting-instructions.pdf p1
A11: Other recurring opex | B11: 136416 | C11: underwriting-instructions.pdf p1
A12: Management fee % of EGI | B12: 0.03 | C12: underwriting-instructions.pdf p1
A13: Replacement reserve per unit | B13: 300 | C13: underwriting-instructions.pdf p1
A14: Cap rate | B14: 0.0575 | C14: underwriting-instructions.pdf p1
A15: Sizing rate | B15: 0.0625 | C15: Greater of note 6.25% and floor 6.00%
A16: Amortization (months) | B16: 360 | C16: underwriting-instructions.pdf p1
... A22: Existing loan payoff | B22: 4200000 | C22: underwriting-instructions.pdf p1

Sheet UW
A1: Underwritten Cash Flow & Debt Sizing
A3: Gross potential rent | B3: =Inputs!B5
A4: Less: economic loss | B4: =-B3*Inputs!B6
A5: Plus: other income | B5: =Inputs!B7*Inputs!B8
A6: Underwritten EGI | B6: =B3+B4+B5
A8: Real estate tax | B8: =Inputs!B9
A9: Insurance | B9: =Inputs!B10
A10: Other recurring opex | B10: =Inputs!B11
A11: Management fee (3% of EGI) | B11: =B6*Inputs!B12
A12: Total operating expenses | B12: =SUM(B8:B11)
A14: NOI before reserves (UW) | B14: =B6-B12
A15: Replacement reserves | B15: =Inputs!B13*Inputs!B8
A16: NCF after reserves | B16: =B14-B15
A18: Cap rate | B18: =Inputs!B14
A19: Capitalization value (NOI / cap) | B19: =B14/B18
A21: Sizing rate | B21: =Inputs!B15
A22: Monthly constant (rate,n=360) | B22: =(B21/12)*(1+B21/12)^Inputs!B16/((1+B21/12)^Inputs!B16-1)
A23: LTV-limited loan | B23: =Inputs!B17*B19
A24: DSCR-limited loan (NCF / DSCR / 12 / constant) | B24: =B16/Inputs!B18/12/B22
A25: Debt-yield-limited loan | B25: =B16/Inputs!B19
A26: Maximum loan | B26: =MIN(B23,B24,B25)
A28: Origination fee | B28: =B26*Inputs!B20
A29: Closing costs | B29: =Inputs!B21
A30: Existing payoff | B30: =Inputs!B22
A31: Net cash-out (neg = additional equity) | B31: =B26-B28-B29-B30
A33: Binding constraint | B33: =IF(B26=B23,"LTV",IF(B26=B24,"DSCR","Debt Yield"))

Sheet RentRoll
A1: Reconciled Rent Roll (certified, as of 2026-08-31; Suite 001 in-place per amendment)
A3: Suite | B3: Type | C3: Area SF | D3: Status | E3: In-place mo. rent | F3: Scheduled mo. rent | G3: Lease exp.
A4: 001 | B4: Studio | C4: 700 | D4: active | E4: 1850 | F4: 1500 | G4: 2029-08-31
A5: 002-016 Studio×15, 1BR×15, 2BR×15 (rows condensed)
A7: Studios total (16 units) | C7: 11200 | E7: 24350 | F7: 24000
A8: 1BR total (16 units) | C8: 13120 | E8: 26400 | F8: 26400
A9: 2BR total (16 units, 1 pending, 1 vacant) | C9: 16480 | E9: 30800 | F9: 30800
A11: Physically occupied units (excl pending) | B11: 44
A12: Pending units | B12: 1
A13: Vacant units | B13: 3
A14: Total units | B14: 48
A15: Occupied area SF | B15: 37220
A16: Total area SF | B16: 40800
A17: Unit occupancy | B17: =B11/B14
A18: Area occupancy | B18: =B15/B16
A20: Annual in-place rent (44 active + Suite 001 amended) | B20: 894600 | C20: (1×$1,850 + 14×$1,500 + 15×$1,650 + 14×$1,925) × 12

Sheet UnitMix
A1: Unit Group Mapping (A=Studio, B=1BR, C=2BR)
A3: Group | B3: Total units | C3: Occupied | D3: Pending | E3: Vacant
A4: A - Studio | B4: 16 | C4: 15 | D4: 0 | E4: 1
A5: B - 1BR | B5: 16 | C5: 15 | D5: 0 | E5: 1
A6: C - 2BR | B6: 16 | C6: 14 | D6: 1 | E6: 1
A7: Total | B7: =SUM(B4:B6) | C7: =SUM(C4:C6) | D7: =SUM(D4:D6) | E7: =SUM(E4:E6)

Sheet Historical
A1: Historical T-12 vs Underwritten
A3: Item | B3: T-12 actual | C3: Underwritten
A4: Rental & ancillary collections / EGI | B4: 876960 | C4: =UW!B6
A5: Real estate tax | B5: 102312 | C5: =UW!B8
A6: Insurance | B6: 34104 | C6: =UW!B9
A7: Other recurring opex | B7: 136416 | C7: =UW!B10
A8: Management fee | B8: 0 | C8: =UW!B11
A9: Reported NOI (T-12) / UW NOI before reserves | B9: 604128 | C9: =UW!B14
A10: Reserves | B10: 0 | C10: =UW!B15
A11: NCF after reserves | B11: Unknown | C11: =UW!B16
A13: Note: T-12 collections are cash, not annualized rent-roll; UW EGI uses scheduled GPR × (1-loss) + other income.

Sheet SourcesUses
A1: Sources & Uses
A3: Sources | B3: $ | C3: Uses | D3: $
A4: Maximum loan | B4: =UW!B26 | C4: Existing payoff | D4: =Inputs!B22
A5: Sponsor equity (plug) | B5: =MAX(0,D6-B4) | C5: Origination fee | D5: =UW!B28
C6: Closing costs | D6: =Inputs!B21+Inputs!B22+UW!B28
A7: Net cash-out to sponsor | B7: =UW!B31

Sheet Sensitivity
A1: Sensitivity: Max loan by sizing rate × cap rate
A3: Cap rate ↓ / Sizing rate → | B3: 0.06 | C3: 0.0625 | D3: 0.065 | E3: 0.0675 | F3: 0.07
A4: 0.055 | B4: =MIN(Inputs!$B$17*UW!$B$14/$A4,UW!$B$16/Inputs!$B$18/12/((B$3/12)*(1+B$3/12)^Inputs!$B$16/((1+B$3/12)^Inputs!$B$16-1)),UW!$B$16/Inputs!$B$19) | C4: =MIN(Inputs!$B$17*UW!$B$14/$A4,UW!$B$16/Inputs!$B$18/12/((C$3/12)*(1+C$3/12)^Inputs!$B$16/((1+C$3/12)^Inputs!$B$16-1)),UW!$B$16/Inputs!$B$19) | D4: =MIN(Inputs!$B$17*UW!$B$14/$A4,UW!$B$16/Inputs!$B$18/12/((D$3/12)*(1+D$3/12)^Inputs!$B$16/((1+D$3/12)^Inputs!$B$16-1)),UW!$B$16/Inputs!$B$19) | E4: =MIN(Inputs!$B$17*UW!$B$14/$A4,UW!$B$16/Inputs!$B$18/12/((E$3/12)*(1+E$3/12)^Inputs!$B$16/((1+E$3/12)^Inputs!$B$16-1)),UW!$B$16/Inputs!$B$19) | F4: =MIN(Inputs!$B$17*UW!$B$14/$A4,UW!$B$16/Inputs!$B$18/12/((F$3/12)*(1+F$3/12)^Inputs!$B$16/((1+F$3/12)^Inputs!$B$16-1)),UW!$B$16/Inputs!$B$19)
A5: 0.0575 | B5: =MIN(Inputs!$B$17*UW!$B$14/$A5,UW!$B$16/Inputs!$B$18/12/((B$3/12)*(1+B$3/12)^Inputs!$B$16/((1+B$3/12)^Inputs!$B$16-1)),UW!$B$16/Inputs!$B$19) | C5: =MIN(Inputs!$B$17*UW!$B$14/$A5,UW!$B$16/Inputs!$B$18/12/((C$3/12)*(1+C$3/12)^Inputs!$B$16/((1+C$3/12)^Inputs!$B$16-1)),UW!$B$16/Inputs!$B$19) | D5: =MIN(Inputs!$B$17*UW!$B$14/$A5,UW!$B$16/Inputs!$B$18/12/((D$3/12)*(1+D$3/12)^Inputs!$B$16/((1+D$3/12)^Inputs!$B$16-1)),UW!$B$16/Inputs!$B$19) | E5: =MIN(Inputs!$B$17*UW!$B$14/$A5,UW!$B$16/Inputs!$B$18/12/((E$3/12)*(1+E$3/12)^Inputs!$B$16/((1+E$3/12)^Inputs!$B$16-1)),UW!$B$16/Inputs!$B$19) | F5: =MIN(Inputs!$B$17*UW!$B$14/$A5,UW!$B$16/Inputs!$B$18/12/((F$3/12)*(1+F$3/12)^Inputs!$B$16/((1+F$3/12)^Inputs!$B$16-1)),UW!$B$16/Inputs!$B$19)
A6: 0.06 | B6: =MIN(Inputs!$B$17*UW!$B$14/$A6,UW!$B$16/Inputs!$B$18/12/((B$3/12)*(1+B$3/12)^Inputs!$B$16/((1+B$3/12)^Inputs!$B$16-1)),UW!$B$16/Inputs!$B$19) | C6: =MIN(Inputs!$B$17*UW!$B$14/$A6,UW!$B$16/Inputs!$B$18/12/((C$3/12)*(1+C$3/12)^Inputs!$B$16/((1+C$3/12)^Inputs!$B$16-1)),UW!$B$16/Inputs!$B$19) | D6: =MIN(Inputs!$B$17*UW!$B$14/$A6,UW!$B$16/Inputs!$B$18/12/((D$3/12)*(1+D$3/12)^Inputs!$B$16/((1+D$3/12)^Inputs!$B$16-1)),UW!$B$16/Inputs!$B$19) | E6: =MIN(Inputs!$B$17*UW!$B$14/$A6,UW!$B$16/Inputs!$B$18/12/((E$3/12)*(1+E$3/12)^Inputs!$B$16/((1+E$3/12)^Inputs!$B$16-1)),UW!$B$16/Inputs!$B$19) | F6: =MIN(Inputs!$B$17*UW!$B$14/$A6,UW!$B$16/Inputs!$B$18/12/((F$3/12)*(1+F$3/12)^Inputs!$B$16/((1+F$3/12)^Inputs!$B$16-1)),UW!$B$16/Inputs!$B$19)
A7: 0.0625 | B7: =MIN(Inputs!$B$17*UW!$B$14/$A7,UW!$B$16/Inputs!$B$18/12/((B$3/12)*(1+B$3/12)^Inputs!$B$16/((1+B$3/12)^Inputs!$B$16-1)),UW!$B$16/Inputs!$B$19) | C7: =MIN(Inputs!$B$17*UW!$B$14/$A7,UW!$B$16/Inputs!$B$18/12/((C$3/12)*(1+C$3/12)^Inputs!$B$16/((1+C$3/12)^Inputs!$B$16-1)),UW!$B$16/Inputs!$B$19) | D7: =MIN(Inputs!$B$17*UW!$B$14/$A7,UW!$B$16/Inputs!$B$18/12/((D$3/12)*(1+D$3/12)^Inputs!$B$16/((1+D$3/12)^Inputs!$B$16-1)),UW!$B$16/Inputs!$B$19) | E7: =MIN(Inputs!$B$17*UW!$B$14/$A7,UW!$B$16/Inputs!$B$18/12/((E$3/12)*(1+E$3/12)^Inputs!$B$16/((1+E$3/12)^Inputs!$B$16-1)),UW!$B$16/Inputs!$B$19) | F7: =MIN(Inputs!$B$17*UW!$B$14/$A7,UW!$B$16/Inputs!$B$18/12/((F$3/12)*(1+F$3/12)^Inputs!$B$16/((1+F$3/12)^Inputs!$B$16-1)),UW!$B$16/Inputs!$B$19)
A8: 0.065 | B8: =MIN(Inputs!$B$17*UW!$B$14/$A8,UW!$B$16/Inputs!$B$18/12/((B$3/12)*(1+B$3/12)^Inputs!$B$16/((1+B$3/12)^Inputs!$B$16-1)),UW!$B$16/Inputs!$B$19) | C8: =MIN(Inputs!$B$17*UW!$B$14/$A8,UW!$B$16/Inputs!$B$18/12/((C$3/12)*(1+C$3/12)^Inputs!$B$16/((1+C$3/12)^Inputs!$B$16-1)),UW!$B$16/Inputs!$B$19) | D8: =MIN(Inputs!$B$17*UW!$B$14/$A8,UW!$B$16/Inputs!$B$18/12/((D$3/12)*(1+D$3/12)^Inputs!$B$16/((1+D$3/12)^Inputs!$B$16-1)),UW!$B$16/Inputs!$B$19) | E8: =MIN(Inputs!$B$17*UW!$B$14/$A8,UW!$B$16/Inputs!$B$18/12/((E$3/12)*(1+E$3/12)^Inputs!$B$16/((1+E$3/12)^Inputs!$B$16-1)),UW!$B$16/Inputs!$B$19) | F8: =MIN(Inputs!$B$17*UW!$B$14/$A8,UW!$B$16/Inputs!$B$18/12/((F$3/12)*(1+F$3/12)^Inputs!$B$16/((1+F$3/12)^Inputs!$B$16-1)),UW!$B$16/Inputs!$B$19)

Sheet Sources
A1: Source Register
A3: File | B3: Page/Cell | C3: Fact
A4: manager-cover.pdf | B4: p1 | C4: Manager counts 45 occupied (includes pending)
A5: underwriting-instructions.pdf | B5: p1 | C5: GPR = certified pre-amendment scheduled ×12; loss 5%; other income $350/unit; tax/ins/other opex; mgmt 3% EGI; reserve $300/unit; cap 5.75%; note 6.25%, floor 6.00%; LTV 65%, DSCR 1.25, DY 9%; 30-yr amort; orig 1%; closing $45,000; payoff $4,200,000
A6: rent-roll-certified.xlsx | B6: A5:G52 | C6: 48 units; suite 45 pending, 46-48 vacant; scheduled rents
A7: rent-roll-archive.xlsx | B7: A5:G52 | C7: Stale as of 2026-06-30; superseded by certified
A8: lease-001.pdf | B8: p1 | C8: Suite 001 executed lease $1,500 mo; no free rent
A9: lease-correspondence.pdf | B9: p1 | C9: Signed amendment 2026-07-20 effective 2026-08-01: +$350 mo on Suite 001
A10: operating-statement.pdf | B10: p1 | C10: T-12 collections $876,960; tax $102,312; ins $34,104; other $136,416; roof $0; NOI $604,128
A11: insurance.pdf | B11: p1 | C11: GL aggregate limit $2,000,000; policy 2026-07-01 to 2027-06-30
A12: diligence-status.pdf | B12: p1 | C12: Legal/enviro/PCA/title pending; no defects asserted
