Workbook

Sheet UW
A1: Maple Crossing Underwriting
A3: Inputs
A4: Gross potential rent (annual) | B4: 818700
A5: Economic loss % | B5: 0.05
A6: Other income (annual) | B6: 3500
A7: Underwritten EGI | B7: =B4*(1-B5)+B6
A8: Cap rate | B8: 0.0675
A10: Real estate taxes | B10: 85964
A11: Insurance expense | B11: 28655
A12: Other recurring opex | B12: 114618
A13: Management fee % of EGI | B13: 0.03
A14: Mgmt fee (calc) | B14: =B7*B13
A15: Total opex excl reserves | B15: =SUM(B10:B12)+B14
A16: NOI before reserves | B16: =B7-B15
A18: Units/Suites | B18: 10
A19: Reserves per unit | B19: 300
A20: Annual reserves | B20: =B18*B19
A21: NCF after reserves | B21: =B16-B20
A23: Capitalization value | B23: =B16/B8
A25: Sizing note rate | B25: 0.075
A26: Amortization years | B26: 30
A27: Annual payment constant | B27: =ABS(PMT(B25/12,B26*12,1))*12
A28: DSCR minimum | B28: 1.25
A29: Debt yield minimum | B29: 0.09
A30: LTV maximum | B30: 0.65
A31: LTV constraint ($) | B31: =B23*B30
A32: DSCR constraint ($) | B32: =(B21/B28)/B27
A33: Debt yield constraint ($) | B33: =B21/B29
A34: Maximum loan | B34: =MIN(B31,B32,B33)
A36: Origination fee % | B36: 0.01
A37: Origination fee ($) | B37: =B34*B36
A38: Closing costs ($) | B38: 45000
A39: Existing payoff ($) | B39: 4300000
A40: Net cash out ($) | B40: =B34-(B37+B38+B39)

Sheet Sensitivity
A1: Sensitivity
A3: NOI (from UW) | B3: ='UW'!B16 | D3: Sizing rate | E3: Max Loan vs Rate
D4: 0.06 | E4: =MIN('UW'!B31,('UW'!B21/'UW'!B28)/(ABS(PMT(D4/12,'UW'!B26*12,1))*12),'UW'!B33)
A5: Cap rate | B5: Value | D5: 0.0625 | E5: =MIN('UW'!B31,('UW'!B21/'UW'!B28)/(ABS(PMT(D5/12,'UW'!B26*12,1))*12),'UW'!B33)
A6: 0.0625 | B6: =B3/A6 | D6: 0.065 | E6: =MIN('UW'!B31,('UW'!B21/'UW'!B28)/(ABS(PMT(D6/12,'UW'!B26*12,1))*12),'UW'!B33)
A7: 0.065 | B7: =B3/A7 | D7: 0.0675 | E7: =MIN('UW'!B31,('UW'!B21/'UW'!B28)/(ABS(PMT(D7/12,'UW'!B26*12,1))*12),'UW'!B33)
A8: 0.0675 | B8: =B3/A8 | D8: 0.07 | E8: =MIN('UW'!B31,('UW'!B21/'UW'!B28)/(ABS(PMT(D8/12,'UW'!B26*12,1))*12),'UW'!B33)
A9: 0.07 | B9: =B3/A9 | D9: 0.0725 | E9: =MIN('UW'!B31,('UW'!B21/'UW'!B28)/(ABS(PMT(D9/12,'UW'!B26*12,1))*12),'UW'!B33)
A10: 0.0725 | B10: =B3/A10 | D10: 0.075 | E10: =MIN('UW'!B31,('UW'!B21/'UW'!B28)/(ABS(PMT(D10/12,'UW'!B26*12,1))*12),'UW'!B33)

Sheet Sources
A1: Source Register
A3: Document | B3: Location | C3: Key data used
A4: rent-roll-certified.xlsx | B4: Rent Roll!A2:B14 | C4: As-of date; units, areas, statuses, monthly rent, expirations
A5: rent-roll-archive.xlsx | B5: Rent Roll!A2:B14 | C5: Prior as-of; confirms rent step-up timing
A6: operating-statement.pdf | B6: Page 1 | C6: T12 collections; taxes; insurance; other opex; reported NOI; capital note
A7: insurance.pdf | B7: Page 1 | C7: Policy limit; effective/expiry dates
A8: lease-001.pdf | B8: Page 1 | C8: Suite 001 base rent and terms
A9: lease-correspondence.pdf | B9: Page 1 | C9: Signed amendment +$350/mo effective 8/1/2026
A10: manager-cover.pdf | B10: Page 1 | C10: Occupancy headline includes pending; A/B/C group mapping
A11: underwriting-instructions.pdf | B11: Page 1 | C11: Underwriting assumptions; sizing rules; constraints; cap rate; fees/costs
