Workbook

Sheet Revision Log
A1: Magnolia Terrace - Revision R1 (revision-notice.pdf p.1, effective 2026-09-01)
A2: Approved copy preserved exactly: "Source-backed analysis. Assumptions remain subject to diligence."
A4: Item | B4: Prior (initial) | C4: Revised (R1) | D4: Driver
A5: Controlling roll date | B5: 2026-08-31 | C5: 2026-09-01 | D5: Revised certified roll supersedes prior roll
A6: Suite 045 status | B6: pending (no possession) | C6: active | D6: revision-notice.pdf p.1; rent-roll-revised.xlsx D49
A7: Suite 045 scheduled rent / mo | B7: 1925 | C7: 2150 | D7: +$225 per revision notice
A8: Occupied units / pending units | B8: 44 / 1 | C8: 45 / 0 | D8: Suite 045 took possession
A9: Gross potential rent | B9: 974400 | C9: 977100 | D9: All-unit scheduled rent on new roll x 12
A10: Cap rate | B10: 0.0575 | C10: 0.06 | D10: +25 bps per revision notice
A11: Sizing rate | B11: 0.0625 | C11: 0.07 | D11: Initial sizing rate 6.2500% + 75 bps; floor 6.0000% still not binding
A12: Maximum loan | B12: 6788545 | C12: =Debt!B17 -> 5719015.5 | D12: DSCR remains the binding test at the higher sizing rate
A13: Net cash-out | B13: 2475660 | C13: =Debt!B32 -> 1416825.4 | D13: Lower proceeds; payoff and cost assumptions unchanged
A15: Unchanged and preserved: 48 units and 40,800 SF; unit type mix and group mapping A/B/C = Studio/1BR/2BR; all lease expirations 2029-08-31; Suite 001 executed amendment (+$350, in-place $1,850); T12 operating statement figures and reported NOI $604,128; prescribed expense lines, 5% loss, $350/unit other income, 3% management, $300/unit reserves; 65% LTV, 1.25x DSCR, 9% debt yield, 30-yr amortization, 1% fee, $45,000 closing costs, $4,200,000 payoff; insurance policy limit $2,000,000; diligence status. Prior initial workbook and OM remain in the audit archive and are not replaced.

Sheet Rent Roll
A1: Magnolia Terrace - Revised certified rent roll (controlling)
A2: Roll date | B2: 2026-09-01 | I2: Suite 001 signed amendment ($/mo) | J2: 350
A4: Suite | B4: Unit type | C4: Group | D4: Area SF | E4: Possession | F4: Sched. rent/mo | G4: In-place rent/mo | H4: Expiration
A5: 001 | B5: Studio | C5: A | D5: 700 | E5: active | F5: 1500 | G5: =F5+$J$2 -> 1850 | H5: 2029-08-31
A6: 002 | B6: 1BR | C6: B | D6: 820 | E6: active | F6: 1650 | G6: =F6 -> 1650 | H6: 2029-08-31
A7: 003 | B7: 2BR | C7: C | D7: 1030 | E7: active | F7: 1925 | G7: =F7 -> 1925 | H7: 2029-08-31
A8: 004 | B8: Studio | C8: A | D8: 700 | E8: active | F8: 1500 | G8: =F8 -> 1500 | H8: 2029-08-31
A9: 005 | B9: 1BR | C9: B | D9: 820 | E9: active | F9: 1650 | G9: =F9 -> 1650 | H9: 2029-08-31
A10: 006 | B10: 2BR | C10: C | D10: 1030 | E10: active | F10: 1925 | G10: =F10 -> 1925 | H10: 2029-08-31
A11: 007 | B11: Studio | C11: A | D11: 700 | E11: active | F11: 1500 | G11: =F11 -> 1500 | H11: 2029-08-31
A12: 008 | B12: 1BR | C12: B | D12: 820 | E12: active | F12: 1650 | G12: =F12 -> 1650 | H12: 2029-08-31
A13: 009 | B13: 2BR | C13: C | D13: 1030 | E13: active | F13: 1925 | G13: =F13 -> 1925 | H13: 2029-08-31
A14: 010 | B14: Studio | C14: A | D14: 700 | E14: active | F14: 1500 | G14: =F14 -> 1500 | H14: 2029-08-31
A15: 011 | B15: 1BR | C15: B | D15: 820 | E15: active | F15: 1650 | G15: =F15 -> 1650 | H15: 2029-08-31
A16: 012 | B16: 2BR | C16: C | D16: 1030 | E16: active | F16: 1925 | G16: =F16 -> 1925 | H16: 2029-08-31
A17: 013 | B17: Studio | C17: A | D17: 700 | E17: active | F17: 1500 | G17: =F17 -> 1500 | H17: 2029-08-31
... A48: 044 | B48: 1BR | C48: B | D48: 820 | E48: active | F48: 1650 | G48: =F48 -> 1650 | H48: 2029-08-31
A49: 045 | B49: 2BR | C49: C | D49: 1030 | E49: active | F49: 2150 | G49: =F49 -> 2150 | H49: 2029-08-31 | I49: R1: now active; rent +$225
A50: 046 | B50: Studio | C50: A | D50: 700 | E50: vacant | F50: 1500 | G50: =F50 -> 1500 | H50: 2029-08-31
A51: 047 | B51: 1BR | C51: B | D51: 820 | E51: vacant | F51: 1650 | G51: =F51 -> 1650 | H51: 2029-08-31
A52: 048 | B52: 2BR | C52: C | D52: 1030 | E52: vacant | F52: 1925 | G52: =F52 -> 1925 | H52: 2029-08-31
A54: Roll summary
A55: Total units | B55: =COUNTA(A5:A52) -> 48
A56: Occupied units (active possession) | B56: =COUNTIF(E5:E52,"active") -> 45
A57: Pending units (no possession) | B57: =COUNTIF(E5:E52,"pending") -> 0
A58: Vacant units | B58: =COUNTIF(E5:E52,"vacant") -> 3
A59: Total area SF | B59: =SUM(D5:D52) -> 40800
A60: Occupied area SF | B60: =SUMIF(E5:E52,"active",D5:D52) -> 38250
A61: Unit occupancy (decimal) | B61: =B56/B55 -> 0.9375
A62: Area occupancy (decimal) | B62: =B60/B59 -> 0.9375
A63: Scheduled monthly rent, all 48 suites (revised roll) | B63: =SUM(F5:F52) -> 81425
A64: Gross potential rent, annual (roll x 12) | B64: =B63*12 -> 977100
A65: In-place monthly rent, occupied suites (executed) | B65: =SUMIF(E5:E52,"active",G5:G52) -> 76700
A66: Annual in-place rent (occupied x 12) | B66: =B65*12 -> 920400
A67: Suite 001 monthly rent after signed amendment | B67: =G5 -> 1850
A69: Group | B69: Type | C69: Units | D69: Occupied | E69: Area SF
A70: A | B70: Studio | C70: =COUNTIF($C$5:$C$52,"A") -> 16 | D70: =COUNTIFS($C$5:$C$52,"A",$E$5:$E$52,"active") -> 15 | E70: =SUMIF($C$5:$C$52,"A",$D$5:$D$52) -> 11200
A71: B | B71: 1BR | C71: =COUNTIF($C$5:$C$52,"B") -> 16 | D71: =COUNTIFS($C$5:$C$52,"B",$E$5:$E$52,"active") -> 15 | E71: =SUMIF($C$5:$C$52,"B",$D$5:$D$52) -> 13120
A72: C | B72: 2BR | C72: =COUNTIF($C$5:$C$52,"C") -> 16 | D72: =COUNTIFS($C$5:$C$52,"C",$E$5:$E$52,"active") -> 15 | E72: =SUMIF($C$5:$C$52,"C",$D$5:$D$52) -> 16480
A74: On the revised roll there are no pending suites; the manager's 45-of-48 headline now equals certified physical occupancy. Group mapping A/B/C = Studio/1BR/2BR per manager-cover.pdf p.1.

Sheet Underwriting
A1: Magnolia Terrace - Revised underwritten cash flow (roll as of 2026-09-01)
A3: Income | B3: Amount | C3: Source / note
A4: Gross potential rent (annual) [INPUT] | B4: 977100 | C4: Revised roll all-unit scheduled rent 81,425/mo x 12 (rent-roll-revised.xlsx E5:E52)
A5: Economic loss (vacancy/credit) [INPUT] | B5: 0.05 | C5: underwriting-instructions.pdf p.1 (unchanged)
A6: Effective rental income | B6: =B4*(1-B5) -> 928245
A7: Other income per unit per year [INPUT] | B7: 350 | C7: Reimbursements already included; not added twice
A8: Units | B8: ='Rent Roll'!B55 -> 48
A9: Other income (annual) | B9: =B7*B8 -> 16800
A10: Underwritten EGI | B10: =B6+B9 -> 945045
A12: Operating expenses | B12: Amount
A13: Real estate taxes [INPUT] | B13: 102312
A14: Insurance expense [INPUT] | B14: 34104
A15: Other recurring operating expenses [INPUT] | B15: 136416
A16: Management fee % of EGI [INPUT] | B16: 0.03
A17: Management fee | B17: =B16*B10 -> 28351.35
A18: Total underwritten operating expenses | B18: =SUM(B13:B15)+B17 -> 301183.35
A19: Underwritten NOI before reserves | B19: =B10-B18 -> 643861.65
A20: Replacement reserve per unit [INPUT] | B20: 300
A21: Replacement reserves | B21: =B20*B8 -> 14400
A22: Underwritten NCF after reserves | B22: =B19-B21 -> 629461.65
A24: Valuation
A25: Capitalization rate [INPUT] | B25: 0.06 | C25: Prior 5.7500% + 25 bps (revision-notice.pdf p.1)
A26: Capitalization value (NOI before reserves / cap rate) | B26: =B19/B25 -> 10731028
A28: Historical comparison (T12 09/2025-08/2026, unchanged)
A29: Reported collections | B29: 876960 | C29: operating-statement.pdf p.1
A30: Reported T12 NOI | B30: 604128 | C30: Cash basis; before management fee and reserves
A31: Revised underwritten NOI vs reported T12 NOI | B31: =B19-B30 -> 39733.65
A32: Annual in-place rent (executed, occupied suites) | B32: ='Rent Roll'!B66 -> 920400
A34: Definitions unchanged: T12 NOI is cash-basis actual before management fee and reserves; underwritten NOI is stabilized all-unit gross potential less 5% loss plus other income, less prescribed expenses; NCF deducts $300/unit reserves.

Sheet Debt
A1: Revised debt sizing and sources / uses
A3: Constraint inputs | B3: Value | C3: Note
A4: Maximum LTV | B4: 0.65
A5: Minimum DSCR (on NCF) | B5: 1.25
A6: Minimum NCF debt yield | B6: 0.09
A7: Amortization (years) | B7: 30
A8: Note rate | B8: 0.0625
A9: Underwriting rate floor | B9: 0.06 | C9: Floor still below note rate; not binding
A10: Sizing rate (initial 6.2500% + 75 bps) [INPUT] | B10: 0.08 | C10: revision-notice.pdf p.1; exceeds both note rate and floor
A12: Sizing tests | B12: Loan amount
A13: LTV limit | B13: =B4*Underwriting!B26 -> 6975167.9
A14: Maximum annual debt service at min DSCR | B14: =Underwriting!B22/B5 -> 503569.32
A15: DSCR limit (PV of monthly payment, 30-yr amort) | B15: =(B14/12)*(1-(1+B10/12)^(-B7*12))/(B10/12) -> 5719015.5
A16: Debt yield limit | B16: =Underwriting!B22/B6 -> 6994018.3
A17: Maximum loan (binding = minimum) | B17: =MIN(B13,B15,B16) -> 5719015.5
A18: Binding constraint | B18: =IF(B17=B15,"DSCR",IF(B17=B13,"LTV","Debt yield")) -> DSCR
A19: Loan to capitalization value | B19: =B17/Underwriting!B26 -> 0.53294203
A20: Actual annual debt service at sized loan | B20: =-PMT(B10/12,B7*12,B17)*12 -> 503569.32
A21: DSCR at sized loan (NCF basis) | B21: =Underwriting!B22/B20 -> 1.25
A22: NCF debt yield at sized loan | B22: =Underwriting!B22/B17 -> 0.11006469
A24: Sources | B24: Amount
A25: Sized first mortgage | B25: =B17 -> 5719015.5
A27: Uses | B27: Amount
A28: Existing loan payoff | B28: 4200000
A29: Origination fee (1% of sized loan) | B29: =0.01*B17 -> 57190.155
A30: Closing costs | B30: 45000
A31: Total uses before distribution | B31: =SUM(B28:B30) -> 4302190.2
A32: Net cash-out (negative = equity required) | B32: =B25-B31 -> 1416825.4
A34: Refinance shortfall test | B34: =IF(B32<0,"Shortfall","No shortfall") -> No shortfall
A36: Change vs initial: maximum loan falls from $6,788,545 to the amount above because the sizing rate rises 75 bps; the higher cap rate lowers the LTV ceiling, while DSCR remains binding.

Sheet Sensitivity
A1: Revised maximum loan sensitivity - cap rate (rows) vs sizing rate (columns)
A2: Each cell = MIN(LTV limit, DSCR limit, debt yield limit) holding revised NOI/NCF constant. Base case shaded by rate 7.0000% / cap 6.0000%.
A4: Cap rate \ Sizing rate | B4: 0.065 | C4: 0.07 | D4: 0.075 | E4: 0.08
A5: 0.055 | B5: =MIN(Debt!$B$4*Underwriting!$B$19/$A5,(Underwriting!$B$22/Debt!$B$5/12)*(1-(1+B$4/12)^(-Debt!$B$7*12))/(B$4/12),Underwriting!$B$22/Debt!$B$6) -> 6639176.2 | C5: =MIN(Debt!$B$4*Underwriting!$B$19/$A5,(Underwriting!$B$22/Debt!$B$5/12)*(1-(1+C$4/12)^(-Debt!$B$7*12))/(C$4/12),Underwriting!$B$22/Debt!$B$6) -> 6307523.3 | D5: =MIN(Debt!$B$4*Underwriting!$B$19/$A5,(Underwriting!$B$22/Debt!$B$5/12)*(1-(1+D$4/12)^(-Debt!$B$7*12))/(D$4/12),Underwriting!$B$22/Debt!$B$6) -> 6001607.4 | E5: =MIN(Debt!$B$4*Underwriting!$B$19/$A5,(Underwriting!$B$22/Debt!$B$5/12)*(1-(1+E$4/12)^(-Debt!$B$7*12))/(E$4/12),Underwriting!$B$22/Debt!$B$6) -> 5719015.5
A6: 0.0575 | B6: =MIN(Debt!$B$4*Underwriting!$B$19/$A6,(Underwriting!$B$22/Debt!$B$5/12)*(1-(1+B$4/12)^(-Debt!$B$7*12))/(B$4/12),Underwriting!$B$22/Debt!$B$6) -> 6639176.2 | C6: =MIN(Debt!$B$4*Underwriting!$B$19/$A6,(Underwriting!$B$22/Debt!$B$5/12)*(1-(1+C$4/12)^(-Debt!$B$7*12))/(C$4/12),Underwriting!$B$22/Debt!$B$6) -> 6307523.3 | D6: =MIN(Debt!$B$4*Underwriting!$B$19/$A6,(Underwriting!$B$22/Debt!$B$5/12)*(1-(1+D$4/12)^(-Debt!$B$7*12))/(D$4/12),Underwriting!$B$22/Debt!$B$6) -> 6001607.4 | E6: =MIN(Debt!$B$4*Underwriting!$B$19/$A6,(Underwriting!$B$22/Debt!$B$5/12)*(1-(1+E$4/12)^(-Debt!$B$7*12))/(E$4/12),Underwriting!$B$22/Debt!$B$6) -> 5719015.5
A7: 0.06 | B7: =MIN(Debt!$B$4*Underwriting!$B$19/$A7,(Underwriting!$B$22/Debt!$B$5/12)*(1-(1+B$4/12)^(-Debt!$B$7*12))/(B$4/12),Underwriting!$B$22/Debt!$B$6) -> 6639176.2 | C7: =MIN(Debt!$B$4*Underwriting!$B$19/$A7,(Underwriting!$B$22/Debt!$B$5/12)*(1-(1+C$4/12)^(-Debt!$B$7*12))/(C$4/12),Underwriting!$B$22/Debt!$B$6) -> 6307523.3 | D7: =MIN(Debt!$B$4*Underwriting!$B$19/$A7,(Underwriting!$B$22/Debt!$B$5/12)*(1-(1+D$4/12)^(-Debt!$B$7*12))/(D$4/12),Underwriting!$B$22/Debt!$B$6) -> 6001607.4 | E7: =MIN(Debt!$B$4*Underwriting!$B$19/$A7,(Underwriting!$B$22/Debt!$B$5/12)*(1-(1+E$4/12)^(-Debt!$B$7*12))/(E$4/12),Underwriting!$B$22/Debt!$B$6) -> 5719015.5
A8: 0.0625 | B8: =MIN(Debt!$B$4*Underwriting!$B$19/$A8,(Underwriting!$B$22/Debt!$B$5/12)*(1-(1+B$4/12)^(-Debt!$B$7*12))/(B$4/12),Underwriting!$B$22/Debt!$B$6) -> 6639176.2 | C8: =MIN(Debt!$B$4*Underwriting!$B$19/$A8,(Underwriting!$B$22/Debt!$B$5/12)*(1-(1+C$4/12)^(-Debt!$B$7*12))/(C$4/12),Underwriting!$B$22/Debt!$B$6) -> 6307523.3 | D8: =MIN(Debt!$B$4*Underwriting!$B$19/$A8,(Underwriting!$B$22/Debt!$B$5/12)*(1-(1+D$4/12)^(-Debt!$B$7*12))/(D$4/12),Underwriting!$B$22/Debt!$B$6) -> 6001607.4 | E8: =MIN(Debt!$B$4*Underwriting!$B$19/$A8,(Underwriting!$B$22/Debt!$B$5/12)*(1-(1+E$4/12)^(-Debt!$B$7*12))/(E$4/12),Underwriting!$B$22/Debt!$B$6) -> 5719015.5
A9: 0.065 | B9: =MIN(Debt!$B$4*Underwriting!$B$19/$A9,(Underwriting!$B$22/Debt!$B$5/12)*(1-(1+B$4/12)^(-Debt!$B$7*12))/(B$4/12),Underwriting!$B$22/Debt!$B$6) -> 6438616.5 | C9: =MIN(Debt!$B$4*Underwriting!$B$19/$A9,(Underwriting!$B$22/Debt!$B$5/12)*(1-(1+C$4/12)^(-Debt!$B$7*12))/(C$4/12),Underwriting!$B$22/Debt!$B$6) -> 6307523.3 | D9: =MIN(Debt!$B$4*Underwriting!$B$19/$A9,(Underwriting!$B$22/Debt!$B$5/12)*(1-(1+D$4/12)^(-Debt!$B$7*12))/(D$4/12),Underwriting!$B$22/Debt!$B$6) -> 6001607.4 | E9: =MIN(Debt!$B$4*Underwriting!$B$19/$A9,(Underwriting!$B$22/Debt!$B$5/12)*(1-(1+E$4/12)^(-Debt!$B$7*12))/(E$4/12),Underwriting!$B$22/Debt!$B$6) -> 5719015.5
A11: Net cash-out at revised base case | B11: =Debt!B32 -> 1416825.4
A12: Net cash-out at prior initial base case (archive) | B12: 2475660
A13: DSCR governs throughout this grid at the revised rates; the debt yield ceiling of NCF/9% and the LTV ceiling sit above it.

Sheet Sources
A1: Source register (revision R1)
A3: File | B3: Location | C3: Facts used / status
A4: rent-roll-revised.xlsx | B4: Rent Roll A2:G52 | C4: CONTROLLING roll dated 2026-09-01: 48 units, 45 active, 0 pending, 3 vacant; suite 045 active at $2,150/mo; all expirations 2029-08-31
A5: revision-notice.pdf | B5: p.1 | C5: Supersession effective 2026-09-01; suite 045 active and +$225 rent; sizing rate +75 bps; cap rate +25 bps; all other rules and payoff unchanged
A6: rent-roll-certified.xlsx | B6: Rent Roll A2:G52 | C6: Prior certified roll dated 2026-08-31; superseded, retained for audit trail
A7: rent-roll-archive.xlsx | B7: Rent Roll A2:G52 | C7: Stale archive dated 2026-06-30; superseded, not used
A8: lease-001.pdf | B8: p.1 | C8: Suite 001 executed lease: $1,500/mo, 700 SF, expiry 2029-08-31, deposit $3,000, no free rent
A9: lease-correspondence.pdf | B9: p.1 | C9: Signed amendment executed 2026-07-20, effective 2026-08-01: +$350/mo; continues to apply (in-place $1,850)
A10: operating-statement.pdf | B10: p.1 | C10: T12 09/2025-08/2026: collections 876,960; tax 102,312; insurance 34,104; other 136,416; roof capital 0; reported NOI 604,128
A11: insurance.pdf | B11: p.1 | C11: GL aggregate limit $2,000,000; policy 2026-07-01 to 2027-06-30
A12: manager-cover.pdf | B12: p.1 | C12: Raleigh, NC multifamily; A/B/C = Studio/1BR/2BR; approved copy sentence
A13: underwriting-instructions.pdf | B13: p.1 | C13: 5% loss, $350/unit other income, expense lines, 3% management, $300/unit reserves, 65% LTV / 1.25x DSCR / 9% debt yield, 30-yr amort, note 6.2500% vs floor 6.0000%, 1% fee, $45,000 closing, $4,200,000 payoff
A14: diligence-status.pdf | B14: p.1 | C14: Legal, environmental, PCA and title reviews incomplete - routine pending items, no defect findings
A16: Not supplied (explicitly unknown, not zero): photographs, asking price, market sale/rent comparables, sponsor history, capital budget, tax/insurance renewal quotes, suite 045 possession-date documentation beyond the revision notice.
A18: Approved copy: "Source-backed analysis. Assumptions remain subject to diligence."
