Workbook

Sheet Assumptions
A1: Stonebridge Logistics - Refinance underwriting assumptions
A2: As of 2026-08-31 | fictional packet | USD
A3: Cells in column B are editable inputs driving all downstream sheets
A4: Assumption | B4: Value | C4: Source
A5: Valuation cap rate (INPUT) | B5: 0.0675 | C5: Lender-Terms.pdf p1 Valuation
A6: Index rate | B6: 0.0325 | C6: Lender-Terms.pdf p1 Contract rate
A7: Index floor | B7: 0.04 | C7: Lender-Terms.pdf p1 Contract rate
A8: Spread (applied after floor) | B8: 0.0275 | C8: Lender-Terms.pdf p1 Contract rate
A9: Contract rate (computed) | B9: =MAX(B6,B7)+B8 -> 0.0675 | C9: MAX(index, floor) + spread
A10: Underwriting (sizing) rate floor | B10: 0.0725 | C10: Lender-Terms.pdf p1 Sizing rate
A11: Sizing rate increment (INPUT; 0.01 = +100bps) | B11: 0 | C11: Property-and-Plan.pdf p2 sensitivity instruction
A12: Sizing rate (computed, INPUT-driven) | B12: =MAX(B9,B10)+B11 -> 0.0725 | C12: MAX(contract rate, 7.25% floor) + increment
A13: Amortization term (months) | B13: 300 | C13: Lender-Terms.pdf p1 Amortization 25 years
A14: Interest-only period (months) | B14: 12 | C14: Lender-Terms.pdf p1 IO period
A15: Gross potential base rent (INPUT, annual) | B15: 900000 | C15: Property-and-Plan.pdf p2 supplied scenario
A16: Combined revenue loss % of GPR | B16: 0.08 | C16: Property-and-Plan.pdf p2
A17: Other income / recoveries (INPUT, annual) | B17: 195000 | C17: Property-and-Plan.pdf p2, added after revenue loss
A18: EGI multiplier (INPUT; 0.95 = EGI -5%) | B18: 1 | C18: Scales GPR and other income; loss % held constant
A19: Total rentable SF | B19: 85000 | C19: Rent-Roll.xlsx rows 7-10
A20: Replacement reserves per SF per year | B20: 0.2 | C20: Property-and-Plan.pdf p2
A21: Management fee % of underwritten EGI | B21: 0.03 | C21: Property-and-Plan.pdf p2 greater of T12 or 3%
A22: T12 actual management fee | B22: 25200 | C22: T12-Statement.pdf p2 annual column
A23: Maximum LTV | B23: 0.6 | C23: Lender-Terms.pdf p1 LTV
A24: Minimum DSCR (NCF after reserves) | B24: 1.3 | C24: Lender-Terms.pdf p1 DSCR
... A28: Fixed closing costs | B28: 70000 | C28: Property-and-Plan.pdf p1
A30: Underwritten operating expenses excluding management | B30: Annual | C30: Basis
A31: Real estate taxes | B31: 132000 | C31: Property-and-Plan.pdf p2 (T12 actual $126,000)
A32: Property insurance | B32: 33600 | C32: Plan p2 renewal confirmation dated 2026-08-25
A33: Utilities | B33: 12000 | C33: T12 actual per plan
A34: Repairs and maintenance | B34: 18000 | C34: T12 $24,000 less $6,000 one-time casualty cleanup
A35: Payroll / contract labor | B35: 18000 | C35: T12 actual per plan
A36: Administrative / legal | B36: 18000 | C36: T12 actual per plan

Sheet Historical T12
A1: Historical T12 - September 2025 through August 2026 actual
A2: Source: T12-Statement.pdf pages 1-2, Annual column
A4: Line | B4: T12 actual | C4: Note
A5: Gross potential base rent | B5: 852000
A6: Vacancy loss | B6: -150000
A7: Concessions | B7: -36000
A8: Bad debt | B8: -6000
A9: Other income / recoveries | B9: 186000
A10: T12 effective gross income | B10: =SUM(B5:B9) -> 846000
A12: Real estate taxes | B12: 126000
A13: Property insurance | B13: 30000
A14: Utilities | B14: 12000
A15: Repairs and maintenance | B15: 24000 | C15: Includes $6,000 one-time casualty cleanup
A16: Payroll / contract labor | B16: 18000
A17: Administrative / legal | B17: 18000
A18: Management fee | B18: 25200
A19: T12 operating expenses (excl. reserves, capex, debt, depreciation) | B19: =SUM(B12:B18) -> 253200
A21: T12 NOI before replacement reserves | B21: =B10-B19 -> 592800
A22: T12 replacement reserves (below NOI) | B22: 17000
A23: T12 NCF after replacement reserves | B23: =B21-B22 -> 575800
A25: Memo: capital improvements (below cash flow) | B25: 220000
A26: Memo: loan principal and interest (below cash flow) | B26: 294000
A27: Memo: depreciation (noncash) | B27: 180000
A29: Historical results are actuals, not annualized rent roll and not underwriting.

Sheet Rent Roll
A1: Contractual rent and occupancy as of 2026-08-31
A2: Source: Rent-Roll.xlsx rows 7-10; Lease-File.pdf p1 for premises 101
A4: Unit | B4: Tenant | C4: Area SF | D4: Status | E4: Monthly base rent | F4: Market monthly rent | G4: Lease expiry
A5: 101 | B5: Tenant A LLC | C5: 18000 | D5: Occupied | E5: 15000 | F5: 15000 | G5: 2030-08-31
A6: 102 | B6: Tenant B LLC | C6: 22000 | D6: Occupied | E6: 18700 | F6: 18700 | G6: 2028-08-31
A7: 103 | B7: Tenant C LLC | C7: 30000 | D7: Occupied | E7: 27000 | F7: 27000 | G7: 2029-08-31
A8: 104 | B8: Vacant | C8: 15000 | D8: Vacant | E8: 0 | F8: 12500 | G8: n/a
A10: Totals | C10: =SUM(C5:C8) -> 85000 | E10: =SUM(E5:E8) -> 60700
A12: Space count | C12: =COUNTA(A5:A8) -> 4
A13: Occupied count | C13: =COUNTIF(D5:D8,"Occupied") -> 3
A14: Occupied SF | C14: =SUMIF(D5:D8,"Occupied",C5:C8) -> 70000
A15: Occupancy by count (percent) | C15: =100*C13/C12 -> 75
A16: Occupancy by area (percent) | C16: =100*C14/C10 -> 82.352941
A17: Annualized contractual base rent (context only) | C17: =E10*12 -> 728400
A19: Executed lease for premises 101 confirms $15,000 per month, expiry 2030-08-31, $30,000 security deposit; no amendment or renewal exercise notice is in the packet.

Sheet Underwriting
A1: Underwritten cash flow - supplied scenario, September 2026 forward
A2: Source: Property-and-Plan.pdf p2; live links to Assumptions
A4: Line | B4: Underwritten | C4: Basis
A5: Gross potential base rent | B5: =Assumptions!B15*Assumptions!B18 -> 900000 | C5: GPR input times EGI multiplier
A6: Combined revenue loss (vacancy, concessions, bad debt) | B6: =-B5*Assumptions!B16 -> -72000 | C6: 8.00% of underwritten GPR
A7: Other income / recoveries | B7: =Assumptions!B17*Assumptions!B18 -> 195000 | C7: Added after revenue loss
A8: Underwritten effective gross income (EGI) | B8: =B5+B6+B7 -> 1023000
A10: Real estate taxes | B10: =Assumptions!B31 -> 132000
A11: Property insurance | B11: =Assumptions!B32 -> 33600
A12: Utilities | B12: =Assumptions!B33 -> 12000
A13: Repairs and maintenance | B13: =Assumptions!B34 -> 18000
A14: Payroll / contract labor | B14: =Assumptions!B35 -> 18000
A15: Administrative / legal | B15: =Assumptions!B36 -> 18000
A16: Management fee (greater of T12 actual and 3.00% of EGI) | B16: =MAX(Assumptions!B22,Assumptions!B21*B8) -> 30690
A17: Underwritten operating expenses before reserves | B17: =SUM(B10:B16) -> 262290
A19: Underwritten NOI before replacement reserves | B19: =B8-B17 -> 760710
A20: Replacement reserves (per SF times SF) | B20: =Assumptions!B19*Assumptions!B20 -> 17000
A21: Underwritten NCF after replacement reserves | B21: =B19-B20 -> 743710
A23: Indicative capitalized value (NOI before reserves / cap rate) | B23: =B19/Assumptions!B5 -> 11269778
A24: Expense ratio (opex / EGI) | B24: =B17/B8 -> 0.25639296

Sheet Loan Sizing
A1: Loan sizing - three constraints
A2: Source: Lender-Terms.pdf p1; unrounded intermediates
A4: Item | B4: Value | C4: Definition
A5: Contract rate (current; first-year debt service) | B5: =Assumptions!B9 -> 0.0675 | C5: MAX(3.25% index, 4.00% floor) plus 2.75% spread
A6: Sizing rate (underwriting) | B6: =Assumptions!B12 -> 0.0725 | C6: Greater of contract rate and 7.25% floor plus increment
A7: Annual debt constant per $1 at sizing rate | B7: =-PMT(B6/12,Assumptions!B13,1)*12 -> 0.086736824 | C7: 12 monthly payments, 300-month amortization
A9: LTV limit | B9: =Assumptions!B23*Underwriting!B23 -> 6761866.7 | C9: 60.00% times capitalized value
A10: DSCR limit | B10: =Underwriting!B21/(Assumptions!B24*B7) -> 6595637.1 | C10: UW NCF divided by (1.30 times annual constant)
A11: Debt yield limit | B11: =Underwriting!B21/Assumptions!B25 -> 7437100 | C11: UW NCF divided by 10.00%
A12: Maximum loan (lowest constraint) | B12: =MIN(B9:B11) -> 6595637.1
A13: Binding constraint | B13: =IF(B12=B9,"LTV",IF(B12=B10,"DSCR","Debt yield")) -> DSCR
A15: Sizing annual debt service (amortizing, sizing rate) | B15: =B12*B7 -> 572084.62
A16: Sizing DSCR (UW NCF / sizing debt service) | B16: =Underwriting!B21/B15 -> 1.3
A17: Sizing debt yield (UW NCF / maximum loan) | B17: =Underwriting!B21/B12 -> 0.11275787
A18: First-year contractual debt service (12-month IO at contract rate) | B18: =IF(Assumptions!B14>=12,B12*B5,-PMT(B5/12,Assumptions!B13,B12)*12) -> 445205.51
A19: Memo: amortizing annual debt service at contract rate | B19: =-PMT(B5/12,Assumptions!B13,B12)*12 -> 546840.21
A20: Memo: DSCR on first-year contractual (IO) debt service | B20: =Underwriting!B21/B18 -> 1.670487
A21: Memo: loan per rentable SF | B21: =B12/Assumptions!B19 -> 77.595731

Sheet Sources Uses
A1: Sources and uses at the maximum loan
A2: Source: Property-and-Plan.pdf p1; Lender-Terms.pdf p1
A4: Sources | B4: Amount | C4: Reference
A5: New first-mortgage loan proceeds | B5: ='Loan Sizing'!B12 -> 6595637.1 | C5: Loan Sizing!B12
A6: Borrower cash contribution (if required) | B6: =MAX(0,-B14) -> 0 | C6: Cash-in only if proceeds are insufficient
A7: Total sources | B7: =B5+B6 -> 6595637.1
A9: Uses
A10: Existing debt payoff | B10: =Assumptions!B27 -> 4200000 | C10: Property-and-Plan.pdf p1
A11: Origination fee (1.25% of principal) | B11: =Assumptions!B26*B5 -> 82445.464 | C11: Lender-Terms.pdf p1
A12: Fixed closing costs | B12: =Assumptions!B28 -> 70000 | C12: Property-and-Plan.pdf p1
A13: Total uses before distribution | B13: =SUM(B10:B12) -> 4352445.5
A14: Net cash to borrower (negative equals cash in) | B14: =B5-B13 -> 2243191.7
A16: No fee capitalization, interest reserve, holdback or earn-out is assumed (Lender-Terms.pdf p1).

Sheet Sensitivity
A1: Sensitivity scenarios
A2: EGI -5% recomputes the management minimum; other operating expenses and reserves held constant (Property-and-Plan.pdf p2)
A4: Metric | B4: Base case | C4: EGI -5% | D4: EGI -5% and rate +100bps | E4: Cap rate +50bps
A5: EGI | B5: =Underwriting!B8 -> 1023000 | C5: =Underwriting!B8*0.95 -> 971850 | D5: =C5 -> 971850 | E5: =B5 -> 1023000
A6: Management fee | B6: =Underwriting!B16 -> 30690 | C6: =MAX(Assumptions!B22,Assumptions!B21*C5) -> 29155.5 | D6: =C6 -> 29155.5 | E6: =B6 -> 30690
A7: Other operating expenses (unchanged) | B7: =Underwriting!B17-Underwriting!B16 -> 231600 | C7: =B7 -> 231600 | D7: =B7 -> 231600 | E7: =B7 -> 231600
A8: NOI before reserves | B8: =B5-B6-B7 -> 760710 | C8: =C5-C6-C7 -> 711094.5 | D8: =D5-D6-D7 -> 711094.5 | E8: =E5-E6-E7 -> 760710
A9: Replacement reserves | B9: =Underwriting!B20 -> 17000 | C9: =B9 -> 17000 | D9: =B9 -> 17000 | E9: =B9 -> 17000
A10: NCF after reserves | B10: =B8-B9 -> 743710 | C10: =C8-C9 -> 694094.5 | D10: =D8-D9 -> 694094.5 | E10: =E8-E9 -> 743710
A11: Cap rate used | B11: =Assumptions!B5 -> 0.0675 | C11: =Assumptions!B5 -> 0.0675 | D11: =Assumptions!B5 -> 0.0675 | E11: =Assumptions!B5+0.005 -> 0.0725
A12: Indicative value | B12: =B8/B11 -> 11269778 | C12: =C8/C11 -> 10534733 | D12: =D8/D11 -> 10534733 | E12: =E8/E11 -> 10492552
A13: Sizing rate used | B13: =Assumptions!B12 -> 0.0725 | C13: =Assumptions!B12 -> 0.0725 | D13: =Assumptions!B12+0.01 -> 0.0825 | E13: =Assumptions!B12 -> 0.0725
A14: Annual debt constant | B14: =-PMT(B13/12,Assumptions!B13,1)*12 -> 0.086736824 | C14: =-PMT(C13/12,Assumptions!B13,1)*12 -> 0.086736824 | D14: =-PMT(D13/12,Assumptions!B13,1)*12 -> 0.094614016 | E14: =-PMT(E13/12,Assumptions!B13,1)*12 -> 0.086736824
A15: LTV limit | B15: =Assumptions!B23*B12 -> 6761866.7 | C15: =Assumptions!B23*C12 -> 6320840 | D15: =Assumptions!B23*D12 -> 6320840 | E15: =Assumptions!B23*E12 -> 6295531
A16: DSCR limit | B16: =B10/(Assumptions!B24*B14) -> 6595637.1 | C16: =C10/(Assumptions!B24*C14) -> 6155619.1 | D16: =D10/(Assumptions!B24*D14) -> 5643126.3 | E16: =E10/(Assumptions!B24*E14) -> 6595637.1
A17: Debt yield limit | B17: =B10/Assumptions!B25 -> 7437100 | C17: =C10/Assumptions!B25 -> 6940945 | D17: =D10/Assumptions!B25 -> 6940945 | E17: =E10/Assumptions!B25 -> 7437100
A18: Maximum loan | B18: =MIN(B15:B17) -> 6595637.1 | C18: =MIN(C15:C17) -> 6155619.1 | D18: =MIN(D15:D17) -> 5643126.3 | E18: =MIN(E15:E17) -> 6295531
A19: Binding constraint | B19: =IF(B18=B15,"LTV",IF(B18=B16,"DSCR","Debt yield")) -> DSCR | C19: =IF(C18=C15,"LTV",IF(C18=C16,"DSCR","Debt yield")) -> DSCR | D19: =IF(D18=D15,"LTV",IF(D18=D16,"DSCR","Debt yield")) -> DSCR | E19: =IF(E18=E15,"LTV",IF(E18=E16,"DSCR","Debt yield")) -> LTV
A20: Net cash to borrower (negative equals cash in) | B20: =B18-Assumptions!B27-Assumptions!B26*B18-Assumptions!B28 -> 2243191.7 | C20: =C18-Assumptions!B27-Assumptions!B26*C18-Assumptions!B28 -> 1808673.8 | D20: =D18-Assumptions!B27-Assumptions!B26*D18-Assumptions!B28 -> 1302587.3 | E20: =E18-Assumptions!B27-Assumptions!B26*E18-Assumptions!B28 -> 1946836.9

Sheet Input Output Map
A1: Reviewer map - editable inputs and key outputs
A3: Editable input | B3: Location | C3: Note
A4: Cap rate | B4: Assumptions!B5 | C4: Valuation cap rate; +50bps case in Sensitivity column E
A5: Sizing rate increment | B5: Assumptions!B11 | C5: Enter 0.01 for +100bps; sizing rate computes at Assumptions!B12
A6: Gross potential base rent | B6: Assumptions!B15 | C6: Drives underwritten EGI
A7: Other income / recoveries | B7: Assumptions!B17 | C7: Added after revenue loss
A8: EGI multiplier | B8: Assumptions!B18 | C8: Set 0.95 to scale EGI down 5%, loss % constant
A9: Revenue loss percentage | B9: Assumptions!B16
A10: Expense, reserve and loan term inputs | B10: Assumptions!B10:B36
A12: Key output | B12: Location | C12: Live value
A13: Underwritten NOI before reserves | B13: Underwriting!B19 | C13: =Underwriting!B19 -> 760710
A14: Underwritten NCF after reserves | B14: Underwriting!B21 | C14: =Underwriting!B21 -> 743710
A15: Capitalized value | B15: Underwriting!B23 | C15: =Underwriting!B23 -> 11269778
A16: LTV limit | B16: Loan Sizing!B9 | C16: ='Loan Sizing'!B9 -> 6761866.7
A17: DSCR limit | B17: Loan Sizing!B10 | C17: ='Loan Sizing'!B10 -> 6595637.1
A18: Debt yield limit | B18: Loan Sizing!B11 | C18: ='Loan Sizing'!B11 -> 7437100
A19: Maximum loan | B19: Loan Sizing!B12 | C19: ='Loan Sizing'!B12 -> 6595637.1
A20: Binding constraint | B20: Loan Sizing!B13 | C20: ='Loan Sizing'!B13 -> DSCR
A21: First-year contractual debt service | B21: Loan Sizing!B18 | C21: ='Loan Sizing'!B18 -> 445205.51
A22: Net cash to borrower | B22: Sources Uses!B14 | C22: ='Sources Uses'!B14 -> 2243191.7
A23: Stress NOI (EGI -5%) | B23: Sensitivity!C8 | C23: =Sensitivity!C8 -> 711094.5
A24: Stress maximum loan (EGI -5%, rate +100bps) | B24: Sensitivity!D18 | C24: =Sensitivity!D18 -> 5643126.3
A25: T12 NOI before reserves | B25: Historical T12!B21 | C25: ='Historical T12'!B21 -> 592800
A26: T12 NCF after reserves | B26: Historical T12!B23 | C26: ='Historical T12'!B23 -> 575800
