Workbook

Sheet README
A1: Maple Crossing — Underwriting Workbook (Revision 2)
A3: Revision: | B3: Rev 2 — applies revision-notice.pdf and rent-roll-revised.xlsx (as-of 2026-09-01)
A4: Prior version: | B4: Rev 1 (2026-08-31) preserved in audit archive; not replaced
A5: Source packet: | B5: CRE Bench — original fictional evaluation material
A6: Prepared per: | B6: underwriting-instructions.pdf + revision-notice.pdf
A8: CHANGES vs. Rev 1
A9: • Rent roll: | B9: Superseded by rent-roll-revised.xlsx (as-of 2026-09-01)
A10: • Suite 002: | B10: Scheduled monthly rent +$225 → $7,025 (status active on both rolls)
A11: • Cap rate: | B11: 6.7500% → 7.0000% (+25 bps)
A12: • Sizing rate: | B12: 6.5000% → 7.2500% (initial sizing rate +75 bps; floor 6.00% unchanged)
A13: • Suite 001 amendment: | B13: Continues to apply — GPR method unchanged (S001 pre-amendment)
A14: • Payoff, fees, opex, loss, other income, reserves, LTV/DSCR/DY limits: | B14: Unchanged
A15: • Correction to Rev 1 arithmetic: | B15: total_area_sf 32,150 (was 31,150 in Rev 1 memo — arithmetic error; source cells unchanged)
A17: Input cells (yellow = editable; orange = changed by revision)
A18: Field | B18: Location | C18: Purpose
A19: gross_potential_rent | B19: Inputs!B7 | C19: All-suite scheduled monthly rent × 12, per revised certified roll (Suite 001 pre-amendment)
A20: cap_rate | B20: Inputs!B22 | C20: Direct cap rate applied to NOI before reserves (revised +25 bps)
A21: sizing_rate | B21: Inputs!B27 | C21: Loan sizing rate = MAX(note rate, floor); note rate revised +75 bps
A23: Output cells (formula-driven)
A24: Field | B24: Location | C24: Definition
A25: uw_egi | B25: UW!B10 | C25: GPR × (1 − economic loss) + other income
A26: uw_noi | B26: UW!B22 | C26: EGI − operating expenses (before replacement reserves)
A27: uw_ncf | B27: UW!B25 | C27: NOI − replacement reserves
A28: capitalization_value | B28: UW!B32 | C28: UW NOI ÷ cap rate
A29: maximum_loan | B29: Debt!B24 | C29: MIN(LTV, DSCR, Debt Yield constraints)
A30: net_cash_out | B30: Debt!B32 | C30: Maximum loan − payoff − origination fee − closing costs

Sheet Inputs
A1: Underwriting Inputs (Rev 2)
A3: INCOME
A4: Suite count (all) | B4: 10 | C4: count | D4: RentRoll
A5: Economic loss | B5: 0.05 | C5: ratio | D5: underwriting-instructions.pdf
A6: Other income per suite (annual) | B6: 350 | C6: USD | D6: underwriting-instructions.pdf
A7: gross_potential_rent (annual) | B7: 817200 | C7: USD | D7: revised roll ×12, S001 pre-amendment [CHANGED from 814,500]
A9: EXPENSES
A10: uw_tax | B10: 85964 | C10: USD | D10: underwriting-instructions.pdf
A11: uw_insurance | B11: 28655 | C11: USD | D11: underwriting-instructions.pdf
A12: uw_other_operating_expenses | B12: 114618 | C12: USD | D12: underwriting-instructions.pdf
A13: management_fee_pct | B13: 0.03 | C13: ratio | D13: underwriting-instructions.pdf
A14: replacement_reserve_per_suite | B14: 300 | C14: USD | D14: underwriting-instructions.pdf
A17: VALUATION & DEBT
A19: note_rate | B19: 0.0725 | C19: ratio | D19: revised +75 bps [was 6.5000%]
A20: floor_rate | B20: 0.06 | C20: ratio | D20: underwriting-instructions.pdf (unchanged)
A22: cap_rate | B22: 0.07 | C22: ratio | D22: revised +25 bps [was 6.7500%]
A24: ltv_limit | B24: 0.65 | C24: ratio
A25: dscr_limit | B25: 1.25 | C25: ratio
A26: debt_yield_limit | B26: 0.09 | C26: ratio
A27: sizing_rate | B27: =MAX(B19,B20) | C27: ratio | D27: MAX(note_rate, floor_rate) — evaluates to 7.2500%
A28: amortization_years | B28: 30 | C28: years
A29: origination_fee_pct | B29: 0.01 | C29: ratio
A30: closing_costs | B30: 45000 | C30: USD
A31: existing_payoff | B31: 4300000 | C31: USD

Sheet RentRoll
A1: Certified Rent Roll (REVISED) — as of 2026-09-01
A2: Source: rent-roll-revised.xlsx (supersedes 2026-08-31 roll per revision-notice.pdf). Suite 002 rent +$225 to $7,025; all other terms unchanged.
A4: Suite | B4: Unit type | C4: Type group | D4: Area SF | E4: Possession | F4: Monthly rent | G4: Lease expiry
A5: 001 | B5: Small suite | C5: A | D5: 3080 | E5: active | F5: 6650 | G5: 2029-08-31
A6: 002 | B6: Standard suite | C6: B | D6: 3200 | E6: active | F6: 7025 | G6: 2029-08-31
A7: 003 | B7: Large suite | C7: C | D7: 3410 | E7: active | F7: 7075 | G7: 2029-08-31
A8: 004 | B8: Small suite | C8: A | D8: 3080 | E8: active | F8: 6650 | G8: 2029-08-31
A9: 005 | B9: Standard suite | C9: B | D9: 3200 | E9: active | F9: 6800 | G9: 2029-08-31
A10: 006 | B10: Large suite | C10: C | D10: 3410 | E10: active | F10: 7075 | G10: 2029-08-31
A11: 007 | B11: Small suite | C11: A | D11: 3080 | E11: active | F11: 6650 | G11: 2029-08-31
A12: 008 | B12: Standard suite | C12: B | D12: 3200 | E12: active | F12: 6800 | G12: 2029-08-31
A13: 009 | B13: Large suite | C13: C | D13: 3410 | E13: active | F13: 7075 | G13: 2029-08-31
A14: 010 | B14: Small suite | C14: A | D14: 3080 | E14: vacant | F14: 6650 | G14: 2029-08-31
A16: TOTALS / DERIVED
A17: total_units | B17: =COUNTA(A5:A14)
A18: occupied_units (active) | B18: =COUNTIF(E5:E14,"active")
A19: pending_units | B19: 0
A20: total_area_sf | B20: =SUM(D5:D14)
A21: occupied_area_sf | B21: =SUMIF(E5:E14,"active",D5:D14)
A22: unit_occupancy | B22: =B18/B17
A23: area_occupancy | B23: =B21/B20
A24: annual_in_place_rent | B24: =SUMIF(E5:E14,"active",F5:F14)*12
A27: TYPE MAPPING (per manager cover)
A28: Type | B28: Units | C28: Occupied
A29: A (Small) | B29: =COUNTIF(C5:C14,"A") | C29: =COUNTIFS(C5:C14,"A",E5:E14,"active")
A30: B (Standard) | B30: =COUNTIF(C5:C14,"B") | C30: =COUNTIFS(C5:C14,"B",E5:E14,"active")
A31: C (Large) | B31: =COUNTIF(C5:C14,"C") | C31: =COUNTIFS(C5:C14,"C",E5:E14,"active")
A34: GPR RECONCILIATION
A35: All-suite monthly rent (revised) | B35: =SUM(F5:F14)
A36: Less: Suite 001 amendment ($350/mo) | B36: -350
A37: Adjusted monthly (pre-amendment S001) | B37: =B35+B36
A38: GPR annual (×12) | B38: =B37*12

Sheet UW
A1: Underwritten Cash Flow (Rev 2)
A2: Applies revised roll (2026-09-01). Suite 001 GPR method (pre-amendment) preserved per revision notice.
A4: INCOME
A5: gross_potential_rent | B5: =Inputs!B7
A6: economic_loss (%) | B6: =Inputs!B5
A7: effective_rent | B7: =B5*(1-B6)
A8: other_income (annual, $350 × suites) | B8: =Inputs!B6*Inputs!B4
A10: uw_egi | B10: =B7+B8
A12: EXPENSES
A13: uw_tax | B13: =Inputs!B10
A14: uw_insurance | B14: =Inputs!B11
A15: uw_other_operating_expenses | B15: =Inputs!B12
A16: management_fee (3% of EGI) | B16: =Inputs!B13*B10
A17: uw_operating_expenses (total) | B17: =SUM(B13:B16)
A19: NOI & NCF
A22: uw_noi (before reserves) | B22: =B10-B17
A23: replacement_reserves ($300/suite) | B23: =Inputs!B14*Inputs!B4
A25: uw_ncf | B25: =B22-B23
A28: VALUATION
A30: cap_rate | B30: =Inputs!B22
A31: NOI (before reserves) used for cap | B31: =B22
A32: capitalization_value | B32: =B31/B30

Sheet Debt
A1: Debt Sizing & Sources / Uses (Rev 2)
A2: Sizing rate = MAX(note 7.25%, floor 6.00%) per revision. DSCR & DY on NCF after reserves.
A4: ASSUMPTIONS
A5: sizing_rate | B5: =Inputs!B27
A6: amortization_years | B6: =Inputs!B28
A7: monthly_rate | B7: =Inputs!B27/12
A8: n_months | B8: =Inputs!B28*12
A9: PMT per $1 loan (monthly) | B9: =B7*(1+B7)^B8/((1+B7)^B8-1)
A10: Annual DS per $1 loan | B10: =B9*12
A11: ltv_limit | B11: =Inputs!B24
A12: dscr_limit | B12: =Inputs!B25
A13: debt_yield_limit | B13: =Inputs!B26
A16: CONSTRAINTS
A17: Loan by LTV = ltv × value | B17: =B11*UW!B32
A18: Loan by DSCR = (NCF / dscr) / annual DS per $ | B18: =(UW!B25/B12)/B10
A19: Loan by DY = NCF / debt yield | B19: =UW!B25/B13
A21: Binding constraint | B21: =IF(B24=B17,"LTV",IF(B24=B18,"DSCR","Debt Yield"))
A24: maximum_loan | B24: =MIN(B17,B18,B19)
A27: SOURCES & USES (net cash-out)
A28: existing_payoff | B28: =Inputs!B31
A29: origination_fee (1% of loan) | B29: =Inputs!B29*B24
A30: closing_costs | B30: =Inputs!B30
A31: Total uses | B31: =SUM(B28:B30)
A32: net_cash_out (negative = additional equity) | B32: =B24-B31
A35: IMPLIED METRICS AT MAX LOAN
A36: LTV realized | B36: =B24/UW!B32
A37: Annual DS at sizing rate | B37: =B24*B10
A38: DSCR realized (on NCF) | B38: =UW!B25/B37
A39: Debt yield realized (on NCF) | B39: =UW!B25/B24

Sheet Sensitivity
A1: Sensitivity — Cap Rate × Sizing Rate (Rev 2)
A2: Table A: Capitalization value = UW NOI / cap_rate. Table B: Maximum loan by binding constraint at given cap and sizing rate. Base case highlighted (7.00% cap / 7.25% sizing).
A4: Table A — Capitalization value at NOI | D4: Table B — Maximum loan (LTV 65%, DSCR 1.25, DY 9%)
A5: cap_rate ↓ | B5: value | D5: sizing_rate ↓ / cap_rate → | E5: 0.0625 | F5: 0.065 | G5: 0.0675 | H5: 0.07 | I5: 0.0725 | J5: 0.075 | K5: 0.0775
A6: 0.0625 | B6: =UW!$B$22/A6 | D6: 0.065 | E6: =MIN(Debt!$B$11*(UW!$B$22/E$5),(UW!$B$25/Debt!$B$12)/(((0.065/12)*(1+0.065/12)^(Debt!$B$8))/((1+0.065/12)^(Debt!$B$8)-1)*12),UW!$B$25/Debt!$B$13) | F6: =MIN(Debt!$B$11*(UW!$B$22/F$5),(UW!$B$25/Debt!$B$12)/(((0.065/12)*(1+0.065/12)^(Debt!$B$8))/((1+0.065/12)^(Debt!$B$8)-1)*12),UW!$B$25/Debt!$B$13) | G6: =MIN(Debt!$B$11*(UW!$B$22/G$5),(UW!$B$25/Debt!$B$12)/(((0.065/12)*(1+0.065/12)^(Debt!$B$8))/((1+0.065/12)^(Debt!$B$8)-1)*12),UW!$B$25/Debt!$B$13) | H6: =MIN(Debt!$B$11*(UW!$B$22/H$5),(UW!$B$25/Debt!$B$12)/(((0.065/12)*(1+0.065/12)^(Debt!$B$8))/((1+0.065/12)^(Debt!$B$8)-1)*12),UW!$B$25/Debt!$B$13) | I6: =MIN(Debt!$B$11*(UW!$B$22/I$5),(UW!$B$25/Debt!$B$12)/(((0.065/12)*(1+0.065/12)^(Debt!$B$8))/((1+0.065/12)^(Debt!$B$8)-1)*12),UW!$B$25/Debt!$B$13) | J6: =MIN(Debt!$B$11*(UW!$B$22/J$5),(UW!$B$25/Debt!$B$12)/(((0.065/12)*(1+0.065/12)^(Debt!$B$8))/((1+0.065/12)^(Debt!$B$8)-1)*12),UW!$B$25/Debt!$B$13) | K6: =MIN(Debt!$B$11*(UW!$B$22/K$5),(UW!$B$25/Debt!$B$12)/(((0.065/12)*(1+0.065/12)^(Debt!$B$8))/((1+0.065/12)^(Debt!$B$8)-1)*12),UW!$B$25/Debt!$B$13)
A7: 0.065 | B7: =UW!$B$22/A7 | D7: 0.0675 | E7: =MIN(Debt!$B$11*(UW!$B$22/E$5),(UW!$B$25/Debt!$B$12)/(((0.0675/12)*(1+0.0675/12)^(Debt!$B$8))/((1+0.0675/12)^(Debt!$B$8)-1)*12),UW!$B$25/Debt!$B$13) | F7: =MIN(Debt!$B$11*(UW!$B$22/F$5),(UW!$B$25/Debt!$B$12)/(((0.0675/12)*(1+0.0675/12)^(Debt!$B$8))/((1+0.0675/12)^(Debt!$B$8)-1)*12),UW!$B$25/Debt!$B$13) | G7: =MIN(Debt!$B$11*(UW!$B$22/G$5),(UW!$B$25/Debt!$B$12)/(((0.0675/12)*(1+0.0675/12)^(Debt!$B$8))/((1+0.0675/12)^(Debt!$B$8)-1)*12),UW!$B$25/Debt!$B$13) | H7: =MIN(Debt!$B$11*(UW!$B$22/H$5),(UW!$B$25/Debt!$B$12)/(((0.0675/12)*(1+0.0675/12)^(Debt!$B$8))/((1+0.0675/12)^(Debt!$B$8)-1)*12),UW!$B$25/Debt!$B$13) | I7: =MIN(Debt!$B$11*(UW!$B$22/I$5),(UW!$B$25/Debt!$B$12)/(((0.0675/12)*(1+0.0675/12)^(Debt!$B$8))/((1+0.0675/12)^(Debt!$B$8)-1)*12),UW!$B$25/Debt!$B$13) | J7: =MIN(Debt!$B$11*(UW!$B$22/J$5),(UW!$B$25/Debt!$B$12)/(((0.0675/12)*(1+0.0675/12)^(Debt!$B$8))/((1+0.0675/12)^(Debt!$B$8)-1)*12),UW!$B$25/Debt!$B$13) | K7: =MIN(Debt!$B$11*(UW!$B$22/K$5),(UW!$B$25/Debt!$B$12)/(((0.0675/12)*(1+0.0675/12)^(Debt!$B$8))/((1+0.0675/12)^(Debt!$B$8)-1)*12),UW!$B$25/Debt!$B$13)
A8: 0.0675 | B8: =UW!$B$22/A8 | D8: 0.07 | E8: =MIN(Debt!$B$11*(UW!$B$22/E$5),(UW!$B$25/Debt!$B$12)/(((0.07/12)*(1+0.07/12)^(Debt!$B$8))/((1+0.07/12)^(Debt!$B$8)-1)*12),UW!$B$25/Debt!$B$13) | F8: =MIN(Debt!$B$11*(UW!$B$22/F$5),(UW!$B$25/Debt!$B$12)/(((0.07/12)*(1+0.07/12)^(Debt!$B$8))/((1+0.07/12)^(Debt!$B$8)-1)*12),UW!$B$25/Debt!$B$13) | G8: =MIN(Debt!$B$11*(UW!$B$22/G$5),(UW!$B$25/Debt!$B$12)/(((0.07/12)*(1+0.07/12)^(Debt!$B$8))/((1+0.07/12)^(Debt!$B$8)-1)*12),UW!$B$25/Debt!$B$13) | H8: =MIN(Debt!$B$11*(UW!$B$22/H$5),(UW!$B$25/Debt!$B$12)/(((0.07/12)*(1+0.07/12)^(Debt!$B$8))/((1+0.07/12)^(Debt!$B$8)-1)*12),UW!$B$25/Debt!$B$13) | I8: =MIN(Debt!$B$11*(UW!$B$22/I$5),(UW!$B$25/Debt!$B$12)/(((0.07/12)*(1+0.07/12)^(Debt!$B$8))/((1+0.07/12)^(Debt!$B$8)-1)*12),UW!$B$25/Debt!$B$13) | J8: =MIN(Debt!$B$11*(UW!$B$22/J$5),(UW!$B$25/Debt!$B$12)/(((0.07/12)*(1+0.07/12)^(Debt!$B$8))/((1+0.07/12)^(Debt!$B$8)-1)*12),UW!$B$25/Debt!$B$13) | K8: =MIN(Debt!$B$11*(UW!$B$22/K$5),(UW!$B$25/Debt!$B$12)/(((0.07/12)*(1+0.07/12)^(Debt!$B$8))/((1+0.07/12)^(Debt!$B$8)-1)*12),UW!$B$25/Debt!$B$13)
A9: 0.07 | B9: =UW!$B$22/A9 | D9: 0.0725 | E9: =MIN(Debt!$B$11*(UW!$B$22/E$5),(UW!$B$25/Debt!$B$12)/(((0.0725/12)*(1+0.0725/12)^(Debt!$B$8))/((1+0.0725/12)^(Debt!$B$8)-1)*12),UW!$B$25/Debt!$B$13) | F9: =MIN(Debt!$B$11*(UW!$B$22/F$5),(UW!$B$25/Debt!$B$12)/(((0.0725/12)*(1+0.0725/12)^(Debt!$B$8))/((1+0.0725/12)^(Debt!$B$8)-1)*12),UW!$B$25/Debt!$B$13) | G9: =MIN(Debt!$B$11*(UW!$B$22/G$5),(UW!$B$25/Debt!$B$12)/(((0.0725/12)*(1+0.0725/12)^(Debt!$B$8))/((1+0.0725/12)^(Debt!$B$8)-1)*12),UW!$B$25/Debt!$B$13) | H9: =MIN(Debt!$B$11*(UW!$B$22/H$5),(UW!$B$25/Debt!$B$12)/(((0.0725/12)*(1+0.0725/12)^(Debt!$B$8))/((1+0.0725/12)^(Debt!$B$8)-1)*12),UW!$B$25/Debt!$B$13) | I9: =MIN(Debt!$B$11*(UW!$B$22/I$5),(UW!$B$25/Debt!$B$12)/(((0.0725/12)*(1+0.0725/12)^(Debt!$B$8))/((1+0.0725/12)^(Debt!$B$8)-1)*12),UW!$B$25/Debt!$B$13) | J9: =MIN(Debt!$B$11*(UW!$B$22/J$5),(UW!$B$25/Debt!$B$12)/(((0.0725/12)*(1+0.0725/12)^(Debt!$B$8))/((1+0.0725/12)^(Debt!$B$8)-1)*12),UW!$B$25/Debt!$B$13) | K9: =MIN(Debt!$B$11*(UW!$B$22/K$5),(UW!$B$25/Debt!$B$12)/(((0.0725/12)*(1+0.0725/12)^(Debt!$B$8))/((1+0.0725/12)^(Debt!$B$8)-1)*12),UW!$B$25/Debt!$B$13)
A10: 0.0725 | B10: =UW!$B$22/A10 | D10: 0.075 | E10: =MIN(Debt!$B$11*(UW!$B$22/E$5),(UW!$B$25/Debt!$B$12)/(((0.075/12)*(1+0.075/12)^(Debt!$B$8))/((1+0.075/12)^(Debt!$B$8)-1)*12),UW!$B$25/Debt!$B$13) | F10: =MIN(Debt!$B$11*(UW!$B$22/F$5),(UW!$B$25/Debt!$B$12)/(((0.075/12)*(1+0.075/12)^(Debt!$B$8))/((1+0.075/12)^(Debt!$B$8)-1)*12),UW!$B$25/Debt!$B$13) | G10: =MIN(Debt!$B$11*(UW!$B$22/G$5),(UW!$B$25/Debt!$B$12)/(((0.075/12)*(1+0.075/12)^(Debt!$B$8))/((1+0.075/12)^(Debt!$B$8)-1)*12),UW!$B$25/Debt!$B$13) | H10: =MIN(Debt!$B$11*(UW!$B$22/H$5),(UW!$B$25/Debt!$B$12)/(((0.075/12)*(1+0.075/12)^(Debt!$B$8))/((1+0.075/12)^(Debt!$B$8)-1)*12),UW!$B$25/Debt!$B$13) | I10: =MIN(Debt!$B$11*(UW!$B$22/I$5),(UW!$B$25/Debt!$B$12)/(((0.075/12)*(1+0.075/12)^(Debt!$B$8))/((1+0.075/12)^(Debt!$B$8)-1)*12),UW!$B$25/Debt!$B$13) | J10: =MIN(Debt!$B$11*(UW!$B$22/J$5),(UW!$B$25/Debt!$B$12)/(((0.075/12)*(1+0.075/12)^(Debt!$B$8))/((1+0.075/12)^(Debt!$B$8)-1)*12),UW!$B$25/Debt!$B$13) | K10: =MIN(Debt!$B$11*(UW!$B$22/K$5),(UW!$B$25/Debt!$B$12)/(((0.075/12)*(1+0.075/12)^(Debt!$B$8))/((1+0.075/12)^(Debt!$B$8)-1)*12),UW!$B$25/Debt!$B$13)
A11: 0.075 | B11: =UW!$B$22/A11
A12: 0.0775 | B12: =UW!$B$22/A12
A15: Highlighted cells = Rev 2 base case (cap 7.00%, sizing rate 7.25%).

Sheet Historical
A1: Historical T12 vs Underwriting (Rev 2)
A2: T12 period: 2025-09-01 through 2026-08-31 (source: operating-statement.pdf). Underwriting reflects revised roll & rates.
A3: Historical NOI, underwritten NOI, and NCF have different definitions and are labeled distinctly.
A5: Line item | B5: T12 Actual | C5: Underwritten | D5: Delta / Note
A6: Rental & ancillary collections | B6: 736830 | C6: =Inputs!B7 | D6: UW GPR pre-loss/other; not directly comparable
A7: Economic loss (UW only) | C7: =-UW!B5*UW!B6 | D7: Applied to UW GPR at 5%
A8: Other income (UW only, $350/suite) | C8: =UW!B8 | D8: Instructions
A9: Effective / Underwritten EGI | B9: 736830 | C9: =UW!B10 | D9: Historical shown as collections; UW = GPR×(1−loss)+OI
A10: Real estate tax | B10: -85964 | C10: =-UW!B13 | D10: Same source figure
A11: Insurance expense | B11: -28655 | C11: =-UW!B14 | D11: Same source figure
A12: Other recurring operating expenses | B12: -114618 | C12: =-UW!B15 | D12: Same source figure
A13: Management fee | B13: 0 | C13: =-UW!B16 | D13: Not in T12 ledger; underwritten at 3% of EGI
A14: Roof replacement (capex) | B14: 0 | C14: 0 | D14: Capital improvement; not in recurring OpEx per T12
A15: Reported / Underwritten NOI | B15: 507593 | C15: =UW!B22 | D15: T12 reported NOI vs UW NOI (before reserves)
A16: Replacement reserves | C16: =-UW!B23 | D16: UW only ($300/suite)
A17: Underwritten NCF | C17: =UW!B25 | D17: For DSCR & debt yield sizing

Sheet Sources
A1: Source Register (Rev 2)
A3: # | B3: Field / Assumption | C3: Value | D3: Evidence (file — page/cell)
A4: 1 | B4: Revised certified rent roll (as-of date) | C4: 2026-09-01 | D4: rent-roll-revised.xlsx — Sheet Rent Roll, B2
A5: 2 | B5: Superseded certified roll | C5: as-of 2026-08-31 | D5: rent-roll-certified.xlsx — B2 (superseded)
A6: 3 | B6: Revised roll suite count / status | C6: 10 total; 9 active, 1 vacant | D6: rent-roll-revised.xlsx — Rent Roll, A5:E14
A7: 4 | B7: Suite 002 revised monthly rent | C7: $7,025 (+$225 vs prior) | D7: rent-roll-revised.xlsx — E6; revision-notice.pdf — page 1
A8: 5 | B8: Suite 001 monthly rent (post-amendment) | C8: $6,650 (unchanged) | D8: rent-roll-revised.xlsx — E5
A9: 6 | B9: Suite 001 amendment (+$350/mo, eff. 2026-08-01) | C9: +$350 continues to apply | D9: lease-correspondence.pdf — page 1; revision-notice.pdf — page 1
A10: 7 | B10: Suite 001 executed base rent (pre-amendment) | C10: $6,650 (lease excerpt) | D10: lease-001.pdf — page 1
A11: 8 | B11: Archive roll (2026-06-30) Suite 001 rent | C11: $6,575 | D11: rent-roll-archive.xlsx — E5 (superseded)
A12: 9 | B12: Type mapping (A=Small, B=Standard, C=Large) | C12: Manager methodology | D12: manager-cover.pdf — page 1
A13: 10 | B13: Manager headline occupancy claim | C13: 9 of 10 (occupied + pending as leased) | D13: manager-cover.pdf — page 1
A14: 11 | B14: T12 collections | C14: $736,830 | D14: operating-statement.pdf — page 1 (table)
A15: 12 | B15: T12 real estate tax | C15: $85,964 | D15: operating-statement.pdf — page 1
... A33: 30 | B33: Diligence status — legal/env/PCA/title | C33: Pending, no findings | D33: diligence-status.pdf — page 1

Sheet Fields
A1: Reported Named Fields — Values, Units, Evidence (Rev 2)
A3: Field | B3: Value (Rev 2) | C3: Prior (Rev 1) | D3: Unit | E3: Evidence | F3: Location
A4: total_units | B4: 10 | C4: 10 | D4: count | E4: rent-roll-revised.xlsx | F4: Rent Roll A5:A14
A5: occupied_units | B5: 9 | C5: 9 | D5: count | E5: rent-roll-revised.xlsx | F5: Rent Roll D5:D14 (=active)
A6: pending_units | B6: 0 | C6: 0 | D6: count | E6: rent-roll-revised.xlsx | F6: no "pending" status on roll
A7: total_area_sf | B7: 32150 | C7: 31150 | D7: SF | E7: rent-roll-revised.xlsx | F7: Rent Roll C5:C14 (Rev 1 memo had arithmetic error)
A8: occupied_area_sf | B8: 29070 | C8: 28170 | D8: SF | E8: rent-roll-revised.xlsx | F8: Rent Roll C5:C14 where D=active (Rev 1 memo had arithmetic error)
A9: unit_occupancy | B9: 0.9 | C9: 0.9 | D9: ratio | E9: rent-roll-revised.xlsx | F9: derived: 9/10
A10: area_occupancy | B10: 0.9042 | C10: 0.9042 | D10: ratio | E10: rent-roll-revised.xlsx | F10: derived: 29,070/32,150
A11: annual_in_place_rent | B11: 741600 | C11: 735300 | D11: USD | E11: rent-roll-revised.xlsx | F11: sum active × 12 = 61,800 × 12
A12: unit_001_monthly_rent | B12: 6650 | C12: 6650 | D12: USD | E12: rent-roll-revised.xlsx | F12: Rent Roll E5 (post-amendment)
A13: gross_potential_rent | B13: 817200 | C13: 814500 | D13: USD | E13: underwriting-instructions.pdf + revision-notice.pdf | F13: revised sum − S001 amend ×12 = 68,100 × 12
A14: uw_egi | B14: 779840 | C14: 777275 | D14: USD | E14: model | F14: UW!B10
A15: uw_tax | B15: 85964 | C15: 85964 | D15: USD | E15: underwriting-instructions.pdf | F15: Inputs!B10
... A28: insurance_policy_limit | B28: 2000000 | C28: 2000000 | D28: USD | E28: insurance.pdf | F28: page 1 — GL aggregate (not an expense)
A29: selected_roll_date | B29: 2026-09-01 | C29: 2026-08-31 | D29: date | E29: rent-roll-revised.xlsx | F29: B2
A30: reported_t12_noi | B30: 507593 | C30: 507593 | D30: USD | E30: operating-statement.pdf | F30: page 1 — table
A31: type_a_units | B31: 4 | C31: 4 | D31: count | E31: rent-roll-revised.xlsx + manager-cover.pdf | F31: Small suites
A32: type_a_occupied | B32: 3 | C32: 3 | D32: count | E32: rent-roll-revised.xlsx | F32: active Small suites
A33: type_b_units | B33: 3 | C33: 3 | D33: count | E33: rent-roll-revised.xlsx + manager-cover.pdf | F33: Standard suites
A34: type_b_occupied | B34: 3 | C34: 3 | D34: count | E34: rent-roll-revised.xlsx | F34: active Standard suites
A35: type_c_units | B35: 3 | C35: 3 | D35: count | E35: rent-roll-revised.xlsx + manager-cover.pdf | F35: Large suites
A36: type_c_occupied | B36: 3 | C36: 3 | D36: count | E36: rent-roll-revised.xlsx | F36: active Large suites
A37: risk_pending_in_occupancy | B37: present | C37: present | D37: flag | E37: manager-cover.pdf | F37: headline conflates occupied+pending as leased
A38: risk_near_term_rollover | B38: absent | C38: absent | D38: flag | E38: rent-roll-revised.xlsx | F38: all expiries 2029-08-31 — >12 months out
A39: risk_missing_insurance | B39: absent | C39: absent | D39: flag | E39: insurance.pdf + operating-statement.pdf | F39: policy in force; T12 insurance expense present
A40: risk_capital_in_opex | B40: absent | C40: absent | D40: flag | E40: operating-statement.pdf | F40: roof replacement is $0 in repairs — properly capitalized
A41: risk_unsigned_rent_change | B41: absent | C41: absent | D41: flag | E41: packet review | F41: no unsigned rent proposal; revision instructs +$225 as authorized revision
A42: risk_temporary_free_rent | B42: absent | C42: absent | D42: flag | E42: lease-001.pdf | F42: no free-rent concession applies as of evaluation date
A43: risk_sizing_floor_binding | B43: absent | C43: absent | D43: flag | E43: revision-notice.pdf + underwriting-instructions.pdf | F43: note rate 7.25% > floor 6.00%; note binds
A44: risk_refinance_shortfall | B44: absent | C44: absent | D44: flag | E44: model | F44: net cash-out positive: $501,546
