Workbook

Sheet Revision Notes
A1: BEACON PLAZA — REVISION v2 (as of 2026-09-01)
A2: Approved copy (preserved verbatim): | B2: "Source-backed analysis. Assumptions remain subject to diligence."
A4: Change | B4: Prior (v1) | C4: Revised (v2) | D4: Source
A5: Certified rent roll as-of | B5: 2026-08-31 | C5: 2026-09-01 | D5: revision-notice.pdf; rent-roll-revised.xlsx
A6: Suite 010 possession | B6: pending | C6: active | D6: rent-roll-revised.xlsx (Suite 010 row)
A7: Suite 010 monthly rent | B7: $11,050 | C7: $11,275 (+$225) | D7: revision-notice.pdf; rent-roll-revised.xlsx
A8: Cap rate | B8: 7.50% | C8: 7.75% (+25 bps) | D8: revision-notice.pdf
A9: Initial sizing rate | B9: 6.75% | C9: 7.50% (+75 bps) | D9: revision-notice.pdf (Note rate +75 bps; floor unchanged 6.00%)
A10: Suite 001 amendment | B10: applies | C10: applies (preserved) | D10: revision-notice.pdf: 'Prior executed Suite 001 amendments continue to apply.'
A11: Existing payoff | B11: $6,500,000 | C11: $6,500,000 (unchanged) | D11: revision-notice.pdf
A12: Other UW rules | B12: as v1 | C12: unchanged | D12: underwriting-instructions.pdf
A14: Audit note | B14: This workbook is v2. The prior v1 workbook (Beacon_Plaza_Underwriting.xlsx) is preserved separately in the audit archive and is not overwritten.

Sheet Inputs
A1: BEACON PLAZA — UNDERWRITING INPUTS (v2)
A2: Evaluation date | B2: 2026-09-01 | D2: Revised roll supersedes prior (revision-notice.pdf)
A3: Legend | B3: Blue = input | C3: Yellow = key | D3: Peach fill = changed vs v1
A5: LOAN CONSTRAINTS & RATES
A6: ltv_limit | B6: 0.6 | D6: Maximum LTV — instructions (unchanged)
A7: dscr_limit | B7: 1.25 | D7: Minimum DSCR — instructions (unchanged)
A8: debt_yield_limit | B8: 0.09 | D8: Minimum NCF debt yield — instructions (unchanged)
A9: note_rate | B9: 0.075 | D9: Note rate +75 bps per revision (was 6.75%)
A10: rate_floor | B10: 0.06 | D10: UW rate floor — instructions (unchanged)
A11: amort_years | B11: 30 | D11: Amortization years — instructions (unchanged)
A12: origination_fee_pct | B12: 0.01 | D12: 1% of sized loan — instructions (unchanged)
A13: closing_costs | B13: 45000 | D13: Closing costs — instructions (unchanged)
A14: existing_payoff | B14: 6500000 | D14: Existing payoff — unchanged per revision
A15: SIZING RATE (computed — surfaced as required output)
A16: sizing_rate | B16: =MAX(B9,B10) -> 0.075 | D16: MAX(note_rate, rate_floor). Now 7.50% (note); floor 6.00% not binding.
A18: UNDERWRITING ASSUMPTIONS
A19: economic_loss_pct | B19: 0.05 | D19: Economic loss — instructions (unchanged)
A20: other_income_per_unit | B20: 350 | D20: $350 / unit / year — instructions (unchanged)
A21: management_fee_pct | B21: 0.03 | D21: 3% of EGI — instructions (unchanged)
A22: replacement_reserve_per_unit | B22: 300 | D22: $300 / unit / year — instructions (unchanged)
A23: cap_rate | B23: 0.0775 | D23: +25 bps per revision (was 7.50%)
A24: uw_tax | B24: 169974 | D24: Real estate tax — unchanged
A25: uw_insurance | B25: 56658 | D25: Insurance expense — unchanged
A26: uw_other_recurring_opex | B26: 226632 | D26: Other recurring opex — unchanged
A27: total_units | B27: 12 | D27: Certified rent roll — unchanged

Sheet Rent Roll
A1: BEACON PLAZA — REVISED CERTIFIED RENT ROLL (AS OF 2026-09-01)
A3: Suite | B3: Unit type | C3: Group | D3: Area SF | E3: Possession | F3: Monthly rent (revised) | G3: Lease expiration | H3: Monthly rent for GPR (pre-001 amend.) | I3: Annual in-place rent | J3: Near-term rollover?
A4: 001 | B4: Small suite | C4: A | D4: 5380 | E4: active | F4: 11050 | G4: 2027-02-28 | H4: 10975 | I4: =IF(E4="active",F4*12,0) -> 132600 | J4: =IF(AND(E4="active",DATEVALUE(G4)<DATEVALUE("2027-09-01")),"YES","") -> YES
A5: 002 | B5: Standard suite | C5: B | D5: 5500 | E5: active | F5: 11200 | G5: 2029-08-31 | H5: 11200 | I5: =IF(E5="active",F5*12,0) -> 134400 | J5: =IF(AND(E5="active",DATEVALUE(G5)<DATEVALUE("2027-09-01")),"YES","")
A6: 003 | B6: Large suite | C6: C | D6: 5710 | E6: active | F6: 11475 | G6: 2029-08-31 | H6: 11475 | I6: =IF(E6="active",F6*12,0) -> 137700 | J6: =IF(AND(E6="active",DATEVALUE(G6)<DATEVALUE("2027-09-01")),"YES","")
A7: 004 | B7: Small suite | C7: A | D7: 5380 | E7: active | F7: 11050 | G7: 2029-08-31 | H7: 11050 | I7: =IF(E7="active",F7*12,0) -> 132600 | J7: =IF(AND(E7="active",DATEVALUE(G7)<DATEVALUE("2027-09-01")),"YES","")
A8: 005 | B8: Standard suite | C8: B | D8: 5500 | E8: active | F8: 11200 | G8: 2029-08-31 | H8: 11200 | I8: =IF(E8="active",F8*12,0) -> 134400 | J8: =IF(AND(E8="active",DATEVALUE(G8)<DATEVALUE("2027-09-01")),"YES","")
A9: 006 | B9: Large suite | C9: C | D9: 5710 | E9: active | F9: 11475 | G9: 2029-08-31 | H9: 11475 | I9: =IF(E9="active",F9*12,0) -> 137700 | J9: =IF(AND(E9="active",DATEVALUE(G9)<DATEVALUE("2027-09-01")),"YES","")
A10: 007 | B10: Small suite | C10: A | D10: 5380 | E10: active | F10: 11050 | G10: 2029-08-31 | H10: 11050 | I10: =IF(E10="active",F10*12,0) -> 132600 | J10: =IF(AND(E10="active",DATEVALUE(G10)<DATEVALUE("2027-09-01")),"YES","")
A11: 008 | B11: Standard suite | C11: B | D11: 5500 | E11: active | F11: 11200 | G11: 2029-08-31 | H11: 11200 | I11: =IF(E11="active",F11*12,0) -> 134400 | J11: =IF(AND(E11="active",DATEVALUE(G11)<DATEVALUE("2027-09-01")),"YES","")
A12: 009 | B12: Large suite | C12: C | D12: 5710 | E12: active | F12: 11475 | G12: 2029-08-31 | H12: 11475 | I12: =IF(E12="active",F12*12,0) -> 137700 | J12: =IF(AND(E12="active",DATEVALUE(G12)<DATEVALUE("2027-09-01")),"YES","")
A13: 010 | B13: Small suite | C13: A | D13: 5380 | E13: active | F13: 11275 | G13: 2029-08-31 | H13: 11275 | I13: =IF(E13="active",F13*12,0) -> 135300 | J13: =IF(AND(E13="active",DATEVALUE(G13)<DATEVALUE("2027-09-01")),"YES","")
A14: 011 | B14: Standard suite | C14: B | D14: 5500 | E14: vacant | F14: 11200 | G14: 2029-08-31 | H14: 11200 | I14: =IF(E14="active",F14*12,0) -> 0 | J14: =IF(AND(E14="active",DATEVALUE(G14)<DATEVALUE("2027-09-01")),"YES","")
A15: 012 | B15: Large suite | C15: C | D15: 5710 | E15: vacant | F15: 11475 | G15: 2029-08-31 | H15: 11475 | I15: =IF(E15="active",F15*12,0) -> 0 | J15: =IF(AND(E15="active",DATEVALUE(G15)<DATEVALUE("2027-09-01")),"YES","")
A16: TOTAL | D16: =SUM(D4:D15) -> 66360 | F16: =SUM(F4:F15) -> 135125 | H16: =SUM(H4:H15) -> 135050 | I16: =SUM(I4:I15) -> 1349400
A18: Notes:
A19: Group mapping (manager cover): A = Small suite, B = Standard suite, C = Large suite.
A20: "Active" only counts as in physical possession; certified detail controls physical occupancy (manager cover).
A21: Suite 001 GPR uses pre-amendment monthly ($10,975 from archive roll) per underwriting instructions; Suite 010 GPR uses the new roll monthly ($11,275).
A22: Near-term rollover horizon = active leases expiring on or before 2027-09-01 (12 months from evaluation date 2026-09-01).

Sheet Underwriting
A1: BEACON PLAZA — RECONCILED UNDERWRITING (v2)
A3: INCOME
A4: gross_potential_rent | B4: 1540425 | D4: All-suite scheduled monthly (new roll; 001 pre-amend) × 12
A5: Economic loss (vacancy/credit) | B5: =-Underwriting!$B$4*Inputs!$B$19 -> -77021.25
A6: Effective rental income | B6: =Underwriting!$B$4+Underwriting!$B$5 -> 1463403.8
A7: Other income ($350 × total units) | B7: =Inputs!$B$20*Inputs!$B$27 -> 4200
A8: uw_egi | B8: =Underwriting!$B$6+Underwriting!$B$7 -> 1467603.8
A10: OPERATING EXPENSES
A11: uw_tax | B11: =Inputs!$B$24 -> 169974
A12: uw_insurance | B12: =Inputs!$B$25 -> 56658
A13: Other recurring opex | B13: =Inputs!$B$26 -> 226632
A14: Management fee (3% of EGI) | B14: =Underwriting!$B$8*Inputs!$B$21 -> 44028.113
A15: uw_operating_expenses | B15: =Underwriting!$B$11+Underwriting!$B$12+Underwriting!$B$13+Underwriting!$B$14 -> 497292.11
A17: NOI / NCF
A18: uw_noi (before reserves) | B18: =Underwriting!$B$8-Underwriting!$B$15 -> 970311.64
A19: Replacement reserves ($300 × units) | B19: =Inputs!$B$22*Inputs!$B$27 -> 3600
A20: uw_ncf (after reserves) | B20: =Underwriting!$B$18-Underwriting!$B$19 -> 966711.64
A22: VALUATION
A23: capitalization_value (NOI ÷ cap_rate) | B23: =Underwriting!$B$18/Inputs!$B$23 -> 12520150
A25: DEBT SIZING
A26: Sizing rate (MAX of note vs floor) | B26: =Inputs!$B$16 -> 0.075
A27: Monthly rate | B27: =Underwriting!$B$26/12 -> 0.00625
A28: Amort periods (months) | B28: =Inputs!$B$11*12 -> 360
A29: Annual debt service constant per $1 | B29: =12*(Underwriting!$B$27*(1+Underwriting!$B$27)^Underwriting!$B$28)/((1+Underwriting!$B$27)^Underwriting!$B$28-1) -> 0.083905741
A30: LTV-constrained loan | B30: =Underwriting!$B$23*Inputs!$B$6 -> 7512090.1
A31: DSCR-constrained loan (NCF basis) | B31: =Underwriting!$B$20/(Inputs!$B$7*Underwriting!$B$29) -> 9217120.3
A32: Debt yield-constrained loan (NCF basis) | B32: =Underwriting!$B$20/Inputs!$B$8 -> 10741240
A33: maximum_loan (binding constraint) | B33: =MIN(Underwriting!$B$30,Underwriting!$B$31,Underwriting!$B$32) -> 7512090.1
A34: Binding constraint | B34: =IF(Underwriting!$B$33=Underwriting!$B$30,"LTV",IF(Underwriting!$B$33=Underwriting!$B$31,"DSCR","Debt Yield")) -> LTV
A36: SOURCES & USES
A37: Origination fee (1% of sized loan) | B37: =Underwriting!$B$33*Inputs!$B$12 -> 75120.901
A38: Closing costs | B38: =Inputs!$B$13 -> 45000
A39: Existing loan payoff | B39: =Inputs!$B$14 -> 6500000
A40: net_cash_out (negative = equity required) | B40: =Underwriting!$B$33-Underwriting!$B$37-Underwriting!$B$38-Underwriting!$B$39 -> 891969.2
A42: CREDIT METRICS AT SIZED LOAN
A43: LTV at sized loan | B43: =Underwriting!$B$33/Underwriting!$B$23 -> 0.6
A44: DSCR at sized loan (NCF) | B44: =Underwriting!$B$20/(Underwriting!$B$33*Underwriting!$B$29) -> 1.5337144
A45: Debt yield at sized loan (NCF) | B45: =Underwriting!$B$20/Underwriting!$B$33 -> 0.12868744

Sheet Historical vs UW
A1: HISTORICAL T-12 (2025-09-01 → 2026-08-31) vs UNDERWRITTEN (v2)
A3: Line item | B3: Historical T-12 | C3: Underwritten | D3: Δ | E3: Notes
A4: Rental / ancillary (hist) vs UW EGI | B4: 1456920 | C4: =Underwriting!$B$8 -> 1467603.8 | D4: =C4-B4 -> 10683.75 | E4: Cash collections vs prescribed UW EGI
A5: Real estate tax | B5: -169974 | C5: =-Underwriting!$B$11 -> -169974 | D5: =C5-B5 -> 0 | E5: Unchanged
A6: Insurance expense | B6: -56658 | C6: =-Underwriting!$B$12 -> -56658 | D6: =C6-B6 -> 0 | E6: Unchanged
A7: Other recurring opex | B7: -226632 | C7: =-Underwriting!$B$13 -> -226632 | D7: =C7-B7 -> 0 | E7: Unchanged
A8: Roof replacement (capital, not opex) | B8: 0 | C8: 0 | D8: =C8-B8 -> 0 | E8: Operating statement — capital classification preserved
A9: Management fee (UW only) | B9: 0 | C9: =-Underwriting!$B$14 -> -44028.113 | D9: =C9-B9 -> -44028.113 | E9: UW adds 3% of EGI
A10: Replacement reserves (UW only) | B10: 0 | C10: =-Underwriting!$B$19 -> -3600 | D10: =C10-B10 -> -3600 | E10: UW adds $300/unit
A11: Reported historical NOI (as stated) | B11: 1003656 | E11: Operating statement, 'Reported NOI'. Cash basis; no mgmt/reserves.
A12: uw_noi (before reserves) | C12: =Underwriting!$B$18 -> 970311.64
A13: uw_ncf (after reserves) | C13: =Underwriting!$B$20 -> 966711.64

Sheet Occupancy & Mix
A1: OCCUPANCY & UNIT MIX (as of 2026-09-01, revised roll)
A3: Metric | B3: Type A (Small) | C3: Type B (Standard) | D3: Type C (Large) | E3: Total | F3: Notes
A4: Units in group | B4: =COUNTIF('Rent Roll'!C4:C15,"A") -> 4 | C4: =COUNTIF('Rent Roll'!C4:C15,"B") -> 4 | D4: =COUNTIF('Rent Roll'!C4:C15,"C") -> 4 | E4: =SUM(B4:D4) -> 12
A5: Occupied (active) in group | B5: =COUNTIFS('Rent Roll'!C4:C15,"A",'Rent Roll'!E4:E15,"active") -> 4 | C5: =COUNTIFS('Rent Roll'!C4:C15,"B",'Rent Roll'!E4:E15,"active") -> 3 | D5: =COUNTIFS('Rent Roll'!C4:C15,"C",'Rent Roll'!E4:E15,"active") -> 3 | E5: =SUM(B5:D5) -> 10 | F5: Suite 010 now active (was pending in v1).
A6: Pending in group | B6: =COUNTIFS('Rent Roll'!C4:C15,"A",'Rent Roll'!E4:E15,"pending") -> 0 | C6: =COUNTIFS('Rent Roll'!C4:C15,"B",'Rent Roll'!E4:E15,"pending") -> 0 | D6: =COUNTIFS('Rent Roll'!C4:C15,"C",'Rent Roll'!E4:E15,"pending") -> 0 | E6: =SUM(B6:D6) -> 0
A7: Vacant in group | B7: =COUNTIFS('Rent Roll'!C4:C15,"A",'Rent Roll'!E4:E15,"vacant") -> 0 | C7: =COUNTIFS('Rent Roll'!C4:C15,"B",'Rent Roll'!E4:E15,"vacant") -> 1 | D7: =COUNTIFS('Rent Roll'!C4:C15,"C",'Rent Roll'!E4:E15,"vacant") -> 1 | E7: =SUM(B7:D7) -> 2
A8: Total area SF (group) | B8: =SUMIF('Rent Roll'!C4:C15,"A",'Rent Roll'!D4:D15) -> 21520 | C8: =SUMIF('Rent Roll'!C4:C15,"B",'Rent Roll'!D4:D15) -> 22000 | D8: =SUMIF('Rent Roll'!C4:C15,"C",'Rent Roll'!D4:D15) -> 22840 | E8: =SUM(B8:D8) -> 66360
A9: Occupied area SF (active) | B9: =SUMIFS('Rent Roll'!D4:D15,'Rent Roll'!C4:C15,"A",'Rent Roll'!E4:E15,"active") -> 21520 | C9: =SUMIFS('Rent Roll'!D4:D15,'Rent Roll'!C4:C15,"B",'Rent Roll'!E4:E15,"active") -> 16500 | D9: =SUMIFS('Rent Roll'!D4:D15,'Rent Roll'!C4:C15,"C",'Rent Roll'!E4:E15,"active") -> 17130 | E9: =SUM(B9:D9) -> 55150
A11: Unit occupancy | E11: ='Occupancy & Mix'!$E$5/'Occupancy & Mix'!$E$4 -> 0.83333333
A12: Area occupancy | E12: ='Occupancy & Mix'!$E$9/'Occupancy & Mix'!$E$8 -> 0.83107294
A13: Annual in-place rent (active suites) | E13: ='Rent Roll'!I16 -> 1349400

Sheet Sensitivity
A1: SENSITIVITY: Maximum loan by cap rate & sizing rate (v2)
A3: Cap rate ↓ / Sizing rate → | B3: 0.07 | C3: 0.0725 | D3: 0.075 | E3: 0.0775 | F3: 0.08 | G3: 0.0825 | H3: 0.085
A4: 0.07 | B4: =MIN((Inputs!$B$6*(Underwriting!$B$18/0.07)),(Underwriting!$B$20/(Inputs!$B$7*(12*((0.07/12)*(1+(0.07/12))^360)/((1+(0.07/12))^360-1)))),(Underwriting!$B$20/Inputs!$B$8)) -> 8316956.9 | C4: =MIN((Inputs!$B$6*(Underwriting!$B$18/0.07)),(Underwriting!$B$20/(Inputs!$B$7*(12*((0.0725/12)*(1+(0.0725/12))^360)/((1+(0.0725/12))^360-1)))),(Underwriting!$B$20/Inputs!$B$8)) -> 8316956.9 | D4: =MIN((Inputs!$B$6*(Underwriting!$B$18/0.07)),(Underwriting!$B$20/(Inputs!$B$7*(12*((0.075/12)*(1+(0.075/12))^360)/((1+(0.075/12))^360-1)))),(Underwriting!$B$20/Inputs!$B$8)) -> 8316956.9 | E4: =MIN((Inputs!$B$6*(Underwriting!$B$18/0.07)),(Underwriting!$B$20/(Inputs!$B$7*(12*((0.0775/12)*(1+(0.0775/12))^360)/((1+(0.0775/12))^360-1)))),(Underwriting!$B$20/Inputs!$B$8)) -> 8316956.9 | F4: =MIN((Inputs!$B$6*(Underwriting!$B$18/0.07)),(Underwriting!$B$20/(Inputs!$B$7*(12*((0.08/12)*(1+(0.08/12))^360)/((1+(0.08/12))^360-1)))),(Underwriting!$B$20/Inputs!$B$8)) -> 8316956.9 | G4: =MIN((Inputs!$B$6*(Underwriting!$B$18/0.07)),(Underwriting!$B$20/(Inputs!$B$7*(12*((0.0825/12)*(1+(0.0825/12))^360)/((1+(0.0825/12))^360-1)))),(Underwriting!$B$20/Inputs!$B$8)) -> 8316956.9 | H4: =MIN((Inputs!$B$6*(Underwriting!$B$18/0.07)),(Underwriting!$B$20/(Inputs!$B$7*(12*((0.085/12)*(1+(0.085/12))^360)/((1+(0.085/12))^360-1)))),(Underwriting!$B$20/Inputs!$B$8)) -> 8316956.9
A5: 0.075 | B5: =MIN((Inputs!$B$6*(Underwriting!$B$18/0.075)),(Underwriting!$B$20/(Inputs!$B$7*(12*((0.07/12)*(1+(0.07/12))^360)/((1+(0.07/12))^360-1)))),(Underwriting!$B$20/Inputs!$B$8)) -> 7762493.1 | C5: =MIN((Inputs!$B$6*(Underwriting!$B$18/0.075)),(Underwriting!$B$20/(Inputs!$B$7*(12*((0.0725/12)*(1+(0.0725/12))^360)/((1+(0.0725/12))^360-1)))),(Underwriting!$B$20/Inputs!$B$8)) -> 7762493.1 | D5: =MIN((Inputs!$B$6*(Underwriting!$B$18/0.075)),(Underwriting!$B$20/(Inputs!$B$7*(12*((0.075/12)*(1+(0.075/12))^360)/((1+(0.075/12))^360-1)))),(Underwriting!$B$20/Inputs!$B$8)) -> 7762493.1 | E5: =MIN((Inputs!$B$6*(Underwriting!$B$18/0.075)),(Underwriting!$B$20/(Inputs!$B$7*(12*((0.0775/12)*(1+(0.0775/12))^360)/((1+(0.0775/12))^360-1)))),(Underwriting!$B$20/Inputs!$B$8)) -> 7762493.1 | F5: =MIN((Inputs!$B$6*(Underwriting!$B$18/0.075)),(Underwriting!$B$20/(Inputs!$B$7*(12*((0.08/12)*(1+(0.08/12))^360)/((1+(0.08/12))^360-1)))),(Underwriting!$B$20/Inputs!$B$8)) -> 7762493.1 | G5: =MIN((Inputs!$B$6*(Underwriting!$B$18/0.075)),(Underwriting!$B$20/(Inputs!$B$7*(12*((0.0825/12)*(1+(0.0825/12))^360)/((1+(0.0825/12))^360-1)))),(Underwriting!$B$20/Inputs!$B$8)) -> 7762493.1 | H5: =MIN((Inputs!$B$6*(Underwriting!$B$18/0.075)),(Underwriting!$B$20/(Inputs!$B$7*(12*((0.085/12)*(1+(0.085/12))^360)/((1+(0.085/12))^360-1)))),(Underwriting!$B$20/Inputs!$B$8)) -> 7762493.1
A6: 0.0775 | B6: =MIN((Inputs!$B$6*(Underwriting!$B$18/0.0775)),(Underwriting!$B$20/(Inputs!$B$7*(12*((0.07/12)*(1+(0.07/12))^360)/((1+(0.07/12))^360-1)))),(Underwriting!$B$20/Inputs!$B$8)) -> 7512090.1 | C6: =MIN((Inputs!$B$6*(Underwriting!$B$18/0.0775)),(Underwriting!$B$20/(Inputs!$B$7*(12*((0.0725/12)*(1+(0.0725/12))^360)/((1+(0.0725/12))^360-1)))),(Underwriting!$B$20/Inputs!$B$8)) -> 7512090.1 | D6: =MIN((Inputs!$B$6*(Underwriting!$B$18/0.0775)),(Underwriting!$B$20/(Inputs!$B$7*(12*((0.075/12)*(1+(0.075/12))^360)/((1+(0.075/12))^360-1)))),(Underwriting!$B$20/Inputs!$B$8)) -> 7512090.1 | E6: =MIN((Inputs!$B$6*(Underwriting!$B$18/0.0775)),(Underwriting!$B$20/(Inputs!$B$7*(12*((0.0775/12)*(1+(0.0775/12))^360)/((1+(0.0775/12))^360-1)))),(Underwriting!$B$20/Inputs!$B$8)) -> 7512090.1 | F6: =MIN((Inputs!$B$6*(Underwriting!$B$18/0.0775)),(Underwriting!$B$20/(Inputs!$B$7*(12*((0.08/12)*(1+(0.08/12))^360)/((1+(0.08/12))^360-1)))),(Underwriting!$B$20/Inputs!$B$8)) -> 7512090.1 | G6: =MIN((Inputs!$B$6*(Underwriting!$B$18/0.0775)),(Underwriting!$B$20/(Inputs!$B$7*(12*((0.0825/12)*(1+(0.0825/12))^360)/((1+(0.0825/12))^360-1)))),(Underwriting!$B$20/Inputs!$B$8)) -> 7512090.1 | H6: =MIN((Inputs!$B$6*(Underwriting!$B$18/0.0775)),(Underwriting!$B$20/(Inputs!$B$7*(12*((0.085/12)*(1+(0.085/12))^360)/((1+(0.085/12))^360-1)))),(Underwriting!$B$20/Inputs!$B$8)) -> 7512090.1
A7: 0.08 | B7: =MIN((Inputs!$B$6*(Underwriting!$B$18/0.08)),(Underwriting!$B$20/(Inputs!$B$7*(12*((0.07/12)*(1+(0.07/12))^360)/((1+(0.07/12))^360-1)))),(Underwriting!$B$20/Inputs!$B$8)) -> 7277337.3 | C7: =MIN((Inputs!$B$6*(Underwriting!$B$18/0.08)),(Underwriting!$B$20/(Inputs!$B$7*(12*((0.0725/12)*(1+(0.0725/12))^360)/((1+(0.0725/12))^360-1)))),(Underwriting!$B$20/Inputs!$B$8)) -> 7277337.3 | D7: =MIN((Inputs!$B$6*(Underwriting!$B$18/0.08)),(Underwriting!$B$20/(Inputs!$B$7*(12*((0.075/12)*(1+(0.075/12))^360)/((1+(0.075/12))^360-1)))),(Underwriting!$B$20/Inputs!$B$8)) -> 7277337.3 | E7: =MIN((Inputs!$B$6*(Underwriting!$B$18/0.08)),(Underwriting!$B$20/(Inputs!$B$7*(12*((0.0775/12)*(1+(0.0775/12))^360)/((1+(0.0775/12))^360-1)))),(Underwriting!$B$20/Inputs!$B$8)) -> 7277337.3 | F7: =MIN((Inputs!$B$6*(Underwriting!$B$18/0.08)),(Underwriting!$B$20/(Inputs!$B$7*(12*((0.08/12)*(1+(0.08/12))^360)/((1+(0.08/12))^360-1)))),(Underwriting!$B$20/Inputs!$B$8)) -> 7277337.3 | G7: =MIN((Inputs!$B$6*(Underwriting!$B$18/0.08)),(Underwriting!$B$20/(Inputs!$B$7*(12*((0.0825/12)*(1+(0.0825/12))^360)/((1+(0.0825/12))^360-1)))),(Underwriting!$B$20/Inputs!$B$8)) -> 7277337.3 | H7: =MIN((Inputs!$B$6*(Underwriting!$B$18/0.08)),(Underwriting!$B$20/(Inputs!$B$7*(12*((0.085/12)*(1+(0.085/12))^360)/((1+(0.085/12))^360-1)))),(Underwriting!$B$20/Inputs!$B$8)) -> 7277337.3
A8: 0.085 | B8: =MIN((Inputs!$B$6*(Underwriting!$B$18/0.085)),(Underwriting!$B$20/(Inputs!$B$7*(12*((0.07/12)*(1+(0.07/12))^360)/((1+(0.07/12))^360-1)))),(Underwriting!$B$20/Inputs!$B$8)) -> 6849258.6 | C8: =MIN((Inputs!$B$6*(Underwriting!$B$18/0.085)),(Underwriting!$B$20/(Inputs!$B$7*(12*((0.0725/12)*(1+(0.0725/12))^360)/((1+(0.0725/12))^360-1)))),(Underwriting!$B$20/Inputs!$B$8)) -> 6849258.6 | D8: =MIN((Inputs!$B$6*(Underwriting!$B$18/0.085)),(Underwriting!$B$20/(Inputs!$B$7*(12*((0.075/12)*(1+(0.075/12))^360)/((1+(0.075/12))^360-1)))),(Underwriting!$B$20/Inputs!$B$8)) -> 6849258.6 | E8: =MIN((Inputs!$B$6*(Underwriting!$B$18/0.085)),(Underwriting!$B$20/(Inputs!$B$7*(12*((0.0775/12)*(1+(0.0775/12))^360)/((1+(0.0775/12))^360-1)))),(Underwriting!$B$20/Inputs!$B$8)) -> 6849258.6 | F8: =MIN((Inputs!$B$6*(Underwriting!$B$18/0.085)),(Underwriting!$B$20/(Inputs!$B$7*(12*((0.08/12)*(1+(0.08/12))^360)/((1+(0.08/12))^360-1)))),(Underwriting!$B$20/Inputs!$B$8)) -> 6849258.6 | G8: =MIN((Inputs!$B$6*(Underwriting!$B$18/0.085)),(Underwriting!$B$20/(Inputs!$B$7*(12*((0.0825/12)*(1+(0.0825/12))^360)/((1+(0.0825/12))^360-1)))),(Underwriting!$B$20/Inputs!$B$8)) -> 6849258.6 | H8: =MIN((Inputs!$B$6*(Underwriting!$B$18/0.085)),(Underwriting!$B$20/(Inputs!$B$7*(12*((0.085/12)*(1+(0.085/12))^360)/((1+(0.085/12))^360-1)))),(Underwriting!$B$20/Inputs!$B$8)) -> 6849258.6
A10: Highlighted cell = base case (cap 7.75%, sizing 7.50%).

Sheet I-O Map
A1: INPUT / OUTPUT MAP — v2 (Sheet!A1 locations)
A3: Name | B3: Location (Sheet!A1) | C3: Role | D3: Live value
A4: gross_potential_rent | B4: Underwriting!$B$4 | C4: input | D4: =Underwriting!$B$4 -> 1540425
A5: cap_rate | B5: Inputs!$B$23 | C5: input | D5: =Inputs!$B$23 -> 0.0775
A6: sizing_rate | B6: Inputs!$B$16 | C6: input (computed) | D6: =Inputs!$B$16 -> 0.075
A7: uw_egi | B7: Underwriting!$B$8 | C7: output | D7: =Underwriting!$B$8 -> 1467603.8
A8: uw_noi | B8: Underwriting!$B$18 | C8: output | D8: =Underwriting!$B$18 -> 970311.64
A9: uw_ncf | B9: Underwriting!$B$20 | C9: output | D9: =Underwriting!$B$20 -> 966711.64
A10: capitalization_value | B10: Underwriting!$B$23 | C10: output | D10: =Underwriting!$B$23 -> 12520150
A11: maximum_loan | B11: Underwriting!$B$33 | C11: output | D11: =Underwriting!$B$33 -> 7512090.1
A12: net_cash_out | B12: Underwriting!$B$40 | C12: output | D12: =Underwriting!$B$40 -> 891969.2

Sheet Source Register
A1: SOURCE REGISTER (v2)
A3: Source file | B3: Content | C3: Date / As-of | D3: How used in v2
A4: revision-notice.pdf | B4: Revision instructions: new roll supersedes; Suite 010 active +$225; sizing +75 bps; cap +25 bps; payoff unchanged; preserve 001 amendment; preserve approved copy | C4: 2026-09-01 | D4: Drives all v2 changes. Applied verbatim.
A5: rent-roll-revised.xlsx | B5: Revised certified rent roll — Suite 010 now active at $11,275; all others unchanged | C5: 2026-09-01 | D5: Primary rent roll for v2.
A6: rent-roll-certified.xlsx | B6: Prior certified rent roll (v1 primary) | C6: 2026-08-31 | D6: Superseded by revised roll (per revision notice). Retained for audit.
A7: rent-roll-archive.xlsx | B7: Prior roll — pre-Suite-001-amendment monthly ($10,975) | C7: 2026-06-30 | D7: Still used to source pre-amendment 001 monthly for GPR per UW instructions.
A8: lease-001.pdf | B8: Executed lease excerpt — Suite 001, $11,050 monthly, exp 2027-02-28 | C8: n/a | D8: Suite 001 in-place rent; no free rent.
A9: lease-correspondence.pdf | B9: PM confirmation — no amendments/new concessions affect Suite 001 | C9: 2026-08-31 | D9: Preserved; still applies.
A10: operating-statement.pdf | B10: T-12 cash operating statement | C10: 2025-09-01 → 2026-08-31 | D10: Historical NOI and capital classification unchanged.
A11: insurance.pdf | B11: GL aggregate limit $2,000,000 | C11: Effective 2026-07-01 → 2027-06-30 | D11: Preserved. Distinct from insurance expense.
A12: underwriting-instructions.pdf | B12: All base UW rules | C12: n/a | D12: All rules other than sizing rate / cap rate remain in force per revision notice.
A13: diligence-status.pdf | B13: Routine pending diligence | C13: n/a | D13: Preserved.
A14: manager-cover.pdf | B14: Group mapping; approved copy; physical-occupancy convention | C14: n/a | D14: Approved sentence preserved verbatim in v2.
