Workbook

Sheet UW
A1: Falcon Distribution – Underwriting Summary
A3: Selected roll date | B3: 2026-08-31
A4: Total units | B4: 8
A5: Occupied units | B5: 7
A6: Pending units | B6: 0
A8: Gross potential rent (annual) | B8: 1402800
A9: Cap rate | B9: 0.0625
A10: Sizing rate (max(note rate, floor)) | B10: 0.08
A12: Other income per unit (annual) | B12: 350
A13: Other income total (annual) | B13: =B12*B4 -> 2800
A14: Economic loss % | B14: 0.05
A15: Underwritten EGI | B15: =B8*(1-B14)+B13 -> 1335460
A17: Real estate tax | B17: 147294
A18: Insurance | B18: 49098
A19: Other recurring operating expenses | B19: 196392
A20: Management fee (3% of UW EGI) | B20: =0.03*B15 -> 40063.8
A21: UW operating expenses (excl. tax & insurance) | B21: =B19+B20 -> 236455.8
A22: UW NOI (before reserves) | B22: =B15-B17-B18-B21 -> 902612.2
A23: Replacement reserves ($300/unit) | B23: =300*B4 -> 2400
A24: UW NCF (after reserves) | B24: =B22-B23 -> 900212.2
A26: Capitalization value (NOI / cap rate) | B26: =B22/B9 -> 14441795
A28: Amortization (years) | B28: 30
A29: Annual debt constant at sizing rate | B29: =12*PMT(B10/12,B28*12,1) -> -0.088051749
A30: LTV limit (65% of value) | B30: =0.65*B26 -> 9387166.9
A31: DSCR limit (NCF / 1.25 / debt constant) | B31: =B24/1.25/ABS(B29) -> 8178937.6
A32: Debt yield limit (NCF / 9%) | B32: =B24/0.09 -> 10002358
A33: Maximum loan (min of constraints) | B33: =MIN(B30,B31,B32) -> 8178937.6
A34: Origination fee (1%) | B34: =0.01*B33 -> 81789.376
A35: Closing costs | B35: 45000
A36: Existing payoff | B36: 7800000
A37: Net cash out (after fees & payoff) | B37: =B33-B34-B35-B36 -> 252148.23

Sheet Data
A1: Selected roll date | B1: 2026-08-31
A2: Total units | B2: 8
A3: Occupied units | B3: 7
A4: Total area sf | B4: 176060
A5: Occupied area sf | B5: 154060
A6: Unit occupancy | B6: =B3/B2 -> 0.875
A7: Area occupancy | B7: =B5/B4 -> 0.8750426
A8: Annual in-place rent (occupied) | B8: 1227600
A9: Unit 001 monthly rent | B9: 14450
A10: All-suite monthly rent sum | B10: 116900
A11: Roll GPR annual (from certified roll) | B11: =B10*12 -> 1402800
A13: Type A units (Small) | B13: 3
A14: Type A occupied | B14: 3
A15: Type B units (Standard) | B15: 3
A16: Type B occupied | B16: 2
A17: Type C units (Large) | B17: 2
A18: Type C occupied | B18: 2
A20: Insurance policy limit | B20: 2000000
A21: Reported T12 NOI | B21: 869736

Sheet Sensitivity
A1: Cap rate | B1: Value (NOI / cap rate) | D1: Sizing rate | E1: Maximum loan
A2: 0.058 | B2: =UW!B22/A2 -> 15562279 | D2: 0.06 | E2: =MIN(0.65*UW!B26, UW!B24/1.25/ABS(12*PMT(D2/12, UW!B28*12, 1)), UW!B24/0.09) -> 9387166.9
A3: 0.06 | B3: =UW!B22/A3 -> 15043537 | D3: 0.065 | E3: =MIN(0.65*UW!B26, UW!B24/1.25/ABS(12*PMT(D3/12, UW!B28*12, 1)), UW!B24/0.09) -> 9387166.9
A4: 0.0625 | B4: =UW!B22/A4 -> 14441795 | D4: 0.07 | E4: =MIN(0.65*UW!B26, UW!B24/1.25/ABS(12*PMT(D4/12, UW!B28*12, 1)), UW!B24/0.09) -> 9020580.4
A5: 0.065 | B5: =UW!B22/A5 -> 13886342 | D5: 0.075 | E5: =MIN(0.65*UW!B26, UW!B24/1.25/ABS(12*PMT(D5/12, UW!B28*12, 1)), UW!B24/0.09) -> 8583080.9
A6: 0.0675 | B6: =UW!B22/A6 -> 13372033 | D6: 0.08 | E6: =MIN(0.65*UW!B26, UW!B24/1.25/ABS(12*PMT(D6/12, UW!B28*12, 1)), UW!B24/0.09) -> 8178937.6
A7: 0.07 | B7: =UW!B22/A7 -> 12894460

Sheet Sources
A1: Source register (file and location)
A3: manager-cover.pdf p.1 – unit type mapping A/B/C; pending counted in headline; certified detail controls occupancy
A4: rent-roll-certified.xlsx Rent Roll!B2 – As of date 2026-08-31
A5: rent-roll-certified.xlsx Rent Roll!A5:A12, C5:C12, D5:D12, E5:E12 – units, areas, status, monthly base rent
A6: rent-roll-archive.xlsx Rent Roll!E5:E12 – prior monthly rents for comparison
A7: lease-001.pdf p.1 – Suite 001 executed rent $14,450; no free rent; unsigned proposal does not control
A8: lease-correspondence.pdf p.1 – PM confirms no amendments or new concessions for Suite 001 as of 2026-08-31
A9: operating-statement.pdf p.1 – T12 collections, taxes $147,294, insurance $49,098, other opex $196,392, NOI $869,736
A10: insurance.pdf p.1 – GL aggregate limit $2,000,000 effective 2026-07-01 to 2027-06-30
A11: diligence-status.pdf p.1 – status of legal/env/PC/title; label differences among historical NOI, UW NOI, and NCF
A12: underwriting-instructions.pdf p.1 – UW assumptions, cap rate 6.25%, loss 5%, other income $350/unit, mgmt 3%, reserves $300/unit; loan constraints; note 6.10%, floor 7.00%
