Workbook

Sheet Rent Roll
A1: Magnolia Terrace - Certified rent roll (controlling)
A2: Roll date | B2: 2026-08-31 | I2: Suite 001 signed amendment ($/mo) | J2: 350
A4: Suite | B4: Unit type | C4: Group | D4: Area SF | E4: Possession | F4: Sched. rent/mo | G4: In-place rent/mo | H4: Expiration
A5: 001 | B5: Studio | C5: A | D5: 700 | E5: active | F5: 1500 | G5: =F5+$J$2 | H5: 2029-08-31
A6: 002 | B6: 1BR | C6: B | D6: 820 | E6: active | F6: 1650 | G6: =F6 | H6: 2029-08-31
A7: 003 | B7: 2BR | C7: C | D7: 1030 | E7: active | F7: 1925 | G7: =F7 | H7: 2029-08-31
A8: 004 | B8: Studio | C8: A | D8: 700 | E8: active | F8: 1500 | G8: =F8 | H8: 2029-08-31
A9: 005 | B9: 1BR | C9: B | D9: 820 | E9: active | F9: 1650 | G9: =F9 | H9: 2029-08-31
A10: 006 | B10: 2BR | C10: C | D10: 1030 | E10: active | F10: 1925 | G10: =F10 | H10: 2029-08-31
A11: 007 | B11: Studio | C11: A | D11: 700 | E11: active | F11: 1500 | G11: =F11 | H11: 2029-08-31
A12: 008 | B12: 1BR | C12: B | D12: 820 | E12: active | F12: 1650 | G12: =F12 | H12: 2029-08-31
A13: 009 | B13: 2BR | C13: C | D13: 1030 | E13: active | F13: 1925 | G13: =F13 | H13: 2029-08-31
A14: 010 | B14: Studio | C14: A | D14: 700 | E14: active | F14: 1500 | G14: =F14 | H14: 2029-08-31
A15: 011 | B15: 1BR | C15: B | D15: 820 | E15: active | F15: 1650 | G15: =F15 | H15: 2029-08-31
A16: 012 | B16: 2BR | C16: C | D16: 1030 | E16: active | F16: 1925 | G16: =F16 | H16: 2029-08-31
A17: 013 | B17: Studio | C17: A | D17: 700 | E17: active | F17: 1500 | G17: =F17 | H17: 2029-08-31
... A52: 048 | B52: 2BR | C52: C | D52: 1030 | E52: vacant | F52: 1925 | G52: =F52 | H52: 2029-08-31
A54: Roll summary
A55: Total units | B55: =COUNTA(A5:A52)
A56: Occupied units (active possession) | B56: =COUNTIF(E5:E52,"active")
A57: Pending units (no possession) | B57: =COUNTIF(E5:E52,"pending")
A58: Vacant units | B58: =COUNTIF(E5:E52,"vacant")
A59: Total area SF | B59: =SUM(D5:D52)
A60: Occupied area SF | B60: =SUMIF(E5:E52,"active",D5:D52)
A61: Unit occupancy (decimal) | B61: =B56/B55
A62: Area occupancy (decimal) | B62: =B60/B59
A63: Scheduled monthly rent, all 48 suites (pre-amendment) | B63: =SUM(F5:F52)
A64: Gross potential rent, annual (roll x 12, pre-amendment) | B64: =B63*12
A65: In-place monthly rent, occupied suites (executed) | B65: =SUMIF(E5:E52,"active",G5:G52)
A66: Annual in-place rent (occupied x 12) | B66: =B65*12
A67: Suite 001 monthly rent after signed amendment | B67: =G5
A69: Group | B69: Type | C69: Units | D69: Occupied | E69: Area SF
A70: A | B70: Studio | C70: =COUNTIF($C$5:$C$52,"A") | D70: =COUNTIFS($C$5:$C$52,"A",$E$5:$E$52,"active") | E70: =SUMIF($C$5:$C$52,"A",$D$5:$D$52)
A71: B | B71: 1BR | C71: =COUNTIF($C$5:$C$52,"B") | D71: =COUNTIFS($C$5:$C$52,"B",$E$5:$E$52,"active") | E71: =SUMIF($C$5:$C$52,"B",$D$5:$D$52)
A72: C | B72: 2BR | C72: =COUNTIF($C$5:$C$52,"C") | D72: =COUNTIFS($C$5:$C$52,"C",$E$5:$E$52,"active") | E72: =SUMIF($C$5:$C$52,"C",$D$5:$D$52)
A74: Manager headline: 45 of 48 leased (occupied + pending); pending occupants have not taken possession (manager-cover.pdf p.1). Physical occupancy per certified detail is 44 of 48.

Sheet Underwriting
A1: Magnolia Terrace - Underwritten cash flow (as of 2026-08-31)
A3: Income | B3: Amount | C3: Source / note
A4: Gross potential rent (annual) [INPUT] | B4: 974400 | C4: Certified roll scheduled rent 81,200/mo x 12, pre-amendment (rent-roll-certified.xlsx E5:E52)
A5: Economic loss (vacancy/credit) [INPUT] | B5: 0.05 | C5: underwriting-instructions.pdf p.1
A6: Effective rental income | B6: =B4*(1-B5)
A7: Other income per unit per year [INPUT] | B7: 350 | C7: Reimbursements already included; not added twice
A8: Units | B8: ='Rent Roll'!B55
A9: Other income (annual) | B9: =B7*B8
A10: Underwritten EGI | B10: =B6+B9
A12: Operating expenses | B12: Amount
A13: Real estate taxes [INPUT] | B13: 102312 | C13: underwriting-instructions.pdf p.1; matches T12
A14: Insurance expense [INPUT] | B14: 34104 | C14: underwriting-instructions.pdf p.1; matches T12
A15: Other recurring operating expenses [INPUT] | B15: 136416
A16: Management fee % of EGI [INPUT] | B16: 0.03
A17: Management fee | B17: =B16*B10
A18: Total underwritten operating expenses | B18: =SUM(B13:B15)+B17
A19: Underwritten NOI before reserves | B19: =B10-B18
A20: Replacement reserve per unit [INPUT] | B20: 300
A21: Replacement reserves | B21: =B20*B8
A22: Underwritten NCF after reserves | B22: =B19-B21
A24: Valuation
A25: Capitalization rate [INPUT] | B25: 0.0575
A26: Capitalization value (NOI before reserves / cap rate) | B26: =B19/B25
A28: Historical comparison (T12 09/2025-08/2026)
A29: Reported collections | B29: 876960 | C29: operating-statement.pdf p.1
A30: Reported T12 NOI | B30: 604128 | C30: operating-statement.pdf p.1 (no mgmt fee or reserves)
A31: Underwritten NOI vs reported T12 NOI | B31: =B19-B30
A32: Annual in-place rent (executed, occupied suites) | B32: ='Rent Roll'!B66
A34: Underwriting definitions differ: T12 NOI is cash-basis actual before management fee and reserves; underwritten NOI is a stabilized prescribed gross potential less 5% loss plus other income, less prescribed expenses; NCF deducts reserves.

Sheet Debt
A1: Debt sizing and sources / uses
A3: Constraint inputs | B3: Value | C3: Note
A4: Maximum LTV | B4: 0.65
A5: Minimum DSCR (on NCF) | B5: 1.25
A6: Minimum NCF debt yield | B6: 0.09
A7: Amortization (years) | B7: 30
A8: Note rate | B8: 0.0625 | C8: underwriting-instructions.pdf p.1
A9: Underwriting rate floor | B9: 0.06 | C9: Floor below note rate; not binding
A10: Sizing rate (greater of note rate and floor) [INPUT] | B10: 0.0725 | C10: = MAX(B8,B9); sized on amortizing basis despite 24-month IO
A12: Sizing tests | B12: Loan amount
A13: LTV limit | B13: =B4*Underwriting!B26
A14: Maximum annual debt service at min DSCR | B14: =Underwriting!B22/B5
A15: DSCR limit (PV of monthly payment, 30-yr amort) | B15: =(B14/12)*(1-(1+B10/12)^(-B7*12))/(B10/12)
A16: Debt yield limit | B16: =Underwriting!B22/B6
A17: Maximum loan (binding = minimum) | B17: =MIN(B13,B15,B16)
A18: Binding constraint | B18: =IF(B17=B15,"DSCR",IF(B17=B13,"LTV","Debt yield"))
A19: Loan to capitalization value | B19: =B17/Underwriting!B26
A20: Actual annual debt service at sized loan | B20: =-PMT(B10/12,B7*12,B17)*12
A21: DSCR at sized loan (NCF basis) | B21: =Underwriting!B22/B20
A22: NCF debt yield at sized loan | B22: =Underwriting!B22/B17
A24: Sources | B24: Amount
A25: Sized first mortgage | B25: =B17
A27: Uses | B27: Amount
A28: Existing loan payoff | B28: 4200000
A29: Origination fee (1% of sized loan) | B29: =0.01*B17
A30: Closing costs | B30: 45000
A31: Total uses before distribution | B31: =SUM(B28:B30)
A32: Net cash-out (negative = equity required) | B32: =B25-B31
A34: Refinance shortfall test (loan net of costs vs payoff) | B34: =IF(B32<0,"Shortfall","No shortfall")

Sheet Sensitivity
A1: Maximum loan sensitivity - cap rate (rows) vs sizing rate (columns)
A2: Each cell = MIN(LTV limit, DSCR limit, debt yield limit) holding NOI/NCF constant
A4: Cap rate \ Sizing rate | B4: 0.06 | C4: 0.0625 | D4: 0.065 | E4: 0.07
A5: 0.0525 | B5: =MIN(Debt!$B$4*Underwriting!$B$19/$A5,(Underwriting!$B$22/Debt!$B$5/12)*(1-(1+B$4/12)^(-Debt!$B$7*12))/(B$4/12),Underwriting!$B$22/Debt!$B$6) | C5: =MIN(Debt!$B$4*Underwriting!$B$19/$A5,(Underwriting!$B$22/Debt!$B$5/12)*(1-(1+C$4/12)^(-Debt!$B$7*12))/(C$4/12),Underwriting!$B$22/Debt!$B$6) | D5: =MIN(Debt!$B$4*Underwriting!$B$19/$A5,(Underwriting!$B$22/Debt!$B$5/12)*(1-(1+D$4/12)^(-Debt!$B$7*12))/(D$4/12),Underwriting!$B$22/Debt!$B$6) | E5: =MIN(Debt!$B$4*Underwriting!$B$19/$A5,(Underwriting!$B$22/Debt!$B$5/12)*(1-(1+E$4/12)^(-Debt!$B$7*12))/(E$4/12),Underwriting!$B$22/Debt!$B$6)
A6: 0.055 | B6: =MIN(Debt!$B$4*Underwriting!$B$19/$A6,(Underwriting!$B$22/Debt!$B$5/12)*(1-(1+B$4/12)^(-Debt!$B$7*12))/(B$4/12),Underwriting!$B$22/Debt!$B$6) | C6: =MIN(Debt!$B$4*Underwriting!$B$19/$A6,(Underwriting!$B$22/Debt!$B$5/12)*(1-(1+C$4/12)^(-Debt!$B$7*12))/(C$4/12),Underwriting!$B$22/Debt!$B$6) | D6: =MIN(Debt!$B$4*Underwriting!$B$19/$A6,(Underwriting!$B$22/Debt!$B$5/12)*(1-(1+D$4/12)^(-Debt!$B$7*12))/(D$4/12),Underwriting!$B$22/Debt!$B$6) | E6: =MIN(Debt!$B$4*Underwriting!$B$19/$A6,(Underwriting!$B$22/Debt!$B$5/12)*(1-(1+E$4/12)^(-Debt!$B$7*12))/(E$4/12),Underwriting!$B$22/Debt!$B$6)
A7: 0.0575 | B7: =MIN(Debt!$B$4*Underwriting!$B$19/$A7,(Underwriting!$B$22/Debt!$B$5/12)*(1-(1+B$4/12)^(-Debt!$B$7*12))/(B$4/12),Underwriting!$B$22/Debt!$B$6) | C7: =MIN(Debt!$B$4*Underwriting!$B$19/$A7,(Underwriting!$B$22/Debt!$B$5/12)*(1-(1+C$4/12)^(-Debt!$B$7*12))/(C$4/12),Underwriting!$B$22/Debt!$B$6) | D7: =MIN(Debt!$B$4*Underwriting!$B$19/$A7,(Underwriting!$B$22/Debt!$B$5/12)*(1-(1+D$4/12)^(-Debt!$B$7*12))/(D$4/12),Underwriting!$B$22/Debt!$B$6) | E7: =MIN(Debt!$B$4*Underwriting!$B$19/$A7,(Underwriting!$B$22/Debt!$B$5/12)*(1-(1+E$4/12)^(-Debt!$B$7*12))/(E$4/12),Underwriting!$B$22/Debt!$B$6)
A8: 0.06 | B8: =MIN(Debt!$B$4*Underwriting!$B$19/$A8,(Underwriting!$B$22/Debt!$B$5/12)*(1-(1+B$4/12)^(-Debt!$B$7*12))/(B$4/12),Underwriting!$B$22/Debt!$B$6) | C8: =MIN(Debt!$B$4*Underwriting!$B$19/$A8,(Underwriting!$B$22/Debt!$B$5/12)*(1-(1+C$4/12)^(-Debt!$B$7*12))/(C$4/12),Underwriting!$B$22/Debt!$B$6) | D8: =MIN(Debt!$B$4*Underwriting!$B$19/$A8,(Underwriting!$B$22/Debt!$B$5/12)*(1-(1+D$4/12)^(-Debt!$B$7*12))/(D$4/12),Underwriting!$B$22/Debt!$B$6) | E8: =MIN(Debt!$B$4*Underwriting!$B$19/$A8,(Underwriting!$B$22/Debt!$B$5/12)*(1-(1+E$4/12)^(-Debt!$B$7*12))/(E$4/12),Underwriting!$B$22/Debt!$B$6)
A9: 0.0625 | B9: =MIN(Debt!$B$4*Underwriting!$B$19/$A9,(Underwriting!$B$22/Debt!$B$5/12)*(1-(1+B$4/12)^(-Debt!$B$7*12))/(B$4/12),Underwriting!$B$22/Debt!$B$6) | C9: =MIN(Debt!$B$4*Underwriting!$B$19/$A9,(Underwriting!$B$22/Debt!$B$5/12)*(1-(1+C$4/12)^(-Debt!$B$7*12))/(C$4/12),Underwriting!$B$22/Debt!$B$6) | D9: =MIN(Debt!$B$4*Underwriting!$B$19/$A9,(Underwriting!$B$22/Debt!$B$5/12)*(1-(1+D$4/12)^(-Debt!$B$7*12))/(D$4/12),Underwriting!$B$22/Debt!$B$6) | E9: =MIN(Debt!$B$4*Underwriting!$B$19/$A9,(Underwriting!$B$22/Debt!$B$5/12)*(1-(1+E$4/12)^(-Debt!$B$7*12))/(E$4/12),Underwriting!$B$22/Debt!$B$6)
A11: Net cash-out at base case | B11: =Debt!B32
A12: Debt yield limit is a flat ceiling; DSCR governs at the base case.

Sheet Sources
A1: Source register
A3: File | B3: Location | C3: Facts used / status
A4: rent-roll-certified.xlsx | B4: Rent Roll A2:G52 | C4: Controlling roll dated 2026-08-31: 48 units, 44 active, 1 pending, 3 vacant, areas, scheduled rents, expirations 2029-08-31
A5: rent-roll-archive.xlsx | B5: Rent Roll A2:G52 | C5: Stale archive dated 2026-06-30 (lower rents); superseded, not used for underwriting
A6: lease-001.pdf | B6: p.1 | C6: Suite 001 executed lease: $1,500/mo, 700 SF, expiry 2029-08-31, deposit $3,000, no free rent
A7: lease-correspondence.pdf | B7: p.1 | C7: Signed amendment executed 2026-07-20, effective 2026-08-01: +$350/mo; Suite 001 in-place rent $1,850
A8: operating-statement.pdf | B8: p.1 | C8: T12 09/2025-08/2026: collections 876,960; tax 102,312; insurance 34,104; other 136,416; roof capital booked 0; reported NOI 604,128
A9: insurance.pdf | B9: p.1 | C9: GL aggregate limit $2,000,000; policy 2026-07-01 to 2027-06-30 (coverage limit, not expense)
A10: manager-cover.pdf | B10: p.1 | C10: Raleigh, NC multifamily; group mapping A/B/C = Studio/1BR/2BR; manager headline 45 of 48 leased includes pending
A11: underwriting-instructions.pdf | B11: p.1 | C11: Prescribed GPR method, 5% loss, $350/unit other income, expense line items, 3% management, $300/unit reserves, 5.75% cap, 65% LTV / 1.25x DSCR / 9% debt yield, 6.25% note vs 6.00% floor, 1% fee, $45,000 closing, $4,200,000 payoff
A12: diligence-status.pdf | B12: p.1 | C12: Legal, environmental, PCA, title reviews incomplete - routine pending items, no defect findings
A14: Not supplied (explicitly unknown, not zero): photographs, asking price, market sale/rent comparables, sponsor history, capital budget, unit-level concessions detail, tax/insurance renewal quotes.
