Workbook

Sheet Inputs
A1: Stonebridge Logistics | Underwriting inputs
A2: Cap rate | B2: 0.0675 | D2: Change B2, B3 and B6/B8 to test value and sizing; EGI scales with loss % held constant.
A3: Sizing rate | B3: 0.0825
A4: Contract rate (IO year) | B4: 0.0675
A5: Total rentable SF | B5: 85000
A6: UW gross potential base rent | B6: 900000 | D6: All dollars are annual unless noted. Rates are decimals.
A7: Combined revenue loss % | B7: 0.08
A8: Other income / recoveries | B8: 195000
A9: Mgmt fee minimum % of EGI | B9: 0.03
A10: T12 management fee (actual) | B10: 25200
A11: UW real estate taxes | B11: 132000
A12: UW insurance (renewal) | B12: 33600
A13: UW utilities | B13: 12000
A14: UW repairs & maintenance | B14: 18000
A15: UW payroll / contract labor | B15: 18000
A16: UW administrative / legal | B16: 18000
A17: Replacement reserves $/SF/yr | B17: 0.2
A19: Existing debt payoff | B19: 4200000
... A21: Origination fee rate | B21: 0.0125
A22: Cap rate +50 bps | B22: =B2+0.005 -> 0.0725
A23: Debt yield minimum | B23: 0.1
A24: DSCR minimum | B24: 1.3
A25: LTV maximum | B25: 0.6
A26: Amortization (years) | B26: 25
A27: Interest-only months (YR1) | B27: 12

Sheet Rent Roll
A1: Stonebridge Logistics | Rent roll as of 2026-08-31
A3: Unit/suite | B3: Tenant | C3: Area SF | D3: Status | E3: Monthly base rent | F3: Market monthly rent | G3: Lease expiry
A4: 101 | B4: Tenant A LLC | C4: 18000 | D4: Occupied | E4: 15000 | F4: 15000 | G4: 2030-08-31
A5: 102 | B5: Tenant B LLC | C5: 22000 | D5: Occupied | E5: 18700 | F5: 18700 | G5: 2028-08-31
A6: 103 | B6: Tenant C LLC | C6: 30000 | D6: Occupied | E6: 27000 | F6: 27000 | G6: 2029-08-31
A7: 104 | B7: Vacant | C7: 15000 | D7: Vacant | E7: 0 | F7: 12500
A9: Total space count | B9: =COUNTA(A4:A7) -> 4
A10: Occupied count | B10: =COUNTIF(D4:D7,"Occupied") -> 3
A11: Total rentable SF | B11: =SUM(C4:C7) -> 85000
A12: Occupied rentable SF | B12: =SUMIF(D4:D7,"Occupied",C4:C7) -> 70000
A13: Physical occupancy by count % | B13: =IF(B9=0,NA(),B10/B9) -> 0.75
A14: Occupancy by area % | B14: =IF(B11=0,NA(),B12/B11) -> 0.82352941
A15: Monthly base rent (printed) | B15: =SUM(E4:E7) -> 60700

Sheet T12
A1: Stonebridge Logistics | Historical T12 (Sep-2025 to Aug-2026)
A3: Gross potential base rent | B3: 852000
A4: Vacancy loss | B4: -150000
A5: Concessions | B5: -36000
A6: Bad debt | B6: -6000
A7: Other income / recoveries | B7: 186000
A8: Effective gross income (EGI) | B8: =B3+B4+B5+B6+B7 -> 846000
A10: Real estate taxes | B10: 126000
A11: Property insurance | B11: 30000
A12: Utilities | B12: 12000
A13: Repairs and maintenance | B13: 24000
A14: Payroll / contract labor | B14: 18000
A15: Administrative / legal | B15: 18000
A16: Management fee | B16: 25200
A17: Operating expenses before reserves | B17: =SUM(B10:B16) -> 253200
A19: NOI before reserves | B19: =B8-B17 -> 592800
A21: Replacement reserves | B21: 17000
A22: NCF after reserves | B22: =B19-B21 -> 575800

Sheet Underwriting
A1: Stonebridge Logistics | Underwriting (annual)
A2: Underwritten GP base rent | B2: =Inputs!B6 -> 900000
A3: Combined revenue loss % | B3: =Inputs!B7 -> 0.08
A4: Other income / recoveries | B4: =Inputs!B8 -> 195000
A6: Effective gross income (EGI) | B6: =B2*(1-B3)+B4 -> 1023000
A8: Mgmt fee minimum % of EGI | B8: =Inputs!B9 -> 0.03
A9: T12 management fee (actual) | B9: =Inputs!B10 -> 25200
A10: Underwritten management fee | B10: =MAX(B9,B8*B6) -> 30690
A12: Real estate taxes | B12: =Inputs!B11 -> 132000
A13: Insurance (renewal) | B13: =Inputs!B12 -> 33600
A14: Utilities | B14: =Inputs!B13 -> 12000
A15: Repairs & maintenance | B15: =Inputs!B14 -> 18000
A16: Payroll / contract labor | B16: =Inputs!B15 -> 18000
A17: Administrative / legal | B17: =Inputs!B16 -> 18000
A18: Operating expenses before reserves | B18: =SUM(B10,B12:B17) -> 262290
A20: NOI before reserves | B20: =B6-B18 -> 760710
A22: Rentable SF | B22: =Inputs!B5 -> 85000
A23: Reserves $/SF | B23: =Inputs!B17 -> 0.2
A24: Replacement reserves | B24: =B22*B23 -> 17000
A26: NCF after reserves | B26: =B20-B24 -> 743710
A28: Cap rate | B28: =Inputs!B2 -> 0.0675
A29: Capitalization value | B29: =B20/B28 -> 11269778
A30: Cap rate +50 bps | B30: =Inputs!B22 -> 0.0725
A31: Value at cap+50 bps | B31: =B20/B30 -> 10492552

Sheet Sizing
A1: Stonebridge Logistics | Loan sizing and proceeds
A2: Sizing rate | B2: =Inputs!B3 -> 0.0825 | D2: Inputs: Sizing rate and cap rate on Inputs tab; EGI controlled by GP rent and Other income. Management fee uses greater of T12 or % of EGI.
A3: Amortization (years) | B3: =Inputs!B26 -> 25
A4: Annual debt constant (at sizing rate) | B4: =ABS(12*PMT(B2/12,B3*12,1)) -> 0.094614016
A6: DSCR minimum | B6: =Inputs!B24 -> 1.3
A7: Debt yield minimum | B7: =Inputs!B23 -> 0.1
A8: LTV maximum | B8: =Inputs!B25 -> 0.6
A10: LTV limit | B10: =B8*Underwriting!B29 -> 6761866.7
A11: DSCR limit | B11: =Underwriting!B26/(B6*B4) -> 6046510.2
A12: Debt yield limit | B12: =Underwriting!B26/B7 -> 7437100
A14: Maximum loan | B14: =MIN(B10,B11,B12) -> 6046510.2
A15: Binding constraint | B15: =IF(B14=B11,"DSCR",IF(B14=B10,"LTV","Debt yield")) -> DSCR
A17: Sizing annual debt service | B17: =B14*B4 -> 572084.62
A18: Sizing DSCR | B18: =Underwriting!B26/B17 -> 1.3
A19: Sizing debt yield | B19: =Underwriting!B26/B14 -> 0.12299822
A21: Contract rate (IO year) | B21: =Inputs!B4 -> 0.0675
A22: First-year debt service (IO) | B22: =B14*B21 -> 408139.44
A24: Existing debt payoff | B24: =Inputs!B19 -> 4200000
A25: Fixed closing costs | B25: =Inputs!B20 -> 70000
A26: Origination fee rate | B26: =Inputs!B21 -> 0.0125
A27: Origination fee $ | B27: =B26*B14 -> 75581.378
A28: Net cash to borrower (cash-out if +) | B28: =B14-B24-B25-B27 -> 1700928.8
A30: Stress: EGI (-5%) | B30: =Underwriting!B6*0.95 -> 971850
A31: Stress: management fee | B31: =MAX(Inputs!B10,Inputs!B9*B30) -> 29155.5
A32: Stress: other op ex before mgmt | B32: =Underwriting!B18-Underwriting!B10 -> 231600
A33: Stress: NOI before reserves | B33: =B30-(B31+B32) -> 711094.5
A34: Stress: NCF after reserves | B34: =B33-Underwriting!B24 -> 694094.5
A35: Stress: sizing rate (+100 bps) | B35: =B2+0.01 -> 0.0925
A36: Stress: annual debt constant | B36: =ABS(12*PMT(B35/12,B3*12,1)) -> 0.10276582
A37: Stress: LTV limit | B37: =B8*(B33/Underwriting!B28) -> 6320840
A38: Stress: DSCR limit | B38: =B34/(B6*B36) -> 5195490.5
A39: Stress: Debt yield limit | B39: =B34/B7 -> 6940945
A40: Stress: maximum loan | B40: =MIN(B37,B38,B39) -> 5195490.5
