Workbook

Sheet UW
A1: Beacon Plaza - Underwriting Model
A3: Inputs
A5: Gross potential rent (annual) | B5: 1618800
A6: Economic loss % | B6: 0.05
A7: Annual other income | B7: 4200
A8: Tax expense | B8: 169974
A9: Insurance expense | B9: 56658
A10: Other recurring opex | B10: 226632
A11: Management fee % | B11: 0.03
A12: Replacement reserve per unit | B12: 300
A13: Units | B13: 12
A14: Cap rate | B14: 0.075
A15: Sizing rate | B15: 0.0675
A16: LTV limit | B16: 0.6
... A21: Existing payoff | B21: 6500000
A23: Outputs
A24: Underwritten EGI | C24: =B5*(1-B6)+B7 -> 1542060
A25: Management fee ($) | C25: =C24*B11 -> 46261.8
A26: Total operating expenses | C26: =B8+B9+B10+C25 -> 499525.8
A27: UW NOI before reserves | C27: =C24-C26 -> 1042534.2
A28: Reserves ($) | C28: =B12*B13 -> 3600
A29: UW NCF (after reserves) | C29: =C27-C28 -> 1038934.2
A31: Capitalization value | C31: =C27/B14 -> 13900456
A33: Loan sizing
A34: Loan - LTV | C34: =C31*B16 -> 8340273.6
A35: Annual DSCR-based debt service | C35: =C29/B17 -> 831147.36
A36: Monthly DSCR payment limit | C36: =C35/12 -> 69262.28
A37: Loan - DSCR | C37: =C36/(-PMT(B15/12,360,1)) -> 10678767
A38: Loan - Debt Yield | C38: =C29/B18 -> 11543713
A39: Maximum loan | C39: =MIN(C34,C37,C38) -> 8340273.6
A40: Origination fee ($) | C40: =C39*B19 -> 83402.736
A41: Net cash out | C41: =C39-C40-B20-B21 -> 1711870.9

Sheet Sensitivity
A1: Max Loan Sensitivity (by Cap Rate and Sizing Rate)
A3: Sizing Rate → / Cap Rate ↓
B4: 0.0625 | C4: 0.0675 | D4: 0.0725
A5: 0.07 | B5: =MIN((UW!C27/A5)*UW!B16, (UW!C29/UW!B17/12)/(-PMT(B4/12,360,1)), UW!C29/UW!B18) -> 8936007.4 | C5: =MIN((UW!C27/A5)*UW!B16, (UW!C29/UW!B17/12)/(-PMT(C4/12,360,1)), UW!C29/UW!B18) -> 8936007.4 | D5: =MIN((UW!C27/A5)*UW!B16, (UW!C29/UW!B17/12)/(-PMT(D4/12,360,1)), UW!C29/UW!B18) -> 8936007.4
A6: 0.075 | B6: =MIN((UW!C27/A6)*UW!B16, (UW!C29/UW!B17/12)/(-PMT(B4/12,360,1)), UW!C29/UW!B18) -> 8340273.6 | C6: =MIN((UW!C27/A6)*UW!B16, (UW!C29/UW!B17/12)/(-PMT(C4/12,360,1)), UW!C29/UW!B18) -> 8340273.6 | D6: =MIN((UW!C27/A6)*UW!B16, (UW!C29/UW!B17/12)/(-PMT(D4/12,360,1)), UW!C29/UW!B18) -> 8340273.6
A7: 0.08 | B7: =MIN((UW!C27/A7)*UW!B16, (UW!C29/UW!B17/12)/(-PMT(B4/12,360,1)), UW!C29/UW!B18) -> 7819006.5 | C7: =MIN((UW!C27/A7)*UW!B16, (UW!C29/UW!B17/12)/(-PMT(C4/12,360,1)), UW!C29/UW!B18) -> 7819006.5 | D7: =MIN((UW!C27/A7)*UW!B16, (UW!C29/UW!B17/12)/(-PMT(D4/12,360,1)), UW!C29/UW!B18) -> 7819006.5

Sheet Source Register
A1: Source Register
A3: File | B3: Location | C3: Note
A4: manager-cover.pdf | B4: p1 | C4: Unit group mapping; headline counts include pending as leased
A5: rent-roll-certified.xlsx | B5: Rent Roll!B2, rows 5-16 | C5: Certified as-of date; unit mix, areas, occupancy, rents
A6: operating-statement.pdf | B6: p1 | C6: T12 taxes, insurance, other opex; reported NOI
A7: lease-001.pdf | B7: p1 | C7: Suite 001 rent, area, expiration; no free rent
A8: lease-correspondence.pdf | B8: p1 | C8: No amendments or new concessions for Suite 001 as of 2026-08-31
A9: insurance.pdf | B9: p1 | C9: Policy aggregate limit and dates
