Workbook

Sheet Inputs
A1: Falcon Distribution | Underwriting inputs (as of 2026-08-31)
A2: Original fictional evaluation material; no real transaction.
A3: Gross potential rent (annual, all suites) | B3: 1402800 | C3: All-suite certified scheduled monthly rent $116,900 x 12 (rent-roll-certified.xlsx E5:E12)
A4: Economic loss (vacancy/credit) | B4: 0.05 | C4: underwriting-instructions.pdf p.1
A5: Other income per unit/suite (annual) | B5: 350 | C5: Reimbursements already included; not double counted
A6: Unit/suite count | B6: 8
A7: Real estate tax expense | B7: 147294
A8: Insurance expense | B8: 49098
A9: Other recurring operating expenses | B9: 196392
A10: Management fee (% of underwritten EGI) | B10: 0.03
A11: Replacement reserve per unit/suite | B11: 300
A12: Capitalization rate (NOI before reserves) | B12: 0.0625
A13: Sizing rate (greater of note rate and floor) | B13: 0.08 | C13: Floor 7.0000% exceeds note rate 6.1000%; floor binds
A14: Note rate (contract) | B14: 0.061
A15: Underwriting rate floor | B15: 0.07
A16: Amortization (years, monthly pay) | B16: 30
A17: Maximum LTV | B17: 0.65
A18: Minimum DSCR (on NCF) | B18: 1.25
A19: Minimum NCF debt yield | B19: 0.09
A20: Origination fee (% of sized loan) | B20: 0.01
A21: Closing costs | B21: 45000
A22: Existing loan payoff | B22: 7800000
A24: Rate-floor check: greater of note and floor | B24: =MAX(B14,B15) -> 0.07 | C24: Ties to sizing rate input B13

Sheet Rent Roll
A1: Certified rent roll as of 2026-08-31 (rent-roll-certified.xlsx)
A2: Manager group mapping: A = Small suite, B = Standard suite, C = Large suite (manager-cover.pdf p.1)
A4: Suite | B4: Unit type | C4: Group | D4: Area SF | E4: Status | F4: Monthly rent | G4: Annual rent | H4: Expiration
A5: 001 | B5: Small suite | C5: A | D5: 21880 | E5: active | F5: 14450 | G5: =F5*12 -> 173400 | H5: 2029-08-31
A6: 002 | B6: Standard suite | C6: B | D6: 22000 | E6: active | F6: 14600 | G6: =F6*12 -> 175200 | H6: 2029-08-31
A7: 003 | B7: Large suite | C7: C | D7: 22210 | E7: active | F7: 14875 | G7: =F7*12 -> 178500 | H7: 2029-08-31
A8: 004 | B8: Small suite | C8: A | D8: 21880 | E8: active | F8: 14450 | G8: =F8*12 -> 173400 | H8: 2029-08-31
A9: 005 | B9: Standard suite | C9: B | D9: 22000 | E9: active | F9: 14600 | G9: =F9*12 -> 175200 | H9: 2029-08-31
A10: 006 | B10: Large suite | C10: C | D10: 22210 | E10: active | F10: 14875 | G10: =F10*12 -> 178500 | H10: 2029-08-31
A11: 007 | B11: Small suite | C11: A | D11: 21880 | E11: active | F11: 14450 | G11: =F11*12 -> 173400 | H11: 2029-08-31
A12: 008 | B12: Standard suite | C12: B | D12: 22000 | E12: vacant | F12: 14600 | G12: =F12*12 -> 175200 | H12: 2029-08-31
A13: Total | D13: =SUM(D5:D12) -> 176060 | F13: =SUM(F5:F12) -> 116900 | G13: =SUM(G5:G12) -> 1402800
A15: Total units | B15: =COUNTA(A5:A12) -> 8
A16: Occupied units (status active) | B16: =COUNTIF(E5:E12,"active") -> 7
A17: Pending units (leased, no possession) | B17: =COUNTIF(E5:E12,"pending") -> 0
A18: Vacant units | B18: =COUNTIF(E5:E12,"vacant") -> 1
A19: Total area SF | B19: =D13 -> 176060
A20: Occupied area SF | B20: =SUMIF(E5:E12,"active",D5:D12) -> 154060
A21: Unit occupancy | B21: =B16/B15 -> 0.875
A22: Area occupancy | B22: =B20/B19 -> 0.8750426
A23: Annual in-place rent (active suites) | B23: =SUMIF(E5:E12,"active",G5:G12) -> 1227600
A24: Gross potential rent (all suites, annual) | B24: =G13 -> 1402800
A26: Group | B26: Units | C26: Occupied | D26: Area SF
A27: A (Small suite) | B27: =COUNTIF($C$5:$C$12,"A") -> 3 | C27: =COUNTIFS($C$5:$C$12,"A",$E$5:$E$12,"active") -> 3 | D27: =SUMIF($C$5:$C$12,"A",$D$5:$D$12) -> 65640
A28: B (Standard suite) | B28: =COUNTIF($C$5:$C$12,"B") -> 3 | C28: =COUNTIFS($C$5:$C$12,"B",$E$5:$E$12,"active") -> 2 | D28: =SUMIF($C$5:$C$12,"B",$D$5:$D$12) -> 66000
A29: C (Large suite) | B29: =COUNTIF($C$5:$C$12,"C") -> 2 | C29: =COUNTIFS($C$5:$C$12,"C",$E$5:$E$12,"active") -> 2 | D29: =SUMIF($C$5:$C$12,"C",$D$5:$D$12) -> 44420
A31: Suite 001 monthly rent per executed lease (lease-001.pdf p.1) | B31: 14450
A32: Active suite expiries within 12 months of 2026-08-31 | B32: 0
A33: Stale archive roll (2026-06-30) rents are superseded; not used.

Sheet Underwriting
A1: Underwritten cash flow (before and after reserves)
A2: Per underwriting-instructions.pdf p.1
A3: Gross potential rent (annual) | B3: =Inputs!B3 -> 1402800
A4: Economic loss at 5% | B4: =-Inputs!B3*Inputs!B4 -> -70140
A5: Other income ($350 per suite) | B5: =Inputs!B5*Inputs!B6 -> 2800
A6: Underwritten EGI | B6: =B3+B4+B5 -> 1335460
A8: Real estate tax | B8: =Inputs!B7 -> 147294
A9: Insurance | B9: =Inputs!B8 -> 49098
A10: Other recurring operating expenses | B10: =Inputs!B9 -> 196392
A11: Management fee (3% of EGI) | B11: =Inputs!B10*B6 -> 40063.8
A12: Total operating expenses | B12: =SUM(B8:B11) -> 432847.8
A14: Underwritten NOI before reserves | B14: =B6-B12 -> 902612.2
A15: Replacement reserves ($300 per suite) | B15: =Inputs!B11*Inputs!B6 -> 2400
A16: Underwritten NCF after reserves | B16: =B14-B15 -> 900212.2
A18: Capitalization rate | B18: =Inputs!B12 -> 0.0625
A19: Capitalization value (NOI before reserves / cap rate) | B19: =B14/B18 -> 14441795
A21: Operating expense ratio (share of EGI) | B21: =B12/B6 -> 0.32411888
A23: Historical T-12 comparison (operating-statement.pdf p.1)
A24: T-12 rental and ancillary collections | B24: 1262520
A25: T-12 real estate tax | B25: 147294
A26: T-12 insurance | B26: 49098
A27: T-12 other recurring operating expenses | B27: 196392
A28: Roof replacement booked in repairs (capital) | B28: 0
A29: Reported T-12 NOI (no management fee or reserves) | B29: =B24-B25-B26-B27-B28 -> 869736 | C29: Ties to reported NOI 869,736 on the statement
A30: Underwritten NOI less reported T-12 NOI | B30: =B14-B29 -> 32876.2

Sheet Debt
A1: Debt sizing and sources / uses
A2: Sized on the greater of note rate and floor; 30-year amortization, monthly pay
A3: LTV limit (65% of capitalization value) | B3: =Underwriting!B19*Inputs!B17 -> 9387166.9
A4: Maximum annual debt service at 1.25x DSCR on NCF | B4: =Underwriting!B16/Inputs!B18 -> 720169.76
A5: Sizing rate applied | B5: =Inputs!B13 -> 0.08
A6: Annual debt service constant per $1 of loan | B6: =-PMT(B5/12,Inputs!B16*12,1)*12 -> 0.088051749
A7: DSCR-constrained loan | B7: =B4/B6 -> 8178937.6
A8: Debt-yield-constrained loan (NCF / 9%) | B8: =Underwriting!B16/Inputs!B19 -> 10002358
A9: Maximum loan (binding constraint) | B9: =MIN(B3,B7,B8) -> 8178937.6
A10: Binding test | B10: =IF(B9=B7,"DSCR",IF(B9=B3,"LTV","Debt yield")) -> DSCR
A12: Sources and uses
A13: Loan proceeds (source) | B13: =B9 -> 8178937.6
A14: Origination fee at 1% (use) | B14: =-B9*Inputs!B20 -> -81789.376
A15: Closing costs (use) | B15: =-Inputs!B21 -> -45000
A16: Existing loan payoff (use) | B16: =-Inputs!B22 -> -7800000
A17: Net cash-out (negative = additional equity required) | B17: =B13+B14+B15+B16 -> 252148.23
A19: Implied DSCR at maximum loan | B19: =Underwriting!B16/(B9*B6) -> 1.25
A20: Implied NCF debt yield | B20: =Underwriting!B16/B9 -> 0.11006469
A21: Implied LTV on capitalization value | B21: =B9/Underwriting!B19 -> 0.56633801
A22: Interest-only annual interest, first 24 months at note rate | B22: =B9*Inputs!B14 -> 498915.19 | C22: Shown for information; sizing uses the 7.00% floor and 30-year amortization

Sheet Sensitivity
A1: Maximum loan sensitivity: sizing rate (rows) vs cap rate (columns)
A2: Each cell = MIN(LTV limit, DSCR limit, debt yield limit) holding underwritten NOI and NCF constant
A4: Sizing rate / Cap rate | B4: 0.0575 | C4: 0.06 | D4: 0.0625 | E4: 0.065 | F4: 0.0675
A5: 0.065 | B5: =MIN(Underwriting!$B$14/B$4*Inputs!$B$17,(Underwriting!$B$16/Inputs!$B$18)/(-PMT($A5/12,Inputs!$B$16*12,1)*12),Underwriting!$B$16/Inputs!$B$19) -> 9494887.3 | C5: =MIN(Underwriting!$B$14/C$4*Inputs!$B$17,(Underwriting!$B$16/Inputs!$B$18)/(-PMT($A5/12,Inputs!$B$16*12,1)*12),Underwriting!$B$16/Inputs!$B$19) -> 9494887.3 | D5: =MIN(Underwriting!$B$14/D$4*Inputs!$B$17,(Underwriting!$B$16/Inputs!$B$18)/(-PMT($A5/12,Inputs!$B$16*12,1)*12),Underwriting!$B$16/Inputs!$B$19) -> 9387166.9 | E5: =MIN(Underwriting!$B$14/E$4*Inputs!$B$17,(Underwriting!$B$16/Inputs!$B$18)/(-PMT($A5/12,Inputs!$B$16*12,1)*12),Underwriting!$B$16/Inputs!$B$19) -> 9026122 | F5: =MIN(Underwriting!$B$14/F$4*Inputs!$B$17,(Underwriting!$B$16/Inputs!$B$18)/(-PMT($A5/12,Inputs!$B$16*12,1)*12),Underwriting!$B$16/Inputs!$B$19) -> 8691821.2
A6: 0.0675 | B6: =MIN(Underwriting!$B$14/B$4*Inputs!$B$17,(Underwriting!$B$16/Inputs!$B$18)/(-PMT($A6/12,Inputs!$B$16*12,1)*12),Underwriting!$B$16/Inputs!$B$19) -> 9252902.1 | C6: =MIN(Underwriting!$B$14/C$4*Inputs!$B$17,(Underwriting!$B$16/Inputs!$B$18)/(-PMT($A6/12,Inputs!$B$16*12,1)*12),Underwriting!$B$16/Inputs!$B$19) -> 9252902.1 | D6: =MIN(Underwriting!$B$14/D$4*Inputs!$B$17,(Underwriting!$B$16/Inputs!$B$18)/(-PMT($A6/12,Inputs!$B$16*12,1)*12),Underwriting!$B$16/Inputs!$B$19) -> 9252902.1 | E6: =MIN(Underwriting!$B$14/E$4*Inputs!$B$17,(Underwriting!$B$16/Inputs!$B$18)/(-PMT($A6/12,Inputs!$B$16*12,1)*12),Underwriting!$B$16/Inputs!$B$19) -> 9026122 | F6: =MIN(Underwriting!$B$14/F$4*Inputs!$B$17,(Underwriting!$B$16/Inputs!$B$18)/(-PMT($A6/12,Inputs!$B$16*12,1)*12),Underwriting!$B$16/Inputs!$B$19) -> 8691821.2
A7: 0.07 | B7: =MIN(Underwriting!$B$14/B$4*Inputs!$B$17,(Underwriting!$B$16/Inputs!$B$18)/(-PMT($A7/12,Inputs!$B$16*12,1)*12),Underwriting!$B$16/Inputs!$B$19) -> 9020580.4 | C7: =MIN(Underwriting!$B$14/C$4*Inputs!$B$17,(Underwriting!$B$16/Inputs!$B$18)/(-PMT($A7/12,Inputs!$B$16*12,1)*12),Underwriting!$B$16/Inputs!$B$19) -> 9020580.4 | D7: =MIN(Underwriting!$B$14/D$4*Inputs!$B$17,(Underwriting!$B$16/Inputs!$B$18)/(-PMT($A7/12,Inputs!$B$16*12,1)*12),Underwriting!$B$16/Inputs!$B$19) -> 9020580.4 | E7: =MIN(Underwriting!$B$14/E$4*Inputs!$B$17,(Underwriting!$B$16/Inputs!$B$18)/(-PMT($A7/12,Inputs!$B$16*12,1)*12),Underwriting!$B$16/Inputs!$B$19) -> 9020580.4 | F7: =MIN(Underwriting!$B$14/F$4*Inputs!$B$17,(Underwriting!$B$16/Inputs!$B$18)/(-PMT($A7/12,Inputs!$B$16*12,1)*12),Underwriting!$B$16/Inputs!$B$19) -> 8691821.2
A8: 0.0725 | B8: =MIN(Underwriting!$B$14/B$4*Inputs!$B$17,(Underwriting!$B$16/Inputs!$B$18)/(-PMT($A8/12,Inputs!$B$16*12,1)*12),Underwriting!$B$16/Inputs!$B$19) -> 8797454.3 | C8: =MIN(Underwriting!$B$14/C$4*Inputs!$B$17,(Underwriting!$B$16/Inputs!$B$18)/(-PMT($A8/12,Inputs!$B$16*12,1)*12),Underwriting!$B$16/Inputs!$B$19) -> 8797454.3 | D8: =MIN(Underwriting!$B$14/D$4*Inputs!$B$17,(Underwriting!$B$16/Inputs!$B$18)/(-PMT($A8/12,Inputs!$B$16*12,1)*12),Underwriting!$B$16/Inputs!$B$19) -> 8797454.3 | E8: =MIN(Underwriting!$B$14/E$4*Inputs!$B$17,(Underwriting!$B$16/Inputs!$B$18)/(-PMT($A8/12,Inputs!$B$16*12,1)*12),Underwriting!$B$16/Inputs!$B$19) -> 8797454.3 | F8: =MIN(Underwriting!$B$14/F$4*Inputs!$B$17,(Underwriting!$B$16/Inputs!$B$18)/(-PMT($A8/12,Inputs!$B$16*12,1)*12),Underwriting!$B$16/Inputs!$B$19) -> 8691821.2
A9: 0.075 | B9: =MIN(Underwriting!$B$14/B$4*Inputs!$B$17,(Underwriting!$B$16/Inputs!$B$18)/(-PMT($A9/12,Inputs!$B$16*12,1)*12),Underwriting!$B$16/Inputs!$B$19) -> 8583080.9 | C9: =MIN(Underwriting!$B$14/C$4*Inputs!$B$17,(Underwriting!$B$16/Inputs!$B$18)/(-PMT($A9/12,Inputs!$B$16*12,1)*12),Underwriting!$B$16/Inputs!$B$19) -> 8583080.9 | D9: =MIN(Underwriting!$B$14/D$4*Inputs!$B$17,(Underwriting!$B$16/Inputs!$B$18)/(-PMT($A9/12,Inputs!$B$16*12,1)*12),Underwriting!$B$16/Inputs!$B$19) -> 8583080.9 | E9: =MIN(Underwriting!$B$14/E$4*Inputs!$B$17,(Underwriting!$B$16/Inputs!$B$18)/(-PMT($A9/12,Inputs!$B$16*12,1)*12),Underwriting!$B$16/Inputs!$B$19) -> 8583080.9 | F9: =MIN(Underwriting!$B$14/F$4*Inputs!$B$17,(Underwriting!$B$16/Inputs!$B$18)/(-PMT($A9/12,Inputs!$B$16*12,1)*12),Underwriting!$B$16/Inputs!$B$19) -> 8583080.9
A11: Gross potential rent scenarios (5% loss, other income and expenses per instructions)
A12: GPR | B12: EGI | C12: NOI before reserves | D12: NCF | E12: Cap value | F12: Maximum loan
A13: =Inputs!$B$3*0.95 -> 1332660 | B13: =A13*(1-Inputs!$B$4)+Inputs!$B$5*Inputs!$B$6 -> 1268827 | C13: =B13*(1-Inputs!$B$10)-Inputs!$B$7-Inputs!$B$8-Inputs!$B$9 -> 837978.19 | D13: =C13-Inputs!$B$11*Inputs!$B$6 -> 835578.19 | E13: =C13/Inputs!$B$12 -> 13407651 | F13: =MIN(E13*Inputs!$B$17,(D13/Inputs!$B$18)/(-PMT(Inputs!$B$13/12,Inputs!$B$16*12,1)*12),D13/Inputs!$B$19) -> 7591701
A14: =Inputs!$B$3 -> 1402800 | B14: =A14*(1-Inputs!$B$4)+Inputs!$B$5*Inputs!$B$6 -> 1335460 | C14: =B14*(1-Inputs!$B$10)-Inputs!$B$7-Inputs!$B$8-Inputs!$B$9 -> 902612.2 | D14: =C14-Inputs!$B$11*Inputs!$B$6 -> 900212.2 | E14: =C14/Inputs!$B$12 -> 14441795 | F14: =MIN(E14*Inputs!$B$17,(D14/Inputs!$B$18)/(-PMT(Inputs!$B$13/12,Inputs!$B$16*12,1)*12),D14/Inputs!$B$19) -> 8178937.6
A15: =Inputs!$B$3*1.05 -> 1472940 | B15: =A15*(1-Inputs!$B$4)+Inputs!$B$5*Inputs!$B$6 -> 1402093 | C15: =B15*(1-Inputs!$B$10)-Inputs!$B$7-Inputs!$B$8-Inputs!$B$9 -> 967246.21 | D15: =C15-Inputs!$B$11*Inputs!$B$6 -> 964846.21 | E15: =C15/Inputs!$B$12 -> 15475939 | F15: =MIN(E15*Inputs!$B$17,(D15/Inputs!$B$18)/(-PMT(Inputs!$B$13/12,Inputs!$B$16*12,1)*12),D15/Inputs!$B$19) -> 8766174.2
A17: Row 14 ties to the base case on the Underwriting and Debt sheets.

Sheet Sources
A1: Source register
A3: File | B3: Location | C3: Fact used
A4: rent-roll-certified.xlsx | B4: Rent Roll A2:F12 | C4: As-of 2026-08-31; 8 suites, 176,060 SF, 7 active / 1 vacant, monthly rents, expirations 2029-08-31
A5: rent-roll-archive.xlsx | B5: Rent Roll A2:F12 | C5: Stale 2026-06-30 roll with lower rents; superseded and not used
A6: lease-001.pdf | B6: p.1 | C6: Executed Suite 001 lease: $14,450 per month, 21,880 SF, expiry 2029-08-31, deposit $28,900, no free rent
A7: lease-correspondence.pdf | B7: p.1 | C7: Manager confirmation dated 2026-08-31: no amendments or new concessions affect Suite 001
A8: operating-statement.pdf | B8: p.1 | C8: T-12 to 2026-08-31: collections 1,262,520; tax 147,294; insurance 49,098; other 196,392; roof in repairs 0; reported NOI 869,736
A9: insurance.pdf | B9: p.1 | C9: General liability aggregate limit $2,000,000; policy period 2026-07-01 to 2027-06-30
A10: underwriting-instructions.pdf | B10: p.1 | C10: All underwriting and sizing assumptions, loan constraints, fees, closing costs and payoff
A11: manager-cover.pdf | B11: p.1 | C11: Indianapolis industrial; 7-of-8 leased headline including pending occupants; A/B/C group mapping; certified detail controls occupancy
A12: diligence-status.pdf | B12: p.1 | C12: Legal, environmental, property condition and title reviews incomplete; no defect findings supplied
A14: Not supplied (explicitly unknown) | B14: Unknown | C14: Photos, asking price, market sales and rent comps, sponsor history, tenant financials, appraisal, pending-unit schedule
