Workbook

Sheet Inputs
A1: Beacon Plaza — Underwriting Inputs
A3: Gross potential rent (annual, all suites) | B3: 1618800 | C3: Certified roll monthly rents ×12 (before Suite 001 amendment; per instructions)
A4: Other income per unit (annual) | B4: 350
A5: Unit count | B5: 12
A6: Economic loss % | B6: 0.05
A7: Real estate tax | B7: 169974
A8: Insurance expense | B8: 56658
A9: Other recurring opex | B9: 226632
A10: Management fee % of EGI | B10: 0.03
A11: Replacement reserve per unit | B11: 300
A12: Cap rate | B12: 0.075
A13: Note rate | B13: 0.0675
A14: UW rate floor | B14: 0.06
A15: Sizing rate (greater of above) | B15: =MAX(B13,B14)
A16: Amortization (months) | B16: 360
A17: Max LTV | B17: 0.6
A18: Min DSCR | B18: 1.25
A19: Min debt yield | B19: 0.09
A20: Origination fee % | B20: 0.01
A21: Closing costs | B21: 45000
A22: Existing payoff | B22: 6500000

Sheet UW
A1: Underwriting
A3: Gross potential rent | B3: =Inputs!B3
A4: Other income | B4: =Inputs!B4*Inputs!B5
A5: Gross income | B5: =B3+B4
A6: Economic loss | B6: =-B5*Inputs!B6
A7: Underwritten EGI | B7: =B5+B6
A9: Real estate tax | B9: =-Inputs!B7
A10: Insurance | B10: =-Inputs!B8
A11: Other recurring opex | B11: =-Inputs!B9
A12: Management fee | B12: =-B7*Inputs!B10
A13: Total operating expenses | B13: =SUM(B9:B12)
A15: Underwritten NOI (before reserves) | B15: =B7+B13
A16: Replacement reserves | B16: =-Inputs!B11*Inputs!B5
A17: Underwritten NCF | B17: =B15+B16
A19: Capitalization value (NOI / cap) | B19: =B15/Inputs!B12

Sheet Debt
A1: Debt sizing
A3: Sizing rate | B3: =Inputs!B15
A4: Monthly constant | B4: =(B3/12)/(1-(1+B3/12)^(-Inputs!B16))
A5: Annual constant | B5: =B4*12
A7: LTV-constrained loan | B7: =UW!B19*Inputs!B17
A8: DSCR-constrained loan | B8: =(UW!B17/Inputs!B18)/B5
A9: Debt-yield-constrained loan | B9: =UW!B17/Inputs!B19
A11: Maximum loan | B11: =MIN(B7,B8,B9)
A12: Binding constraint | B12: =IF(B11=B7,"LTV",IF(B11=B8,"DSCR","Debt yield"))
A14: Origination fee | B14: =-B11*Inputs!B20
A15: Closing costs | B15: =-Inputs!B21
A16: Existing payoff | B16: =-Inputs!B22
A17: Net cash-out to sponsor | B17: =B11+B14+B15+B16

Sheet Sensitivity
A1: Max loan sensitivity — cap rate (rows) × sizing rate (cols)
A3: Cap \ Sizing | B3: 0.06 | C3: 0.0625 | D3: 0.065 | E3: 0.0675 | F3: 0.07
A4: 0.07 | B4: =MIN(UW!$B$15/$A4*Inputs!$B$17, (UW!$B$17/Inputs!$B$18)/((B$3/12)/(1-(1+B$3/12)^(-Inputs!$B$16))*12), UW!$B$17/Inputs!$B$19) | C4: =MIN(UW!$B$15/$A4*Inputs!$B$17, (UW!$B$17/Inputs!$B$18)/((C$3/12)/(1-(1+C$3/12)^(-Inputs!$B$16))*12), UW!$B$17/Inputs!$B$19) | D4: =MIN(UW!$B$15/$A4*Inputs!$B$17, (UW!$B$17/Inputs!$B$18)/((D$3/12)/(1-(1+D$3/12)^(-Inputs!$B$16))*12), UW!$B$17/Inputs!$B$19) | E4: =MIN(UW!$B$15/$A4*Inputs!$B$17, (UW!$B$17/Inputs!$B$18)/((E$3/12)/(1-(1+E$3/12)^(-Inputs!$B$16))*12), UW!$B$17/Inputs!$B$19) | F4: =MIN(UW!$B$15/$A4*Inputs!$B$17, (UW!$B$17/Inputs!$B$18)/((F$3/12)/(1-(1+F$3/12)^(-Inputs!$B$16))*12), UW!$B$17/Inputs!$B$19)
A5: 0.0725 | B5: =MIN(UW!$B$15/$A5*Inputs!$B$17, (UW!$B$17/Inputs!$B$18)/((B$3/12)/(1-(1+B$3/12)^(-Inputs!$B$16))*12), UW!$B$17/Inputs!$B$19) | C5: =MIN(UW!$B$15/$A5*Inputs!$B$17, (UW!$B$17/Inputs!$B$18)/((C$3/12)/(1-(1+C$3/12)^(-Inputs!$B$16))*12), UW!$B$17/Inputs!$B$19) | D5: =MIN(UW!$B$15/$A5*Inputs!$B$17, (UW!$B$17/Inputs!$B$18)/((D$3/12)/(1-(1+D$3/12)^(-Inputs!$B$16))*12), UW!$B$17/Inputs!$B$19) | E5: =MIN(UW!$B$15/$A5*Inputs!$B$17, (UW!$B$17/Inputs!$B$18)/((E$3/12)/(1-(1+E$3/12)^(-Inputs!$B$16))*12), UW!$B$17/Inputs!$B$19) | F5: =MIN(UW!$B$15/$A5*Inputs!$B$17, (UW!$B$17/Inputs!$B$18)/((F$3/12)/(1-(1+F$3/12)^(-Inputs!$B$16))*12), UW!$B$17/Inputs!$B$19)
A6: 0.075 | B6: =MIN(UW!$B$15/$A6*Inputs!$B$17, (UW!$B$17/Inputs!$B$18)/((B$3/12)/(1-(1+B$3/12)^(-Inputs!$B$16))*12), UW!$B$17/Inputs!$B$19) | C6: =MIN(UW!$B$15/$A6*Inputs!$B$17, (UW!$B$17/Inputs!$B$18)/((C$3/12)/(1-(1+C$3/12)^(-Inputs!$B$16))*12), UW!$B$17/Inputs!$B$19) | D6: =MIN(UW!$B$15/$A6*Inputs!$B$17, (UW!$B$17/Inputs!$B$18)/((D$3/12)/(1-(1+D$3/12)^(-Inputs!$B$16))*12), UW!$B$17/Inputs!$B$19) | E6: =MIN(UW!$B$15/$A6*Inputs!$B$17, (UW!$B$17/Inputs!$B$18)/((E$3/12)/(1-(1+E$3/12)^(-Inputs!$B$16))*12), UW!$B$17/Inputs!$B$19) | F6: =MIN(UW!$B$15/$A6*Inputs!$B$17, (UW!$B$17/Inputs!$B$18)/((F$3/12)/(1-(1+F$3/12)^(-Inputs!$B$16))*12), UW!$B$17/Inputs!$B$19)
A7: 0.0775 | B7: =MIN(UW!$B$15/$A7*Inputs!$B$17, (UW!$B$17/Inputs!$B$18)/((B$3/12)/(1-(1+B$3/12)^(-Inputs!$B$16))*12), UW!$B$17/Inputs!$B$19) | C7: =MIN(UW!$B$15/$A7*Inputs!$B$17, (UW!$B$17/Inputs!$B$18)/((C$3/12)/(1-(1+C$3/12)^(-Inputs!$B$16))*12), UW!$B$17/Inputs!$B$19) | D7: =MIN(UW!$B$15/$A7*Inputs!$B$17, (UW!$B$17/Inputs!$B$18)/((D$3/12)/(1-(1+D$3/12)^(-Inputs!$B$16))*12), UW!$B$17/Inputs!$B$19) | E7: =MIN(UW!$B$15/$A7*Inputs!$B$17, (UW!$B$17/Inputs!$B$18)/((E$3/12)/(1-(1+E$3/12)^(-Inputs!$B$16))*12), UW!$B$17/Inputs!$B$19) | F7: =MIN(UW!$B$15/$A7*Inputs!$B$17, (UW!$B$17/Inputs!$B$18)/((F$3/12)/(1-(1+F$3/12)^(-Inputs!$B$16))*12), UW!$B$17/Inputs!$B$19)
A8: 0.08 | B8: =MIN(UW!$B$15/$A8*Inputs!$B$17, (UW!$B$17/Inputs!$B$18)/((B$3/12)/(1-(1+B$3/12)^(-Inputs!$B$16))*12), UW!$B$17/Inputs!$B$19) | C8: =MIN(UW!$B$15/$A8*Inputs!$B$17, (UW!$B$17/Inputs!$B$18)/((C$3/12)/(1-(1+C$3/12)^(-Inputs!$B$16))*12), UW!$B$17/Inputs!$B$19) | D8: =MIN(UW!$B$15/$A8*Inputs!$B$17, (UW!$B$17/Inputs!$B$18)/((D$3/12)/(1-(1+D$3/12)^(-Inputs!$B$16))*12), UW!$B$17/Inputs!$B$19) | E8: =MIN(UW!$B$15/$A8*Inputs!$B$17, (UW!$B$17/Inputs!$B$18)/((E$3/12)/(1-(1+E$3/12)^(-Inputs!$B$16))*12), UW!$B$17/Inputs!$B$19) | F8: =MIN(UW!$B$15/$A8*Inputs!$B$17, (UW!$B$17/Inputs!$B$18)/((F$3/12)/(1-(1+F$3/12)^(-Inputs!$B$16))*12), UW!$B$17/Inputs!$B$19)

Sheet Sources
A1: Source register
A3: Document | B3: Key facts used | C3: Location
A4: rent-roll-certified.xlsx | B4: 12 suites, statuses, monthly rents, area, expirations | C4: Rent Roll A4:G16
A5: rent-roll-archive.xlsx | B5: Stale 2026-06-30 roll; superseded | C5: Rent Roll A2
A6: lease-001.pdf | B6: Suite 001 executed base rent $11,050; area 5,380 SF; exp 2027-02-28 | C6: p.1
A7: lease-correspondence.pdf | B7: No amendments/concessions to Suite 001 as of 2026-08-31 | C7: p.1
A8: operating-statement.pdf | B8: T12 collections/expenses/reported NOI; roof capital not expensed | C8: p.1
A9: insurance.pdf | B9: GL aggregate limit $2,000,000 (not expense) | C9: p.1
A10: underwriting-instructions.pdf | B10: UW method, sizing, loss %, reserves, fees | C10: p.1
A11: manager-cover.pdf | B11: Group A/B/C mapping; manager 10/12 headline includes pending | C11: p.1
A12: diligence-status.pdf | B12: Legal/env/PCA/title incomplete; label definitions | C12: p.1
