Workbook

Sheet Inputs
A1: Falcon Distribution | Underwriting inputs (REVISED per revision-notice.pdf, roll as of 2026-09-01)
A2: Original fictional evaluation material; no real transaction. Revision 2 supersedes the 2026-08-31 version; prior workbook retained in the archive.
A3: Gross potential rent (annual, all suites) | B3: 1405500 | C3: Revised all-suite scheduled monthly rent $117,125 x 12 (rent-roll-revised.xlsx E5:E12); was $1,402,800
A4: Economic loss (vacancy/credit) | B4: 0.05 | C4: Unchanged (underwriting-instructions.pdf p.1)
A5: Other income per unit/suite (annual) | B5: 350 | C5: Unchanged; reimbursements already included, not double counted
A6: Unit/suite count | B6: 8
A7: Real estate tax expense | B7: 147294
A8: Insurance expense | B8: 49098
A9: Other recurring operating expenses | B9: 196392
A10: Management fee (% of underwritten EGI) | B10: 0.03
A11: Replacement reserve per unit/suite | B11: 300
A12: Capitalization rate (NOI before reserves) | B12: 0.065 | C12: REVISED: 6.2500% + 25 bps = 6.5000%
A13: Sizing rate applied | B13: 0.0875 | C13: REVISED: prior sizing rate 7.0000% + 75 bps = 7.7500%; still the greater of note rate and floor
A14: Note rate (contract, unchanged) | B14: 0.061
A15: Underwriting rate floor as revised | B15: 0.0775 | C15: Floor 7.0000% + 75 bps; exceeds the 6.1000% note rate, so the floor still binds
A16: Amortization (years, monthly pay) | B16: 30
A17: Maximum LTV | B17: 0.65
A18: Minimum DSCR (on NCF) | B18: 1.25
A19: Minimum NCF debt yield | B19: 0.09
A20: Origination fee (% of sized loan) | B20: 0.01
A21: Closing costs | B21: 45000
A22: Existing loan payoff (unchanged) | B22: 7800000
A24: Rate-floor check: greater of note rate and revised floor | B24: =MAX(B14,B15) | C24: Ties to the sizing rate input in B13

Sheet Rent Roll
A1: Revised certified rent roll as of 2026-09-01 (rent-roll-revised.xlsx)
A2: Groups: A = Small suite, B = Standard suite, C = Large suite (manager-cover.pdf p.1). Supersedes the 2026-08-31 certified roll; 2026-06-30 archive remains stale.
A4: Suite | B4: Unit type | C4: Group | D4: Area SF | E4: Status | F4: Monthly rent | G4: Annual rent | H4: Expiration | I4: Prior monthly
A5: 001 | B5: Small suite | C5: A | D5: 21880 | E5: active | F5: 14450 | G5: =F5*12 | H5: 2029-08-31 | I5: 14450
A6: 002 | B6: Standard suite | C6: B | D6: 22000 | E6: active | F6: 14825 | G6: =F6*12 | H6: 2029-08-31 | I6: 14600
A7: 003 | B7: Large suite | C7: C | D7: 22210 | E7: active | F7: 14875 | G7: =F7*12 | H7: 2029-08-31 | I7: 14875
A8: 004 | B8: Small suite | C8: A | D8: 21880 | E8: active | F8: 14450 | G8: =F8*12 | H8: 2029-08-31 | I8: 14450
A9: 005 | B9: Standard suite | C9: B | D9: 22000 | E9: active | F9: 14600 | G9: =F9*12 | H9: 2029-08-31 | I9: 14600
A10: 006 | B10: Large suite | C10: C | D10: 22210 | E10: active | F10: 14875 | G10: =F10*12 | H10: 2029-08-31 | I10: 14875
A11: 007 | B11: Small suite | C11: A | D11: 21880 | E11: active | F11: 14450 | G11: =F11*12 | H11: 2029-08-31 | I11: 14450
A12: 008 | B12: Standard suite | C12: B | D12: 22000 | E12: vacant | F12: 14600 | G12: =F12*12 | H12: 2029-08-31 | I12: 14600
A13: Total | D13: =SUM(D5:D12) | F13: =SUM(F5:F12) | G13: =SUM(G5:G12) | I13: =SUM(I5:I12)
A15: Total units | B15: =COUNTA(A5:A12)
A16: Occupied units (status active) | B16: =COUNTIF(E5:E12,"active")
A17: Pending units (leased, no possession) | B17: =COUNTIF(E5:E12,"pending")
A18: Vacant units | B18: =COUNTIF(E5:E12,"vacant")
A19: Total area SF | B19: =D13
A20: Occupied area SF | B20: =SUMIF(E5:E12,"active",D5:D12)
A21: Unit occupancy | B21: =B16/B15
A22: Area occupancy | B22: =B20/B19
A23: Annual in-place rent (active suites) | B23: =SUMIF(E5:E12,"active",G5:G12)
A24: Gross potential rent (all suites, annual) | B24: =G13
A26: Group | B26: Units | C26: Occupied | D26: Area SF
A27: A (Small suite) | B27: =COUNTIF($C$5:$C$12,"A") | C27: =COUNTIFS($C$5:$C$12,"A",$E$5:$E$12,"active") | D27: =SUMIF($C$5:$C$12,"A",$D$5:$D$12)
A28: B (Standard suite) | B28: =COUNTIF($C$5:$C$12,"B") | C28: =COUNTIFS($C$5:$C$12,"B",$E$5:$E$12,"active") | D28: =SUMIF($C$5:$C$12,"B",$D$5:$D$12)
A29: C (Large suite) | B29: =COUNTIF($C$5:$C$12,"C") | C29: =COUNTIFS($C$5:$C$12,"C",$E$5:$E$12,"active") | D29: =SUMIF($C$5:$C$12,"C",$D$5:$D$12)
A31: Suite 001 monthly rent per executed lease (lease-001.pdf p.1) | B31: 14450 | C31: Unchanged; no amendment or unsigned proposal in the packet
A32: Active suite expiries within 12 months of 2026-09-01 | B32: 0
A33: Only change versus the prior roll: Suite 002 scheduled rent +$225 per month ($14,600 to $14,825). Statuses, areas and expirations unchanged.

Sheet Underwriting
A1: Underwritten cash flow (revised)
A2: Rules per underwriting-instructions.pdf p.1; cap rate per revision-notice.pdf p.1
A3: Gross potential rent (annual) | B3: =Inputs!B3
A4: Economic loss at 5% | B4: =-Inputs!B3*Inputs!B4
A5: Other income ($350 per suite) | B5: =Inputs!B5*Inputs!B6
A6: Underwritten EGI | B6: =B3+B4+B5
A8: Real estate tax | B8: =Inputs!B7
A9: Insurance | B9: =Inputs!B8
A10: Other recurring operating expenses | B10: =Inputs!B9
A11: Management fee (3% of EGI) | B11: =Inputs!B10*B6
A12: Total operating expenses | B12: =SUM(B8:B11)
A14: Underwritten NOI before reserves | B14: =B6-B12
A15: Replacement reserves ($300 per suite) | B15: =Inputs!B11*Inputs!B6
A16: Underwritten NCF after reserves | B16: =B14-B15
A18: Capitalization rate (revised 6.5000%) | B18: =Inputs!B12
A19: Capitalization value (NOI before reserves / cap rate) | B19: =B14/B18
A21: Operating expense ratio (share of EGI) | B21: =B12/B6
A23: Historical T-12 comparison (operating-statement.pdf p.1, unchanged)
A24: T-12 rental and ancillary collections | B24: 1262520
A25: T-12 real estate tax | B25: 147294
A26: T-12 insurance | B26: 49098
A27: T-12 other recurring operating expenses | B27: 196392
A28: Roof replacement booked in repairs (capital) | B28: 0
A29: Reported T-12 NOI (no management fee or reserves) | B29: =B24-B25-B26-B27-B28 | C29: Ties to reported NOI 869,736 on the statement
A30: Underwritten NOI less reported T-12 NOI | B30: =B14-B29

Sheet Debt
A1: Debt sizing and sources / uses (revised)
A2: Sized at the revised 7.7500% rate (greater of note rate and revised floor), 30-year monthly amortization
A3: LTV limit (65% of capitalization value) | B3: =Underwriting!B19*Inputs!B17
A4: Maximum annual debt service at 1.25x DSCR on NCF | B4: =Underwriting!B16/Inputs!B18
A5: Sizing rate applied | B5: =Inputs!B13
A6: Annual debt service constant per $1 of loan | B6: =-PMT(B5/12,Inputs!B16*12,1)*12
A7: DSCR-constrained loan | B7: =B4/B6
A8: Debt-yield-constrained loan (NCF / 9%) | B8: =Underwriting!B16/Inputs!B19
A9: Maximum loan (binding constraint) | B9: =MIN(B3,B7,B8)
A10: Binding test | B10: =IF(B9=B7,"DSCR",IF(B9=B3,"LTV","Debt yield"))
A12: Sources and uses
A13: Loan proceeds (source) | B13: =B9
A14: Origination fee at 1% (use) | B14: =-B9*Inputs!B20
A15: Closing costs (use) | B15: =-Inputs!B21
A16: Existing loan payoff (use) | B16: =-Inputs!B22
A17: Net cash-out (negative = additional equity required) | B17: =B13+B14+B15+B16
A19: Implied DSCR at maximum loan | B19: =Underwriting!B16/(B9*B6)
A20: Implied NCF debt yield | B20: =Underwriting!B16/B9
A21: Implied LTV on capitalization value | B21: =B9/Underwriting!B19
A22: Interest-only annual interest, first 24 months at note rate | B22: =B9*Inputs!B14 | C22: Informational; sizing uses the 7.7500% revised rate and 30-year amortization

Sheet Changes
A1: Revision reconciliation: prior (2026-08-31 roll) versus revised (2026-09-01 roll)
A2: Prior workbook artifacts/underwriting-v2.xlsx remains in the audit archive and is not replaced.
A4: Item | B4: Prior | C4: Revised | D4: Change | E4: Driver
A5: Controlling roll date | B5: 2026-08-31 | C5: 2026-09-01 | D5: superseded | E5: revision-notice.pdf p.1
A6: Suite 002 monthly rent | B6: 14600 | C6: 14825 | D6: =C6-B6 | E6: +$225 per revision notice
A7: Gross potential rent | B7: 1402800 | C7: =Inputs!B3 | D7: =C7-B7 | E7: $225 x 12
A8: Annual in-place rent | B8: 1227600 | C8: ='Rent Roll'!B23 | D8: =C8-B8 | E8: Suite 002 already active; rent increase only
A9: Underwritten EGI | B9: 1335460 | C9: =Underwriting!B6 | D9: =C9-B9 | E9: 95% of higher GPR
A10: NOI before reserves | B10: 902612.2 | C10: =Underwriting!B14 | D10: =C10-B10 | E10: EGI increase net of 3% management fee
A11: NCF after reserves | B11: 900212.2 | C11: =Underwriting!B16 | D11: =C11-B11 | E11: Reserves unchanged at $2,400
A12: Capitalization rate | B12: 0.0625 | C12: =Inputs!B12 | D12: =C12-B12 | E12: +25 bps per revision notice
A13: Capitalization value | B13: 14441795 | C13: =Underwriting!B19 | D13: =C13-B13 | E13: Higher NOI more than offset by higher cap rate
A14: Sizing rate | B14: 0.07 | C14: =Inputs!B13 | D14: =C14-B14 | E14: +75 bps per revision notice; still above the 6.1000% note rate
A15: LTV limit | B15: 9387166.9 | C15: =Debt!B3 | D15: =C15-B15 | E15: Lower cap value
A16: DSCR limit | B16: 9020580.4 | C16: =Debt!B7 | D16: =C16-B16 | E16: Higher constant at 7.7500%
A17: Debt yield limit | B17: 10002358 | C17: =Debt!B8 | D17: =C17-B17 | E17: Higher NCF
A18: Maximum loan | B18: 9020580.4 | C18: =Debt!B9 | D18: =C18-B18 | E18: DSCR remains the binding test
A19: Net cash-out | B19: 1085374.6 | C19: =Debt!B17 | D19: =C19-B19 | E19: Smaller loan, same payoff and costs
A21: Unaffected facts preserved: 8 suites, 176,060 SF, 7 active / 1 vacant (Suite 008), occupancy 0.8750 by unit and area, Suite 001 rent $14,450, all expirations 2029-08-31, tax/insurance/other expenses, reserves, LTV/DSCR/debt-yield tests, fees, $7,800,000 payoff, insurance limit $2,000,000, reported T-12 NOI $869,736.

Sheet Sensitivity
A1: Maximum loan sensitivity: sizing rate (rows) vs cap rate (columns) - revised base 7.7500% / 6.5000%
A2: Each cell = MIN(LTV limit, DSCR limit, debt yield limit) holding revised NOI and NCF constant
A4: Sizing rate / Cap rate | B4: 0.06 | C4: 0.0625 | D4: 0.065 | E4: 0.0675 | F4: 0.07
A5: 0.07 | B5: =MIN(Underwriting!$B$14/B$4*Inputs!$B$17,(Underwriting!$B$16/Inputs!$B$18)/(-PMT($A5/12,Inputs!$B$16*12,1)*12),Underwriting!$B$16/Inputs!$B$19) | C5: =MIN(Underwriting!$B$14/C$4*Inputs!$B$17,(Underwriting!$B$16/Inputs!$B$18)/(-PMT($A5/12,Inputs!$B$16*12,1)*12),Underwriting!$B$16/Inputs!$B$19) | D5: =MIN(Underwriting!$B$14/D$4*Inputs!$B$17,(Underwriting!$B$16/Inputs!$B$18)/(-PMT($A5/12,Inputs!$B$16*12,1)*12),Underwriting!$B$16/Inputs!$B$19) | E5: =MIN(Underwriting!$B$14/E$4*Inputs!$B$17,(Underwriting!$B$16/Inputs!$B$18)/(-PMT($A5/12,Inputs!$B$16*12,1)*12),Underwriting!$B$16/Inputs!$B$19) | F5: =MIN(Underwriting!$B$14/F$4*Inputs!$B$17,(Underwriting!$B$16/Inputs!$B$18)/(-PMT($A5/12,Inputs!$B$16*12,1)*12),Underwriting!$B$16/Inputs!$B$19)
A6: 0.0725 | B6: =MIN(Underwriting!$B$14/B$4*Inputs!$B$17,(Underwriting!$B$16/Inputs!$B$18)/(-PMT($A6/12,Inputs!$B$16*12,1)*12),Underwriting!$B$16/Inputs!$B$19) | C6: =MIN(Underwriting!$B$14/C$4*Inputs!$B$17,(Underwriting!$B$16/Inputs!$B$18)/(-PMT($A6/12,Inputs!$B$16*12,1)*12),Underwriting!$B$16/Inputs!$B$19) | D6: =MIN(Underwriting!$B$14/D$4*Inputs!$B$17,(Underwriting!$B$16/Inputs!$B$18)/(-PMT($A6/12,Inputs!$B$16*12,1)*12),Underwriting!$B$16/Inputs!$B$19) | E6: =MIN(Underwriting!$B$14/E$4*Inputs!$B$17,(Underwriting!$B$16/Inputs!$B$18)/(-PMT($A6/12,Inputs!$B$16*12,1)*12),Underwriting!$B$16/Inputs!$B$19) | F6: =MIN(Underwriting!$B$14/F$4*Inputs!$B$17,(Underwriting!$B$16/Inputs!$B$18)/(-PMT($A6/12,Inputs!$B$16*12,1)*12),Underwriting!$B$16/Inputs!$B$19)
A7: 0.075 | B7: =MIN(Underwriting!$B$14/B$4*Inputs!$B$17,(Underwriting!$B$16/Inputs!$B$18)/(-PMT($A7/12,Inputs!$B$16*12,1)*12),Underwriting!$B$16/Inputs!$B$19) | C7: =MIN(Underwriting!$B$14/C$4*Inputs!$B$17,(Underwriting!$B$16/Inputs!$B$18)/(-PMT($A7/12,Inputs!$B$16*12,1)*12),Underwriting!$B$16/Inputs!$B$19) | D7: =MIN(Underwriting!$B$14/D$4*Inputs!$B$17,(Underwriting!$B$16/Inputs!$B$18)/(-PMT($A7/12,Inputs!$B$16*12,1)*12),Underwriting!$B$16/Inputs!$B$19) | E7: =MIN(Underwriting!$B$14/E$4*Inputs!$B$17,(Underwriting!$B$16/Inputs!$B$18)/(-PMT($A7/12,Inputs!$B$16*12,1)*12),Underwriting!$B$16/Inputs!$B$19) | F7: =MIN(Underwriting!$B$14/F$4*Inputs!$B$17,(Underwriting!$B$16/Inputs!$B$18)/(-PMT($A7/12,Inputs!$B$16*12,1)*12),Underwriting!$B$16/Inputs!$B$19)
A8: 0.0775 | B8: =MIN(Underwriting!$B$14/B$4*Inputs!$B$17,(Underwriting!$B$16/Inputs!$B$18)/(-PMT($A8/12,Inputs!$B$16*12,1)*12),Underwriting!$B$16/Inputs!$B$19) | C8: =MIN(Underwriting!$B$14/C$4*Inputs!$B$17,(Underwriting!$B$16/Inputs!$B$18)/(-PMT($A8/12,Inputs!$B$16*12,1)*12),Underwriting!$B$16/Inputs!$B$19) | D8: =MIN(Underwriting!$B$14/D$4*Inputs!$B$17,(Underwriting!$B$16/Inputs!$B$18)/(-PMT($A8/12,Inputs!$B$16*12,1)*12),Underwriting!$B$16/Inputs!$B$19) | E8: =MIN(Underwriting!$B$14/E$4*Inputs!$B$17,(Underwriting!$B$16/Inputs!$B$18)/(-PMT($A8/12,Inputs!$B$16*12,1)*12),Underwriting!$B$16/Inputs!$B$19) | F8: =MIN(Underwriting!$B$14/F$4*Inputs!$B$17,(Underwriting!$B$16/Inputs!$B$18)/(-PMT($A8/12,Inputs!$B$16*12,1)*12),Underwriting!$B$16/Inputs!$B$19)
A9: 0.08 | B9: =MIN(Underwriting!$B$14/B$4*Inputs!$B$17,(Underwriting!$B$16/Inputs!$B$18)/(-PMT($A9/12,Inputs!$B$16*12,1)*12),Underwriting!$B$16/Inputs!$B$19) | C9: =MIN(Underwriting!$B$14/C$4*Inputs!$B$17,(Underwriting!$B$16/Inputs!$B$18)/(-PMT($A9/12,Inputs!$B$16*12,1)*12),Underwriting!$B$16/Inputs!$B$19) | D9: =MIN(Underwriting!$B$14/D$4*Inputs!$B$17,(Underwriting!$B$16/Inputs!$B$18)/(-PMT($A9/12,Inputs!$B$16*12,1)*12),Underwriting!$B$16/Inputs!$B$19) | E9: =MIN(Underwriting!$B$14/E$4*Inputs!$B$17,(Underwriting!$B$16/Inputs!$B$18)/(-PMT($A9/12,Inputs!$B$16*12,1)*12),Underwriting!$B$16/Inputs!$B$19) | F9: =MIN(Underwriting!$B$14/F$4*Inputs!$B$17,(Underwriting!$B$16/Inputs!$B$18)/(-PMT($A9/12,Inputs!$B$16*12,1)*12),Underwriting!$B$16/Inputs!$B$19)
A11: Gross potential rent scenarios (5% loss, other income and expenses per instructions)
A12: GPR | B12: EGI | C12: NOI before reserves | D12: NCF | E12: Cap value | F12: Maximum loan
A13: =Inputs!$B$3*0.95 | B13: =A13*(1-Inputs!$B$4)+Inputs!$B$5*Inputs!$B$6 | C13: =B13*(1-Inputs!$B$10)-Inputs!$B$7-Inputs!$B$8-Inputs!$B$9 | D13: =C13-Inputs!$B$11*Inputs!$B$6 | E13: =C13/Inputs!$B$12 | F13: =MIN(E13*Inputs!$B$17,(D13/Inputs!$B$18)/(-PMT(Inputs!$B$13/12,Inputs!$B$16*12,1)*12),D13/Inputs!$B$19)
A14: =Inputs!$B$3 | B14: =A14*(1-Inputs!$B$4)+Inputs!$B$5*Inputs!$B$6 | C14: =B14*(1-Inputs!$B$10)-Inputs!$B$7-Inputs!$B$8-Inputs!$B$9 | D14: =C14-Inputs!$B$11*Inputs!$B$6 | E14: =C14/Inputs!$B$12 | F14: =MIN(E14*Inputs!$B$17,(D14/Inputs!$B$18)/(-PMT(Inputs!$B$13/12,Inputs!$B$16*12,1)*12),D14/Inputs!$B$19)
A15: =Inputs!$B$3*1.05 | B15: =A15*(1-Inputs!$B$4)+Inputs!$B$5*Inputs!$B$6 | C15: =B15*(1-Inputs!$B$10)-Inputs!$B$7-Inputs!$B$8-Inputs!$B$9 | D15: =C15-Inputs!$B$11*Inputs!$B$6 | E15: =C15/Inputs!$B$12 | F15: =MIN(E15*Inputs!$B$17,(D15/Inputs!$B$18)/(-PMT(Inputs!$B$13/12,Inputs!$B$16*12,1)*12),D15/Inputs!$B$19)
A17: Row 14 and the 7.7500% / 6.5000% cell tie to the revised base case on the Underwriting and Debt sheets.

Sheet Sources
A1: Source register (revision 2)
A3: File | B3: Location | C3: Fact used
A4: rent-roll-revised.xlsx | B4: Rent Roll A2:F12 | C4: Controlling roll as of 2026-09-01: 8 suites, 176,060 SF, 7 active / 1 vacant, Suite 002 at $14,825, expirations 2029-08-31
A5: revision-notice.pdf | B5: p.1 | C5: Revised roll supersedes prior roll; Suite 002 rent +$225; sizing rate +75 bps; cap rate +25 bps; all other rules and payoff unchanged
A6: rent-roll-certified.xlsx | B6: Rent Roll A2:F12 | C6: Prior 2026-08-31 roll; superseded, retained for comparison on the Changes sheet
A7: rent-roll-archive.xlsx | B7: Rent Roll A2:F12 | C7: Stale 2026-06-30 roll; excluded
A8: lease-001.pdf | B8: p.1 | C8: Executed Suite 001 lease: $14,450 per month, 21,880 SF, expiry 2029-08-31, deposit $28,900, no free rent
A9: lease-correspondence.pdf | B9: p.1 | C9: Manager confirmation dated 2026-08-31: no amendments or new concessions affect Suite 001
A10: operating-statement.pdf | B10: p.1 | C10: T-12 to 2026-08-31: collections 1,262,520; tax 147,294; insurance 49,098; other 196,392; roof in repairs 0; reported NOI 869,736
A11: insurance.pdf | B11: p.1 | C11: General liability aggregate limit $2,000,000; policy period 2026-07-01 to 2027-06-30
A12: underwriting-instructions.pdf | B12: p.1 | C12: Underwriting rules, expense amounts, loan constraints, fees, closing costs, payoff, greater-of-rate sizing
A13: manager-cover.pdf | B13: p.1 | C13: Indianapolis industrial; leased headline includes unpossessed pending occupants; A/B/C group mapping; approved copy
A14: diligence-status.pdf | B14: p.1 | C14: Legal, environmental, property condition and title reviews incomplete; no defect findings supplied
A16: Not supplied (explicitly unknown) | B16: Unknown | C16: Photos, asking price, market sales and rent comps, sponsor history, appraisal, tenant financials, Suite 008 leasing plan, signed Suite 002 amendment document
