Workbook

Sheet Inputs
A1: Cedar Landing | Editable underwriting assumptions (as of 2026-08-31)
A3: Assumption | B3: Value | C3: Source
A4: UW gross potential base rent (annual) | B4: 1003200 | C4: Property-and-Plan.pdf p.2
A5: Combined revenue loss % of GPR | B5: 0.07 | C5: Property-and-Plan.pdf p.2 (vacancy/concessions/bad debt)
A6: Other income / recoveries (annual) | B6: 41040 | C6: Property-and-Plan.pdf p.2; added after loss
A7: Capitalization rate | B7: 0.0575 | C7: Lender-Terms.pdf p.1 (NOI before reserves / 5.75%)
A8: Maximum LTV | B8: 0.6 | C8: Lender-Terms.pdf p.1
A9: Minimum DSCR (NCF after reserves) | B9: 1.3 | C9: Lender-Terms.pdf p.1
A10: Minimum debt yield (NCF after reserves) | B10: 0.09 | C10: Lender-Terms.pdf p.1
A11: Contract (note) rate | B11: 0.0625 | C11: Lender-Terms.pdf p.1
A12: Underwriting rate floor | B12: 0.065 | C12: Lender-Terms.pdf p.1 (sizing = greater of contract and floor)
A13: Sizing rate adjustment (decimal, e.g. 0.01 = +100 bps) | B13: 0 | C13: Reviewer stress lever
A14: Sizing rate applied | B14: =MAX(B11,B12)+B13 -> 0.065
A15: Amortization (years, monthly pay) | B15: 30 | C15: Lender-Terms.pdf p.1
A16: Interest-only period (months) | B16: 36 | C16: Lender-Terms.pdf p.1
A17: Maturity (months) | B17: 60 | C17: Lender-Terms.pdf p.1
A18: Origination fee % of initial principal | B18: 0.01 | C18: Lender-Terms.pdf p.1
A19: Fixed closing costs | B19: 65000 | C19: Property-and-Plan.pdf p.1
A20: Existing debt payoff | B20: 4500000 | C20: Property-and-Plan.pdf p.1
A21: Replacement reserves per unit per year | B21: 325 | C21: Property-and-Plan.pdf p.2
A22: Unit count (from rent roll) | B22: ='Rent Roll'!B56 -> 48 | C22: Rent-Roll.xlsx rows 7-54
A24: Underwritten operating expenses (annual) | B24: Value | C24: Source / treatment
A25: Real estate taxes | B25: 138000 | C25: Plan p.2 UW (T12 132,000)
A26: Property insurance | B26: 45600 | C26: Plan p.2 renewal allowance dated 2026-08-25 (T12 40,800)
A27: Utilities | B27: 33600 | C27: Plan p.2: T12 actual
A28: Repairs and maintenance | B28: 42000 | C28: T12 54,000 less 12,000 one-time casualty cleanup
A29: Payroll / contract labor | B29: 55200 | C29: Plan p.2: T12 actual
A30: Administrative / legal | B30: 27600 | C30: Plan p.2: T12 actual
A31: Management fee % of underwritten EGI | B31: 0.035 | C31: Plan p.2: greater of T12 actual and 3.50% of EGI
A32: Management fee floor (T12 actual) | B32: 28000 | C32: T12-Statement.pdf p.2 annual column

Sheet Rent Roll
A1: Cedar Landing | Contractual rent roll as of 2026-08-31 (source: Rent-Roll.xlsx)
A3: Vacant units show market rent in the source file only; no contractual base rent is credited.
A6: Unit | B6: Tenant | C6: Area SF | D6: Status | E6: Monthly base rent | F6: Lease expiry
A7: 101 | B7: Household 101 | C7: 700 | D7: Occupied | E7: 1575 | F7: 2027-06-30
A8: 102 | B8: Household 102 | C8: 700 | D8: Occupied | E8: 1575 | F8: 2026-10-31
A9: 103 | B9: Household 103 | C9: 700 | D9: Occupied | E9: 1575 | F9: 2026-11-30
A10: 104 | B10: Household 104 | C10: 700 | D10: Occupied | E10: 1575 | F10: 2026-12-31
A11: 105 | B11: Household 105 | C11: 700 | D11: Occupied | E11: 1575 | F11: 2027-01-31
A12: 106 | B12: Household 106 | C12: 700 | D12: Occupied | E12: 1575 | F12: 2027-02-28
A13: 107 | B13: Household 107 | C13: 700 | D13: Occupied | E13: 1575 | F13: 2027-03-31
A14: 108 | B14: Household 108 | C14: 700 | D14: Occupied | E14: 1575 | F14: 2027-04-30
A15: 109 | B15: Household 109 | C15: 700 | D15: Occupied | E15: 1575 | F15: 2027-05-31
A16: 110 | B16: Household 110 | C16: 700 | D16: Occupied | E16: 1575 | F16: 2027-06-30
A17: 111 | B17: Household 111 | C17: 700 | D17: Occupied | E17: 1575 | F17: 2027-07-31
A18: 112 | B18: Household 112 | C18: 700 | D18: Occupied | E18: 1575 | F18: 2027-08-31
... A39: 133 | B39: Household 133 | C39: 1100 | D39: Occupied | E39: 2025 | F39: 2027-05-31
A40: 134 | B40: Vacant | C40: 1100 | D40: Vacant | F40: n/a
A41: 135 | B41: Vacant | C41: 1100 | D41: Vacant | F41: n/a
A42: 136 | B42: Vacant | C42: 1100 | D42: Vacant | F42: n/a
A43: 137 | B43: Vacant | C43: 1100 | D43: Vacant | F43: n/a
A44: 138 | B44: Vacant | C44: 1100 | D44: Vacant | F44: n/a
A45: 139 | B45: Vacant | C45: 1100 | D45: Vacant | F45: n/a
A46: 140 | B46: Vacant | C46: 1100 | D46: Vacant | F46: n/a
A47: 141 | B47: Vacant | C47: 1100 | D47: Vacant | F47: n/a
A48: 142 | B48: Vacant | C48: 1100 | D48: Vacant | F48: n/a
A49: 143 | B49: Vacant | C49: 1100 | D49: Vacant | F49: n/a
A50: 144 | B50: Vacant | C50: 1100 | D50: Vacant | F50: n/a
A51: 145 | B51: Vacant | C51: 1100 | D51: Vacant | F51: n/a
... A54: 148 | B54: Vacant | C54: 1100 | D54: Vacant | F54: n/a
A56: Total units / suites | B56: =COUNTA(A7:A54) -> 48
A57: Occupied units | B57: =COUNTIF(D7:D54,"Occupied") -> 33
A58: Total rentable SF | B58: =SUM(C7:C54) -> 43200
A59: Occupied rentable SF | B59: =SUMIF(D7:D54,"Occupied",C7:C54) -> 26700
A60: Occupancy by count (%) | B60: =100*B57/B56 -> 68.75
A61: Occupancy by area (%) | B61: =100*B59/B58 -> 61.805556
A62: Monthly base rent as printed | B62: =SUM(E7:E54) -> 56025
A63: Effective monthly base rent after authoritative amendments | B63: =B62 -> 56025
A64: Annualized contractual base rent (point in time) | B64: =B63*12 -> 672300
A66: No signed amendment or renewal-exercise notice was delivered for any unit, so effective rent equals printed rent. Annualized rent roll is not used as underwritten revenue.

Sheet T12 Historical
A1: Historical T12: September 2025 - August 2026 actual (T12-Statement.pdf, annual column)
A3: Line | B3: Annual actual | C3: Note
A4: Gross potential base rent | B4: 1036800 | C4: p.2 Annual
A5: Vacancy loss | B5: -302400
A6: Concessions | B6: -64800
A7: Bad debt | B7: -8400
A8: Other income / recoveries | B8: 30000
A9: T12 effective gross income | B9: =SUM(B4:B8) -> 691200
A11: Real estate taxes | B11: 132000
A12: Property insurance | B12: 40800
A13: Utilities | B13: 33600
A14: Repairs and maintenance | B14: 54000 | C14: Includes 12,000 one-time casualty cleanup
A15: Payroll / contract labor | B15: 55200
A16: Administrative / legal | B16: 27600
A17: Management fee | B17: 28000
A18: T12 operating expenses (excl. reserves, capex, debt, depreciation) | B18: =SUM(B11:B17) -> 371200
A19: T12 NOI before replacement reserves | B19: =B9-B18 -> 320000
A20: T12 replacement reserves | B20: 14400
A21: T12 NCF after reserves (reported by owner as "property NOI") | B21: =B19-B20 -> 305600
A23: Below cash flow - not operating expenses
A24: Capital improvements | B24: 184000
A25: Loan principal and interest (existing debt) | B25: 294000
A26: Depreciation (noncash) | B26: 180000
A28: T12 expense ratio (opex / EGI) | B28: =B18/B9 -> 0.53703704

Sheet Underwriting
A1: Underwritten (supplied scenario, September 2026 forward) - not a lender-approved forecast
A3: Line | B3: Annual UW | C3: Basis
A4: Gross potential base rent | B4: =Inputs!B4 -> 1003200 | C4: Inputs!B4
A5: Combined revenue loss (vacancy/concessions/bad debt) | B5: =-Inputs!B4*Inputs!B5 -> -70224 | C5: 7.00% of UW GPR
A6: Net rental revenue | B6: =B4+B5 -> 932976
A7: Other income / recoveries | B7: =Inputs!B6 -> 41040 | C7: Added after loss
A8: Underwritten EGI | B8: =B6+B7 -> 974016
A10: Real estate taxes | B10: =Inputs!B25 -> 138000
A11: Property insurance | B11: =Inputs!B26 -> 45600
A12: Utilities | B12: =Inputs!B27 -> 33600
A13: Repairs and maintenance | B13: =Inputs!B28 -> 42000
A14: Payroll / contract labor | B14: =Inputs!B29 -> 55200
A15: Administrative / legal | B15: =Inputs!B30 -> 27600
A16: Management fee (lender-normalized) | B16: =MAX(Inputs!B32,Inputs!B31*B8) -> 34090.56 | C16: Greater of T12 actual and 3.50% of UW EGI
A17: Underwritten operating expenses before reserves | B17: =SUM(B10:B16) -> 376090.56
A18: Underwritten NOI before reserves | B18: =B8-B17 -> 597925.44
A19: Replacement reserves | B19: =Inputs!B21*Inputs!B22 -> 15600 | C19: $325 per unit x units
A20: Underwritten NCF after reserves | B20: =B18-B19 -> 582325.44
A22: Indicative capitalization value | B22: =B18/Inputs!B7 -> 10398703 | C22: UW NOI before reserves / cap rate
A23: UW expense ratio (opex / EGI) | B23: =B17/B8 -> 0.3861236
A24: Change vs T12 NOI before reserves | B24: =B18-'T12 Historical'!B19 -> 277925.44

Sheet Loan Sizing
A1: Loan sizing under lender constraints (Lender-Terms.pdf p.1)
A3: Item | B3: Value | C3: Definition
A4: Contract rate | B4: =Inputs!B11 -> 0.0625
A5: Sizing rate | B5: =Inputs!B14 -> 0.065 | C5: Greater of contract rate and 6.50% floor (+ adjustment)
A6: Annual debt constant per $1 principal | B6: =12*(-PMT(B5/12,Inputs!B15*12,1)) -> 0.075848163 | C6: 12 monthly payments, 30-year amortization
A8: LTV constraint | B8: =Inputs!B8*Underwriting!B22 -> 6239222 | C8: 60.00% x indicative value
A9: DSCR constraint | B9: =(Underwriting!B20/Inputs!B9)/B6 -> 5905781.1 | C9: (UW NCF / 1.30x) / debt constant
A10: Debt yield constraint | B10: =Underwriting!B20/Inputs!B10 -> 6470282.7 | C10: UW NCF after reserves / 9.00%
A11: Maximum loan | B11: =MIN(B8:B10) -> 5905781.1
A12: Binding constraint | B12: =IF(AND(B8<=B9,B8<=B10),"LTV",IF(AND(B9<=B8,B9<=B10),"DSCR","Debt yield")) -> DSCR
A14: Sizing annual debt service (amortizing, sizing rate) | B14: =B11*B6 -> 447942.65
A15: Sizing DSCR (UW NCF / sizing debt service) | B15: =Underwriting!B20/B14 -> 1.3
A16: Sizing debt yield (UW NCF / maximum loan) | B16: =Underwriting!B20/B11 -> 0.098602612
A18: First-year contractual debt service (36-month IO at 6.25%) | B18: =IF(Inputs!B16>=12,B11*Inputs!B11,12*(-PMT(Inputs!B11/12,Inputs!B15*12,B11))) -> 369111.32
A19: Monthly interest-only payment | B19: =B11*Inputs!B11/12 -> 30759.277
A20: Post-IO amortizing monthly payment at contract rate | B20: =-PMT(Inputs!B11/12,Inputs!B15*12,B11) -> 36362.91
A21: Post-IO annual amortizing debt service at contract rate | B21: =B20*12 -> 436354.92
A22: First-year DSCR on contractual (IO) debt service | B22: =Underwriting!B20/B18 -> 1.5776418
A23: Sizing debt service less first-year contractual debt service | B23: =B14-B18 -> 78831.328

Sheet Sources & Uses
A1: Sources and uses at maximum loan
A3: Sources | B3: Amount | C3: Note
A4: New first-mortgage loan | B4: ='Loan Sizing'!B11 -> 5905781.1
A5: Borrower cash contribution (if required) | B5: =MAX(0,-B12) -> 0
A6: Total sources | B6: =B4+B5 -> 5905781.1
A8: Uses
A9: Existing debt payoff | B9: =Inputs!B20 -> 4500000
A10: Origination fee (1.00% of initial principal) | B10: =B4*Inputs!B18 -> 59057.811
A11: Fixed closing costs | B11: =Inputs!B19 -> 65000
A12: Net cash to borrower (negative = cash in) | B12: =B4-B9-B10-B11 -> 1281723.3
A13: Cash distributed to borrower (if positive) | B13: =MAX(0,B12) -> 1281723.3
A14: Total uses | B14: =B9+B10+B11+B13 -> 5905781.1
A16: Check: total sources less total uses | B16: =B6-B14 -> 0
A18: No fee capitalization, interest reserve, holdback or earn-out is assumed (Lender-Terms.pdf p.1).

Sheet Sensitivity
A1: Sensitivity: EGI, sizing rate and cap rate levers
A4: EGI stress factor (0.95 = EGI -5%) | B4: 0.95
A5: Sizing rate stress (decimal) | B5: 0.01
A6: Cap rate stress (decimal) | B6: 0.005
A8: Metric | B8: Base | C8: EGI -5% | D8: Sizing rate +100 bps | E8: Combined EGI -5% & rate +100 bps | F8: Cap rate +50 bps
A9: EGI factor applied | B9: 1 | C9: =$B$4 -> 0.95 | D9: 1 | E9: =$B$4 -> 0.95 | F9: 1
A10: Sizing rate add-on | B10: 0 | C10: 0 | D10: =$B$5 -> 0.01 | E10: =$B$5 -> 0.01 | F10: 0
A11: Cap rate add-on | B11: 0 | C11: 0 | D11: 0 | E11: 0 | F11: =$B$6 -> 0.005
A12: EGI | B12: =Underwriting!$B$8*B9 -> 974016 | C12: =Underwriting!$B$8*C9 -> 925315.2 | D12: =Underwriting!$B$8*D9 -> 974016 | E12: =Underwriting!$B$8*E9 -> 925315.2 | F12: =Underwriting!$B$8*F9 -> 974016
A13: Management fee (recomputed) | B13: =MAX(Inputs!$B$32,Inputs!$B$31*B12) -> 34090.56 | C13: =MAX(Inputs!$B$32,Inputs!$B$31*C12) -> 32386.032 | D13: =MAX(Inputs!$B$32,Inputs!$B$31*D12) -> 34090.56 | E13: =MAX(Inputs!$B$32,Inputs!$B$31*E12) -> 32386.032 | F13: =MAX(Inputs!$B$32,Inputs!$B$31*F12) -> 34090.56
A14: Other operating expenses (held constant) | B14: =SUM(Inputs!$B$25:$B$30) -> 342000 | C14: =SUM(Inputs!$B$25:$B$30) -> 342000 | D14: =SUM(Inputs!$B$25:$B$30) -> 342000 | E14: =SUM(Inputs!$B$25:$B$30) -> 342000 | F14: =SUM(Inputs!$B$25:$B$30) -> 342000
A15: Total operating expenses | B15: =B13+B14 -> 376090.56 | C15: =C13+C14 -> 374386.03 | D15: =D13+D14 -> 376090.56 | E15: =E13+E14 -> 374386.03 | F15: =F13+F14 -> 376090.56
A16: NOI before reserves | B16: =B12-B15 -> 597925.44 | C16: =C12-C15 -> 550929.17 | D16: =D12-D15 -> 597925.44 | E16: =E12-E15 -> 550929.17 | F16: =F12-F15 -> 597925.44
A17: Replacement reserves | B17: =Underwriting!$B$19 -> 15600 | C17: =Underwriting!$B$19 -> 15600 | D17: =Underwriting!$B$19 -> 15600 | E17: =Underwriting!$B$19 -> 15600 | F17: =Underwriting!$B$19 -> 15600
A18: NCF after reserves | B18: =B16-B17 -> 582325.44 | C18: =C16-C17 -> 535329.17 | D18: =D16-D17 -> 582325.44 | E18: =E16-E17 -> 535329.17 | F18: =F16-F17 -> 582325.44
A19: Cap rate applied | B19: =Inputs!$B$7+B11 -> 0.0575 | C19: =Inputs!$B$7+C11 -> 0.0575 | D19: =Inputs!$B$7+D11 -> 0.0575 | E19: =Inputs!$B$7+E11 -> 0.0575 | F19: =Inputs!$B$7+F11 -> 0.0625
A20: Indicative value | B20: =B16/B19 -> 10398703 | C20: =C16/C19 -> 9581376.8 | D20: =D16/D19 -> 10398703 | E20: =E16/E19 -> 9581376.8 | F20: =F16/F19 -> 9566807
A21: Sizing rate applied | B21: =Inputs!$B$14+B10 -> 0.065 | C21: =Inputs!$B$14+C10 -> 0.065 | D21: =Inputs!$B$14+D10 -> 0.075 | E21: =Inputs!$B$14+E10 -> 0.075 | F21: =Inputs!$B$14+F10 -> 0.065
A22: Annual debt constant | B22: =12*(-PMT(B21/12,Inputs!$B$15*12,1)) -> 0.075848163 | C22: =12*(-PMT(C21/12,Inputs!$B$15*12,1)) -> 0.075848163 | D22: =12*(-PMT(D21/12,Inputs!$B$15*12,1)) -> 0.083905741 | E22: =12*(-PMT(E21/12,Inputs!$B$15*12,1)) -> 0.083905741 | F22: =12*(-PMT(F21/12,Inputs!$B$15*12,1)) -> 0.075848163
A23: LTV constraint | B23: =Inputs!$B$8*B20 -> 6239222 | C23: =Inputs!$B$8*C20 -> 5748826.1 | D23: =Inputs!$B$8*D20 -> 6239222 | E23: =Inputs!$B$8*E20 -> 5748826.1 | F23: =Inputs!$B$8*F20 -> 5740084.2
A24: DSCR constraint | B24: =(B18/Inputs!$B$9)/B22 -> 5905781.1 | C24: =(C18/Inputs!$B$9)/C22 -> 5429158.1 | D24: =(D18/Inputs!$B$9)/D22 -> 5338641.2 | E24: =(E18/Inputs!$B$9)/E22 -> 4907788.9 | F24: =(F18/Inputs!$B$9)/F22 -> 5905781.1
A25: Debt yield constraint | B25: =B18/Inputs!$B$10 -> 6470282.7 | C25: =C18/Inputs!$B$10 -> 5948101.9 | D25: =D18/Inputs!$B$10 -> 6470282.7 | E25: =E18/Inputs!$B$10 -> 5948101.9 | F25: =F18/Inputs!$B$10 -> 6470282.7
A26: Maximum loan | B26: =MIN(B23:B25) -> 5905781.1 | C26: =MIN(C23:C25) -> 5429158.1 | D26: =MIN(D23:D25) -> 5338641.2 | E26: =MIN(E23:E25) -> 4907788.9 | F26: =MIN(F23:F25) -> 5740084.2
A27: Binding constraint | B27: =IF(AND(B23<=B24,B23<=B25),"LTV",IF(AND(B24<=B23,B24<=B25),"DSCR","Debt yield")) -> DSCR | C27: =IF(AND(C23<=C24,C23<=C25),"LTV",IF(AND(C24<=C23,C24<=C25),"DSCR","Debt yield")) -> DSCR | D27: =IF(AND(D23<=D24,D23<=D25),"LTV",IF(AND(D24<=D23,D24<=D25),"DSCR","Debt yield")) -> DSCR | E27: =IF(AND(E23<=E24,E23<=E25),"LTV",IF(AND(E24<=E23,E24<=E25),"DSCR","Debt yield")) -> DSCR | F27: =IF(AND(F23<=F24,F23<=F25),"LTV",IF(AND(F24<=F23,F24<=F25),"DSCR","Debt yield")) -> LTV
A28: Change in maximum loan vs base | C28: =C26-$B$26 -> -476622.99 | D28: =D26-$B$26 -> -567139.89 | E28: =E26-$B$26 -> -997992.16 | F28: =F26-$B$26 -> -165696.87
A30: Management fee is recomputed in every case; all other operating expenses and reserves are held constant. Cap rate is unchanged in the combined downside.

Sheet Map
A1: Reviewer map: editable inputs and key outputs
A3: Item | B3: Location | C3: Comment
A4: EDITABLE INPUTS
A5: Cap rate | B5: Inputs!B7 | C5: Drives indicative value and LTV constraint
A6: Sizing rate floor | B6: Inputs!B12 | C6: Sizing rate = MAX(contract, floor) + adjustment
A7: Sizing rate adjustment / increment | B7: Inputs!B13 | C7: Enter 0.01 for +100 bps
A8: Sizing rate applied (calculated) | B8: Inputs!B14
A9: EGI driver: gross potential base rent | B9: Inputs!B4 | C9: Loss % held constant at Inputs!B5
A10: EGI driver: other income | B10: Inputs!B6
A11: Calculated underwritten EGI | B11: Underwriting!B8
A12: Contract rate | B12: Inputs!B11
A13: LTV / DSCR / debt yield tests | B13: Inputs!B8, B9, B10
A14: Reserves per unit / unit count | B14: Inputs!B21, Inputs!B22
A15: Underwritten expense lines | B15: Inputs!B25:B32
A16: Sensitivity levers (EGI, rate, cap) | B16: Sensitivity!B4, B5, B6
A18: KEY OUTPUTS
A19: UW NOI before reserves | B19: Underwriting!B18 | C19: =Underwriting!B18 -> 597925.44
A20: UW NCF after reserves | B20: Underwriting!B20 | C20: =Underwriting!B20 -> 582325.44
A21: Capitalization value | B21: Underwriting!B22 | C21: =Underwriting!B22 -> 10398703
A22: LTV constraint | B22: Loan Sizing!B8 | C22: ='Loan Sizing'!B8 -> 6239222
A23: DSCR constraint | B23: Loan Sizing!B9 | C23: ='Loan Sizing'!B9 -> 5905781.1
A24: Debt yield constraint | B24: Loan Sizing!B10 | C24: ='Loan Sizing'!B10 -> 6470282.7
A25: Maximum loan / binding constraint | B25: Loan Sizing!B11 / B12 | C25: ='Loan Sizing'!B11 -> 5905781.1
A26: Sizing annual debt service | B26: Loan Sizing!B14 | C26: ='Loan Sizing'!B14 -> 447942.65
A27: First-year contractual debt service | B27: Loan Sizing!B18 | C27: ='Loan Sizing'!B18 -> 369111.32
A28: Net cash to borrower | B28: Sources & Uses!B12 | C28: ='Sources & Uses'!B12 -> 1281723.3
A29: Stress NOI (EGI -5%) | B29: Sensitivity!C16 | C29: =Sensitivity!C16 -> 550929.17
A30: Stress maximum loan (combined) | B30: Sensitivity!E26 | C30: =Sensitivity!E26 -> 4907788.9
A31: Cap rate +50 bps maximum loan | B31: Sensitivity!F26 | C31: =Sensitivity!F26 -> 5740084.2
A33: Historical T12 (Sep-2025 to Aug-2026) is on sheet 'T12 Historical'; the underwriting scenario is on 'Underwriting'. They are never blended.
