Workbook

Sheet Inputs
A1: Maple Crossing — Underwriting Inputs (REVISED, roll as of 2026-09-01)
A2: Revision 2 per revision-notice.pdf p1. Original fictional evaluation material. No real transaction. Prior version underwriting-v1.xlsx retained in the audit archive.
A3: Item | B3: Value | C3: Source / change
A4: Gross potential rent (annual, all suites) | B4: 821400 | C4: CHANGED: rent-roll-revised.xlsx E5:E14 sum $68,450/mo x 12 (was $818,700)
A5: Economic loss (vacancy/credit) | B5: 0.05 | C5: underwriting-instructions.pdf p1 (unchanged)
A6: Other income per suite (annual) | B6: 350 | C6: underwriting-instructions.pdf p1 (unchanged)
A7: Suite count | B7: 10 | C7: rent-roll-revised.xlsx A5:A14 (unchanged)
A8: Real estate taxes | B8: 85964 | C8: underwriting-instructions.pdf p1 (unchanged)
A9: Insurance expense | B9: 28655 | C9: underwriting-instructions.pdf p1 (unchanged)
A10: Other recurring operating expenses | B10: 114618 | C10: underwriting-instructions.pdf p1 (unchanged)
A11: Management fee (% of EGI) | B11: 0.03 | C11: underwriting-instructions.pdf p1 (unchanged)
A12: Replacement reserve per suite | B12: 300 | C12: underwriting-instructions.pdf p1 (unchanged)
A13: Capitalization rate (revised) | B13: 0.075 | C13: CHANGED: 6.7500% + 25 bps = 7.0000% (revision-notice.pdf p1)
A14: Original note rate | B14: 0.065 | C14: underwriting-instructions.pdf p1 (unchanged)
A15: Underwriting rate floor | B15: 0.06 | C15: underwriting-instructions.pdf p1 (unchanged)
A16: Initial sizing rate before revision (greater of note/floor) | B16: =MAX(B14,B15) -> 0.065 | C16: 6.5000% note exceeds 6.00% floor; floor not binding
A17: Sizing rate increment (revision) | B17: 0.0075 | C17: CHANGED: +75 bps to initial sizing rate (revision-notice.pdf p1)
A18: Sizing rate (revised, used for debt sizing) | B18: =MAX(B16+B17,B15) -> 0.0725 | C18: 6.5000% + 0.7500% = 7.2500%, still above the 6.00% floor
A19: Amortization (years, monthly pay) | B19: 30 | C19: underwriting-instructions.pdf p1 (unchanged); first 24 months IO, sized amortizing
A20: Maximum LTV | B20: 0.65 | C20: underwriting-instructions.pdf p1 (unchanged)
A21: Minimum DSCR (on NCF) | B21: 1.25 | C21: underwriting-instructions.pdf p1 (unchanged)
A22: Minimum NCF debt yield | B22: 0.09 | C22: underwriting-instructions.pdf p1 (unchanged)
A23: Origination fee (% of loan) | B23: 0.01 | C23: underwriting-instructions.pdf p1 (unchanged)
A24: Closing costs | B24: 45000 | C24: underwriting-instructions.pdf p1 (unchanged)
A25: Existing loan payoff | B25: 4300000 | C25: underwriting-instructions.pdf p1 (unchanged)
A26: Suite 001 signed amendment — monthly rent increase | B26: 350 | C26: lease-correspondence.pdf p1; revision notice confirms prior executed amendments continue to apply

Sheet Rent Roll
A1: Revised Certified Rent Roll — as of 2026-09-01 (controlling)
A2: Source: rent-roll-revised.xlsx, Rent Roll A5:F14. Supersedes the 2026-08-31 certified roll and the 2026-06-30 archive roll. Only change: Suite 002 scheduled rent $6,800 -> $7,025 (+$225).
A4: Suite | B4: Unit type | C4: Group | D4: Possession | E4: Area SF | F4: Roll monthly rent | G4: In-place monthly rent | H4: Lease expiry
A5: 001 | B5: Small suite | C5: A | D5: active | E5: 3080 | F5: 6650 | G5: =F5+Inputs!$B$26 -> 7000 | H5: 2029-08-31
A6: 002 | B6: Standard suite | C6: B | D6: active | E6: 3200 | F6: 7025 | G6: =F6 -> 7025 | H6: 2029-08-31
A7: 003 | B7: Large suite | C7: C | D7: active | E7: 3410 | F7: 7075 | G7: =F7 -> 7075 | H7: 2029-08-31
A8: 004 | B8: Small suite | C8: A | D8: active | E8: 3080 | F8: 6650 | G8: =F8 -> 6650 | H8: 2029-08-31
A9: 005 | B9: Standard suite | C9: B | D9: active | E9: 3200 | F9: 6800 | G9: =F9 -> 6800 | H9: 2029-08-31
A10: 006 | B10: Large suite | C10: C | D10: active | E10: 3410 | F10: 7075 | G10: =F10 -> 7075 | H10: 2029-08-31
A11: 007 | B11: Small suite | C11: A | D11: active | E11: 3080 | F11: 6650 | G11: =F11 -> 6650 | H11: 2029-08-31
A12: 008 | B12: Standard suite | C12: B | D12: active | E12: 3200 | F12: 6800 | G12: =F12 -> 6800 | H12: 2029-08-31
A13: 009 | B13: Large suite | C13: C | D13: active | E13: 3410 | F13: 7075 | G13: =F13 -> 7075 | H13: 2029-08-31
A14: 010 | B14: Small suite | C14: A | D14: vacant | E14: 3080 | F14: 6650 | G14: 0 | H14: 2029-08-31
A16: Totals / metrics
A17: Total suites | B17: =COUNTA(A5:A14) -> 10
A18: Occupied (possession taken) suites | B18: =COUNTIF(D5:D14,"active") -> 9
A19: Pending (leased, no possession) suites | B19: =COUNTIF(D5:D14,"pending") -> 0
A20: Vacant suites | B20: =COUNTIF(D5:D14,"vacant") -> 1
A21: Total area SF | B21: =SUM(E5:E14) -> 32150
A22: Occupied area SF | B22: =SUMIF(D5:D14,"active",E5:E14) -> 29070
A23: Unit occupancy | B23: =B18/B17 -> 0.9
A24: Area occupancy | B24: =B22/B21 -> 0.90419907
A25: Annual in-place rent (occupied, post-amendment) | B25: =SUM(G5:G14)*12 -> 745800
A26: Gross potential rent check (all suites, roll rent x 12) | B26: =SUM(F5:F14)*12 -> 821400
A27: Tie to Inputs!B4 (0 = tie) | B27: =B26-Inputs!B4 -> 0
A29: Group A (Small) suites / occupied | B29: =COUNTIF(C5:C14,"A") -> 4 | C29: =COUNTIFS(C5:C14,"A",D5:D14,"active") -> 3
A30: Group B (Standard) suites / occupied | B30: =COUNTIF(C5:C14,"B") -> 3 | C30: =COUNTIFS(C5:C14,"B",D5:D14,"active") -> 3
A31: Group C (Large) suites / occupied | B31: =COUNTIF(C5:C14,"C") -> 3 | C31: =COUNTIFS(C5:C14,"C",D5:D14,"active") -> 3
A33: Suite 002 was already active on the 2026-08-31 roll and remains active; the revision notice confirms active status and raises its scheduled rent by $225. Occupancy counts, areas and expiries are unchanged. Manager headline (occupied plus pending) still overstates method but the roll shows zero pending suites.

Sheet Underwriting
A1: Underwritten Cash Flow and Capitalized Value (Revised)
A3: Line | B3: Revised (USD) | C3: Prior version (USD) | D3: Basis / change
A4: Gross potential rent | B4: =Inputs!B4 -> 821400 | C4: 818700 | D4: Revised roll; Suite 002 +$225/mo = +$2,700/yr
A5: Economic loss (5%) | B5: =-B4*Inputs!B5 -> -41070 | C5: -40935 | D5: Rate unchanged
A6: Other income ($350 per suite) | B6: =Inputs!B6*Inputs!B7 -> 3500 | C6: 3500 | D6: Unchanged; reimbursements not double counted
A7: Underwritten EGI | B7: =B4+B5+B6 -> 783830 | C7: 781265
A9: Real estate taxes | B9: =Inputs!B8 -> 85964 | C9: 85964
A10: Insurance | B10: =Inputs!B9 -> 28655 | C10: 28655
A11: Other recurring operating expenses | B11: =Inputs!B10 -> 114618 | C11: 114618
A12: Management fee (3% of EGI) | B12: =Inputs!B11*B7 -> 23514.9 | C12: 23438
A13: Total operating expenses (before reserves) | B13: =SUM(B9:B12) -> 252751.9 | C13: 252675
A14: Underwritten NOI (before reserves) | B14: =B7-B13 -> 531078.1 | C14: 528590
A15: Replacement reserves ($300 per suite) | B15: =Inputs!B12*Inputs!B7 -> 3000 | C15: 3000
A16: Underwritten NCF (after reserves) | B16: =B14-B15 -> 528078.1 | C16: 525590
A18: Capitalization value (NOI before reserves / cap rate) | B18: =B14/Inputs!B13 -> 7081041.3 | C18: 7830964 | D18: Cap rate 7.0000% vs 6.7500% prior
A20: Operating expense ratio (of EGI) | B20: =B13/B7 -> 0.32245755
A22: Historical comparison (unchanged sources)
A23: T12 rental and ancillary collections | B23: 736830 | D23: operating-statement.pdf p1
A24: Reported T12 NOI (cash, before reserves/management) | B24: 507593 | D24: operating-statement.pdf p1
A25: Roof replacement booked in repairs (capital in opex) | B25: 0 | D25: Capital item carried at $0 in the ledger
A26: Revised UW NOI less reported T12 NOI | B26: =B14-B24 -> 23485.1
A27: Reported T12 NOI is cash-basis, excludes a management fee and reserves, and is not an annualized roll; revised UW NOI applies the revised roll's scheduled gross potential, 5% loss and $350/suite other income.

Sheet Debt
A1: Debt Sizing and Sources & Uses (Revised)
A3: Line | B3: Revised | C3: Prior version | D3: Note
A4: Sizing rate used | B4: =Inputs!B18 -> 0.0725 | C4: 0.065 | D4: Initial 6.5000% + 75 bps; floor 6.00% not binding
A5: Monthly payment factor per $1 of loan | B5: =-PMT(B4/12,Inputs!B19*12,1) -> 0.0068217628 | C5: 0.00632068 | D5: 30-yr monthly amortization; 24-month IO ignored for sizing
A6: LTV limit (65% of capitalized value) | B6: =Inputs!B20*Underwriting!B18 -> 4602676.9 | C6: 5090126
A7: Maximum annual debt service at 1.25x NCF | B7: =Underwriting!B16/Inputs!B21 -> 422462.48 | C7: 420472
A8: DSCR limit loan | B8: =B7/12/B5 -> 5160719.8 | C8: 5543602
A9: Debt yield limit loan (NCF / 9%) | B9: =Underwriting!B16/Inputs!B22 -> 5867534.4 | C9: 5839889
A10: Maximum loan (lesser of tests) | B10: =MIN(B6,B8,B9) -> 4602676.9 | C10: 5090126
A11: Binding constraint | B11: =IF(B10=B6,"LTV",IF(B10=B8,"DSCR","Debt yield")) -> LTV | C11: LTV
A13: Metrics at maximum loan
A14: Annual debt service | B14: =B10*B5*12 -> 376780.44 | C14: 386077
A15: NCF DSCR | B15: =Underwriting!B16/B14 -> 1.4015539 | C15: 1.3613
A16: NCF debt yield | B16: =Underwriting!B16/B10 -> 0.11473282 | C16: 0.1033
A17: LTV on capitalized value | B17: =B10/Underwriting!B18 -> 0.65 | C17: 0.65
A19: Sources
A20: Loan proceeds | B20: =B10 -> 4602676.9
A21: Total sources | B21: =B20 -> 4602676.9
A23: Uses
A24: Existing loan payoff | B24: =Inputs!B25 -> 4300000 | C24: 4300000
A25: Origination fee (1%) | B25: =Inputs!B23*B10 -> 46026.769 | C25: 50901
A26: Closing costs | B26: =Inputs!B24 -> 45000 | C26: 45000
A27: Subtotal uses | B27: =SUM(B24:B26) -> 4391026.8
A28: Net cash-out to sponsor (negative = equity required) | B28: =B21-B27 -> 211650.1 | C28: 694225
A29: Total uses including net cash-out | B29: =B27+B28 -> 4602676.9
A31: Proceeds still exceed the $4,300,000 payoff plus costs, so no refinance shortfall; the higher cap rate and sizing rate reduce cash-out.

Sheet Sensitivity
A1: Maximum Loan Sensitivity (Revised) — cap rate (rows) vs sizing rate (columns)
A2: Each cell = MIN(LTV limit, DSCR limit, debt yield limit) with revised UW NOI and NCF held constant. Bold-total cell is the adopted case (7.0000% cap / 7.2500% sizing).
A3: Cap rate \ Sizing rate | B3: 0.065 | C3: 0.0725 | D3: 0.0775 | E3: 0.0825
A4: 0.065 | B4: =MIN(Inputs!$B$20*Underwriting!$B$14/$A4,Underwriting!$B$16/Inputs!$B$21/12/(-PMT(B$3/12,Inputs!$B$19*12,1)),Underwriting!$B$16/Inputs!$B$22) -> 5310781 | C4: =MIN(Inputs!$B$20*Underwriting!$B$14/$A4,Underwriting!$B$16/Inputs!$B$21/12/(-PMT(C$3/12,Inputs!$B$19*12,1)),Underwriting!$B$16/Inputs!$B$22) -> 5160719.8 | D4: =MIN(Inputs!$B$20*Underwriting!$B$14/$A4,Underwriting!$B$16/Inputs!$B$21/12/(-PMT(D$3/12,Inputs!$B$19*12,1)),Underwriting!$B$16/Inputs!$B$22) -> 4914099 | E4: =MIN(Inputs!$B$20*Underwriting!$B$14/$A4,Underwriting!$B$16/Inputs!$B$21/12/(-PMT(E$3/12,Inputs!$B$19*12,1)),Underwriting!$B$16/Inputs!$B$22) -> 4686113.6
A5: 0.0675 | B5: =MIN(Inputs!$B$20*Underwriting!$B$14/$A5,Underwriting!$B$16/Inputs!$B$21/12/(-PMT(B$3/12,Inputs!$B$19*12,1)),Underwriting!$B$16/Inputs!$B$22) -> 5114085.4 | C5: =MIN(Inputs!$B$20*Underwriting!$B$14/$A5,Underwriting!$B$16/Inputs!$B$21/12/(-PMT(C$3/12,Inputs!$B$19*12,1)),Underwriting!$B$16/Inputs!$B$22) -> 5114085.4 | D5: =MIN(Inputs!$B$20*Underwriting!$B$14/$A5,Underwriting!$B$16/Inputs!$B$21/12/(-PMT(D$3/12,Inputs!$B$19*12,1)),Underwriting!$B$16/Inputs!$B$22) -> 4914099 | E5: =MIN(Inputs!$B$20*Underwriting!$B$14/$A5,Underwriting!$B$16/Inputs!$B$21/12/(-PMT(E$3/12,Inputs!$B$19*12,1)),Underwriting!$B$16/Inputs!$B$22) -> 4686113.6
A6: 0.07 | B6: =MIN(Inputs!$B$20*Underwriting!$B$14/$A6,Underwriting!$B$16/Inputs!$B$21/12/(-PMT(B$3/12,Inputs!$B$19*12,1)),Underwriting!$B$16/Inputs!$B$22) -> 4931439.5 | C6: =MIN(Inputs!$B$20*Underwriting!$B$14/$A6,Underwriting!$B$16/Inputs!$B$21/12/(-PMT(C$3/12,Inputs!$B$19*12,1)),Underwriting!$B$16/Inputs!$B$22) -> 4931439.5 | D6: =MIN(Inputs!$B$20*Underwriting!$B$14/$A6,Underwriting!$B$16/Inputs!$B$21/12/(-PMT(D$3/12,Inputs!$B$19*12,1)),Underwriting!$B$16/Inputs!$B$22) -> 4914099 | E6: =MIN(Inputs!$B$20*Underwriting!$B$14/$A6,Underwriting!$B$16/Inputs!$B$21/12/(-PMT(E$3/12,Inputs!$B$19*12,1)),Underwriting!$B$16/Inputs!$B$22) -> 4686113.6
A7: 0.0725 | B7: =MIN(Inputs!$B$20*Underwriting!$B$14/$A7,Underwriting!$B$16/Inputs!$B$21/12/(-PMT(B$3/12,Inputs!$B$19*12,1)),Underwriting!$B$16/Inputs!$B$22) -> 4761389.9 | C7: =MIN(Inputs!$B$20*Underwriting!$B$14/$A7,Underwriting!$B$16/Inputs!$B$21/12/(-PMT(C$3/12,Inputs!$B$19*12,1)),Underwriting!$B$16/Inputs!$B$22) -> 4761389.9 | D7: =MIN(Inputs!$B$20*Underwriting!$B$14/$A7,Underwriting!$B$16/Inputs!$B$21/12/(-PMT(D$3/12,Inputs!$B$19*12,1)),Underwriting!$B$16/Inputs!$B$22) -> 4761389.9 | E7: =MIN(Inputs!$B$20*Underwriting!$B$14/$A7,Underwriting!$B$16/Inputs!$B$21/12/(-PMT(E$3/12,Inputs!$B$19*12,1)),Underwriting!$B$16/Inputs!$B$22) -> 4686113.6
A8: 0.075 | B8: =MIN(Inputs!$B$20*Underwriting!$B$14/$A8,Underwriting!$B$16/Inputs!$B$21/12/(-PMT(B$3/12,Inputs!$B$19*12,1)),Underwriting!$B$16/Inputs!$B$22) -> 4602676.9 | C8: =MIN(Inputs!$B$20*Underwriting!$B$14/$A8,Underwriting!$B$16/Inputs!$B$21/12/(-PMT(C$3/12,Inputs!$B$19*12,1)),Underwriting!$B$16/Inputs!$B$22) -> 4602676.9 | D8: =MIN(Inputs!$B$20*Underwriting!$B$14/$A8,Underwriting!$B$16/Inputs!$B$21/12/(-PMT(D$3/12,Inputs!$B$19*12,1)),Underwriting!$B$16/Inputs!$B$22) -> 4602676.9 | E8: =MIN(Inputs!$B$20*Underwriting!$B$14/$A8,Underwriting!$B$16/Inputs!$B$21/12/(-PMT(E$3/12,Inputs!$B$19*12,1)),Underwriting!$B$16/Inputs!$B$22) -> 4602676.9
A10: GPR sensitivity (cap 7.0000%, sizing 7.2500%)
A11: GPR change | B11: UW NOI | C11: UW NCF | D11: Max loan | E11: Net cash-out
A12: -0.05 | B12: =(Inputs!$B$4*(1+$A12)*(1-Inputs!$B$5)+Inputs!$B$6*Inputs!$B$7)*(1-Inputs!$B$11)-Inputs!$B$8-Inputs!$B$9-Inputs!$B$10 -> 493232.09 | C12: =B12-Inputs!$B$12*Inputs!$B$7 -> 490232.09 | D12: =MIN(Inputs!$B$20*B12/Inputs!$B$13,C12/Inputs!$B$21/12/(-PMT(Inputs!$B$18/12,Inputs!$B$19*12,1)),C12/Inputs!$B$22) -> 4274678.2 | E12: =D12*(1-Inputs!$B$23)-Inputs!$B$24-Inputs!$B$25 -> -113068.62
A13: 0 | B13: =(Inputs!$B$4*(1+$A13)*(1-Inputs!$B$5)+Inputs!$B$6*Inputs!$B$7)*(1-Inputs!$B$11)-Inputs!$B$8-Inputs!$B$9-Inputs!$B$10 -> 531078.1 | C13: =B13-Inputs!$B$12*Inputs!$B$7 -> 528078.1 | D13: =MIN(Inputs!$B$20*B13/Inputs!$B$13,C13/Inputs!$B$21/12/(-PMT(Inputs!$B$18/12,Inputs!$B$19*12,1)),C13/Inputs!$B$22) -> 4602676.9 | E13: =D13*(1-Inputs!$B$23)-Inputs!$B$24-Inputs!$B$25 -> 211650.1
A14: 0.05 | B14: =(Inputs!$B$4*(1+$A14)*(1-Inputs!$B$5)+Inputs!$B$6*Inputs!$B$7)*(1-Inputs!$B$11)-Inputs!$B$8-Inputs!$B$9-Inputs!$B$10 -> 568924.1 | C14: =B14-Inputs!$B$12*Inputs!$B$7 -> 565924.1 | D14: =MIN(Inputs!$B$20*B14/Inputs!$B$13,C14/Inputs!$B$21/12/(-PMT(Inputs!$B$18/12,Inputs!$B$19*12,1)),C14/Inputs!$B$22) -> 4930675.6 | E14: =D14*(1-Inputs!$B$23)-Inputs!$B$24-Inputs!$B$25 -> 536368.82

Sheet Changes
A1: Revision Change Log (v1 -> v2)
A2: Driver: revision-notice.pdf p1 and rent-roll-revised.xlsx (roll as of 2026-09-01). Prior deliverables underwriting-v1.xlsx and memorandum-v1.pdf remain in the audit archive and are not replaced.
A3: Item | B3: Prior (v1) | C3: Revised (v2) | D3: Reason
A4: Controlling roll date | B4: 2026-08-31 | C4: 2026-09-01 | D4: Revised certified roll supersedes prior roll
A5: Suite 002 scheduled rent (monthly) | B5: 6800 | C5: 7025 | D5: +$225 per revision notice; suite confirmed active
A6: Gross potential rent | B6: 818700 | C6: =Inputs!B4 -> 821400 | D6: +$2,700 annually
A7: Cap rate | B7: 0.0675 | C7: =Inputs!B13 -> 0.075 | D7: +25 bps per revision notice
A8: Sizing rate | B8: 0.065 | C8: =Inputs!B18 -> 0.0725 | D8: +75 bps applied to the initial sizing rate
A9: UW EGI | B9: 781265 | C9: =Underwriting!B7 -> 783830 | D9: Higher GPR at unchanged 5% loss
A10: UW NOI before reserves | B10: 528590 | C10: =Underwriting!B14 -> 531078.1 | D10: +$2,488
A11: UW NCF | B11: 525590 | C11: =Underwriting!B16 -> 528078.1 | D11: +$2,488; reserves unchanged
A12: Capitalization value | B12: 7830964 | C12: =Underwriting!B18 -> 7081041.3 | D12: Higher cap rate outweighs higher NOI
A13: Maximum loan | B13: 5090126 | C13: =Debt!B10 -> 4602676.9 | D13: LTV still binds on a lower value
A14: Net cash-out | B14: 694225 | C14: =Debt!B28 -> 211650.1 | D14: Still positive; no shortfall
A15: Occupancy, areas, expiries, expenses, LTV/DSCR/DY tests, fees, payoff | B15: unchanged | C15: unchanged | D15: Revision notice states all other lease details and underwriting rules remain unchanged
A17: Approved copy preserved exactly: "Source-backed analysis. Assumptions remain subject to diligence."

Sheet Sources
A1: Source Register (Revised)
A3: Document | B3: Location | C3: Fact used / treatment
A4: rent-roll-revised.xlsx | B4: Rent Roll A2, A5:F14 | C4: CONTROLLING roll as of 2026-09-01: 10 suites, 9 active, 1 vacant, 32,150 SF, scheduled rent $68,450/mo (Suite 002 $7,025)
A5: revision-notice.pdf | B5: p1 | C5: Revised roll supersedes prior; Suite 002 active with +$225 rent; sizing rate +75 bps; cap rate +25 bps; all other rules and payoff unchanged; preserve approved copy
A6: rent-roll-certified.xlsx | B6: Rent Roll A2, E5:E14 | C6: Prior controlling roll dated 2026-08-31; now superseded, retained for the v1 to v2 comparison
A7: rent-roll-archive.xlsx | B7: Rent Roll A2, E5:E14 | C7: Stale roll dated 2026-06-30; excluded (conflict resolved by date)
A8: manager-cover.pdf | B8: p1 | C8: Headline 9 of 10 leased counts occupied plus pending; certified detail controls occupancy; A/B/C = Small/Standard/Large; approved copy
A9: underwriting-instructions.pdf | B9: p1 | C9: 5% loss, $350/suite other income, tax/insurance/other expenses, 3% management, $300/suite reserves, 65% LTV, 1.25x DSCR, 9% DY, 30-yr monthly amortization, 6.5000% note vs 6.00% floor, 1% fee, $45,000 costs, $4,300,000 payoff
A10: operating-statement.pdf | B10: p1 | C10: T12 9/1/2025-8/31/2026: collections $736,830; tax $85,964; insurance $28,655; other $114,618; roof in repairs $0; reported NOI $507,593
A11: lease-001.pdf | B11: p1 | C11: Suite 001 executed lease $6,650/mo, 3,080 SF, expiry 2029-08-31, deposit $13,300, no free rent
A12: lease-correspondence.pdf | B12: p1 | C12: Signed amendment executed 2026-07-20, effective 2026-08-01: +$350/mo -> Suite 001 in-place $7,000; continues to apply
A13: insurance.pdf | B13: p1 | C13: GL aggregate limit $2,000,000; term 7/1/2026-6/30/2027; distinct from insurance expense
A14: diligence-status.pdf | B14: p1 | C14: Legal, environmental, PCA and title reviews outstanding; no defect findings asserted
A16: Not supplied (explicitly unknown, not zero): photographs, asking price, market sales/rent comps, appraisal, sponsor history, tenant credit, monthly T12 detail, TI/LC and capital budgets.
