Workbook

Sheet Inputs
A1: Maple Crossing — Underwriting Inputs (as of 2026-08-31)
A2: Original fictional evaluation material. No real transaction.
A3: Item | B3: Value | C3: Source
A4: Gross potential rent (annual, all suites) | B4: 818700 | C4: rent-roll-certified.xlsx E5:E14 x 12 (pre-amendment); underwriting-instructions.pdf p1
A5: Economic loss (vacancy/credit) | B5: 0.05 | C5: underwriting-instructions.pdf p1
A6: Other income per suite (annual) | B6: 350 | C6: underwriting-instructions.pdf p1
A7: Suite count | B7: 10 | C7: rent-roll-certified.xlsx A5:A14
A8: Real estate taxes | B8: 85964 | C8: underwriting-instructions.pdf p1; operating-statement.pdf p1
A9: Insurance expense | B9: 28655 | C9: underwriting-instructions.pdf p1; operating-statement.pdf p1
A10: Other recurring operating expenses | B10: 114618 | C10: underwriting-instructions.pdf p1; operating-statement.pdf p1
A11: Management fee (% of EGI) | B11: 0.03 | C11: underwriting-instructions.pdf p1
A12: Replacement reserve per suite | B12: 300 | C12: underwriting-instructions.pdf p1
A13: Capitalization rate | B13: 0.0725 | C13: underwriting-instructions.pdf p1
A14: Note rate | B14: 0.065 | C14: underwriting-instructions.pdf p1
A15: Underwriting rate floor | B15: 0.06 | C15: underwriting-instructions.pdf p1
A16: Sizing rate (greater of note / floor) | B16: =MAX(B14,B15) | C16: Size on greater rate even though 24 months IO
A17: Amortization (years, monthly pay) | B17: 30 | C17: underwriting-instructions.pdf p1
A18: Maximum LTV | B18: 0.65 | C18: underwriting-instructions.pdf p1
A19: Minimum DSCR (on NCF) | B19: 1.25 | C19: underwriting-instructions.pdf p1
A20: Minimum NCF debt yield | B20: 0.09 | C20: underwriting-instructions.pdf p1
A21: Origination fee (% of loan) | B21: 0.01 | C21: underwriting-instructions.pdf p1
A22: Closing costs | B22: 45000 | C22: underwriting-instructions.pdf p1
A23: Existing loan payoff | B23: 4300000 | C23: underwriting-instructions.pdf p1
A24: Suite 001 signed amendment — monthly rent increase | B24: 350 | C24: lease-correspondence.pdf p1 (executed 2026-07-20, effective 2026-08-01)

Sheet Rent Roll
A1: Certified Rent Roll — as of 2026-08-31 (controlling)
A2: Source: rent-roll-certified.xlsx, Rent Roll A5:F14. Archive roll dated 2026-06-30 is stale and superseded.
A4: Suite | B4: Unit type | C4: Group | D4: Possession | E4: Area SF | F4: Roll monthly rent | G4: In-place monthly rent | H4: Lease expiry
A5: 001 | B5: Small suite | C5: A | D5: active | E5: 3080 | F5: 6650 | G5: =F5+Inputs!$B$24 | H5: 2029-08-31
A6: 002 | B6: Standard suite | C6: B | D6: active | E6: 3200 | F6: 6800 | G6: =F6 | H6: 2029-08-31
A7: 003 | B7: Large suite | C7: C | D7: active | E7: 3410 | F7: 7075 | G7: =F7 | H7: 2029-08-31
A8: 004 | B8: Small suite | C8: A | D8: active | E8: 3080 | F8: 6650 | G8: =F8 | H8: 2029-08-31
A9: 005 | B9: Standard suite | C9: B | D9: active | E9: 3200 | F9: 6800 | G9: =F9 | H9: 2029-08-31
A10: 006 | B10: Large suite | C10: C | D10: active | E10: 3410 | F10: 7075 | G10: =F10 | H10: 2029-08-31
A11: 007 | B11: Small suite | C11: A | D11: active | E11: 3080 | F11: 6650 | G11: =F11 | H11: 2029-08-31
A12: 008 | B12: Standard suite | C12: B | D12: active | E12: 3200 | F12: 6800 | G12: =F12 | H12: 2029-08-31
A13: 009 | B13: Large suite | C13: C | D13: active | E13: 3410 | F13: 7075 | G13: =F13 | H13: 2029-08-31
A14: 010 | B14: Small suite | C14: A | D14: vacant | E14: 3080 | F14: 6650 | G14: 0 | H14: 2029-08-31
A16: Totals / metrics
A17: Total suites | B17: =COUNTA(A5:A14)
A18: Occupied (possession taken) suites | B18: =COUNTIF(D5:D14,"active")
A19: Pending (leased, no possession) suites | B19: =COUNTIF(D5:D14,"pending")
A20: Vacant suites | B20: =COUNTIF(D5:D14,"vacant")
A21: Total area SF | B21: =SUM(E5:E14)
A22: Occupied area SF | B22: =SUMIF(D5:D14,"active",E5:E14)
A23: Unit occupancy | B23: =B18/B17
A24: Area occupancy | B24: =B22/B21
A25: Annual in-place rent (occupied, post-amendment) | B25: =SUM(G5:G14)*12
A26: Gross potential rent check (all suites, roll rent x 12) | B26: =SUM(F5:F14)*12
A27: Tie to Inputs!B4 (0 = tie) | B27: =B26-Inputs!B4
A29: Group A (Small) suites / occupied | B29: =COUNTIF(C5:C14,"A") | C29: =COUNTIFS(C5:C14,"A",D5:D14,"active")
A30: Group B (Standard) suites / occupied | B30: =COUNTIF(C5:C14,"B") | C30: =COUNTIFS(C5:C14,"B",D5:D14,"active")
A31: Group C (Large) suites / occupied | B31: =COUNTIF(C5:C14,"C") | C31: =COUNTIFS(C5:C14,"C",D5:D14,"active")
A33: Manager headline: 9 of 10 leased (occupied plus pending). Certified roll shows 9 active and 1 vacant; no pending-possession suite is present, so the headline equals physical occupancy.

Sheet Underwriting
A1: Underwritten Cash Flow and Capitalized Value
A3: Line | B3: Amount (USD) | C3: Basis
A4: Gross potential rent | B4: =Inputs!B4 | C4: Certified roll scheduled rent x 12, pre-amendment
A5: Economic loss (5%) | B5: =-B4*Inputs!B5 | C5: Prescribed stabilized assumption
A6: Other income ($350 per suite) | B6: =Inputs!B6*Inputs!B7 | C6: Reimbursements already included; not double counted
A7: Underwritten EGI | B7: =B4+B5+B6
A9: Real estate taxes | B9: =Inputs!B8
A10: Insurance | B10: =Inputs!B9
A11: Other recurring operating expenses | B11: =Inputs!B10
A12: Management fee (3% of EGI) | B12: =Inputs!B11*B7
A13: Total operating expenses (before reserves) | B13: =SUM(B9:B12)
A14: Underwritten NOI (before reserves) | B14: =B7-B13
A15: Replacement reserves ($300 per suite) | B15: =Inputs!B12*Inputs!B7
A16: Underwritten NCF (after reserves) | B16: =B14-B15
A18: Capitalization value (NOI before reserves / cap rate) | B18: =B14/Inputs!B13
A20: Operating expense ratio (of EGI) | B20: =B13/B7
A22: Historical comparison
A23: T12 rental and ancillary collections | B23: 736830 | C23: operating-statement.pdf p1
A24: Reported T12 NOI (cash, before reserves/management) | B24: 507593 | C24: operating-statement.pdf p1
A25: Roof replacement booked in repairs (capital in opex) | B25: 0 | C25: operating-statement.pdf p1: capital item, $0 in ledger
A26: UW NOI less reported T12 NOI | B26: =B14-B24
A27: Reported T12 NOI excludes a management fee and reserves and reflects actual collections; UW NOI applies the prescribed stabilized gross potential, 5% loss and $350/suite other income.

Sheet Debt
A1: Debt Sizing and Sources & Uses
A3: Line | B3: Value | C3: Note
A4: Sizing rate (greater of note 6.50% / floor 6.00%) | B4: =Inputs!B16
A5: Monthly payment factor per $1 of loan | B5: =-PMT(B4/12,Inputs!B17*12,1) | C5: 30-yr amortization, monthly; sized on amortizing payment despite 24-month IO
A6: LTV limit (65% of capitalized value) | B6: =Inputs!B18*Underwriting!B18
A7: Maximum annual debt service at 1.25x NCF | B7: =Underwriting!B16/Inputs!B19
A8: DSCR limit loan | B8: =B7/12/B5
A9: Debt yield limit loan (NCF / 9%) | B9: =Underwriting!B16/Inputs!B20
A10: Maximum loan (lesser of tests) | B10: =MIN(B6,B8,B9)
A11: Binding constraint | B11: =IF(B10=B6,"LTV",IF(B10=B8,"DSCR","Debt yield"))
A13: Metrics at maximum loan
A14: Annual debt service | B14: =B10*B5*12
A15: NCF DSCR | B15: =Underwriting!B16/B14
A16: NCF debt yield | B16: =Underwriting!B16/B10
A17: LTV on capitalized value | B17: =B10/Underwriting!B18
A19: Sources
A20: Loan proceeds | B20: =B10
A21: Total sources | B21: =B20
A23: Uses
A24: Existing loan payoff | B24: =Inputs!B23
A25: Origination fee (1%) | B25: =Inputs!B21*B10
A26: Closing costs | B26: =Inputs!B22
A27: Subtotal uses | B27: =SUM(B24:B26)
A28: Net cash-out to sponsor (negative = equity required) | B28: =B21-B27
A29: Total uses including net cash-out | B29: =B27+B28
A31: Refinance test: proceeds cover payoff and costs when net cash-out is positive.

Sheet Sensitivity
A1: Maximum Loan Sensitivity — cap rate (rows) vs sizing rate (columns)
A2: Each cell = MIN(LTV limit, DSCR limit, debt yield limit) using UW NOI and NCF held constant.
A3: Cap rate \ Sizing rate | B3: 0.06 | C3: 0.065 | D3: 0.07 | E3: 0.075
A4: 0.0625 | B4: =MIN(Inputs!$B$18*Underwriting!$B$14/$A4,Underwriting!$B$16/Inputs!$B$19/12/(-PMT(B$3/12,Inputs!$B$17*12,1)),Underwriting!$B$16/Inputs!$B$20) | C4: =MIN(Inputs!$B$18*Underwriting!$B$14/$A4,Underwriting!$B$16/Inputs!$B$19/12/(-PMT(C$3/12,Inputs!$B$17*12,1)),Underwriting!$B$16/Inputs!$B$20) | D4: =MIN(Inputs!$B$18*Underwriting!$B$14/$A4,Underwriting!$B$16/Inputs!$B$19/12/(-PMT(D$3/12,Inputs!$B$17*12,1)),Underwriting!$B$16/Inputs!$B$20) | E4: =MIN(Inputs!$B$18*Underwriting!$B$14/$A4,Underwriting!$B$16/Inputs!$B$19/12/(-PMT(E$3/12,Inputs!$B$17*12,1)),Underwriting!$B$16/Inputs!$B$20)
A5: 0.065 | B5: =MIN(Inputs!$B$18*Underwriting!$B$14/$A5,Underwriting!$B$16/Inputs!$B$19/12/(-PMT(B$3/12,Inputs!$B$17*12,1)),Underwriting!$B$16/Inputs!$B$20) | C5: =MIN(Inputs!$B$18*Underwriting!$B$14/$A5,Underwriting!$B$16/Inputs!$B$19/12/(-PMT(C$3/12,Inputs!$B$17*12,1)),Underwriting!$B$16/Inputs!$B$20) | D5: =MIN(Inputs!$B$18*Underwriting!$B$14/$A5,Underwriting!$B$16/Inputs!$B$19/12/(-PMT(D$3/12,Inputs!$B$17*12,1)),Underwriting!$B$16/Inputs!$B$20) | E5: =MIN(Inputs!$B$18*Underwriting!$B$14/$A5,Underwriting!$B$16/Inputs!$B$19/12/(-PMT(E$3/12,Inputs!$B$17*12,1)),Underwriting!$B$16/Inputs!$B$20)
A6: 0.0675 | B6: =MIN(Inputs!$B$18*Underwriting!$B$14/$A6,Underwriting!$B$16/Inputs!$B$19/12/(-PMT(B$3/12,Inputs!$B$17*12,1)),Underwriting!$B$16/Inputs!$B$20) | C6: =MIN(Inputs!$B$18*Underwriting!$B$14/$A6,Underwriting!$B$16/Inputs!$B$19/12/(-PMT(C$3/12,Inputs!$B$17*12,1)),Underwriting!$B$16/Inputs!$B$20) | D6: =MIN(Inputs!$B$18*Underwriting!$B$14/$A6,Underwriting!$B$16/Inputs!$B$19/12/(-PMT(D$3/12,Inputs!$B$17*12,1)),Underwriting!$B$16/Inputs!$B$20) | E6: =MIN(Inputs!$B$18*Underwriting!$B$14/$A6,Underwriting!$B$16/Inputs!$B$19/12/(-PMT(E$3/12,Inputs!$B$17*12,1)),Underwriting!$B$16/Inputs!$B$20)
A7: 0.07 | B7: =MIN(Inputs!$B$18*Underwriting!$B$14/$A7,Underwriting!$B$16/Inputs!$B$19/12/(-PMT(B$3/12,Inputs!$B$17*12,1)),Underwriting!$B$16/Inputs!$B$20) | C7: =MIN(Inputs!$B$18*Underwriting!$B$14/$A7,Underwriting!$B$16/Inputs!$B$19/12/(-PMT(C$3/12,Inputs!$B$17*12,1)),Underwriting!$B$16/Inputs!$B$20) | D7: =MIN(Inputs!$B$18*Underwriting!$B$14/$A7,Underwriting!$B$16/Inputs!$B$19/12/(-PMT(D$3/12,Inputs!$B$17*12,1)),Underwriting!$B$16/Inputs!$B$20) | E7: =MIN(Inputs!$B$18*Underwriting!$B$14/$A7,Underwriting!$B$16/Inputs!$B$19/12/(-PMT(E$3/12,Inputs!$B$17*12,1)),Underwriting!$B$16/Inputs!$B$20)
A8: 0.0725 | B8: =MIN(Inputs!$B$18*Underwriting!$B$14/$A8,Underwriting!$B$16/Inputs!$B$19/12/(-PMT(B$3/12,Inputs!$B$17*12,1)),Underwriting!$B$16/Inputs!$B$20) | C8: =MIN(Inputs!$B$18*Underwriting!$B$14/$A8,Underwriting!$B$16/Inputs!$B$19/12/(-PMT(C$3/12,Inputs!$B$17*12,1)),Underwriting!$B$16/Inputs!$B$20) | D8: =MIN(Inputs!$B$18*Underwriting!$B$14/$A8,Underwriting!$B$16/Inputs!$B$19/12/(-PMT(D$3/12,Inputs!$B$17*12,1)),Underwriting!$B$16/Inputs!$B$20) | E8: =MIN(Inputs!$B$18*Underwriting!$B$14/$A8,Underwriting!$B$16/Inputs!$B$19/12/(-PMT(E$3/12,Inputs!$B$17*12,1)),Underwriting!$B$16/Inputs!$B$20)
A10: GPR sensitivity (cap rate 6.7500%, sizing rate 6.5000%)
A11: GPR change | B11: UW NOI | C11: UW NCF | D11: Max loan
A12: -0.05 | B12: =(Inputs!$B$4*(1+$A12)*(1-Inputs!$B$5)+Inputs!$B$6*Inputs!$B$7)*(1-Inputs!$B$11)-Inputs!$B$8-Inputs!$B$9-Inputs!$B$10 | C12: =B12-Inputs!$B$12*Inputs!$B$7 | D12: =MIN(Inputs!$B$18*B12/Inputs!$B$13,C12/Inputs!$B$19/12/(-PMT(Inputs!$B$16/12,Inputs!$B$17*12,1)),C12/Inputs!$B$20)
A13: 0 | B13: =(Inputs!$B$4*(1+$A13)*(1-Inputs!$B$5)+Inputs!$B$6*Inputs!$B$7)*(1-Inputs!$B$11)-Inputs!$B$8-Inputs!$B$9-Inputs!$B$10 | C13: =B13-Inputs!$B$12*Inputs!$B$7 | D13: =MIN(Inputs!$B$18*B13/Inputs!$B$13,C13/Inputs!$B$19/12/(-PMT(Inputs!$B$16/12,Inputs!$B$17*12,1)),C13/Inputs!$B$20)
A14: 0.05 | B14: =(Inputs!$B$4*(1+$A14)*(1-Inputs!$B$5)+Inputs!$B$6*Inputs!$B$7)*(1-Inputs!$B$11)-Inputs!$B$8-Inputs!$B$9-Inputs!$B$10 | C14: =B14-Inputs!$B$12*Inputs!$B$7 | D14: =MIN(Inputs!$B$18*B14/Inputs!$B$13,C14/Inputs!$B$19/12/(-PMT(Inputs!$B$16/12,Inputs!$B$17*12,1)),C14/Inputs!$B$20)

Sheet Sources
A1: Source Register
A3: Document | B3: Location | C3: Fact used / treatment
A4: rent-roll-certified.xlsx | B4: Rent Roll A2, A5:F14 | C4: Controlling roll as of 2026-08-31: 10 suites, 9 active, 1 vacant, 32,150 SF, scheduled rent $68,225/mo
A5: rent-roll-archive.xlsx | B5: Rent Roll A2, E5:E14 | C5: Stale roll dated 2026-06-30 with lower rents; excluded from underwriting (conflict resolved by date)
A6: manager-cover.pdf | B6: p1 | C6: Headline 9 of 10 leased counts occupied plus pending; certified detail controls occupancy; A/B/C = Small/Standard/Large
A7: underwriting-instructions.pdf | B7: p1 | C7: All underwriting conventions: 5% loss, $350/suite other income, expense inputs, 6.75% cap, 65% LTV, 1.25x, 9% DY, 6.50% note vs 6.00% floor, fees, payoff
A8: operating-statement.pdf | B8: p1 | C8: T12 9/1/2025-8/31/2026: collections $736,830; tax $85,964; insurance $28,655; other $114,618; roof in repairs $0; reported NOI $507,593
A9: lease-001.pdf | B9: p1 | C9: Suite 001 executed lease $6,650/mo, 3,080 SF, expiry 2029-08-31, deposit $13,300, no free rent
A10: lease-correspondence.pdf | B10: p1 | C10: Signed amendment executed 2026-07-20, effective 2026-08-01: +$350/mo -> Suite 001 in-place $7,000
A11: insurance.pdf | B11: p1 | C11: GL aggregate limit $2,000,000; term 7/1/2026-6/30/2027; distinct from insurance expense
A12: diligence-status.pdf | B12: p1 | C12: Legal, environmental, PCA and title reviews outstanding; no defect findings asserted
A14: Not supplied (explicitly unknown): photos, asking price, market sales/rent comps, sponsor history, tenant credit, appraisal, T12 by month, capital plan.
