Workbook

Sheet Inputs & Outputs
A1: Inputs (edit yellow cells) | D1: Sensitivity inputs | G1: Cap rate +50 bps sensitivity
A3: Cap rate | B3: 0.065 | D3: EGI downside -5% (auto) | E3: =B24*0.95 -> 850554 | G3: Cap rate +50 bps | H3: =B3+0.005 -> 0.07
A4: Sizing rate (annual) | B4: 0.075 | D4: Sizing rate downside +100 bps | E4: =B4+0.01 -> 0.085 | G4: Value at cap +50 bps | H4: =B27/H3 -> 9526577.1
A5: EGI (underwritten) | B5: 895320
A6: Other income (underwritten) | B6: 162000 | D6: Mgmt fee under downside (max of T12 and 3%) | E6: =MAX(B10, 0.03*E3) -> 26400
A7: GPR (underwritten) | B7: 756000 | D7: Other opex base (excl mgmt) | E7: =B13+B14+B15+B16+B17+B18 -> 201600
A8: Revenue loss % of GPR | B8: 0.03 | D8: Total opex under downside | E8: =E7+E6 -> 228000
A9: Mgmt fee min % of EGI | B9: 0.03 | D9: NOI before reserves under downside | E9: =E3-E8 -> 622554
A10: Mgmt fee T12 actual $ | B10: 26400 | D10: NCF under downside | E10: =E9-B28 -> 608154
A11: Reserves $/SF/yr | B11: 0.2 | D11: Value under downside (cap unchanged) | E11: =E9/B3 -> 9577753.8
A12: Rentable SF | B12: 72000 | D12: LTV limit (downside) | E12: =0.6*E11 -> 5746652.3
A13: Taxes (UW) | B13: 108000 | D13: Annual constant at stressed sizing rate | E13: =ABS(12*PMT(E4/12,360,1)) -> 0.092269618
A14: Insurance (UW provisional) | B14: 36000 | D14: DSCR limit (downside) | E14: =(E10/1.3)/E13 -> 5070041.2
A15: Utilities (UW) | B15: 9600 | D15: Debt yield limit (downside) | E15: =E10/0.095 -> 6401621.1
A16: Repairs & Maint (UW) | B16: 19200 | D16: Maximum loan (downside) | E16: =MIN(E12,E14,E15) -> 5070041.2
A17: Payroll / Contract (UW) | B17: 12000
A18: Admin / Legal (UW) | B18: 16800
A19: Existing payoff | B19: 3600000
A20: Fixed closing costs | B20: 55000
A21: Contract rate (annual) | B21: 0.061
A23: Outputs
A24: UW EGI | B24: =B7 - (B7*B8) + B6 -> 895320
A25: Mgmt fee (UW) | B25: =MAX(B10, B9*B24) -> 26859.6
A26: UW Operating Expenses before reserves | B26: =B13+B14+B15+B16+B17+B18+B25 -> 228459.6
A27: UW NOI before reserves | B27: =B24-B26 -> 666860.4
A28: UW Reserves | B28: =B11*B12 -> 14400
A29: UW NCF after reserves | B29: =B27-B28 -> 652460.4
A31: Capitalization value | B31: =B27/B3 -> 10259391
A32: LTV limit (60%) | B32: =0.6*B31 -> 6155634.5
A33: Annual debt constant at sizing rate | B33: =12*PMT(B4/12,360,1) -> -0.083905741
A34: DSCR limit (1.30x) | B34: =(B29/1.3)/ABS(B33) -> 5981624.3
A35: Debt yield limit (9.50%) | B35: =B29/0.095 -> 6868004.2
A36: Maximum loan (min of 3) | B36: =MIN(B32,B34,B35) -> 5981624.3
A37: Annual amortizing debt service at sizing rate | B37: =B36*ABS(B33) -> 501892.62
A38: Sizing DSCR (UW NCF / sizing debt svc) | B38: =B29/B37 -> 1.3
A39: Sizing debt yield (UW NCF / loan) | B39: =B29/B36 -> 0.10907746
A40: First-year contractual debt service (IO year 1) | B40: =B21*B36 -> 364879.08
A41: Origination fee (1%) | B41: =0.01*B36 -> 59816.243
A42: Cash to borrower (neg = cash in) | B42: =B36-B19-B41-B20 -> 2266808

Sheet T12
A1: Trailing 12-month actuals (Sep 2025 - Aug 2026)
A3: Gross potential base rent | B3: 744000
A4: Concessions | B4: -18000
A5: Bad debt | B5: -2400
A6: Other income / recoveries | B6: 158400
A7: Effective gross income (EGI) | B7: =B3+B4+B5+B6 -> 882000
A9: Real estate taxes | B9: 102000
A10: Property insurance | B10: 26400
A11: Utilities | B11: 9600
A12: Repairs and maintenance | B12: 19200
A13: Payroll / contract labor | B13: 12000
A14: Administrative / legal | B14: 16800
A15: Management fee | B15: 26400
A16: Operating expenses before reserves | B16: =SUM(B9:B15) -> 212400
A17: NOI before reserves | B17: =B7-B16 -> 669600
A18: Replacement reserves (below NOI) | B18: 14400
A19: NCF after reserves | B19: =B17-B18 -> 655200

Sheet Rent Roll
A1: Rent roll as of 2026-08-31
A3: Unit | B3: Tenant | C3: Area SF | D3: Status | E3: Monthly base rent | F3: Market monthly rent | G3: Lease expiry
A4: 101 | B4: Tenant A LLC | C4: 16000 | D4: Occupied | E4: 12800 | F4: 12800 | G4: 2028-08-31
A5: 102 | B5: Tenant B LLC | C5: 24000 | D5: Occupied | E5: 20400 | F5: 20400 | G5: 2028-08-31
A6: 103 | B6: Tenant C LLC | C6: 32000 | D6: Occupied | E6: 28800 | F6: 28800 | G6: 2029-08-31
A8: Totals | C8: =SUM(C4:C6) -> 72000 | E8: =SUM(E4:E6) -> 62000

Sheet Sizing Sources Uses
A1: Loan sizing and sources/uses
A3: LTV limit | B3: ='Inputs & Outputs'!B32 -> 6155634.5 | D3: Downside maximum loan | E3: ='Inputs & Outputs'!E16 -> 5070041.2
A4: DSCR limit | B4: ='Inputs & Outputs'!B34 -> 5981624.3
A5: Debt yield limit | B5: ='Inputs & Outputs'!B35 -> 6868004.2
A6: Maximum loan (binding) | B6: ='Inputs & Outputs'!B36 -> 5981624.3
A8: Annual amortizing debt service | B8: ='Inputs & Outputs'!B37 -> 501892.62
A9: First-year contractual debt service (IO) | B9: ='Inputs & Outputs'!B40 -> 364879.08
A11: Origination fee (1%) | B11: ='Inputs & Outputs'!B41 -> 59816.243
A12: Existing payoff | B12: ='Inputs & Outputs'!B19 -> 3600000
A13: Fixed closing costs | B13: ='Inputs & Outputs'!B20 -> 55000
A14: Cash to borrower (neg = cash in) | B14: ='Inputs & Outputs'!B42 -> 2266808
