Workbook

Sheet README
A1: Maple Crossing — Underwriting Workbook
A3: Source packet: | B3: CRE Bench — original fictional evaluation material (9 files)
A4: Valuation date: | B4: 2026-08-31
A5: Prepared per: | B5: underwriting-instructions.pdf
A7: Input cells (user-editable)
A8: Field | B8: Location | C8: Purpose
A9: gross_potential_rent | B9: Inputs!B7 | C9: All-suite scheduled monthly rent × 12, per certified roll (Suite 001 pre-amendment)
A10: cap_rate | B10: Inputs!B22 | C10: Direct cap rate applied to NOI before reserves
A11: sizing_rate | B11: Inputs!B27 | C11: Loan sizing rate = MAX(note rate, floor)
A13: Output cells (formula-driven)
A14: Field | B14: Location | C14: Definition
A15: uw_egi | B15: UW!B10 | C15: GPR × (1 − economic loss) + other income
A16: uw_noi | B16: UW!B22 | C16: EGI − operating expenses (before replacement reserves)
A17: uw_ncf | B17: UW!B25 | C17: NOI − replacement reserves
A18: capitalization_value | B18: UW!B32 | C18: UW NOI ÷ cap rate
A19: maximum_loan | B19: Debt!B24 | C19: MIN(LTV, DSCR, Debt Yield constraints)
A20: net_cash_out | B20: Debt!B32 | C20: Maximum loan − payoff − origination fee − closing costs
A22: Sheet map
A23: Inputs | B23: All model assumptions (yellow = editable)
A24: RentRoll | B24: Certified rent roll as of 2026-08-31 with derived stats
A25: UW | B25: Underwritten income / expense / NOI / NCF
A26: Debt | B26: Debt sizing across LTV / DSCR / debt yield and sources & uses
A27: Sensitivity | B27: Cap rate × sizing rate sensitivity on value & max loan
A28: Historical | B28: T12 operating statement vs. underwriting comparison
A29: Sources | B29: Source register — every input traced to filename and location
A30: Fields | B30: Reported named fields with values, units, and evidence

Sheet Inputs
A1: Underwriting Inputs
A3: INCOME
A4: Suite count (all) | B4: 10 | C4: count | D4: RentRoll
A5: Economic loss | B5: 0.05 | C5: ratio | D5: underwriting-instructions.pdf
A6: Other income per suite (annual) | B6: 350 | C6: USD | D6: underwriting-instructions.pdf
A7: gross_potential_rent (annual) | B7: 777765 | C7: USD | D7: certified roll ×12, S001 pre-amendment
A9: EXPENSES
A10: uw_tax | B10: 85964 | C10: USD | D10: underwriting-instructions.pdf
A11: uw_insurance | B11: 28655 | C11: USD | D11: underwriting-instructions.pdf
A12: uw_other_operating_expenses | B12: 114618 | C12: USD | D12: underwriting-instructions.pdf
A13: management_fee_pct | B13: 0.03 | C13: ratio | D13: underwriting-instructions.pdf
A14: replacement_reserve_per_suite | B14: 300 | C14: USD | D14: underwriting-instructions.pdf
A17: VALUATION & DEBT
A19: note_rate | B19: 0.065 | C19: ratio | D19: underwriting-instructions.pdf
A20: floor_rate | B20: 0.06 | C20: ratio | D20: underwriting-instructions.pdf
A22: cap_rate | B22: 0.0675 | C22: ratio | D22: underwriting-instructions.pdf
A24: ltv_limit | B24: 0.65 | C24: ratio
A25: dscr_limit | B25: 1.25 | C25: ratio
A26: debt_yield_limit | B26: 0.09 | C26: ratio
A27: sizing_rate | B27: =MAX(B19,B20) | C27: ratio | D27: MAX(note_rate, floor_rate)
A28: amortization_years | B28: 30 | C28: years
A29: origination_fee_pct | B29: 0.01 | C29: ratio
A30: closing_costs | B30: 45000 | C30: USD
A31: existing_payoff | B31: 4300000 | C31: USD

Sheet RentRoll
A1: Certified Rent Roll — as of 2026-08-31
A2: Source: rent-roll-certified.xlsx (property manager certified). Suite 001 monthly rent shown at certified value $6,650 (post-amendment).
A4: Suite | B4: Unit type | C4: Type group | D4: Area SF | E4: Possession | F4: Monthly rent | G4: Lease expiry
A5: 001 | B5: Small suite | C5: A | D5: 3080 | E5: active | F5: 6650 | G5: 2029-08-31
A6: 002 | B6: Standard suite | C6: B | D6: 3200 | E6: active | F6: 6800 | G6: 2029-08-31
A7: 003 | B7: Large suite | C7: C | D7: 3410 | E7: active | F7: 7075 | G7: 2029-08-31
A8: 004 | B8: Small suite | C8: A | D8: 3080 | E8: active | F8: 6650 | G8: 2029-08-31
A9: 005 | B9: Standard suite | C9: B | D9: 3200 | E9: active | F9: 6800 | G9: 2029-08-31
A10: 006 | B10: Large suite | C10: C | D10: 3410 | E10: active | F10: 7075 | G10: 2029-08-31
A11: 007 | B11: Small suite | C11: A | D11: 3080 | E11: active | F11: 6650 | G11: 2029-08-31
A12: 008 | B12: Standard suite | C12: B | D12: 3200 | E12: active | F12: 6800 | G12: 2029-08-31
A13: 009 | B13: Large suite | C13: C | D13: 3410 | E13: active | F13: 7075 | G13: 2029-08-31
A14: 010 | B14: Small suite | C14: A | D14: 3080 | E14: vacant | F14: 6650 | G14: 2029-08-31
A16: TOTALS / DERIVED
A17: total_units | B17: =COUNTA(A5:A14)
A18: occupied_units (active) | B18: =COUNTIF(E5:E14,"active")
A19: pending_units | B19: 0
A20: total_area_sf | B20: =SUM(D5:D14)
A21: occupied_area_sf | B21: =SUMIF(E5:E14,"active",D5:D14)
A22: unit_occupancy | B22: =B18/B17
A23: area_occupancy | B23: =B21/B20
A24: annual_in_place_rent | B24: =SUMIF(E5:E14,"active",F5:F14)*12
A27: TYPE MAPPING (per manager cover)
A28: Type | B28: Units | C28: Occupied
A29: A (Small) | B29: =COUNTIF(C5:C14,"A") | C29: =COUNTIFS(C5:C14,"A",E5:E14,"active")
A30: B (Standard) | B30: =COUNTIF(C5:C14,"B") | C30: =COUNTIFS(C5:C14,"B",E5:E14,"active")
A31: C (Large) | B31: =COUNTIF(C5:C14,"C") | C31: =COUNTIFS(C5:C14,"C",E5:E14,"active")
A34: GPR RECONCILIATION
A35: All-suite monthly rent (certified) | B35: =SUM(F5:F14)
A36: Less: Suite 001 amendment ($350/mo) | B36: -350
A37: Adjusted monthly (pre-amendment S001) | B37: =B35+B36
A38: GPR annual (×12) | B38: =B37*12

Sheet UW
A1: Underwritten Cash Flow
A2: Per underwriting-instructions.pdf — Suite 001 rent pre-amendment; 5% economic loss; $350/suite other income.
A4: INCOME
A5: gross_potential_rent | B5: =Inputs!B7
A6: economic_loss (%) | B6: =Inputs!B5
A7: effective_rent | B7: =B5*(1-B6)
A8: other_income (annual, $350 × suites) | B8: =Inputs!B6*Inputs!B4
A10: uw_egi | B10: =B7+B8
A12: EXPENSES
A13: uw_tax | B13: =Inputs!B10
A14: uw_insurance | B14: =Inputs!B11
A15: uw_other_operating_expenses | B15: =Inputs!B12
A16: management_fee (3% of EGI) | B16: =Inputs!B13*B10
A17: uw_operating_expenses (total) | B17: =SUM(B13:B16)
A19: NOI & NCF
A22: uw_noi (before reserves) | B22: =B10-B17
A23: replacement_reserves ($300/suite) | B23: =Inputs!B14*Inputs!B4
A25: uw_ncf | B25: =B22-B23
A28: VALUATION
A30: cap_rate | B30: =Inputs!B22
A31: NOI (before reserves) used for cap | B31: =B22
A32: capitalization_value | B32: =B31/B30

Sheet Debt
A1: Debt Sizing & Sources / Uses
A2: Sized on greater of note rate and floor per instructions; DSCR & DY on NCF after reserves.
A4: ASSUMPTIONS
A5: sizing_rate | B5: =Inputs!B27
A6: amortization_years | B6: =Inputs!B28
A7: monthly_rate | B7: =Inputs!B27/12
A8: n_months | B8: =Inputs!B28*12
A9: PMT per $1 loan (monthly) | B9: =B7*(1+B7)^B8/((1+B7)^B8-1)
A10: Annual DS per $1 loan | B10: =B9*12
A11: ltv_limit | B11: =Inputs!B24
A12: dscr_limit | B12: =Inputs!B25
A13: debt_yield_limit | B13: =Inputs!B26
A16: CONSTRAINTS
A17: Loan by LTV = ltv × value | B17: =B11*UW!B32
A18: Loan by DSCR = (NCF / dscr) / annual DS per $ | B18: =(UW!B25/B12)/B10
A19: Loan by DY = NCF / debt yield | B19: =UW!B25/B13
A21: Binding constraint | B21: =IF(B24=B17,"LTV",IF(B24=B18,"DSCR","Debt Yield"))
A24: maximum_loan | B24: =MIN(B17,B18,B19)
A27: SOURCES & USES (net cash-out)
A28: existing_payoff | B28: =Inputs!B31
A29: origination_fee (1% of loan) | B29: =Inputs!B29*B24
A30: closing_costs | B30: =Inputs!B30
A31: Total uses | B31: =SUM(B28:B30)
A32: net_cash_out (negative = additional equity) | B32: =B24-B31
A35: IMPLIED METRICS AT MAX LOAN
A36: LTV realized | B36: =B24/UW!B32
A37: Annual DS at sizing rate | B37: =B24*B10
A38: DSCR realized (on NCF) | B38: =UW!B25/B37
A39: Debt yield realized (on NCF) | B39: =UW!B25/B24

Sheet Sensitivity
A1: Sensitivity — Cap Rate × Sizing Rate
A2: Table A: Capitalization value = UW NOI / cap_rate. Table B: Maximum loan by binding constraint at given cap and sizing rate.
A4: Table A — Capitalization value at NOI | D4: Table B — Maximum loan (LTV @ base 65%, DSCR @1.25, DY @9%)
A5: cap_rate ↓ | B5: value | D5: sizing_rate ↓ / cap_rate → | E5: 0.06 | F5: 0.0625 | G5: 0.065 | H5: 0.0675 | I5: 0.07 | J5: 0.0725 | K5: 0.075
A6: 0.06 | B6: =UW!$B$22/A6 | D6: 0.06 | E6: =MIN(Debt!$B$11*(UW!$B$22/E$5),(UW!$B$25/Debt!$B$12)/((6/6)*((0.06/12)*(1+0.06/12)^(Debt!$B$8))/((1+0.06/12)^(Debt!$B$8)-1)*12),UW!$B$25/Debt!$B$13) | F6: =MIN(Debt!$B$11*(UW!$B$22/F$5),(UW!$B$25/Debt!$B$12)/((6/6)*((0.06/12)*(1+0.06/12)^(Debt!$B$8))/((1+0.06/12)^(Debt!$B$8)-1)*12),UW!$B$25/Debt!$B$13) | G6: =MIN(Debt!$B$11*(UW!$B$22/G$5),(UW!$B$25/Debt!$B$12)/((6/6)*((0.06/12)*(1+0.06/12)^(Debt!$B$8))/((1+0.06/12)^(Debt!$B$8)-1)*12),UW!$B$25/Debt!$B$13) | H6: =MIN(Debt!$B$11*(UW!$B$22/H$5),(UW!$B$25/Debt!$B$12)/((6/6)*((0.06/12)*(1+0.06/12)^(Debt!$B$8))/((1+0.06/12)^(Debt!$B$8)-1)*12),UW!$B$25/Debt!$B$13) | I6: =MIN(Debt!$B$11*(UW!$B$22/I$5),(UW!$B$25/Debt!$B$12)/((6/6)*((0.06/12)*(1+0.06/12)^(Debt!$B$8))/((1+0.06/12)^(Debt!$B$8)-1)*12),UW!$B$25/Debt!$B$13) | J6: =MIN(Debt!$B$11*(UW!$B$22/J$5),(UW!$B$25/Debt!$B$12)/((6/6)*((0.06/12)*(1+0.06/12)^(Debt!$B$8))/((1+0.06/12)^(Debt!$B$8)-1)*12),UW!$B$25/Debt!$B$13) | K6: =MIN(Debt!$B$11*(UW!$B$22/K$5),(UW!$B$25/Debt!$B$12)/((6/6)*((0.06/12)*(1+0.06/12)^(Debt!$B$8))/((1+0.06/12)^(Debt!$B$8)-1)*12),UW!$B$25/Debt!$B$13)
A7: 0.0625 | B7: =UW!$B$22/A7 | D7: 0.0625 | E7: =MIN(Debt!$B$11*(UW!$B$22/E$5),(UW!$B$25/Debt!$B$12)/((7/7)*((0.0625/12)*(1+0.0625/12)^(Debt!$B$8))/((1+0.0625/12)^(Debt!$B$8)-1)*12),UW!$B$25/Debt!$B$13) | F7: =MIN(Debt!$B$11*(UW!$B$22/F$5),(UW!$B$25/Debt!$B$12)/((7/7)*((0.0625/12)*(1+0.0625/12)^(Debt!$B$8))/((1+0.0625/12)^(Debt!$B$8)-1)*12),UW!$B$25/Debt!$B$13) | G7: =MIN(Debt!$B$11*(UW!$B$22/G$5),(UW!$B$25/Debt!$B$12)/((7/7)*((0.0625/12)*(1+0.0625/12)^(Debt!$B$8))/((1+0.0625/12)^(Debt!$B$8)-1)*12),UW!$B$25/Debt!$B$13) | H7: =MIN(Debt!$B$11*(UW!$B$22/H$5),(UW!$B$25/Debt!$B$12)/((7/7)*((0.0625/12)*(1+0.0625/12)^(Debt!$B$8))/((1+0.0625/12)^(Debt!$B$8)-1)*12),UW!$B$25/Debt!$B$13) | I7: =MIN(Debt!$B$11*(UW!$B$22/I$5),(UW!$B$25/Debt!$B$12)/((7/7)*((0.0625/12)*(1+0.0625/12)^(Debt!$B$8))/((1+0.0625/12)^(Debt!$B$8)-1)*12),UW!$B$25/Debt!$B$13) | J7: =MIN(Debt!$B$11*(UW!$B$22/J$5),(UW!$B$25/Debt!$B$12)/((7/7)*((0.0625/12)*(1+0.0625/12)^(Debt!$B$8))/((1+0.0625/12)^(Debt!$B$8)-1)*12),UW!$B$25/Debt!$B$13) | K7: =MIN(Debt!$B$11*(UW!$B$22/K$5),(UW!$B$25/Debt!$B$12)/((7/7)*((0.0625/12)*(1+0.0625/12)^(Debt!$B$8))/((1+0.0625/12)^(Debt!$B$8)-1)*12),UW!$B$25/Debt!$B$13)
A8: 0.065 | B8: =UW!$B$22/A8 | D8: 0.065 | E8: =MIN(Debt!$B$11*(UW!$B$22/E$5),(UW!$B$25/Debt!$B$12)/((8/8)*((0.065/12)*(1+0.065/12)^(Debt!$B$8))/((1+0.065/12)^(Debt!$B$8)-1)*12),UW!$B$25/Debt!$B$13) | F8: =MIN(Debt!$B$11*(UW!$B$22/F$5),(UW!$B$25/Debt!$B$12)/((8/8)*((0.065/12)*(1+0.065/12)^(Debt!$B$8))/((1+0.065/12)^(Debt!$B$8)-1)*12),UW!$B$25/Debt!$B$13) | G8: =MIN(Debt!$B$11*(UW!$B$22/G$5),(UW!$B$25/Debt!$B$12)/((8/8)*((0.065/12)*(1+0.065/12)^(Debt!$B$8))/((1+0.065/12)^(Debt!$B$8)-1)*12),UW!$B$25/Debt!$B$13) | H8: =MIN(Debt!$B$11*(UW!$B$22/H$5),(UW!$B$25/Debt!$B$12)/((8/8)*((0.065/12)*(1+0.065/12)^(Debt!$B$8))/((1+0.065/12)^(Debt!$B$8)-1)*12),UW!$B$25/Debt!$B$13) | I8: =MIN(Debt!$B$11*(UW!$B$22/I$5),(UW!$B$25/Debt!$B$12)/((8/8)*((0.065/12)*(1+0.065/12)^(Debt!$B$8))/((1+0.065/12)^(Debt!$B$8)-1)*12),UW!$B$25/Debt!$B$13) | J8: =MIN(Debt!$B$11*(UW!$B$22/J$5),(UW!$B$25/Debt!$B$12)/((8/8)*((0.065/12)*(1+0.065/12)^(Debt!$B$8))/((1+0.065/12)^(Debt!$B$8)-1)*12),UW!$B$25/Debt!$B$13) | K8: =MIN(Debt!$B$11*(UW!$B$22/K$5),(UW!$B$25/Debt!$B$12)/((8/8)*((0.065/12)*(1+0.065/12)^(Debt!$B$8))/((1+0.065/12)^(Debt!$B$8)-1)*12),UW!$B$25/Debt!$B$13)
A9: 0.0675 | B9: =UW!$B$22/A9 | D9: 0.0675 | E9: =MIN(Debt!$B$11*(UW!$B$22/E$5),(UW!$B$25/Debt!$B$12)/((9/9)*((0.0675/12)*(1+0.0675/12)^(Debt!$B$8))/((1+0.0675/12)^(Debt!$B$8)-1)*12),UW!$B$25/Debt!$B$13) | F9: =MIN(Debt!$B$11*(UW!$B$22/F$5),(UW!$B$25/Debt!$B$12)/((9/9)*((0.0675/12)*(1+0.0675/12)^(Debt!$B$8))/((1+0.0675/12)^(Debt!$B$8)-1)*12),UW!$B$25/Debt!$B$13) | G9: =MIN(Debt!$B$11*(UW!$B$22/G$5),(UW!$B$25/Debt!$B$12)/((9/9)*((0.0675/12)*(1+0.0675/12)^(Debt!$B$8))/((1+0.0675/12)^(Debt!$B$8)-1)*12),UW!$B$25/Debt!$B$13) | H9: =MIN(Debt!$B$11*(UW!$B$22/H$5),(UW!$B$25/Debt!$B$12)/((9/9)*((0.0675/12)*(1+0.0675/12)^(Debt!$B$8))/((1+0.0675/12)^(Debt!$B$8)-1)*12),UW!$B$25/Debt!$B$13) | I9: =MIN(Debt!$B$11*(UW!$B$22/I$5),(UW!$B$25/Debt!$B$12)/((9/9)*((0.0675/12)*(1+0.0675/12)^(Debt!$B$8))/((1+0.0675/12)^(Debt!$B$8)-1)*12),UW!$B$25/Debt!$B$13) | J9: =MIN(Debt!$B$11*(UW!$B$22/J$5),(UW!$B$25/Debt!$B$12)/((9/9)*((0.0675/12)*(1+0.0675/12)^(Debt!$B$8))/((1+0.0675/12)^(Debt!$B$8)-1)*12),UW!$B$25/Debt!$B$13) | K9: =MIN(Debt!$B$11*(UW!$B$22/K$5),(UW!$B$25/Debt!$B$12)/((9/9)*((0.0675/12)*(1+0.0675/12)^(Debt!$B$8))/((1+0.0675/12)^(Debt!$B$8)-1)*12),UW!$B$25/Debt!$B$13)
A10: 0.07 | B10: =UW!$B$22/A10 | D10: 0.07 | E10: =MIN(Debt!$B$11*(UW!$B$22/E$5),(UW!$B$25/Debt!$B$12)/((10/10)*((0.07/12)*(1+0.07/12)^(Debt!$B$8))/((1+0.07/12)^(Debt!$B$8)-1)*12),UW!$B$25/Debt!$B$13) | F10: =MIN(Debt!$B$11*(UW!$B$22/F$5),(UW!$B$25/Debt!$B$12)/((10/10)*((0.07/12)*(1+0.07/12)^(Debt!$B$8))/((1+0.07/12)^(Debt!$B$8)-1)*12),UW!$B$25/Debt!$B$13) | G10: =MIN(Debt!$B$11*(UW!$B$22/G$5),(UW!$B$25/Debt!$B$12)/((10/10)*((0.07/12)*(1+0.07/12)^(Debt!$B$8))/((1+0.07/12)^(Debt!$B$8)-1)*12),UW!$B$25/Debt!$B$13) | H10: =MIN(Debt!$B$11*(UW!$B$22/H$5),(UW!$B$25/Debt!$B$12)/((10/10)*((0.07/12)*(1+0.07/12)^(Debt!$B$8))/((1+0.07/12)^(Debt!$B$8)-1)*12),UW!$B$25/Debt!$B$13) | I10: =MIN(Debt!$B$11*(UW!$B$22/I$5),(UW!$B$25/Debt!$B$12)/((10/10)*((0.07/12)*(1+0.07/12)^(Debt!$B$8))/((1+0.07/12)^(Debt!$B$8)-1)*12),UW!$B$25/Debt!$B$13) | J10: =MIN(Debt!$B$11*(UW!$B$22/J$5),(UW!$B$25/Debt!$B$12)/((10/10)*((0.07/12)*(1+0.07/12)^(Debt!$B$8))/((1+0.07/12)^(Debt!$B$8)-1)*12),UW!$B$25/Debt!$B$13) | K10: =MIN(Debt!$B$11*(UW!$B$22/K$5),(UW!$B$25/Debt!$B$12)/((10/10)*((0.07/12)*(1+0.07/12)^(Debt!$B$8))/((1+0.07/12)^(Debt!$B$8)-1)*12),UW!$B$25/Debt!$B$13)
A11: 0.0725 | B11: =UW!$B$22/A11
A12: 0.075 | B12: =UW!$B$22/A12
A15: Highlighted cells = base case (cap 6.75%, sizing rate 6.50%).

Sheet Historical
A1: Historical T12 vs Underwriting
A2: T12 period: 2025-09-01 through 2026-08-31 (source: operating-statement.pdf).
A3: Historical NOI, underwritten NOI, and NCF have different definitions and are labeled distinctly.
A5: Line item | B5: T12 Actual | C5: Underwritten | D5: Delta / Note
A6: Rental & ancillary collections | B6: 736830 | C6: =Inputs!B7 | D6: UW GPR pre-loss/other; not directly comparable
A7: Economic loss (UW only) | C7: =-UW!B5*UW!B6 | D7: Applied to UW GPR at 5%
A8: Other income (UW only, $350/suite) | C8: =UW!B8 | D8: Instructions
A9: Effective / Underwritten EGI | B9: 736830 | C9: =UW!B10 | D9: Historical shown as collections; UW = GPR×(1−loss)+OI
A10: Real estate tax | B10: -85964 | C10: =-UW!B13 | D10: Same source figure
A11: Insurance expense | B11: -28655 | C11: =-UW!B14 | D11: Same source figure
A12: Other recurring operating expenses | B12: -114618 | C12: =-UW!B15 | D12: Same source figure
A13: Management fee | B13: 0 | C13: =-UW!B16 | D13: Not in T12 ledger; underwritten at 3% of EGI
A14: Roof replacement (capex) | B14: 0 | C14: 0 | D14: Capital improvement; not in recurring OpEx per T12
A15: Reported / Underwritten NOI | B15: 507593 | C15: =UW!B22 | D15: T12 reported NOI vs UW NOI (before reserves)
A16: Replacement reserves | C16: =-UW!B23 | D16: UW only ($300/suite)
A17: Underwritten NCF | C17: =UW!B25 | D17: For DSCR & debt yield sizing

Sheet Sources
A1: Source Register
A3: # | B3: Field / Assumption | C3: Value | D3: Evidence (file — page/cell)
A4: 1 | B4: Certified rent roll (as-of date) | C4: 2026-08-31 | D4: rent-roll-certified.xlsx — Sheet Rent Roll, B2
A5: 2 | B5: Certified roll suite count / status | C5: 10 total; 9 active, 1 vacant | D5: rent-roll-certified.xlsx — Rent Roll, A5:E14
A6: 3 | B6: Suite 001 monthly rent (post-amendment) | C6: $6,650 | D6: rent-roll-certified.xlsx — E5
A7: 4 | B7: Suite 001 amendment (+$350/mo, eff. 2026-08-01) | C7: +$350 | D7: lease-correspondence.pdf — page 1
A8: 5 | B8: Suite 001 executed base rent (pre-amendment) | C8: $6,650 (per lease excerpt) | D8: lease-001.pdf — page 1
A9: 6 | B9: Archive roll (2026-06-30) Suite 001 rent | C9: $6,575 | D9: rent-roll-archive.xlsx — E5 (superseded by certified roll)
A10: 7 | B10: Type mapping (A=Small, B=Standard, C=Large) | C10: Manager methodology | D10: manager-cover.pdf — page 1
A11: 8 | B11: Manager headline occupancy claim | C11: 9 of 10 (occupied + pending as leased) | D11: manager-cover.pdf — page 1
A12: 9 | B12: T12 collections | C12: $736,830 | D12: operating-statement.pdf — page 1 (table)
A13: 10 | B13: T12 real estate tax | C13: $85,964 | D13: operating-statement.pdf — page 1
A14: 11 | B14: T12 insurance expense | C14: $28,655 | D14: operating-statement.pdf — page 1
A15: 12 | B15: T12 other recurring opex | C15: $114,618 | D15: operating-statement.pdf — page 1
... A31: 28 | B31: Diligence status — legal/env/PCA/title | C31: Pending, no findings | D31: diligence-status.pdf — page 1

Sheet Fields
A1: Reported Named Fields — Values, Units, Evidence
A3: Field | B3: Value | C3: Unit | D3: Evidence | E3: Location
A4: total_units | B4: 10 | C4: count | D4: rent-roll-certified.xlsx | E4: Rent Roll A5:A14
A5: occupied_units | B5: 9 | C5: count | D5: rent-roll-certified.xlsx | E5: Rent Roll D5:D14 (=active)
A6: pending_units | B6: 0 | C6: count | D6: rent-roll-certified.xlsx | E6: no "pending" status present on roll
A7: total_area_sf | B7: 31150 | C7: SF | D7: rent-roll-certified.xlsx | E7: Rent Roll C5:C14
A8: occupied_area_sf | B8: 28170 | C8: SF | D8: rent-roll-certified.xlsx | E8: Rent Roll C5:C14 where D=active
A9: unit_occupancy | B9: 0.9 | C9: ratio | D9: rent-roll-certified.xlsx | E9: derived: 9/10
A10: area_occupancy | B10: 0.9042 | C10: ratio | D10: rent-roll-certified.xlsx | E10: derived: 28,170/31,150
A11: annual_in_place_rent | B11: 735300 | C11: USD | D11: rent-roll-certified.xlsx | E11: sum active × 12 = 61,275 × 12
A12: unit_001_monthly_rent | B12: 6650 | C12: USD | D12: rent-roll-certified.xlsx | E12: Rent Roll E5 (post-amendment)
A13: gross_potential_rent | B13: 814500 | C13: USD | D13: underwriting-instructions.pdf | E13: certified sum − S001 amend ×12 = 67,875 × 12
A14: uw_egi | B14: 777275 | C14: USD | D14: model | E14: UW!B10 = GPR×(1−5%)+3,500
A15: uw_tax | B15: 85964 | C15: USD | D15: underwriting-instructions.pdf | E15: Inputs!B10
... A28: insurance_policy_limit | B28: 2000000 | C28: USD | D28: insurance.pdf | E28: page 1 — GL aggregate (not an expense)
A29: selected_roll_date | B29: 2026-08-31 | C29: date | D29: rent-roll-certified.xlsx | E29: B2
A30: reported_t12_noi | B30: 507593 | C30: USD | D30: operating-statement.pdf | E30: page 1 — table
A31: type_a_units | B31: 4 | C31: count | D31: rent-roll-certified.xlsx + manager-cover.pdf | E31: Small suites
A32: type_a_occupied | B32: 3 | C32: count | D32: rent-roll-certified.xlsx | E32: active Small suites
A33: type_b_units | B33: 3 | C33: count | D33: rent-roll-certified.xlsx + manager-cover.pdf | E33: Standard suites
A34: type_b_occupied | B34: 3 | C34: count | D34: rent-roll-certified.xlsx | E34: active Standard suites
A35: type_c_units | B35: 3 | C35: count | D35: rent-roll-certified.xlsx + manager-cover.pdf | E35: Large suites
A36: type_c_occupied | B36: 3 | C36: count | D36: rent-roll-certified.xlsx | E36: active Large suites
A37: risk_pending_in_occupancy | B37: present | C37: flag | D37: manager-cover.pdf | E37: headline conflates occupied+pending as leased
A38: risk_near_term_rollover | B38: absent | C38: flag | D38: rent-roll-certified.xlsx | E38: all expiries 2029-08-31 — >12 months out
A39: risk_missing_insurance | B39: absent | C39: flag | D39: insurance.pdf + operating-statement.pdf | E39: policy in force; T12 insurance expense present
A40: risk_capital_in_opex | B40: absent | C40: flag | D40: operating-statement.pdf | E40: roof replacement is $0 in repairs — properly capitalized
A41: risk_unsigned_rent_change | B41: absent | C41: flag | D41: packet review | E41: no unsigned rent proposal in packet — amendment is signed
A42: risk_temporary_free_rent | B42: absent | C42: flag | D42: lease-001.pdf | E42: no free-rent concession applies as of evaluation date
A43: risk_sizing_floor_binding | B43: absent | C43: flag | D43: underwriting-instructions.pdf | E43: note rate 6.50% > floor 6.00%; note binds
A44: risk_refinance_shortfall | B44: absent | C44: flag | D44: model | E44: net cash-out is positive: $657,328
