Workbook

Sheet Inputs
A1: Maple Crossing – Inputs (Revised 2026-09-01)
A3: Gross Potential Rent (annual) | B3: 821400 | C3: Revised roll: pre-amend Suite 001 $6,650; Suite 002 now $7,025
A4: Other Income per unit (annual) | B4: 350
A5: Total units | B5: 10
A6: Economic loss % | B6: 0.05
A7: Real estate tax | B7: 85964
A8: Insurance expense | B8: 28655
A9: Other recurring opex | B9: 114618
A10: Management % of EGI | B10: 0.03
A11: Replacement reserve per unit | B11: 300
A12: Cap rate (REVISED +25 bps) | B12: 0.075
A13: Sizing rate (REVISED +75 bps; MAX vs floor) | B13: 0.0725
A14: Note rate (revised initial rate) | B14: 0.0725
A15: Underwriting floor rate | B15: 0.06
... A22: Existing payoff | B22: 4300000

Sheet UW
A1: Underwriting (Revised)
A3: Gross Potential Rent | B3: =Inputs!B3 -> 821400
A4: Other income (annual) | B4: =Inputs!B4*Inputs!B5 -> 3500
A5: Gross Revenue | B5: =B3+B4 -> 824900
A6: Less: Economic loss (5%) | B6: =-B5*Inputs!B6 -> -41245
A7: Effective Gross Income (EGI) | B7: =B5+B6 -> 783655
A9: Real estate tax | B9: =Inputs!B7 -> 85964
A10: Insurance | B10: =Inputs!B8 -> 28655
A11: Other recurring opex | B11: =Inputs!B9 -> 114618
A12: Management fee (3% EGI) | B12: =B7*Inputs!B10 -> 23509.65
A13: Total operating expenses | B13: =SUM(B9:B12) -> 252746.65
A15: NOI (before reserves) | B15: =B7-B13 -> 530908.35
A16: Replacement reserves | B16: =Inputs!B11*Inputs!B5 -> 3000
A17: NCF (after reserves) | B17: =B15-B16 -> 527908.35
A19: Capitalization value (NOI/Cap) | B19: =B15/Inputs!B12 -> 7078778

Sheet Debt
A1: Debt sizing & Sources/Uses (Revised)
A3: Sizing rate | B3: =MAX(Inputs!B14,Inputs!B15) -> 0.0725
A4: Annual DS per $1 (30yr amort) | B4: =PMT(B3/12,Inputs!B16,-1)*12 -> 0.081861154
A6: LTV-constrained loan | B6: =UW!B19*Inputs!B17 -> 4601205.7
A7: DSCR-constrained loan | B7: =UW!B17/(Inputs!B18*B4) -> 5159060.9
A8: Debt-yield-constrained loan | B8: =UW!B17/Inputs!B19 -> 5865648.3
A10: Maximum loan (min of tests) | B10: =MIN(B6:B8) -> 4601205.7
A12: Sources / Uses
A13: Loan proceeds | B13: =B10 -> 4601205.7
A14: Existing payoff | B14: =Inputs!B22 -> 4300000
A15: Origination fee (1%) | B15: =B10*Inputs!B20 -> 46012.057
A16: Closing costs | B16: =Inputs!B21 -> 45000
A17: Net cash-out (proceeds - payoff - fee - costs) | B17: =B13-B14-B15-B16 -> 210193.64
A19: Sanity: DSCR at max loan | B19: =UW!B17/(B10*B4) -> 1.4015514
A20: Sanity: Debt yield at max loan | B20: =UW!B17/B10 -> 0.11473261
A21: Sanity: LTV at max loan | B21: =B10/UW!B19 -> 0.65

Sheet Sensitivity
A1: Capitalization value sensitivity (NOI / Cap rate)
A3: Cap Rate \ NOI | B3: =UW!B15*0.95 -> 504362.93 | C3: =UW!B15 -> 530908.35 | D3: =UW!B15*1.05 -> 557453.77
A4: 0.065 | B4: =B$3/$A4 -> 7759429.7 | C4: =C$3/$A4 -> 8167820.8 | D4: =D$3/$A4 -> 8576211.8
A5: 0.07 | B5: =B$3/$A5 -> 7205184.8 | C5: =C$3/$A5 -> 7584405 | D5: =D$3/$A5 -> 7963625.2
A6: 0.075 | B6: =B$3/$A6 -> 6724839.1 | C6: =C$3/$A6 -> 7078778 | D6: =D$3/$A6 -> 7432716.9
A9: Max loan sensitivity to sizing rate
A11: Sizing rate | B11: LTV loan | C11: DSCR loan | D11: DY loan | E11: Max loan
A12: 0.0675 | B12: =UW!$B$19*Inputs!$B$17 -> 4601205.7 | C12: =UW!$B$17/(Inputs!$B$18*(PMT(A12/12,Inputs!$B$16,-1)*12)) -> 5426147.6 | D12: =UW!$B$17/Inputs!$B$19 -> 5865648.3 | E12: =MIN(B12:D12) -> 4601205.7
A13: 0.0725 | B13: =UW!$B$19*Inputs!$B$17 -> 4601205.7 | C13: =UW!$B$17/(Inputs!$B$18*(PMT(A13/12,Inputs!$B$16,-1)*12)) -> 5159060.9 | D13: =UW!$B$17/Inputs!$B$19 -> 5865648.3 | E13: =MIN(B13:D13) -> 4601205.7
A14: 0.0775 | B14: =UW!$B$19*Inputs!$B$17 -> 4601205.7 | C14: =UW!$B$17/(Inputs!$B$18*(PMT(A14/12,Inputs!$B$16,-1)*12)) -> 4912519.3 | D14: =UW!$B$17/Inputs!$B$19 -> 5865648.3 | E14: =MIN(B14:D14) -> 4601205.7
A15: 0.0825 | B15: =UW!$B$19*Inputs!$B$17 -> 4601205.7 | C15: =UW!$B$17/(Inputs!$B$18*(PMT(A15/12,Inputs!$B$16,-1)*12)) -> 4684607.3 | D15: =UW!$B$17/Inputs!$B$19 -> 5865648.3 | E15: =MIN(B15:D15) -> 4601205.7

Sheet RentRoll
A1: Revised Certified Rent Roll (as of 2026-09-01), Suite 001 amendment applied
A3: Suite | B3: Type | C3: Group | D3: Area SF | E3: Status | F3: Contractual Monthly | G3: Certified Monthly (revised roll) | H3: Expiration
A4: 001 | B4: Small | C4: A | D4: 3080 | E4: active | F4: 7000 | G4: 6650 | H4: 2029-08-31
A5: 002 | B5: Standard | C5: B | D5: 3200 | E5: active | F5: 7025 | G5: 7025 | H5: 2029-08-31
A6: 003 | B6: Large | C6: C | D6: 3410 | E6: active | F6: 7075 | G6: 7075 | H6: 2029-08-31
A7: 004 | B7: Small | C7: A | D7: 3080 | E7: active | F7: 6650 | G7: 6650 | H7: 2029-08-31
A8: 005 | B8: Standard | C8: B | D8: 3200 | E8: active | F8: 6800 | G8: 6800 | H8: 2029-08-31
A9: 006 | B9: Large | C9: C | D9: 3410 | E9: active | F9: 7075 | G9: 7075 | H9: 2029-08-31
A10: 007 | B10: Small | C10: A | D10: 3080 | E10: active | F10: 6650 | G10: 6650 | H10: 2029-08-31
A11: 008 | B11: Standard | C11: B | D11: 3200 | E11: active | F11: 6800 | G11: 6800 | H11: 2029-08-31
A12: 009 | B12: Large | C12: C | D12: 3410 | E12: active | F12: 7075 | G12: 7075 | H12: 2029-08-31
A13: 010 | B13: Small | C13: A | D13: 3080 | E13: vacant | F13: 0 | G13: 6650 | H13: 2029-08-31
A15: Totals | D15: =SUM(D4:D13) -> 32150 | F15: =SUM(F4:F13) -> 62150 | G15: =SUM(G4:G13) -> 68450
A17: Occupied units (active) | B17: =COUNTIF(E4:E13,"active") -> 9
A18: Occupied area SF | B18: =SUMIF(E4:E13,"active",D4:D13) -> 29070
A19: In-place annual rent (post-amend Suite 001) | B19: =SUMIF(E4:E13,"active",F4:F13)*12 -> 745800
A20: GPR (all suites revised roll × 12) | B20: =SUM(G4:G13)*12 -> 821400

Sheet Changes
A1: Revision Change Log
A3: Item | B3: Prior | C3: Revised | D3: Driver
A4: Certified roll date | B4: 2026-08-31 | C4: 2026-09-01 | D4: revision-notice.pdf
A5: Suite 002 status | B5: active | C5: active | D5: revised roll
A6: Suite 002 monthly rent | B6: 6800 | C6: 7025 | D6: +$225 per revision
A7: GPR (all suites x12) | B7: 818700 | C7: 821400 | D7: revised roll
A8: Cap rate | B8: 0.0675 | C8: 0.07 | D8: +25 bps
A9: Sizing rate | B9: 0.065 | C9: 0.0725 | D9: +75 bps
A10: EGI | B10: 781090 | C10: 783655 | D10: GPR change
A11: NOI (before reserves) | B11: 528420 | C11: 530908 | D11: EGI change
A12: NCF | B12: 525420 | C12: 527908 | D12: -
A13: Capitalization value | B13: 7828449 | C13: 7584405 | D13: higher cap outweighs NOI
A14: Maximum loan (binding constraint) | B14: 5088492 | C14: 4929863 | D14: LTV still binds
A15: Net cash-out | B15: 692607 | C15: 535565 | D15: -

Sheet Sources
A1: Source Register (Revised)
A3: Item | B3: Value | C3: Source file | D3: Location
A4: Revised certified rent roll date | B4: 2026-09-01 | C4: rent-roll-revised.xlsx | D4: B2
A5: Prior certified rent roll date (superseded) | B5: 2026-08-31 | C5: rent-roll-certified.xlsx | D5: B2
A6: Suite 001 pre-amend rent | B6: 6650 | C6: lease-001.pdf | D6: p.1
A7: Amendment (+$350) executed | B7: 2026-07-20 | C7: lease-correspondence.pdf | D7: p.1
A8: Suite 002 revised monthly rent | B8: 7025 | C8: rent-roll-revised.xlsx | D8: E6
A9: Revision instructions (rate deltas) | B9: +75 bps sizing, +25 bps cap | C9: revision-notice.pdf | D9: p.1
A10: Manager 9/10 leased (incl pending) | B10: note | C10: manager-cover.pdf | D10: p.1
A11: T12 collections | B11: 736830 | C11: operating-statement.pdf | D11: p.1
A12: T12 taxes | B12: 85964 | C12: operating-statement.pdf | D12: p.1
A13: T12 insurance | B13: 28655 | C13: operating-statement.pdf | D13: p.1
A14: T12 other opex | B14: 114618 | C14: operating-statement.pdf | D14: p.1
A15: Reported NOI (T12) | B15: 507593 | C15: operating-statement.pdf | D15: p.1
A16: GL insurance policy limit | B16: 2000000 | C16: insurance.pdf | D16: p.1
A17: Underwriting instructions | B17: prescribed | C17: underwriting-instructions.pdf | D17: p.1
A18: Diligence status | B18: pending routine | C18: diligence-status.pdf | D18: p.1
