Workbook

Sheet UW
A1: Willow Gardens Underwriting
A3: Gross potential rent (annual) | B3: 1354500
A4: Capitalization rate | B4: 0.06
A5: Sizing rate (note vs floor; greater) | B5: 0.079
A6: Total units | B6: 64
A7: Economic loss % | B7: 0.05
A8: Other income per unit (annual) | B8: 350
A9: Other income total (annual) | B9: =B6*B8
A10: Underwritten EGI | B10: =B3*(1-B7)+B9
A11: Management fee % | B11: 0.03
A12: Management fee (annual) | B12: =B10*B11
A13: Real estate taxes (annual) | B13: 142222
A14: Insurance expense (annual) | B14: 47408
A15: Other recurring operating expenses | B15: 189630
A16: UW NOI before reserves | B16: =B10-B12-B13-B14-B15
A17: Replacement reserves per unit (annual) | B17: 300
A18: Replacement reserves total (annual) | B18: =B6*B17
A19: UW NCF after reserves | B19: =B16-B18
A20: Capitalization value | B20: =B16/B4
A21: LTV limit (60% of cap value) | B21: =B20*0.6
A22: Amortization (years) | B22: 30
A23: Annual debt service per $1 | B23: =12*ABS(PMT(B5/12,B22*12,1))
A24: Minimum DSCR | B24: 1.25
A25: DSCR-based loan | B25: =(B19/B24)/B23
A26: Minimum debt yield | B26: 0.09
A27: Debt-yield-based loan | B27: =B19/B26
A28: Maximum loan (min of constraints) | B28: =MIN(B21,B25,B27)
A29: Origination fee % | B29: 0.01
A30: Origination fee (amount) | B30: =B28*B29
A31: Closing costs | B31: 45000
A32: Existing payoff | B32: 7200000
A33: Net cash out (neg = add'l equity req.) | B33: =B28-B30-B31-B32

Sheet Sensitivity
A1: Loan sizing sensitivity
A3: Base sizing rate | B3: ='UW'!B5
A4: Base cap rate | B4: ='UW'!B4
A5: Sizing rate \\ Cap rate | B5: =B4-0.005 | C5: =B4 | D5: =B4+0.005
A6: =B3-0.005 | B6: =MIN('UW'!B16/B5*0.6, ('UW'!B19/'UW'!B24)/(12*ABS(PMT(A6/12,'UW'!B22*12,1))), 'UW'!B19/'UW'!B26) | C6: =MIN('UW'!B16/C5*0.6, ('UW'!B19/'UW'!B24)/(12*ABS(PMT(A6/12,'UW'!B22*12,1))), 'UW'!B19/'UW'!B26) | D6: =MIN('UW'!B16/D5*0.6, ('UW'!B19/'UW'!B24)/(12*ABS(PMT(A6/12,'UW'!B22*12,1))), 'UW'!B19/'UW'!B26)
A7: =B3 | B7: =MIN('UW'!B16/B5*0.6, ('UW'!B19/'UW'!B24)/(12*ABS(PMT(A7/12,'UW'!B22*12,1))), 'UW'!B19/'UW'!B26) | C7: =MIN('UW'!B16/C5*0.6, ('UW'!B19/'UW'!B24)/(12*ABS(PMT(A7/12,'UW'!B22*12,1))), 'UW'!B19/'UW'!B26) | D7: =MIN('UW'!B16/D5*0.6, ('UW'!B19/'UW'!B24)/(12*ABS(PMT(A7/12,'UW'!B22*12,1))), 'UW'!B19/'UW'!B26)
A8: =B3+0.005 | B8: =MIN('UW'!B16/B5*0.6, ('UW'!B19/'UW'!B24)/(12*ABS(PMT(A8/12,'UW'!B22*12,1))), 'UW'!B19/'UW'!B26) | C8: =MIN('UW'!B16/C5*0.6, ('UW'!B19/'UW'!B24)/(12*ABS(PMT(A8/12,'UW'!B22*12,1))), 'UW'!B19/'UW'!B26) | D8: =MIN('UW'!B16/D5*0.6, ('UW'!B19/'UW'!B24)/(12*ABS(PMT(A8/12,'UW'!B22*12,1))), 'UW'!B19/'UW'!B26)

Sheet Sources
A1: Source register
A3: Document | B3: Location (page / cell)
A4: rent-roll-certified.xlsx | B4: B2 as-of date; A5:G68 unit detail; E5 Unit 001 rent
A5: rent-roll-archive.xlsx | B5: B2 as-of date; A5:G68 unit detail
A6: operating-statement.pdf | B6: p1 T12 actuals incl. tax, insurance, other opex, reported NOI
A7: underwriting-instructions.pdf | B7: p1 underwriting assumptions (GPR basis, loss %, mgmt %, reserves, cap rate, loan sizing, fees, payoff)
A8: insurance.pdf | B8: p1 general liability aggregate limit $2,000,000; eff 2026-07-01 to 2027-06-30
A9: manager-cover.pdf | B9: p1 occupancy headline includes pending; A/B/C mapping
A10: lease-001.pdf | B10: p1 Suite 001 rent $1,575; 820 SF; expiry 2029-08-31; no free rent
A11: lease-correspondence.pdf | B11: p1 manager confirmation no amendments or concessions as of 2026-08-31
